Workbook
Name _GoBack: AUTOHOGAR!#REF!
Name entrega: '[1]Sugerencia Rendiciones '!$BP$2:$BP$11
Name tipo: '[1]Sugerencia Rendiciones '!$D$3:$D$11

Sheet AUTOHOGAR
A1: 7 | B1: =IF(A1<>0,VLOOKUP(A1,COB!A1:B9,2),"COBRADOR INEXISTENTE") -> MEDIOS ELECTRONICOS | D1: AGOSTO | E1: 2026 | F1: TOTAL | I1: EL ARRASTE ES EL DINERO PENDIENTE O A FAVOR DEL CLIENTE | AI1: 15 C 1-6 | AS1: SI EL | AU1: SI EL CLIENTE
G2: A COBRAR | I2: PAGOS | N2: SAL. REAL | O2: SALDO | P2: SALDO /P ESTAD | Q2: FECHAS | Z2: SALDO P/ | AB2: PROBLEMAS | AC2: CORDOBA | AE2: NO PASO | AH2: TOTAL | AI2: 25 C 7-X | AS2: CLIEN PAGO | AU2: DEBE ALGO | AY2: CALCULO | AZ2: MOROSO | BA2: X ADEL | BD2: CALCULO | BE2: X ADEL | BF2: MOROSO
A3: COD | B3: CLIENTE | C3: TELEFONO | D3: LOCALIDAD | E3: SOLI | F3: CTA | G3: CUOTAS | H3: ARRASTRE | I3: PAGO | J3: PAGO X ADEL | K3: PAGO ANTES | L3: X OFICINA | M3: BCO O ELECT | N3: CON MORA | O3: SISTEMA | P3: PLANILLA SALIDA | Q3: PAGO | R3: PAGARA | S3: PAGO MES ANT | T3: BAJA | U3: MOTIVO | V3: OBSERVACIONES | W3: TERMOMETRO | X3: COB | Y3: COB XX | Z3: COMISION | AA3: PAGARA | AB3: CON VEND | AC3: CON VENTAS | AD3: CON PROP. EC | AE3: EL COB | AF3: OTROS | AG3: OBSERVACIONES | AH3: CLIENTES | AI3: paramet 1 | AJ3: paramet 2 | AK3: BAJAS 7-X | AL3: CLIENTES | AM3: MOTIVOS | AN3: $ | AO3: BAJAS 1-6 | AP3: CLIENTES | AQ3: MOTIVOS | AR3: $ | AS3: PAGADOS | AT3: CLIENTES | AU3: MORO O BAJA | AV3: N° CLIEN | AW3: MOROSOS 7 -X | AX3: CLIENTES | AY3: $ | BA3: $ | BB3: MOROSOS 1 -6 | BC3: CLIENTES | BD3: $ | BF3: $
A4: 816 | B4: GUEVARA ANTONIO NICOLAS | C4: 264-4837119 | D4: HUACO | E4: 9287 | F4: 93 | G4: 40000 | H4: 0 | N4: =IF(H4>0,G4+H4-I4-J4-K4-L4-M4,G4-I4-J4-K4-L4-M4) -> 40000 | O4: =G4+H4-J4-I4-K4-L4-M4 -> 40000 | P4: =IF(G4+H4<0,0,G4+H4) -> 40000 | S4: 46205 | X4: 7 | Y4: 7 | Z4: =IF(N4<0,0,N4) -> 40000 | AH4: 1 | AI4: =IF(F4<=6,15,25) -> 25 | AJ4: =IF(O4<>0,25,15) -> 25 | AK4: =IF(AI4-T4=24,1,0) -> 0 | AL4: =IF(AH4-AK4=AH4,0,AH4) -> 0 | AM4: =IF(AK4<>0,U4,0) -> 0 | AN4: =IF(AK4=1,O4,0) -> 0 | AO4: =IF(AI4-T4=14,1,0) -> 0 | AP4: =IF(AH4-AO4=AH4,0,AH4) -> 0 | AQ4: =IF(AO4<>0,U4,0) -> 0 | AR4: =IF(AO4=1,O4,0) -> 0 | AS4: =IF(SUM(I4:M4)<>0,1,0) -> 0 | AT4: =AS4 -> 0 | AU4: =IF(O4>0,1,0) -> 1 | AV4: =IF(AK4+AO4+AU4=1,AU4,0) -> 1 | AW4: =IF(AI4-AV4=24,1,0) -> 1 | AX4: =IF(AH4-AW4=AH4,0,AH4) -> 1 | AY4: =IF(AW4=1,O4,0) -> 40000 | AZ4: =IF(AY4-BA4<>0,AY4,0) -> 40000 | BA4: =IF(AY4<0,AY4,0) -> 0 | BB4: =IF(AI4-AV4=14,1,0) -> 0 | BC4: =IF(AH4-BB4=AH4,0,AH4) -> 0 | BD4: =IF(BB4=1,O4,0) -> 0 | BE4: =IF(BD4<0,BD4,0) -> 0 | BF4: =IF(BD4-BE4<>0,BD4,0) -> 0
A5: 823 | B5: JOFRE ELIZABETH DEL VALLE | C5: 264-4122541 | D5: JACHAL | E5: 9375 | F5: 93 | G5: 30000 | H5: -3500 | N5: =IF(H5>0,G5+H5-I5-J5-K5-L5-M5,G5-I5-J5-K5-L5-M5) -> 30000 | O5: =G5+H5-J5-I5-K5-L5-M5 -> 26500 | P5: =IF(G5+H5<0,0,G5+H5) -> 26500 | S5: 46234 | X5: 7 | Y5: 7 | Z5: =IF(N5<0,0,N5) -> 30000 | AH5: 1 | AI5: =IF(F5<=6,15,25) -> 25 | AJ5: =IF(O5<>0,25,15) -> 25 | AK5: =IF(AI5-T5=24,1,0) -> 0 | AL5: =IF(AH5-AK5=AH5,0,AH5) -> 0 | AM5: =IF(AK5<>0,U5,0) -> 0 | AN5: =IF(AK5=1,O5,0) -> 0 | AO5: =IF(AI5-T5=14,1,0) -> 0 | AP5: =IF(AH5-AO5=AH5,0,AH5) -> 0 | AQ5: =IF(AO5<>0,U5,0) -> 0 | AR5: =IF(AO5=1,O5,0) -> 0 | AS5: =IF(SUM(I5:M5)<>0,1,0) -> 0 | AT5: =AS5 -> 0 | AU5: =IF(O5>0,1,0) -> 1 | AV5: =IF(AK5+AO5+AU5=1,AU5,0) -> 1 | AW5: =IF(AI5-AV5=24,1,0) -> 1 | AX5: =IF(AH5-AW5=AH5,0,AH5) -> 1 | AY5: =IF(AW5=1,O5,0) -> 26500 | AZ5: =IF(AY5-BA5<>0,AY5,0) -> 26500 | BA5: =IF(AY5<0,AY5,0) -> 0 | BB5: =IF(AI5-AV5=14,1,0) -> 0 | BC5: =IF(AH5-BB5=AH5,0,AH5) -> 0 | BD5: =IF(BB5=1,O5,0) -> 0 | BE5: =IF(BD5<0,BD5,0) -> 0 | BF5: =IF(BD5-BE5<>0,BD5,0) -> 0
A6: 834 | B6: BALMACEDA ESTER MARIA | C6: 2644442152 | D6: JACHAL | E6: 9034 | F6: 93 | G6: 60000 | H6: -4000 | N6: =IF(H6>0,G6+H6-I6-J6-K6-L6-M6,G6-I6-J6-K6-L6-M6) -> 60000 | O6: =G6+H6-J6-I6-K6-L6-M6 -> 56000 | P6: =IF(G6+H6<0,0,G6+H6) -> 56000 | S6: 46234 | X6: 7 | Y6: 7 | Z6: =IF(N6<0,0,N6) -> 60000 | AH6: 1 | AI6: =IF(F6<=6,15,25) -> 25 | AJ6: =IF(O6<>0,25,15) -> 25 | AK6: =IF(AI6-T6=24,1,0) -> 0 | AL6: =IF(AH6-AK6=AH6,0,AH6) -> 0 | AM6: =IF(AK6<>0,U6,0) -> 0 | AN6: =IF(AK6=1,O6,0) -> 0 | AO6: =IF(AI6-T6=14,1,0) -> 0 | AP6: =IF(AH6-AO6=AH6,0,AH6) -> 0 | AQ6: =IF(AO6<>0,U6,0) -> 0 | AR6: =IF(AO6=1,O6,0) -> 0 | AS6: =IF(SUM(I6:M6)<>0,1,0) -> 0 | AT6: =AS6 -> 0 | AU6: =IF(O6>0,1,0) -> 1 | AV6: =IF(AK6+AO6+AU6=1,AU6,0) -> 1 | AW6: =IF(AI6-AV6=24,1,0) -> 1 | AX6: =IF(AH6-AW6=AH6,0,AH6) -> 1 | AY6: =IF(AW6=1,O6,0) -> 56000 | AZ6: =IF(AY6-BA6<>0,AY6,0) -> 56000 | BA6: =IF(AY6<0,AY6,0) -> 0 | BB6: =IF(AI6-AV6=14,1,0) -> 0 | BC6: =IF(AH6-BB6=AH6,0,AH6) -> 0 | BD6: =IF(BB6=1,O6,0) -> 0 | BE6: =IF(BD6<0,BD6,0) -> 0 | BF6: =IF(BD6-BE6<>0,BD6,0) -> 0
A7: 1186 | B7: GARAY MARCELO | C7: 264-5269535 | D7: SAN JUAN | E7: 8984 | F7: 84 | G7: 80000 | H7: -24000 | N7: =IF(H7>0,G7+H7-I7-J7-K7-L7-M7,G7-I7-J7-K7-L7-M7) -> 80000 | O7: =G7+H7-J7-I7-K7-L7-M7 -> 56000 | P7: =IF(G7+H7<0,0,G7+H7) -> 56000 | S7: 46211 | X7: 7 | Y7: 7 | Z7: =IF(N7<0,0,N7) -> 80000 | AH7: 1 | AI7: =IF(F7<=6,15,25) -> 25 | AJ7: =IF(O7<>0,25,15) -> 25 | AK7: =IF(AI7-T7=24,1,0) -> 0 | AL7: =IF(AH7-AK7=AH7,0,AH7) -> 0 | AM7: =IF(AK7<>0,U7,0) -> 0 | AN7: =IF(AK7=1,O7,0) -> 0 | AO7: =IF(AI7-T7=14,1,0) -> 0 | AP7: =IF(AH7-AO7=AH7,0,AH7) -> 0 | AQ7: =IF(AO7<>0,U7,0) -> 0 | AR7: =IF(AO7=1,O7,0) -> 0 | AS7: =IF(SUM(I7:M7)<>0,1,0) -> 0 | AT7: =AS7 -> 0 | AU7: =IF(O7>0,1,0) -> 1 | AV7: =IF(AK7+AO7+AU7=1,AU7,0) -> 1 | AW7: =IF(AI7-AV7=24,1,0) -> 1 | AX7: =IF(AH7-AW7=AH7,0,AH7) -> 1 | AY7: =IF(AW7=1,O7,0) -> 56000 | AZ7: =IF(AY7-BA7<>0,AY7,0) -> 56000 | BA7: =IF(AY7<0,AY7,0) -> 0 | BB7: =IF(AI7-AV7=14,1,0) -> 0 | BC7: =IF(AH7-BB7=AH7,0,AH7) -> 0 | BD7: =IF(BB7=1,O7,0) -> 0 | BE7: =IF(BD7<0,BD7,0) -> 0 | BF7: =IF(BD7-BE7<>0,BD7,0) -> 0
A8: 1417 | B8: GARAY MARCELO ROBERTO | C8: 264-5269535 | D8: SAN JUAN | E8: 8539 | F8: 77 | G8: 80000 | H8: -6000 | N8: =IF(H8>0,G8+H8-I8-J8-K8-L8-M8,G8-I8-J8-K8-L8-M8) -> 80000 | O8: =G8+H8-J8-I8-K8-L8-M8 -> 74000 | P8: =IF(G8+H8<0,0,G8+H8) -> 74000 | S8: 46211 | X8: 7 | Y8: 7 | Z8: =IF(N8<0,0,N8) -> 80000 | AH8: 1 | AI8: =IF(F8<=6,15,25) -> 25 | AJ8: =IF(O8<>0,25,15) -> 25 | AK8: =IF(AI8-T8=24,1,0) -> 0 | AL8: =IF(AH8-AK8=AH8,0,AH8) -> 0 | AM8: =IF(AK8<>0,U8,0) -> 0 | AN8: =IF(AK8=1,O8,0) -> 0 | AO8: =IF(AI8-T8=14,1,0) -> 0 | AP8: =IF(AH8-AO8=AH8,0,AH8) -> 0 | AQ8: =IF(AO8<>0,U8,0) -> 0 | AR8: =IF(AO8=1,O8,0) -> 0 | AS8: =IF(SUM(I8:M8)<>0,1,0) -> 0 | AT8: =AS8 -> 0 | AU8: =IF(O8>0,1,0) -> 1 | AV8: =IF(AK8+AO8+AU8=1,AU8,0) -> 1 | AW8: =IF(AI8-AV8=24,1,0) -> 1 | AX8: =IF(AH8-AW8=AH8,0,AH8) -> 1 | AY8: =IF(AW8=1,O8,0) -> 74000 | AZ8: =IF(AY8-BA8<>0,AY8,0) -> 74000 | BA8: =IF(AY8<0,AY8,0) -> 0 | BB8: =IF(AI8-AV8=14,1,0) -> 0 | BC8: =IF(AH8-BB8=AH8,0,AH8) -> 0 | BD8: =IF(BB8=1,O8,0) -> 0 | BE8: =IF(BD8<0,BD8,0) -> 0 | BF8: =IF(BD8-BE8<>0,BD8,0) -> 0
A9: 1457 | B9: PASTEN EMILCE SABRINA | C9: 264-4739119 | D9: RIVADAVIA | E9: 8864 | F9: 76 | G9: 60000 | H9: -15000 | N9: =IF(H9>0,G9+H9-I9-J9-K9-L9-M9,G9-I9-J9-K9-L9-M9) -> 60000 | O9: =G9+H9-J9-I9-K9-L9-M9 -> 45000 | P9: =IF(G9+H9<0,0,G9+H9) -> 45000 | S9: 46234 | X9: 7 | Y9: 7 | Z9: =IF(N9<0,0,N9) -> 60000 | AH9: 1 | AI9: =IF(F9<=6,15,25) -> 25 | AJ9: =IF(O9<>0,25,15) -> 25 | AK9: =IF(AI9-T9=24,1,0) -> 0 | AL9: =IF(AH9-AK9=AH9,0,AH9) -> 0 | AM9: =IF(AK9<>0,U9,0) -> 0 | AN9: =IF(AK9=1,O9,0) -> 0 | AO9: =IF(AI9-T9=14,1,0) -> 0 | AP9: =IF(AH9-AO9=AH9,0,AH9) -> 0 | AQ9: =IF(AO9<>0,U9,0) -> 0 | AR9: =IF(AO9=1,O9,0) -> 0 | AS9: =IF(SUM(I9:M9)<>0,1,0) -> 0 | AT9: =AS9 -> 0 | AU9: =IF(O9>0,1,0) -> 1 | AV9: =IF(AK9+AO9+AU9=1,AU9,0) -> 1 | AW9: =IF(AI9-AV9=24,1,0) -> 1 | AX9: =IF(AH9-AW9=AH9,0,AH9) -> 1 | AY9: =IF(AW9=1,O9,0) -> 45000 | AZ9: =IF(AY9-BA9<>0,AY9,0) -> 45000 | BA9: =IF(AY9<0,AY9,0) -> 0 | BB9: =IF(AI9-AV9=14,1,0) -> 0 | BC9: =IF(AH9-BB9=AH9,0,AH9) -> 0 | BD9: =IF(BB9=1,O9,0) -> 0 | BE9: =IF(BD9<0,BD9,0) -> 0 | BF9: =IF(BD9-BE9<>0,BD9,0) -> 0
A10: 1597 | B10: ALMAZAN JUAN ARIEL | C10: 264-6245764 | D10: RAWSON | E10: 9625 | F10: 73 | G10: 60000 | H10: 0 | N10: =IF(H10>0,G10+H10-I10-J10-K10-L10-M10,G10-I10-J10-K10-L10-M10) -> 60000 | O10: =G10+H10-J10-I10-K10-L10-M10 -> 60000 | P10: =IF(G10+H10<0,0,G10+H10) -> 60000 | S10: 46234 | X10: 7 | Y10: 7 | Z10: =IF(N10<0,0,N10) -> 60000 | AH10: 1 | AI10: =IF(F10<=6,15,25) -> 25 | AJ10: =IF(O10<>0,25,15) -> 25 | AK10: =IF(AI10-T10=24,1,0) -> 0 | AL10: =IF(AH10-AK10=AH10,0,AH10) -> 0 | AM10: =IF(AK10<>0,U10,0) -> 0 | AN10: =IF(AK10=1,O10,0) -> 0 | AO10: =IF(AI10-T10=14,1,0) -> 0 | AP10: =IF(AH10-AO10=AH10,0,AH10) -> 0 | AQ10: =IF(AO10<>0,U10,0) -> 0 | AR10: =IF(AO10=1,O10,0) -> 0 | AS10: =IF(SUM(I10:M10)<>0,1,0) -> 0 | AT10: =AS10 -> 0 | AU10: =IF(O10>0,1,0) -> 1 | AV10: =IF(AK10+AO10+AU10=1,AU10,0) -> 1 | AW10: =IF(AI10-AV10=24,1,0) -> 1 | AX10: =IF(AH10-AW10=AH10,0,AH10) -> 1 | AY10: =IF(AW10=1,O10,0) -> 60000 | AZ10: =IF(AY10-BA10<>0,AY10,0) -> 60000 | BA10: =IF(AY10<0,AY10,0) -> 0 | BB10: =IF(AI10-AV10=14,1,0) -> 0 | BC10: =IF(AH10-BB10=AH10,0,AH10) -> 0 | BD10: =IF(BB10=1,O10,0) -> 0 | BE10: =IF(BD10<0,BD10,0) -> 0 | BF10: =IF(BD10-BE10<>0,BD10,0) -> 0
A11: 1601 | B11: BUSTOS ELIZABETH NOEMI | C11: 264-5207638 | D11: SANTA LUCIA | E11: 9594 | F11: 73 | G11: 80000 | H11: 0 | N11: =IF(H11>0,G11+H11-I11-J11-K11-L11-M11,G11-I11-J11-K11-L11-M11) -> 80000 | O11: =G11+H11-J11-I11-K11-L11-M11 -> 80000 | P11: =IF(G11+H11<0,0,G11+H11) -> 80000 | S11: 46209 | X11: 7 | Y11: 7 | Z11: =IF(N11<0,0,N11) -> 80000 | AH11: 1 | AI11: =IF(F11<=6,15,25) -> 25 | AJ11: =IF(O11<>0,25,15) -> 25 | AK11: =IF(AI11-T11=24,1,0) -> 0 | AL11: =IF(AH11-AK11=AH11,0,AH11) -> 0 | AM11: =IF(AK11<>0,U11,0) -> 0 | AN11: =IF(AK11=1,O11,0) -> 0 | AO11: =IF(AI11-T11=14,1,0) -> 0 | AP11: =IF(AH11-AO11=AH11,0,AH11) -> 0 | AQ11: =IF(AO11<>0,U11,0) -> 0 | AR11: =IF(AO11=1,O11,0) -> 0 | AS11: =IF(SUM(I11:M11)<>0,1,0) -> 0 | AT11: =AS11 -> 0 | AU11: =IF(O11>0,1,0) -> 1 | AV11: =IF(AK11+AO11+AU11=1,AU11,0) -> 1 | AW11: =IF(AI11-AV11=24,1,0) -> 1 | AX11: =IF(AH11-AW11=AH11,0,AH11) -> 1 | AY11: =IF(AW11=1,O11,0) -> 80000 | AZ11: =IF(AY11-BA11<>0,AY11,0) -> 80000 | BA11: =IF(AY11<0,AY11,0) -> 0 | BB11: =IF(AI11-AV11=14,1,0) -> 0 | BC11: =IF(AH11-BB11=AH11,0,AH11) -> 0 | BD11: =IF(BB11=1,O11,0) -> 0 | BE11: =IF(BD11<0,BD11,0) -> 0 | BF11: =IF(BD11-BE11<>0,BD11,0) -> 0
A12: 1671 | B12: TRIGO ESPEJO CARLOS JAVIER | C12: 2645414691 | D12: RAWSON | E12: 9740 | F12: 73 | G12: 30000 | H12: -32000 | N12: =IF(H12>0,G12+H12-I12-J12-K12-L12-M12,G12-I12-J12-K12-L12-M12) -> 30000 | O12: =G12+H12-J12-I12-K12-L12-M12 -> -2000 | P12: =IF(G12+H12<0,0,G12+H12) -> 0 | S12: 46234 | X12: 7 | Y12: 7 | Z12: =IF(N12<0,0,N12) -> 30000 | AH12: 1 | AI12: =IF(F12<=6,15,25) -> 25 | AJ12: =IF(O12<>0,25,15) -> 25 | AK12: =IF(AI12-T12=24,1,0) -> 0 | AL12: =IF(AH12-AK12=AH12,0,AH12) -> 0 | AM12: =IF(AK12<>0,U12,0) -> 0 | AN12: =IF(AK12=1,O12,0) -> 0 | AO12: =IF(AI12-T12=14,1,0) -> 0 | AP12: =IF(AH12-AO12=AH12,0,AH12) -> 0 | AQ12: =IF(AO12<>0,U12,0) -> 0 | AR12: =IF(AO12=1,O12,0) -> 0 | AS12: =IF(SUM(I12:M12)<>0,1,0) -> 0 | AT12: =AS12 -> 0 | AU12: =IF(O12>0,1,0) -> 0 | AV12: =IF(AK12+AO12+AU12=1,AU12,0) -> 0 | AW12: =IF(AI12-AV12=24,1,0) -> 0 | AX12: =IF(AH12-AW12=AH12,0,AH12) -> 0 | AY12: =IF(AW12=1,O12,0) -> 0 | AZ12: =IF(AY12-BA12<>0,AY12,0) -> 0 | BA12: =IF(AY12<0,AY12,0) -> 0 | BB12: =IF(AI12-AV12=14,1,0) -> 0 | BC12: =IF(AH12-BB12=AH12,0,AH12) -> 0 | BD12: =IF(BB12=1,O12,0) -> 0 | BE12: =IF(BD12<0,BD12,0) -> 0 | BF12: =IF(BD12-BE12<>0,BD12,0) -> 0
A13: 1791 | B13: MUÑOZ ALICIA ADRIANA | C13: 264-4700323 | D13: CHIMBAS | E13: 9908 | F13: 71 | G13: 60000 | H13: -15000 | N13: =IF(H13>0,G13+H13-I13-J13-K13-L13-M13,G13-I13-J13-K13-L13-M13) -> 60000 | O13: =G13+H13-J13-I13-K13-L13-M13 -> 45000 | P13: =IF(G13+H13<0,0,G13+H13) -> 45000 | S13: 46223 | X13: 7 | Y13: 7 | Z13: =IF(N13<0,0,N13) -> 60000 | AH13: 1 | AI13: =IF(F13<=6,15,25) -> 25 | AJ13: =IF(O13<>0,25,15) -> 25 | AK13: =IF(AI13-T13=24,1,0) -> 0 | AL13: =IF(AH13-AK13=AH13,0,AH13) -> 0 | AM13: =IF(AK13<>0,U13,0) -> 0 | AN13: =IF(AK13=1,O13,0) -> 0 | AO13: =IF(AI13-T13=14,1,0) -> 0 | AP13: =IF(AH13-AO13=AH13,0,AH13) -> 0 | AQ13: =IF(AO13<>0,U13,0) -> 0 | AR13: =IF(AO13=1,O13,0) -> 0 | AS13: =IF(SUM(I13:M13)<>0,1,0) -> 0 | AT13: =AS13 -> 0 | AU13: =IF(O13>0,1,0) -> 1 | AV13: =IF(AK13+AO13+AU13=1,AU13,0) -> 1 | AW13: =IF(AI13-AV13=24,1,0) -> 1 | AX13: =IF(AH13-AW13=AH13,0,AH13) -> 1 | AY13: =IF(AW13=1,O13,0) -> 45000 | AZ13: =IF(AY13-BA13<>0,AY13,0) -> 45000 | BA13: =IF(AY13<0,AY13,0) -> 0 | BB13: =IF(AI13-AV13=14,1,0) -> 0 | BC13: =IF(AH13-BB13=AH13,0,AH13) -> 0 | BD13: =IF(BB13=1,O13,0) -> 0 | BE13: =IF(BD13<0,BD13,0) -> 0 | BF13: =IF(BD13-BE13<>0,BD13,0) -> 0
A14: 1829 | B14: MANRIQUE BRIZUELA BARBARA ELIZABETH | C14: 2644112914 | D14: JACHAL | E14: 9936 | F14: 70 | G14: 300000 | H14: -5000 | N14: =IF(H14>0,G14+H14-I14-J14-K14-L14-M14,G14-I14-J14-K14-L14-M14) -> 300000 | O14: =G14+H14-J14-I14-K14-L14-M14 -> 295000 | P14: =IF(G14+H14<0,0,G14+H14) -> 295000 | S14: 46234 | X14: 7 | Y14: 7 | Z14: =IF(N14<0,0,N14) -> 300000 | AH14: 1 | AI14: =IF(F14<=6,15,25) -> 25 | AJ14: =IF(O14<>0,25,15) -> 25 | AK14: =IF(AI14-T14=24,1,0) -> 0 | AL14: =IF(AH14-AK14=AH14,0,AH14) -> 0 | AM14: =IF(AK14<>0,U14,0) -> 0 | AN14: =IF(AK14=1,O14,0) -> 0 | AO14: =IF(AI14-T14=14,1,0) -> 0 | AP14: =IF(AH14-AO14=AH14,0,AH14) -> 0 | AQ14: =IF(AO14<>0,U14,0) -> 0 | AR14: =IF(AO14=1,O14,0) -> 0 | AS14: =IF(SUM(I14:M14)<>0,1,0) -> 0 | AT14: =AS14 -> 0 | AU14: =IF(O14>0,1,0) -> 1 | AV14: =IF(AK14+AO14+AU14=1,AU14,0) -> 1 | AW14: =IF(AI14-AV14=24,1,0) -> 1 | AX14: =IF(AH14-AW14=AH14,0,AH14) -> 1 | AY14: =IF(AW14=1,O14,0) -> 295000 | AZ14: =IF(AY14-BA14<>0,AY14,0) -> 295000 | BA14: =IF(AY14<0,AY14,0) -> 0 | BB14: =IF(AI14-AV14=14,1,0) -> 0 | BC14: =IF(AH14-BB14=AH14,0,AH14) -> 0 | BD14: =IF(BB14=1,O14,0) -> 0 | BE14: =IF(BD14<0,BD14,0) -> 0 | BF14: =IF(BD14-BE14<>0,BD14,0) -> 0
A15: 1870 | B15: OCHOA ERICA DEBORA | C15: 264-5178841 | D15: SAN JUAN | E15: 9889 | F15: 69 | G15: 40000 | H15: 0 | N15: =IF(H15>0,G15+H15-I15-J15-K15-L15-M15,G15-I15-J15-K15-L15-M15) -> 40000 | O15: =G15+H15-J15-I15-K15-L15-M15 -> 40000 | P15: =IF(G15+H15<0,0,G15+H15) -> 40000 | S15: 46225 | X15: 7 | Y15: 7 | Z15: =IF(N15<0,0,N15) -> 40000 | AH15: 1 | AI15: =IF(F15<=6,15,25) -> 25 | AJ15: =IF(O15<>0,25,15) -> 25 | AK15: =IF(AI15-T15=24,1,0) -> 0 | AL15: =IF(AH15-AK15=AH15,0,AH15) -> 0 | AM15: =IF(AK15<>0,U15,0) -> 0 | AN15: =IF(AK15=1,O15,0) -> 0 | AO15: =IF(AI15-T15=14,1,0) -> 0 | AP15: =IF(AH15-AO15=AH15,0,AH15) -> 0 | AQ15: =IF(AO15<>0,U15,0) -> 0 | AR15: =IF(AO15=1,O15,0) -> 0 | AS15: =IF(SUM(I15:M15)<>0,1,0) -> 0 | AT15: =AS15 -> 0 | AU15: =IF(O15>0,1,0) -> 1 | AV15: =IF(AK15+AO15+AU15=1,AU15,0) -> 1 | AW15: =IF(AI15-AV15=24,1,0) -> 1 | AX15: =IF(AH15-AW15=AH15,0,AH15) -> 1 | AY15: =IF(AW15=1,O15,0) -> 40000 | AZ15: =IF(AY15-BA15<>0,AY15,0) -> 40000 | BA15: =IF(AY15<0,AY15,0) -> 0 | BB15: =IF(AI15-AV15=14,1,0) -> 0 | BC15: =IF(AH15-BB15=AH15,0,AH15) -> 0 | BD15: =IF(BB15=1,O15,0) -> 0 | BE15: =IF(BD15<0,BD15,0) -> 0 | BF15: =IF(BD15-BE15<>0,BD15,0) -> 0
A16: 1871 | B16: FERNANDEZ GORIA GABRIELA CELESTE | C16: 264-5676031 | D16: RIVADAVIA | E16: 9891 | F16: 69 | G16: 35000 | H16: 0 | N16: =IF(H16>0,G16+H16-I16-J16-K16-L16-M16,G16-I16-J16-K16-L16-M16) -> 35000 | O16: =G16+H16-J16-I16-K16-L16-M16 -> 35000 | P16: =IF(G16+H16<0,0,G16+H16) -> 35000 | S16: 46234 | X16: 7 | Y16: 7 | Z16: =IF(N16<0,0,N16) -> 35000 | AH16: 1 | AI16: =IF(F16<=6,15,25) -> 25 | AJ16: =IF(O16<>0,25,15) -> 25 | AK16: =IF(AI16-T16=24,1,0) -> 0 | AL16: =IF(AH16-AK16=AH16,0,AH16) -> 0 | AM16: =IF(AK16<>0,U16,0) -> 0 | AN16: =IF(AK16=1,O16,0) -> 0 | AO16: =IF(AI16-T16=14,1,0) -> 0 | AP16: =IF(AH16-AO16=AH16,0,AH16) -> 0 | AQ16: =IF(AO16<>0,U16,0) -> 0 | AR16: =IF(AO16=1,O16,0) -> 0 | AS16: =IF(SUM(I16:M16)<>0,1,0) -> 0 | AT16: =AS16 -> 0 | AU16: =IF(O16>0,1,0) -> 1 | AV16: =IF(AK16+AO16+AU16=1,AU16,0) -> 1 | AW16: =IF(AI16-AV16=24,1,0) -> 1 | AX16: =IF(AH16-AW16=AH16,0,AH16) -> 1 | AY16: =IF(AW16=1,O16,0) -> 35000 | AZ16: =IF(AY16-BA16<>0,AY16,0) -> 35000 | BA16: =IF(AY16<0,AY16,0) -> 0 | BB16: =IF(AI16-AV16=14,1,0) -> 0 | BC16: =IF(AH16-BB16=AH16,0,AH16) -> 0 | BD16: =IF(BB16=1,O16,0) -> 0 | BE16: =IF(BD16<0,BD16,0) -> 0 | BF16: =IF(BD16-BE16<>0,BD16,0) -> 0
A17: 1900 | B17: CERDA FABIAN ALEJANDRO | C17: 264-6621777 | D17: CHIMBAS | E17: 10012 | F17: 69 | G17: 60000 | H17: -60000 | N17: =IF(H17>0,G17+H17-I17-J17-K17-L17-M17,G17-I17-J17-K17-L17-M17) -> 60000 | O17: =G17+H17-J17-I17-K17-L17-M17 -> 0 | P17: =IF(G17+H17<0,0,G17+H17) -> 0 | S17: 46234 | X17: 7 | Y17: 7 | Z17: =IF(N17<0,0,N17) -> 60000 | AH17: 1 | AI17: =IF(F17<=6,15,25) -> 25 | AJ17: =IF(O17<>0,25,15) -> 15 | AK17: =IF(AI17-T17=24,1,0) -> 0 | AL17: =IF(AH17-AK17=AH17,0,AH17) -> 0 | AM17: =IF(AK17<>0,U17,0) -> 0 | AN17: =IF(AK17=1,O17,0) -> 0 | AO17: =IF(AI17-T17=14,1,0) -> 0 | AP17: =IF(AH17-AO17=AH17,0,AH17) -> 0 | AQ17: =IF(AO17<>0,U17,0) -> 0 | AR17: =IF(AO17=1,O17,0) -> 0 | AS17: =IF(SUM(I17:M17)<>0,1,0) -> 0 | AT17: =AS17 -> 0 | AU17: =IF(O17>0,1,0) -> 0 | AV17: =IF(AK17+AO17+AU17=1,AU17,0) -> 0 | AW17: =IF(AI17-AV17=24,1,0) -> 0 | AX17: =IF(AH17-AW17=AH17,0,AH17) -> 0 | AY17: =IF(AW17=1,O17,0) -> 0 | AZ17: =IF(AY17-BA17<>0,AY17,0) -> 0 | BA17: =IF(AY17<0,AY17,0) -> 0 | BB17: =IF(AI17-AV17=14,1,0) -> 0 | BC17: =IF(AH17-BB17=AH17,0,AH17) -> 0 | BD17: =IF(BB17=1,O17,0) -> 0 | BE17: =IF(BD17<0,BD17,0) -> 0 | BF17: =IF(BD17-BE17<>0,BD17,0) -> 0
A18: 1954 | B18: GUTIERREZ ATENCIO ELDA VANESA | C18: 264-4580614 | D18: ZONDA | E18: 10045 | F18: 67 | G18: 50000 | H18: -30000 | N18: =IF(H18>0,G18+H18-I18-J18-K18-L18-M18,G18-I18-J18-K18-L18-M18) -> 50000 | O18: =G18+H18-J18-I18-K18-L18-M18 -> 20000 | P18: =IF(G18+H18<0,0,G18+H18) -> 20000 | S18: 46204 | X18: 7 | Y18: 7 | Z18: =IF(N18<0,0,N18) -> 50000 | AH18: 1 | AI18: =IF(F18<=6,15,25) -> 25 | AJ18: =IF(O18<>0,25,15) -> 25 | AK18: =IF(AI18-T18=24,1,0) -> 0 | AL18: =IF(AH18-AK18=AH18,0,AH18) -> 0 | AM18: =IF(AK18<>0,U18,0) -> 0 | AN18: =IF(AK18=1,O18,0) -> 0 | AO18: =IF(AI18-T18=14,1,0) -> 0 | AP18: =IF(AH18-AO18=AH18,0,AH18) -> 0 | AQ18: =IF(AO18<>0,U18,0) -> 0 | AR18: =IF(AO18=1,O18,0) -> 0 | AS18: =IF(SUM(I18:M18)<>0,1,0) -> 0 | AT18: =AS18 -> 0 | AU18: =IF(O18>0,1,0) -> 1 | AV18: =IF(AK18+AO18+AU18=1,AU18,0) -> 1 | AW18: =IF(AI18-AV18=24,1,0) -> 1 | AX18: =IF(AH18-AW18=AH18,0,AH18) -> 1 | AY18: =IF(AW18=1,O18,0) -> 20000 | AZ18: =IF(AY18-BA18<>0,AY18,0) -> 20000 | BA18: =IF(AY18<0,AY18,0) -> 0 | BB18: =IF(AI18-AV18=14,1,0) -> 0 | BC18: =IF(AH18-BB18=AH18,0,AH18) -> 0 | BD18: =IF(BB18=1,O18,0) -> 0 | BE18: =IF(BD18<0,BD18,0) -> 0 | BF18: =IF(BD18-BE18<>0,BD18,0) -> 0
A19: 1999 | B19: PEREZ JOSE ISMAEL | C19: 264-5122570 | D19: SAN JUAN | E19: 10192 | F19: 66 | G19: 60000 | H19: -75000 | N19: =IF(H19>0,G19+H19-I19-J19-K19-L19-M19,G19-I19-J19-K19-L19-M19) -> 60000 | O19: =G19+H19-J19-I19-K19-L19-M19 -> -15000 | P19: =IF(G19+H19<0,0,G19+H19) -> 0 | S19: 46213 | X19: 7 | Y19: 7 | Z19: =IF(N19<0,0,N19) -> 60000 | AH19: 1 | AI19: =IF(F19<=6,15,25) -> 25 | AJ19: =IF(O19<>0,25,15) -> 25 | AK19: =IF(AI19-T19=24,1,0) -> 0 | AL19: =IF(AH19-AK19=AH19,0,AH19) -> 0 | AM19: =IF(AK19<>0,U19,0) -> 0 | AN19: =IF(AK19=1,O19,0) -> 0 | AO19: =IF(AI19-T19=14,1,0) -> 0 | AP19: =IF(AH19-AO19=AH19,0,AH19) -> 0 | AQ19: =IF(AO19<>0,U19,0) -> 0 | AR19: =IF(AO19=1,O19,0) -> 0 | AS19: =IF(SUM(I19:M19)<>0,1,0) -> 0 | AT19: =AS19 -> 0 | AU19: =IF(O19>0,1,0) -> 0 | AV19: =IF(AK19+AO19+AU19=1,AU19,0) -> 0 | AW19: =IF(AI19-AV19=24,1,0) -> 0 | AX19: =IF(AH19-AW19=AH19,0,AH19) -> 0 | AY19: =IF(AW19=1,O19,0) -> 0 | AZ19: =IF(AY19-BA19<>0,AY19,0) -> 0 | BA19: =IF(AY19<0,AY19,0) -> 0 | BB19: =IF(AI19-AV19=14,1,0) -> 0 | BC19: =IF(AH19-BB19=AH19,0,AH19) -> 0 | BD19: =IF(BB19=1,O19,0) -> 0 | BE19: =IF(BD19<0,BD19,0) -> 0 | BF19: =IF(BD19-BE19<>0,BD19,0) -> 0
A20: 2010 | B20: PEREYRA NUVIA CELESTE | C20: 264-4829505 | D20: SANTA LUCIA | E20: 10206 | F20: 66 | G20: 30000 | H20: -28000 | N20: =IF(H20>0,G20+H20-I20-J20-K20-L20-M20,G20-I20-J20-K20-L20-M20) -> 30000 | O20: =G20+H20-J20-I20-K20-L20-M20 -> 2000 | P20: =IF(G20+H20<0,0,G20+H20) -> 2000 | S20: 46234 | X20: 7 | Y20: 7 | Z20: =IF(N20<0,0,N20) -> 30000 | AH20: 1 | AI20: =IF(F20<=6,15,25) -> 25 | AJ20: =IF(O20<>0,25,15) -> 25 | AK20: =IF(AI20-T20=24,1,0) -> 0 | AL20: =IF(AH20-AK20=AH20,0,AH20) -> 0 | AM20: =IF(AK20<>0,U20,0) -> 0 | AN20: =IF(AK20=1,O20,0) -> 0 | AO20: =IF(AI20-T20=14,1,0) -> 0 | AP20: =IF(AH20-AO20=AH20,0,AH20) -> 0 | AQ20: =IF(AO20<>0,U20,0) -> 0 | AR20: =IF(AO20=1,O20,0) -> 0 | AS20: =IF(SUM(I20:M20)<>0,1,0) -> 0 | AT20: =AS20 -> 0 | AU20: =IF(O20>0,1,0) -> 1 | AV20: =IF(AK20+AO20+AU20=1,AU20,0) -> 1 | AW20: =IF(AI20-AV20=24,1,0) -> 1 | AX20: =IF(AH20-AW20=AH20,0,AH20) -> 1 | AY20: =IF(AW20=1,O20,0) -> 2000 | AZ20: =IF(AY20-BA20<>0,AY20,0) -> 2000 | BA20: =IF(AY20<0,AY20,0) -> 0 | BB20: =IF(AI20-AV20=14,1,0) -> 0 | BC20: =IF(AH20-BB20=AH20,0,AH20) -> 0 | BD20: =IF(BB20=1,O20,0) -> 0 | BE20: =IF(BD20<0,BD20,0) -> 0 | BF20: =IF(BD20-BE20<>0,BD20,0) -> 0
A21: 2015 | B21: ELIZONDO MARIO SANTIAGO | C21: 264-5061888 | D21: ALBARDON | E21: 10189 | F21: 66 | G21: 70000 | H21: -118000 | N21: =IF(H21>0,G21+H21-I21-J21-K21-L21-M21,G21-I21-J21-K21-L21-M21) -> 70000 | O21: =G21+H21-J21-I21-K21-L21-M21 -> -48000 | P21: =IF(G21+H21<0,0,G21+H21) -> 0 | S21: 70000 | X21: 7 | Y21: 7 | Z21: =IF(N21<0,0,N21) -> 70000 | AH21: 1 | AI21: =IF(F21<=6,15,25) -> 25 | AJ21: =IF(O21<>0,25,15) -> 25 | AK21: =IF(AI21-T21=24,1,0) -> 0 | AL21: =IF(AH21-AK21=AH21,0,AH21) -> 0 | AM21: =IF(AK21<>0,U21,0) -> 0 | AN21: =IF(AK21=1,O21,0) -> 0 | AO21: =IF(AI21-T21=14,1,0) -> 0 | AP21: =IF(AH21-AO21=AH21,0,AH21) -> 0 | AQ21: =IF(AO21<>0,U21,0) -> 0 | AR21: =IF(AO21=1,O21,0) -> 0 | AS21: =IF(SUM(I21:M21)<>0,1,0) -> 0 | AT21: =AS21 -> 0 | AU21: =IF(O21>0,1,0) -> 0 | AV21: =IF(AK21+AO21+AU21=1,AU21,0) -> 0 | AW21: =IF(AI21-AV21=24,1,0) -> 0 | AX21: =IF(AH21-AW21=AH21,0,AH21) -> 0 | AY21: =IF(AW21=1,O21,0) -> 0 | AZ21: =IF(AY21-BA21<>0,AY21,0) -> 0 | BA21: =IF(AY21<0,AY21,0) -> 0 | BB21: =IF(AI21-AV21=14,1,0) -> 0 | BC21: =IF(AH21-BB21=AH21,0,AH21) -> 0 | BD21: =IF(BB21=1,O21,0) -> 0 | BE21: =IF(BD21<0,BD21,0) -> 0 | BF21: =IF(BD21-BE21<>0,BD21,0) -> 0
A22: 2024 | B22: BUENO VALERIA VANESA | C22: 264-5435239 | D22: RAWSON | E22: 10095 | F22: 66 | G22: 30000 | H22: -24000 | N22: =IF(H22>0,G22+H22-I22-J22-K22-L22-M22,G22-I22-J22-K22-L22-M22) -> 30000 | O22: =G22+H22-J22-I22-K22-L22-M22 -> 6000 | P22: =IF(G22+H22<0,0,G22+H22) -> 6000 | S22: 46209 | X22: 7 | Y22: 7 | Z22: =IF(N22<0,0,N22) -> 30000 | AH22: 1 | AI22: =IF(F22<=6,15,25) -> 25 | AJ22: =IF(O22<>0,25,15) -> 25 | AK22: =IF(AI22-T22=24,1,0) -> 0 | AL22: =IF(AH22-AK22=AH22,0,AH22) -> 0 | AM22: =IF(AK22<>0,U22,0) -> 0 | AN22: =IF(AK22=1,O22,0) -> 0 | AO22: =IF(AI22-T22=14,1,0) -> 0 | AP22: =IF(AH22-AO22=AH22,0,AH22) -> 0 | AQ22: =IF(AO22<>0,U22,0) -> 0 | AR22: =IF(AO22=1,O22,0) -> 0 | AS22: =IF(SUM(I22:M22)<>0,1,0) -> 0 | AT22: =AS22 -> 0 | AU22: =IF(O22>0,1,0) -> 1 | AV22: =IF(AK22+AO22+AU22=1,AU22,0) -> 1 | AW22: =IF(AI22-AV22=24,1,0) -> 1 | AX22: =IF(AH22-AW22=AH22,0,AH22) -> 1 | AY22: =IF(AW22=1,O22,0) -> 6000 | AZ22: =IF(AY22-BA22<>0,AY22,0) -> 6000 | BA22: =IF(AY22<0,AY22,0) -> 0 | BB22: =IF(AI22-AV22=14,1,0) -> 0 | BC22: =IF(AH22-BB22=AH22,0,AH22) -> 0 | BD22: =IF(BB22=1,O22,0) -> 0 | BE22: =IF(BD22<0,BD22,0) -> 0 | BF22: =IF(BD22-BE22<>0,BD22,0) -> 0
A23: 2095 | B23: PAREDES HUGO ARIEL | C23: 264-7409479 | D23: RODEO | E23: 10288 | F23: 64 | G23: 65000 | H23: 0 | N23: =IF(H23>0,G23+H23-I23-J23-K23-L23-M23,G23-I23-J23-K23-L23-M23) -> 65000 | O23: =G23+H23-J23-I23-K23-L23-M23 -> 65000 | P23: =IF(G23+H23<0,0,G23+H23) -> 65000 | S23: 46211 | X23: 7 | Y23: 7 | Z23: =IF(N23<0,0,N23) -> 65000 | AH23: 1 | AI23: =IF(F23<=6,15,25) -> 25 | AJ23: =IF(O23<>0,25,15) -> 25 | AK23: =IF(AI23-T23=24,1,0) -> 0 | AL23: =IF(AH23-AK23=AH23,0,AH23) -> 0 | AM23: =IF(AK23<>0,U23,0) -> 0 | AN23: =IF(AK23=1,O23,0) -> 0 | AO23: =IF(AI23-T23=14,1,0) -> 0 | AP23: =IF(AH23-AO23=AH23,0,AH23) -> 0 | AQ23: =IF(AO23<>0,U23,0) -> 0 | AR23: =IF(AO23=1,O23,0) -> 0 | AS23: =IF(SUM(I23:M23)<>0,1,0) -> 0 | AT23: =AS23 -> 0 | AU23: =IF(O23>0,1,0) -> 1 | AV23: =IF(AK23+AO23+AU23=1,AU23,0) -> 1 | AW23: =IF(AI23-AV23=24,1,0) -> 1 | AX23: =IF(AH23-AW23=AH23,0,AH23) -> 1 | AY23: =IF(AW23=1,O23,0) -> 65000 | AZ23: =IF(AY23-BA23<>0,AY23,0) -> 65000 | BA23: =IF(AY23<0,AY23,0) -> 0 | BB23: =IF(AI23-AV23=14,1,0) -> 0 | BC23: =IF(AH23-BB23=AH23,0,AH23) -> 0 | BD23: =IF(BB23=1,O23,0) -> 0 | BE23: =IF(BD23<0,BD23,0) -> 0 | BF23: =IF(BD23-BE23<>0,BD23,0) -> 0
A24: 2119 | B24: RIVEROS HUGO GUSTAVO | C24: 264-4816549 | D24: CHIMBAS | E24: 10430 | F24: 63 | G24: 30000 | H24: 0 | N24: =IF(H24>0,G24+H24-I24-J24-K24-L24-M24,G24-I24-J24-K24-L24-M24) -> 30000 | O24: =G24+H24-J24-I24-K24-L24-M24 -> 30000 | P24: =IF(G24+H24<0,0,G24+H24) -> 30000 | S24: 46176 | X24: 7 | Y24: 7 | Z24: =IF(N24<0,0,N24) -> 30000 | AH24: 1 | AI24: =IF(F24<=6,15,25) -> 25 | AJ24: =IF(O24<>0,25,15) -> 25 | AK24: =IF(AI24-T24=24,1,0) -> 0 | AL24: =IF(AH24-AK24=AH24,0,AH24) -> 0 | AM24: =IF(AK24<>0,U24,0) -> 0 | AN24: =IF(AK24=1,O24,0) -> 0 | AO24: =IF(AI24-T24=14,1,0) -> 0 | AP24: =IF(AH24-AO24=AH24,0,AH24) -> 0 | AQ24: =IF(AO24<>0,U24,0) -> 0 | AR24: =IF(AO24=1,O24,0) -> 0 | AS24: =IF(SUM(I24:M24)<>0,1,0) -> 0 | AT24: =AS24 -> 0 | AU24: =IF(O24>0,1,0) -> 1 | AV24: =IF(AK24+AO24+AU24=1,AU24,0) -> 1 | AW24: =IF(AI24-AV24=24,1,0) -> 1 | AX24: =IF(AH24-AW24=AH24,0,AH24) -> 1 | AY24: =IF(AW24=1,O24,0) -> 30000 | AZ24: =IF(AY24-BA24<>0,AY24,0) -> 30000 | BA24: =IF(AY24<0,AY24,0) -> 0 | BB24: =IF(AI24-AV24=14,1,0) -> 0 | BC24: =IF(AH24-BB24=AH24,0,AH24) -> 0 | BD24: =IF(BB24=1,O24,0) -> 0 | BE24: =IF(BD24<0,BD24,0) -> 0 | BF24: =IF(BD24-BE24<>0,BD24,0) -> 0
A25: 2120 | B25: CALDERON ROSANA ANALIA | C25: 264-5315461 | D25: CHIMBAS | E25: 10281 | F25: 63 | G25: 500000 | H25: -80000 | N25: =IF(H25>0,G25+H25-I25-J25-K25-L25-M25,G25-I25-J25-K25-L25-M25) -> 500000 | O25: =G25+H25-J25-I25-K25-L25-M25 -> 420000 | P25: =IF(G25+H25<0,0,G25+H25) -> 420000 | S25: 46176 | X25: 7 | Y25: 7 | Z25: =IF(N25<0,0,N25) -> 500000 | AH25: 1 | AI25: =IF(F25<=6,15,25) -> 25 | AJ25: =IF(O25<>0,25,15) -> 25 | AK25: =IF(AI25-T25=24,1,0) -> 0 | AL25: =IF(AH25-AK25=AH25,0,AH25) -> 0 | AM25: =IF(AK25<>0,U25,0) -> 0 | AN25: =IF(AK25=1,O25,0) -> 0 | AO25: =IF(AI25-T25=14,1,0) -> 0 | AP25: =IF(AH25-AO25=AH25,0,AH25) -> 0 | AQ25: =IF(AO25<>0,U25,0) -> 0 | AR25: =IF(AO25=1,O25,0) -> 0 | AS25: =IF(SUM(I25:M25)<>0,1,0) -> 0 | AT25: =AS25 -> 0 | AU25: =IF(O25>0,1,0) -> 1 | AV25: =IF(AK25+AO25+AU25=1,AU25,0) -> 1 | AW25: =IF(AI25-AV25=24,1,0) -> 1 | AX25: =IF(AH25-AW25=AH25,0,AH25) -> 1 | AY25: =IF(AW25=1,O25,0) -> 420000 | AZ25: =IF(AY25-BA25<>0,AY25,0) -> 420000 | BA25: =IF(AY25<0,AY25,0) -> 0 | BB25: =IF(AI25-AV25=14,1,0) -> 0 | BC25: =IF(AH25-BB25=AH25,0,AH25) -> 0 | BD25: =IF(BB25=1,O25,0) -> 0 | BE25: =IF(BD25<0,BD25,0) -> 0 | BF25: =IF(BD25-BE25<>0,BD25,0) -> 0
A26: 2207 | B26: ORELLANO VERA YESICA BEATRIZ | C26: 2644656518 | D26: RAWSON | E26: 10449 | F26: 61 | G26: 60000 | H26: 0 | N26: =IF(H26>0,G26+H26-I26-J26-K26-L26-M26,G26-I26-J26-K26-L26-M26) -> 60000 | O26: =G26+H26-J26-I26-K26-L26-M26 -> 60000 | P26: =IF(G26+H26<0,0,G26+H26) -> 60000 | S26: 46209 | X26: 7 | Y26: 7 | Z26: =IF(N26<0,0,N26) -> 60000 | AH26: 1 | AI26: =IF(F26<=6,15,25) -> 25 | AJ26: =IF(O26<>0,25,15) -> 25 | AK26: =IF(AI26-T26=24,1,0) -> 0 | AL26: =IF(AH26-AK26=AH26,0,AH26) -> 0 | AM26: =IF(AK26<>0,U26,0) -> 0 | AN26: =IF(AK26=1,O26,0) -> 0 | AO26: =IF(AI26-T26=14,1,0) -> 0 | AP26: =IF(AH26-AO26=AH26,0,AH26) -> 0 | AQ26: =IF(AO26<>0,U26,0) -> 0 | AR26: =IF(AO26=1,O26,0) -> 0 | AS26: =IF(SUM(I26:M26)<>0,1,0) -> 0 | AT26: =AS26 -> 0 | AU26: =IF(O26>0,1,0) -> 1 | AV26: =IF(AK26+AO26+AU26=1,AU26,0) -> 1 | AW26: =IF(AI26-AV26=24,1,0) -> 1 | AX26: =IF(AH26-AW26=AH26,0,AH26) -> 1 | AY26: =IF(AW26=1,O26,0) -> 60000 | AZ26: =IF(AY26-BA26<>0,AY26,0) -> 60000 | BA26: =IF(AY26<0,AY26,0) -> 0 | BB26: =IF(AI26-AV26=14,1,0) -> 0 | BC26: =IF(AH26-BB26=AH26,0,AH26) -> 0 | BD26: =IF(BB26=1,O26,0) -> 0 | BE26: =IF(BD26<0,BD26,0) -> 0 | BF26: =IF(BD26-BE26<>0,BD26,0) -> 0
A27: 2326 | B27: RUIZ FABIANA ANDREA | C27: 264-4519628 | D27: RAWSON | E27: 11089 | F27: 59 | G27: 60000 | H27: -10000 | N27: =IF(H27>0,G27+H27-I27-J27-K27-L27-M27,G27-I27-J27-K27-L27-M27) -> 60000 | O27: =G27+H27-J27-I27-K27-L27-M27 -> 50000 | P27: =IF(G27+H27<0,0,G27+H27) -> 50000 | S27: 46213 | X27: 7 | Y27: 7 | Z27: =IF(N27<0,0,N27) -> 60000 | AH27: 1 | AI27: =IF(F27<=6,15,25) -> 25 | AJ27: =IF(O27<>0,25,15) -> 25 | AK27: =IF(AI27-T27=24,1,0) -> 0 | AL27: =IF(AH27-AK27=AH27,0,AH27) -> 0 | AM27: =IF(AK27<>0,U27,0) -> 0 | AN27: =IF(AK27=1,O27,0) -> 0 | AO27: =IF(AI27-T27=14,1,0) -> 0 | AP27: =IF(AH27-AO27=AH27,0,AH27) -> 0 | AQ27: =IF(AO27<>0,U27,0) -> 0 | AR27: =IF(AO27=1,O27,0) -> 0 | AS27: =IF(SUM(I27:M27)<>0,1,0) -> 0 | AT27: =AS27 -> 0 | AU27: =IF(O27>0,1,0) -> 1 | AV27: =IF(AK27+AO27+AU27=1,AU27,0) -> 1 | AW27: =IF(AI27-AV27=24,1,0) -> 1 | AX27: =IF(AH27-AW27=AH27,0,AH27) -> 1 | AY27: =IF(AW27=1,O27,0) -> 50000 | AZ27: =IF(AY27-BA27<>0,AY27,0) -> 50000 | BA27: =IF(AY27<0,AY27,0) -> 0 | BB27: =IF(AI27-AV27=14,1,0) -> 0 | BC27: =IF(AH27-BB27=AH27,0,AH27) -> 0 | BD27: =IF(BB27=1,O27,0) -> 0 | BE27: =IF(BD27<0,BD27,0) -> 0 | BF27: =IF(BD27-BE27<>0,BD27,0) -> 0
A28: 2339 | B28: ESCUDERO ANGELA VICTORIA | C28: 264-5534094 | D28: 9 DE JULIO | E28: 11193 | F28: 59 | G28: 60000 | H28: 0 | N28: =IF(H28>0,G28+H28-I28-J28-K28-L28-M28,G28-I28-J28-K28-L28-M28) -> 60000 | O28: =G28+H28-J28-I28-K28-L28-M28 -> 60000 | P28: =IF(G28+H28<0,0,G28+H28) -> 60000 | S28: 46233 | X28: 7 | Y28: 7 | Z28: =IF(N28<0,0,N28) -> 60000 | AH28: 1 | AI28: =IF(F28<=6,15,25) -> 25 | AJ28: =IF(O28<>0,25,15) -> 25 | AK28: =IF(AI28-T28=24,1,0) -> 0 | AL28: =IF(AH28-AK28=AH28,0,AH28) -> 0 | AM28: =IF(AK28<>0,U28,0) -> 0 | AN28: =IF(AK28=1,O28,0) -> 0 | AO28: =IF(AI28-T28=14,1,0) -> 0 | AP28: =IF(AH28-AO28=AH28,0,AH28) -> 0 | AQ28: =IF(AO28<>0,U28,0) -> 0 | AR28: =IF(AO28=1,O28,0) -> 0 | AS28: =IF(SUM(I28:M28)<>0,1,0) -> 0 | AT28: =AS28 -> 0 | AU28: =IF(O28>0,1,0) -> 1 | AV28: =IF(AK28+AO28+AU28=1,AU28,0) -> 1 | AW28: =IF(AI28-AV28=24,1,0) -> 1 | AX28: =IF(AH28-AW28=AH28,0,AH28) -> 1 | AY28: =IF(AW28=1,O28,0) -> 60000 | AZ28: =IF(AY28-BA28<>0,AY28,0) -> 60000 | BA28: =IF(AY28<0,AY28,0) -> 0 | BB28: =IF(AI28-AV28=14,1,0) -> 0 | BC28: =IF(AH28-BB28=AH28,0,AH28) -> 0 | BD28: =IF(BB28=1,O28,0) -> 0 | BE28: =IF(BD28<0,BD28,0) -> 0 | BF28: =IF(BD28-BE28<>0,BD28,0) -> 0
A29: 2360 | B29: NUÑEZ CHIRINO VIVIANA DEL CARMEN | C29: 264-6730916 | D29: POCITOS | E29: 11245 | F29: 59 | G29: 60000 | H29: 0 | N29: =IF(H29>0,G29+H29-I29-J29-K29-L29-M29,G29-I29-J29-K29-L29-M29) -> 60000 | O29: =G29+H29-J29-I29-K29-L29-M29 -> 60000 | P29: =IF(G29+H29<0,0,G29+H29) -> 60000 | S29: 46216 | X29: 7 | Y29: 7 | Z29: =IF(N29<0,0,N29) -> 60000 | AH29: 1 | AI29: =IF(F29<=6,15,25) -> 25 | AJ29: =IF(O29<>0,25,15) -> 25 | AK29: =IF(AI29-T29=24,1,0) -> 0 | AL29: =IF(AH29-AK29=AH29,0,AH29) -> 0 | AM29: =IF(AK29<>0,U29,0) -> 0 | AN29: =IF(AK29=1,O29,0) -> 0 | AO29: =IF(AI29-T29=14,1,0) -> 0 | AP29: =IF(AH29-AO29=AH29,0,AH29) -> 0 | AQ29: =IF(AO29<>0,U29,0) -> 0 | AR29: =IF(AO29=1,O29,0) -> 0 | AS29: =IF(SUM(I29:M29)<>0,1,0) -> 0 | AT29: =AS29 -> 0 | AU29: =IF(O29>0,1,0) -> 1 | AV29: =IF(AK29+AO29+AU29=1,AU29,0) -> 1 | AW29: =IF(AI29-AV29=24,1,0) -> 1 | AX29: =IF(AH29-AW29=AH29,0,AH29) -> 1 | AY29: =IF(AW29=1,O29,0) -> 60000 | AZ29: =IF(AY29-BA29<>0,AY29,0) -> 60000 | BA29: =IF(AY29<0,AY29,0) -> 0 | BB29: =IF(AI29-AV29=14,1,0) -> 0 | BC29: =IF(AH29-BB29=AH29,0,AH29) -> 0 | BD29: =IF(BB29=1,O29,0) -> 0 | BE29: =IF(BD29<0,BD29,0) -> 0 | BF29: =IF(BD29-BE29<>0,BD29,0) -> 0
A30: 2374 | B30: ARABENA HECTOR ARIEL | C30: 264-4742020 | D30: SAN JUAN | E30: 11219 | F30: 58 | G30: 60000 | H30: -4500 | N30: =IF(H30>0,G30+H30-I30-J30-K30-L30-M30,G30-I30-J30-K30-L30-M30) -> 60000 | O30: =G30+H30-J30-I30-K30-L30-M30 -> 55500 | P30: =IF(G30+H30<0,0,G30+H30) -> 55500 | S30: 46234 | X30: 7 | Y30: 7 | Z30: =IF(N30<0,0,N30) -> 60000 | AH30: 1 | AI30: =IF(F30<=6,15,25) -> 25 | AJ30: =IF(O30<>0,25,15) -> 25 | AK30: =IF(AI30-T30=24,1,0) -> 0 | AL30: =IF(AH30-AK30=AH30,0,AH30) -> 0 | AM30: =IF(AK30<>0,U30,0) -> 0 | AN30: =IF(AK30=1,O30,0) -> 0 | AO30: =IF(AI30-T30=14,1,0) -> 0 | AP30: =IF(AH30-AO30=AH30,0,AH30) -> 0 | AQ30: =IF(AO30<>0,U30,0) -> 0 | AR30: =IF(AO30=1,O30,0) -> 0 | AS30: =IF(SUM(I30:M30)<>0,1,0) -> 0 | AT30: =AS30 -> 0 | AU30: =IF(O30>0,1,0) -> 1 | AV30: =IF(AK30+AO30+AU30=1,AU30,0) -> 1 | AW30: =IF(AI30-AV30=24,1,0) -> 1 | AX30: =IF(AH30-AW30=AH30,0,AH30) -> 1 | AY30: =IF(AW30=1,O30,0) -> 55500 | AZ30: =IF(AY30-BA30<>0,AY30,0) -> 55500 | BA30: =IF(AY30<0,AY30,0) -> 0 | BB30: =IF(AI30-AV30=14,1,0) -> 0 | BC30: =IF(AH30-BB30=AH30,0,AH30) -> 0 | BD30: =IF(BB30=1,O30,0) -> 0 | BE30: =IF(BD30<0,BD30,0) -> 0 | BF30: =IF(BD30-BE30<>0,BD30,0) -> 0
A31: 2461 | B31: ANDRES ESPINDOLA WALTER DARIO | C31: 264-4158966 | D31: POCITOS | E31: 11305 | F31: 57 | G31: 55000 | H31: 0 | N31: =IF(H31>0,G31+H31-I31-J31-K31-L31-M31,G31-I31-J31-K31-L31-M31) -> 55000 | O31: =G31+H31-J31-I31-K31-L31-M31 -> 55000 | P31: =IF(G31+H31<0,0,G31+H31) -> 55000 | S31: 46217 | X31: 7 | Y31: 7 | Z31: =IF(N31<0,0,N31) -> 55000 | AH31: 1 | AI31: =IF(F31<=6,15,25) -> 25 | AJ31: =IF(O31<>0,25,15) -> 25 | AK31: =IF(AI31-T31=24,1,0) -> 0 | AL31: =IF(AH31-AK31=AH31,0,AH31) -> 0 | AM31: =IF(AK31<>0,U31,0) -> 0 | AN31: =IF(AK31=1,O31,0) -> 0 | AO31: =IF(AI31-T31=14,1,0) -> 0 | AP31: =IF(AH31-AO31=AH31,0,AH31) -> 0 | AQ31: =IF(AO31<>0,U31,0) -> 0 | AR31: =IF(AO31=1,O31,0) -> 0 | AS31: =IF(SUM(I31:M31)<>0,1,0) -> 0 | AT31: =AS31 -> 0 | AU31: =IF(O31>0,1,0) -> 1 | AV31: =IF(AK31+AO31+AU31=1,AU31,0) -> 1 | AW31: =IF(AI31-AV31=24,1,0) -> 1 | AX31: =IF(AH31-AW31=AH31,0,AH31) -> 1 | AY31: =IF(AW31=1,O31,0) -> 55000 | AZ31: =IF(AY31-BA31<>0,AY31,0) -> 55000 | BA31: =IF(AY31<0,AY31,0) -> 0 | BB31: =IF(AI31-AV31=14,1,0) -> 0 | BC31: =IF(AH31-BB31=AH31,0,AH31) -> 0 | BD31: =IF(BB31=1,O31,0) -> 0 | BE31: =IF(BD31<0,BD31,0) -> 0 | BF31: =IF(BD31-BE31<>0,BD31,0) -> 0
A32: 2486 | B32: ARIAS YESICA TAMARA | C32: 299-5486406 | D32: NEUQUEN | E32: 11347 | F32: 56 | G32: 40000 | H32: -45000 | N32: =IF(H32>0,G32+H32-I32-J32-K32-L32-M32,G32-I32-J32-K32-L32-M32) -> 40000 | O32: =G32+H32-J32-I32-K32-L32-M32 -> -5000 | P32: =IF(G32+H32<0,0,G32+H32) -> 0 | S32: 46216 | X32: 7 | Y32: 7 | Z32: =IF(N32<0,0,N32) -> 40000 | AH32: 1 | AI32: =IF(F32<=6,15,25) -> 25 | AJ32: =IF(O32<>0,25,15) -> 25 | AK32: =IF(AI32-T32=24,1,0) -> 0 | AL32: =IF(AH32-AK32=AH32,0,AH32) -> 0 | AM32: =IF(AK32<>0,U32,0) -> 0 | AN32: =IF(AK32=1,O32,0) -> 0 | AO32: =IF(AI32-T32=14,1,0) -> 0 | AP32: =IF(AH32-AO32=AH32,0,AH32) -> 0 | AQ32: =IF(AO32<>0,U32,0) -> 0 | AR32: =IF(AO32=1,O32,0) -> 0 | AS32: =IF(SUM(I32:M32)<>0,1,0) -> 0 | AT32: =AS32 -> 0 | AU32: =IF(O32>0,1,0) -> 0 | AV32: =IF(AK32+AO32+AU32=1,AU32,0) -> 0 | AW32: =IF(AI32-AV32=24,1,0) -> 0 | AX32: =IF(AH32-AW32=AH32,0,AH32) -> 0 | AY32: =IF(AW32=1,O32,0) -> 0 | AZ32: =IF(AY32-BA32<>0,AY32,0) -> 0 | BA32: =IF(AY32<0,AY32,0) -> 0 | BB32: =IF(AI32-AV32=14,1,0) -> 0 | BC32: =IF(AH32-BB32=AH32,0,AH32) -> 0 | BD32: =IF(BB32=1,O32,0) -> 0 | BE32: =IF(BD32<0,BD32,0) -> 0 | BF32: =IF(BD32-BE32<>0,BD32,0) -> 0
A33: 2489 | B33: YACANTE ALLENDE FRANCISCO JAVIER | C33: 264-4557852 | D33: SAN JUAN | E33: 11359 | F33: 56 | G33: 150000 | H33: -30000 | N33: =IF(H33>0,G33+H33-I33-J33-K33-L33-M33,G33-I33-J33-K33-L33-M33) -> 150000 | O33: =G33+H33-J33-I33-K33-L33-M33 -> 120000 | P33: =IF(G33+H33<0,0,G33+H33) -> 120000 | S33: 46227 | X33: 7 | Y33: 7 | Z33: =IF(N33<0,0,N33) -> 150000 | AH33: 1 | AI33: =IF(F33<=6,15,25) -> 25 | AJ33: =IF(O33<>0,25,15) -> 25 | AK33: =IF(AI33-T33=24,1,0) -> 0 | AL33: =IF(AH33-AK33=AH33,0,AH33) -> 0 | AM33: =IF(AK33<>0,U33,0) -> 0 | AN33: =IF(AK33=1,O33,0) -> 0 | AO33: =IF(AI33-T33=14,1,0) -> 0 | AP33: =IF(AH33-AO33=AH33,0,AH33) -> 0 | AQ33: =IF(AO33<>0,U33,0) -> 0 | AR33: =IF(AO33=1,O33,0) -> 0 | AS33: =IF(SUM(I33:M33)<>0,1,0) -> 0 | AT33: =AS33 -> 0 | AU33: =IF(O33>0,1,0) -> 1 | AV33: =IF(AK33+AO33+AU33=1,AU33,0) -> 1 | AW33: =IF(AI33-AV33=24,1,0) -> 1 | AX33: =IF(AH33-AW33=AH33,0,AH33) -> 1 | AY33: =IF(AW33=1,O33,0) -> 120000 | AZ33: =IF(AY33-BA33<>0,AY33,0) -> 120000 | BA33: =IF(AY33<0,AY33,0) -> 0 | BB33: =IF(AI33-AV33=14,1,0) -> 0 | BC33: =IF(AH33-BB33=AH33,0,AH33) -> 0 | BD33: =IF(BB33=1,O33,0) -> 0 | BE33: =IF(BD33<0,BD33,0) -> 0 | BF33: =IF(BD33-BE33<>0,BD33,0) -> 0
A34: 2526 | B34: CRUZ INES CAROLINA | C34: 264-5111481 | D34: BARREAL | E34: 11399 | F34: 55 | G34: 50000 | H34: 0 | N34: =IF(H34>0,G34+H34-I34-J34-K34-L34-M34,G34-I34-J34-K34-L34-M34) -> 50000 | O34: =G34+H34-J34-I34-K34-L34-M34 -> 50000 | P34: =IF(G34+H34<0,0,G34+H34) -> 50000 | S34: 46217 | X34: 7 | Y34: 7 | Z34: =IF(N34<0,0,N34) -> 50000 | AH34: 1 | AI34: =IF(F34<=6,15,25) -> 25 | AJ34: =IF(O34<>0,25,15) -> 25 | AK34: =IF(AI34-T34=24,1,0) -> 0 | AL34: =IF(AH34-AK34=AH34,0,AH34) -> 0 | AM34: =IF(AK34<>0,U34,0) -> 0 | AN34: =IF(AK34=1,O34,0) -> 0 | AO34: =IF(AI34-T34=14,1,0) -> 0 | AP34: =IF(AH34-AO34=AH34,0,AH34) -> 0 | AQ34: =IF(AO34<>0,U34,0) -> 0 | AR34: =IF(AO34=1,O34,0) -> 0 | AS34: =IF(SUM(I34:M34)<>0,1,0) -> 0 | AT34: =AS34 -> 0 | AU34: =IF(O34>0,1,0) -> 1 | AV34: =IF(AK34+AO34+AU34=1,AU34,0) -> 1 | AW34: =IF(AI34-AV34=24,1,0) -> 1 | AX34: =IF(AH34-AW34=AH34,0,AH34) -> 1 | AY34: =IF(AW34=1,O34,0) -> 50000 | AZ34: =IF(AY34-BA34<>0,AY34,0) -> 50000 | BA34: =IF(AY34<0,AY34,0) -> 0 | BB34: =IF(AI34-AV34=14,1,0) -> 0 | BC34: =IF(AH34-BB34=AH34,0,AH34) -> 0 | BD34: =IF(BB34=1,O34,0) -> 0 | BE34: =IF(BD34<0,BD34,0) -> 0 | BF34: =IF(BD34-BE34<>0,BD34,0) -> 0
A35: 2543 | B35: HIDALGO MORENO MAURO | C35: 264-4059779 | D35: SAN JUAN | E35: 11367 | F35: 54 | G35: 60000 | H35: 0 | N35: =IF(H35>0,G35+H35-I35-J35-K35-L35-M35,G35-I35-J35-K35-L35-M35) -> 60000 | O35: =G35+H35-J35-I35-K35-L35-M35 -> 60000 | P35: =IF(G35+H35<0,0,G35+H35) -> 60000 | S35: 46234 | X35: 7 | Y35: 7 | Z35: =IF(N35<0,0,N35) -> 60000 | AH35: 1 | AI35: =IF(F35<=6,15,25) -> 25 | AJ35: =IF(O35<>0,25,15) -> 25 | AK35: =IF(AI35-T35=24,1,0) -> 0 | AL35: =IF(AH35-AK35=AH35,0,AH35) -> 0 | AM35: =IF(AK35<>0,U35,0) -> 0 | AN35: =IF(AK35=1,O35,0) -> 0 | AO35: =IF(AI35-T35=14,1,0) -> 0 | AP35: =IF(AH35-AO35=AH35,0,AH35) -> 0 | AQ35: =IF(AO35<>0,U35,0) -> 0 | AR35: =IF(AO35=1,O35,0) -> 0 | AS35: =IF(SUM(I35:M35)<>0,1,0) -> 0 | AT35: =AS35 -> 0 | AU35: =IF(O35>0,1,0) -> 1 | AV35: =IF(AK35+AO35+AU35=1,AU35,0) -> 1 | AW35: =IF(AI35-AV35=24,1,0) -> 1 | AX35: =IF(AH35-AW35=AH35,0,AH35) -> 1 | AY35: =IF(AW35=1,O35,0) -> 60000 | AZ35: =IF(AY35-BA35<>0,AY35,0) -> 60000 | BA35: =IF(AY35<0,AY35,0) -> 0 | BB35: =IF(AI35-AV35=14,1,0) -> 0 | BC35: =IF(AH35-BB35=AH35,0,AH35) -> 0 | BD35: =IF(BB35=1,O35,0) -> 0 | BE35: =IF(BD35<0,BD35,0) -> 0 | BF35: =IF(BD35-BE35<>0,BD35,0) -> 0
A36: 2545 | B36: DIAZ ANTONELLA YAMILA | C36: 264-4743505 | D36: JACHAL | E36: 11371 | F36: 54 | G36: 300000 | H36: 0 | N36: =IF(H36>0,G36+H36-I36-J36-K36-L36-M36,G36-I36-J36-K36-L36-M36) -> 300000 | O36: =G36+H36-J36-I36-K36-L36-M36 -> 300000 | P36: =IF(G36+H36<0,0,G36+H36) -> 300000 | S36: 46217 | X36: 7 | Y36: 7 | Z36: =IF(N36<0,0,N36) -> 300000 | AH36: 1 | AI36: =IF(F36<=6,15,25) -> 25 | AJ36: =IF(O36<>0,25,15) -> 25 | AK36: =IF(AI36-T36=24,1,0) -> 0 | AL36: =IF(AH36-AK36=AH36,0,AH36) -> 0 | AM36: =IF(AK36<>0,U36,0) -> 0 | AN36: =IF(AK36=1,O36,0) -> 0 | AO36: =IF(AI36-T36=14,1,0) -> 0 | AP36: =IF(AH36-AO36=AH36,0,AH36) -> 0 | AQ36: =IF(AO36<>0,U36,0) -> 0 | AR36: =IF(AO36=1,O36,0) -> 0 | AS36: =IF(SUM(I36:M36)<>0,1,0) -> 0 | AT36: =AS36 -> 0 | AU36: =IF(O36>0,1,0) -> 1 | AV36: =IF(AK36+AO36+AU36=1,AU36,0) -> 1 | AW36: =IF(AI36-AV36=24,1,0) -> 1 | AX36: =IF(AH36-AW36=AH36,0,AH36) -> 1 | AY36: =IF(AW36=1,O36,0) -> 300000 | AZ36: =IF(AY36-BA36<>0,AY36,0) -> 300000 | BA36: =IF(AY36<0,AY36,0) -> 0 | BB36: =IF(AI36-AV36=14,1,0) -> 0 | BC36: =IF(AH36-BB36=AH36,0,AH36) -> 0 | BD36: =IF(BB36=1,O36,0) -> 0 | BE36: =IF(BD36<0,BD36,0) -> 0 | BF36: =IF(BD36-BE36<>0,BD36,0) -> 0
A37: 2548 | B37: LARA ELVIO ARNALDO | C37: 264-6613176 | D37: SAN JUAN | E37: 11381 | F37: 54 | G37: 60000 | H37: -10000 | N37: =IF(H37>0,G37+H37-I37-J37-K37-L37-M37,G37-I37-J37-K37-L37-M37) -> 60000 | O37: =G37+H37-J37-I37-K37-L37-M37 -> 50000 | P37: =IF(G37+H37<0,0,G37+H37) -> 50000 | S37: 46223 | X37: 7 | Y37: 7 | Z37: =IF(N37<0,0,N37) -> 60000 | AH37: 1 | AI37: =IF(F37<=6,15,25) -> 25 | AJ37: =IF(O37<>0,25,15) -> 25 | AK37: =IF(AI37-T37=24,1,0) -> 0 | AL37: =IF(AH37-AK37=AH37,0,AH37) -> 0 | AM37: =IF(AK37<>0,U37,0) -> 0 | AN37: =IF(AK37=1,O37,0) -> 0 | AO37: =IF(AI37-T37=14,1,0) -> 0 | AP37: =IF(AH37-AO37=AH37,0,AH37) -> 0 | AQ37: =IF(AO37<>0,U37,0) -> 0 | AR37: =IF(AO37=1,O37,0) -> 0 | AS37: =IF(SUM(I37:M37)<>0,1,0) -> 0 | AT37: =AS37 -> 0 | AU37: =IF(O37>0,1,0) -> 1 | AV37: =IF(AK37+AO37+AU37=1,AU37,0) -> 1 | AW37: =IF(AI37-AV37=24,1,0) -> 1 | AX37: =IF(AH37-AW37=AH37,0,AH37) -> 1 | AY37: =IF(AW37=1,O37,0) -> 50000 | AZ37: =IF(AY37-BA37<>0,AY37,0) -> 50000 | BA37: =IF(AY37<0,AY37,0) -> 0 | BB37: =IF(AI37-AV37=14,1,0) -> 0 | BC37: =IF(AH37-BB37=AH37,0,AH37) -> 0 | BD37: =IF(BB37=1,O37,0) -> 0 | BE37: =IF(BD37<0,BD37,0) -> 0 | BF37: =IF(BD37-BE37<>0,BD37,0) -> 0
A38: 2549 | B38: VAZQUEZ LUCIA NILDA | C38: 264-6194557 | D38: RAWSON | E38: 11382 | F38: 54 | G38: 60000 | H38: -24000 | N38: =IF(H38>0,G38+H38-I38-J38-K38-L38-M38,G38-I38-J38-K38-L38-M38) -> 60000 | O38: =G38+H38-J38-I38-K38-L38-M38 -> 36000 | P38: =IF(G38+H38<0,0,G38+H38) -> 36000 | S38: 46211 | X38: 7 | Y38: 7 | Z38: =IF(N38<0,0,N38) -> 60000 | AH38: 1 | AI38: =IF(F38<=6,15,25) -> 25 | AJ38: =IF(O38<>0,25,15) -> 25 | AK38: =IF(AI38-T38=24,1,0) -> 0 | AL38: =IF(AH38-AK38=AH38,0,AH38) -> 0 | AM38: =IF(AK38<>0,U38,0) -> 0 | AN38: =IF(AK38=1,O38,0) -> 0 | AO38: =IF(AI38-T38=14,1,0) -> 0 | AP38: =IF(AH38-AO38=AH38,0,AH38) -> 0 | AQ38: =IF(AO38<>0,U38,0) -> 0 | AR38: =IF(AO38=1,O38,0) -> 0 | AS38: =IF(SUM(I38:M38)<>0,1,0) -> 0 | AT38: =AS38 -> 0 | AU38: =IF(O38>0,1,0) -> 1 | AV38: =IF(AK38+AO38+AU38=1,AU38,0) -> 1 | AW38: =IF(AI38-AV38=24,1,0) -> 1 | AX38: =IF(AH38-AW38=AH38,0,AH38) -> 1 | AY38: =IF(AW38=1,O38,0) -> 36000 | AZ38: =IF(AY38-BA38<>0,AY38,0) -> 36000 | BA38: =IF(AY38<0,AY38,0) -> 0 | BB38: =IF(AI38-AV38=14,1,0) -> 0 | BC38: =IF(AH38-BB38=AH38,0,AH38) -> 0 | BD38: =IF(BB38=1,O38,0) -> 0 | BE38: =IF(BD38<0,BD38,0) -> 0 | BF38: =IF(BD38-BE38<>0,BD38,0) -> 0
... A47: 2714 | B47: VILLACORTA FABIANA ALEJANDRA | C47: 264-6726589 | D47: RAWSON | E47: 11635 | F47: 48 | G47: 80000 | H47: -30000 | N47: =IF(H47>0,G47+H47-I47-J47-K47-L47-M47,G47-I47-J47-K47-L47-M47) -> 80000 | O47: =G47+H47-J47-I47-K47-L47-M47 -> 50000 | P47: =IF(G47+H47<0,0,G47+H47) -> 50000 | S47: 46213 | X47: 7 | Y47: 7 | Z47: =IF(N47<0,0,N47) -> 80000 | AH47: 1 | AI47: =IF(F47<=6,15,25) -> 25 | AJ47: =IF(O47<>0,25,15) -> 25 | AK47: =IF(AI47-T47=24,1,0) -> 0 | AL47: =IF(AH47-AK47=AH47,0,AH47) -> 0 | AM47: =IF(AK47<>0,U47,0) -> 0 | AN47: =IF(AK47=1,O47,0) -> 0 | AO47: =IF(AI47-T47=14,1,0) -> 0 | AP47: =IF(AH47-AO47=AH47,0,AH47) -> 0 | AQ47: =IF(AO47<>0,U47,0) -> 0 | AR47: =IF(AO47=1,O47,0) -> 0 | AS47: =IF(SUM(I47:M47)<>0,1,0) -> 0 | AT47: =AS47 -> 0 | AU47: =IF(O47>0,1,0) -> 1 | AV47: =IF(AK47+AO47+AU47=1,AU47,0) -> 1 | AW47: =IF(AI47-AV47=24,1,0) -> 1 | AX47: =IF(AH47-AW47=AH47,0,AH47) -> 1 | AY47: =IF(AW47=1,O47,0) -> 50000 | AZ47: =IF(AY47-BA47<>0,AY47,0) -> 50000 | BA47: =IF(AY47<0,AY47,0) -> 0 | BB47: =IF(AI47-AV47=14,1,0) -> 0 | BC47: =IF(AH47-BB47=AH47,0,AH47) -> 0 | BD47: =IF(BB47=1,O47,0) -> 0 | BE47: =IF(BD47<0,BD47,0) -> 0 | BF47: =IF(BD47-BE47<>0,BD47,0) -> 0
A48: 2717 | B48: MILLA VERONICA ANTONIA | C48: 264-4727755 | D48: POCITOS | E48: 11639 | F48: 48 | G48: 70000 | H48: 70000 | N48: =IF(H48>0,G48+H48-I48-J48-K48-L48-M48,G48-I48-J48-K48-L48-M48) -> 140000 | O48: =G48+H48-J48-I48-K48-L48-M48 -> 140000 | P48: =IF(G48+H48<0,0,G48+H48) -> 140000 | Q48: 46235 | S48: 46203 | V48: MERCADO PAGO | X48: 7 | Y48: 7 | Z48: =IF(N48<0,0,N48) -> 140000 | AH48: 1 | AI48: =IF(F48<=6,15,25) -> 25 | AJ48: =IF(O48<>0,25,15) -> 25 | AK48: =IF(AI48-T48=24,1,0) -> 0 | AL48: =IF(AH48-AK48=AH48,0,AH48) -> 0 | AM48: =IF(AK48<>0,U48,0) -> 0 | AN48: =IF(AK48=1,O48,0) -> 0 | AO48: =IF(AI48-T48=14,1,0) -> 0 | AP48: =IF(AH48-AO48=AH48,0,AH48) -> 0 | AQ48: =IF(AO48<>0,U48,0) -> 0 | AR48: =IF(AO48=1,O48,0) -> 0 | AS48: =IF(SUM(I48:M48)<>0,1,0) -> 0 | AT48: =AS48 -> 0 | AU48: =IF(O48>0,1,0) -> 1 | AV48: =IF(AK48+AO48+AU48=1,AU48,0) -> 1 | AW48: =IF(AI48-AV48=24,1,0) -> 1 | AX48: =IF(AH48-AW48=AH48,0,AH48) -> 1 | AY48: =IF(AW48=1,O48,0) -> 140000 | AZ48: =IF(AY48-BA48<>0,AY48,0) -> 140000 | BA48: =IF(AY48<0,AY48,0) -> 0 | BB48: =IF(AI48-AV48=14,1,0) -> 0 | BC48: =IF(AH48-BB48=AH48,0,AH48) -> 0 | BD48: =IF(BB48=1,O48,0) -> 0 | BE48: =IF(BD48<0,BD48,0) -> 0 | BF48: =IF(BD48-BE48<>0,BD48,0) -> 0
A49: 2727 | B49: SORIA PALACIO GERMAN OMAR | C49: 264-4758154 | D49: POCITOS | E49: 11644 | F49: 48 | G49: 70000 | H49: 0 | N49: =IF(H49>0,G49+H49-I49-J49-K49-L49-M49,G49-I49-J49-K49-L49-M49) -> 70000 | O49: =G49+H49-J49-I49-K49-L49-M49 -> 70000 | P49: =IF(G49+H49<0,0,G49+H49) -> 70000 | S49: 46233 | X49: 7 | Y49: 7 | Z49: =IF(N49<0,0,N49) -> 70000 | AH49: 1 | AI49: =IF(F49<=6,15,25) -> 25 | AJ49: =IF(O49<>0,25,15) -> 25 | AK49: =IF(AI49-T49=24,1,0) -> 0 | AL49: =IF(AH49-AK49=AH49,0,AH49) -> 0 | AM49: =IF(AK49<>0,U49,0) -> 0 | AN49: =IF(AK49=1,O49,0) -> 0 | AO49: =IF(AI49-T49=14,1,0) -> 0 | AP49: =IF(AH49-AO49=AH49,0,AH49) -> 0 | AQ49: =IF(AO49<>0,U49,0) -> 0 | AR49: =IF(AO49=1,O49,0) -> 0 | AS49: =IF(SUM(I49:M49)<>0,1,0) -> 0 | AT49: =AS49 -> 0 | AU49: =IF(O49>0,1,0) -> 1 | AV49: =IF(AK49+AO49+AU49=1,AU49,0) -> 1 | AW49: =IF(AI49-AV49=24,1,0) -> 1 | AX49: =IF(AH49-AW49=AH49,0,AH49) -> 1 | AY49: =IF(AW49=1,O49,0) -> 70000 | AZ49: =IF(AY49-BA49<>0,AY49,0) -> 70000 | BA49: =IF(AY49<0,AY49,0) -> 0 | BB49: =IF(AI49-AV49=14,1,0) -> 0 | BC49: =IF(AH49-BB49=AH49,0,AH49) -> 0 | BD49: =IF(BB49=1,O49,0) -> 0 | BE49: =IF(BD49<0,BD49,0) -> 0 | BF49: =IF(BD49-BE49<>0,BD49,0) -> 0
A50: 2744 | B50: ARROYO MARIANA DEOLINDA | C50: 264-5725038 | D50: ANGACO | E50: 11631 | F50: 47 | G50: 60000 | H50: -24000 | N50: =IF(H50>0,G50+H50-I50-J50-K50-L50-M50,G50-I50-J50-K50-L50-M50) -> 60000 | O50: =G50+H50-J50-I50-K50-L50-M50 -> 36000 | P50: =IF(G50+H50<0,0,G50+H50) -> 36000 | S50: 46218 | X50: 7 | Y50: 7 | Z50: =IF(N50<0,0,N50) -> 60000 | AH50: 1 | AI50: =IF(F50<=6,15,25) -> 25 | AJ50: =IF(O50<>0,25,15) -> 25 | AK50: =IF(AI50-T50=24,1,0) -> 0 | AL50: =IF(AH50-AK50=AH50,0,AH50) -> 0 | AM50: =IF(AK50<>0,U50,0) -> 0 | AN50: =IF(AK50=1,O50,0) -> 0 | AO50: =IF(AI50-T50=14,1,0) -> 0 | AP50: =IF(AH50-AO50=AH50,0,AH50) -> 0 | AQ50: =IF(AO50<>0,U50,0) -> 0 | AR50: =IF(AO50=1,O50,0) -> 0 | AS50: =IF(SUM(I50:M50)<>0,1,0) -> 0 | AT50: =AS50 -> 0 | AU50: =IF(O50>0,1,0) -> 1 | AV50: =IF(AK50+AO50+AU50=1,AU50,0) -> 1 | AW50: =IF(AI50-AV50=24,1,0) -> 1 | AX50: =IF(AH50-AW50=AH50,0,AH50) -> 1 | AY50: =IF(AW50=1,O50,0) -> 36000 | AZ50: =IF(AY50-BA50<>0,AY50,0) -> 36000 | BA50: =IF(AY50<0,AY50,0) -> 0 | BB50: =IF(AI50-AV50=14,1,0) -> 0 | BC50: =IF(AH50-BB50=AH50,0,AH50) -> 0 | BD50: =IF(BB50=1,O50,0) -> 0 | BE50: =IF(BD50<0,BD50,0) -> 0 | BF50: =IF(BD50-BE50<>0,BD50,0) -> 0
A51: 2747 | B51: MALDONADO NELLY LEONOR | C51: 264-6716597 | D51: SAN JUAN | E51: 11656 | F51: 47 | G51: 99999 | H51: -260011 | N51: =IF(H51>0,G51+H51-I51-J51-K51-L51-M51,G51-I51-J51-K51-L51-M51) -> 99999 | O51: =G51+H51-J51-I51-K51-L51-M51 -> -160012 | P51: =IF(G51+H51<0,0,G51+H51) -> 0 | S51: 46211 | X51: 7 | Y51: 7 | Z51: =IF(N51<0,0,N51) -> 99999 | AH51: 1 | AI51: =IF(F51<=6,15,25) -> 25 | AJ51: =IF(O51<>0,25,15) -> 25 | AK51: =IF(AI51-T51=24,1,0) -> 0 | AL51: =IF(AH51-AK51=AH51,0,AH51) -> 0 | AM51: =IF(AK51<>0,U51,0) -> 0 | AN51: =IF(AK51=1,O51,0) -> 0 | AO51: =IF(AI51-T51=14,1,0) -> 0 | AP51: =IF(AH51-AO51=AH51,0,AH51) -> 0 | AQ51: =IF(AO51<>0,U51,0) -> 0 | AR51: =IF(AO51=1,O51,0) -> 0 | AS51: =IF(SUM(I51:M51)<>0,1,0) -> 0 | AT51: =AS51 -> 0 | AU51: =IF(O51>0,1,0) -> 0 | AV51: =IF(AK51+AO51+AU51=1,AU51,0) -> 0 | AW51: =IF(AI51-AV51=24,1,0) -> 0 | AX51: =IF(AH51-AW51=AH51,0,AH51) -> 0 | AY51: =IF(AW51=1,O51,0) -> 0 | AZ51: =IF(AY51-BA51<>0,AY51,0) -> 0 | BA51: =IF(AY51<0,AY51,0) -> 0 | BB51: =IF(AI51-AV51=14,1,0) -> 0 | BC51: =IF(AH51-BB51=AH51,0,AH51) -> 0 | BD51: =IF(BB51=1,O51,0) -> 0 | BE51: =IF(BD51<0,BD51,0) -> 0 | BF51: =IF(BD51-BE51<>0,BD51,0) -> 0
A52: 2755 | B52: ALVAREZ MORAN CARMEN BEATRIZ | C52: 264-5895577 | D52: EL RINCON | E52: 11668 | F52: 47 | G52: 60000 | H52: 0 | N52: =IF(H52>0,G52+H52-I52-J52-K52-L52-M52,G52-I52-J52-K52-L52-M52) -> 60000 | O52: =G52+H52-J52-I52-K52-L52-M52 -> 60000 | P52: =IF(G52+H52<0,0,G52+H52) -> 60000 | S52: 46205 | X52: 7 | Y52: 7 | Z52: =IF(N52<0,0,N52) -> 60000 | AH52: 1 | AI52: =IF(F52<=6,15,25) -> 25 | AJ52: =IF(O52<>0,25,15) -> 25 | AK52: =IF(AI52-T52=24,1,0) -> 0 | AL52: =IF(AH52-AK52=AH52,0,AH52) -> 0 | AM52: =IF(AK52<>0,U52,0) -> 0 | AN52: =IF(AK52=1,O52,0) -> 0 | AO52: =IF(AI52-T52=14,1,0) -> 0 | AP52: =IF(AH52-AO52=AH52,0,AH52) -> 0 | AQ52: =IF(AO52<>0,U52,0) -> 0 | AR52: =IF(AO52=1,O52,0) -> 0 | AS52: =IF(SUM(I52:M52)<>0,1,0) -> 0 | AT52: =AS52 -> 0 | AU52: =IF(O52>0,1,0) -> 1 | AV52: =IF(AK52+AO52+AU52=1,AU52,0) -> 1 | AW52: =IF(AI52-AV52=24,1,0) -> 1 | AX52: =IF(AH52-AW52=AH52,0,AH52) -> 1 | AY52: =IF(AW52=1,O52,0) -> 60000 | AZ52: =IF(AY52-BA52<>0,AY52,0) -> 60000 | BA52: =IF(AY52<0,AY52,0) -> 0 | BB52: =IF(AI52-AV52=14,1,0) -> 0 | BC52: =IF(AH52-BB52=AH52,0,AH52) -> 0 | BD52: =IF(BB52=1,O52,0) -> 0 | BE52: =IF(BD52<0,BD52,0) -> 0 | BF52: =IF(BD52-BE52<>0,BD52,0) -> 0
A53: 2760 | B53: PEREZ ALEJANDRO MAXIMILIANO | C53: 264-6706973 | D53: ANGUALASTO | E53: 11688 | F53: 47 | G53: 60000 | H53: 0 | N53: =IF(H53>0,G53+H53-I53-J53-K53-L53-M53,G53-I53-J53-K53-L53-M53) -> 60000 | O53: =G53+H53-J53-I53-K53-L53-M53 -> 60000 | P53: =IF(G53+H53<0,0,G53+H53) -> 60000 | S53: 46213 | X53: 7 | Y53: 7 | Z53: =IF(N53<0,0,N53) -> 60000 | AH53: 1 | AI53: =IF(F53<=6,15,25) -> 25 | AJ53: =IF(O53<>0,25,15) -> 25 | AK53: =IF(AI53-T53=24,1,0) -> 0 | AL53: =IF(AH53-AK53=AH53,0,AH53) -> 0 | AM53: =IF(AK53<>0,U53,0) -> 0 | AN53: =IF(AK53=1,O53,0) -> 0 | AO53: =IF(AI53-T53=14,1,0) -> 0 | AP53: =IF(AH53-AO53=AH53,0,AH53) -> 0 | AQ53: =IF(AO53<>0,U53,0) -> 0 | AR53: =IF(AO53=1,O53,0) -> 0 | AS53: =IF(SUM(I53:M53)<>0,1,0) -> 0 | AT53: =AS53 -> 0 | AU53: =IF(O53>0,1,0) -> 1 | AV53: =IF(AK53+AO53+AU53=1,AU53,0) -> 1 | AW53: =IF(AI53-AV53=24,1,0) -> 1 | AX53: =IF(AH53-AW53=AH53,0,AH53) -> 1 | AY53: =IF(AW53=1,O53,0) -> 60000 | AZ53: =IF(AY53-BA53<>0,AY53,0) -> 60000 | BA53: =IF(AY53<0,AY53,0) -> 0 | BB53: =IF(AI53-AV53=14,1,0) -> 0 | BC53: =IF(AH53-BB53=AH53,0,AH53) -> 0 | BD53: =IF(BB53=1,O53,0) -> 0 | BE53: =IF(BD53<0,BD53,0) -> 0 | BF53: =IF(BD53-BE53<>0,BD53,0) -> 0
A54: 2802 | B54: ARAYA PABLO RAUL | C54: 261-7751681 | D54: VILLA TULUMAYA | E54: 11702 | F54: 45 | G54: 60000 | H54: 0 | N54: =IF(H54>0,G54+H54-I54-J54-K54-L54-M54,G54-I54-J54-K54-L54-M54) -> 60000 | O54: =G54+H54-J54-I54-K54-L54-M54 -> 60000 | P54: =IF(G54+H54<0,0,G54+H54) -> 60000 | S54: 46219 | X54: 7 | Y54: 7 | Z54: =IF(N54<0,0,N54) -> 60000 | AH54: 1 | AI54: =IF(F54<=6,15,25) -> 25 | AJ54: =IF(O54<>0,25,15) -> 25 | AK54: =IF(AI54-T54=24,1,0) -> 0 | AL54: =IF(AH54-AK54=AH54,0,AH54) -> 0 | AM54: =IF(AK54<>0,U54,0) -> 0 | AN54: =IF(AK54=1,O54,0) -> 0 | AO54: =IF(AI54-T54=14,1,0) -> 0 | AP54: =IF(AH54-AO54=AH54,0,AH54) -> 0 | AQ54: =IF(AO54<>0,U54,0) -> 0 | AR54: =IF(AO54=1,O54,0) -> 0 | AS54: =IF(SUM(I54:M54)<>0,1,0) -> 0 | AT54: =AS54 -> 0 | AU54: =IF(O54>0,1,0) -> 1 | AV54: =IF(AK54+AO54+AU54=1,AU54,0) -> 1 | AW54: =IF(AI54-AV54=24,1,0) -> 1 | AX54: =IF(AH54-AW54=AH54,0,AH54) -> 1 | AY54: =IF(AW54=1,O54,0) -> 60000 | AZ54: =IF(AY54-BA54<>0,AY54,0) -> 60000 | BA54: =IF(AY54<0,AY54,0) -> 0 | BB54: =IF(AI54-AV54=14,1,0) -> 0 | BC54: =IF(AH54-BB54=AH54,0,AH54) -> 0 | BD54: =IF(BB54=1,O54,0) -> 0 | BE54: =IF(BD54<0,BD54,0) -> 0 | BF54: =IF(BD54-BE54<>0,BD54,0) -> 0
A55: 2816 | B55: ESPINOZA SALAS ELVIA MATILDE | C55: 264-6719959 | D55: 9 DE JULIO | E55: 11701 | F55: 44 | G55: 60000 | H55: 0 | N55: =IF(H55>0,G55+H55-I55-J55-K55-L55-M55,G55-I55-J55-K55-L55-M55) -> 60000 | O55: =G55+H55-J55-I55-K55-L55-M55 -> 60000 | P55: =IF(G55+H55<0,0,G55+H55) -> 60000 | S55: 46234 | X55: 7 | Y55: 7 | Z55: =IF(N55<0,0,N55) -> 60000 | AH55: 1 | AI55: =IF(F55<=6,15,25) -> 25 | AJ55: =IF(O55<>0,25,15) -> 25 | AK55: =IF(AI55-T55=24,1,0) -> 0 | AL55: =IF(AH55-AK55=AH55,0,AH55) -> 0 | AM55: =IF(AK55<>0,U55,0) -> 0 | AN55: =IF(AK55=1,O55,0) -> 0 | AO55: =IF(AI55-T55=14,1,0) -> 0 | AP55: =IF(AH55-AO55=AH55,0,AH55) -> 0 | AQ55: =IF(AO55<>0,U55,0) -> 0 | AR55: =IF(AO55=1,O55,0) -> 0 | AS55: =IF(SUM(I55:M55)<>0,1,0) -> 0 | AT55: =AS55 -> 0 | AU55: =IF(O55>0,1,0) -> 1 | AV55: =IF(AK55+AO55+AU55=1,AU55,0) -> 1 | AW55: =IF(AI55-AV55=24,1,0) -> 1 | AX55: =IF(AH55-AW55=AH55,0,AH55) -> 1 | AY55: =IF(AW55=1,O55,0) -> 60000 | AZ55: =IF(AY55-BA55<>0,AY55,0) -> 60000 | BA55: =IF(AY55<0,AY55,0) -> 0 | BB55: =IF(AI55-AV55=14,1,0) -> 0 | BC55: =IF(AH55-BB55=AH55,0,AH55) -> 0 | BD55: =IF(BB55=1,O55,0) -> 0 | BE55: =IF(BD55<0,BD55,0) -> 0 | BF55: =IF(BD55-BE55<>0,BD55,0) -> 0
A56: 2836 | B56: DELGADO FERNANDO EXEQUIEL | C56: 264-6614350 | D56: SAN JUAN | E56: 11737 | F56: 43 | G56: 55000 | H56: 0 | N56: =IF(H56>0,G56+H56-I56-J56-K56-L56-M56,G56-I56-J56-K56-L56-M56) -> 55000 | O56: =G56+H56-J56-I56-K56-L56-M56 -> 55000 | P56: =IF(G56+H56<0,0,G56+H56) -> 55000 | S56: 46218 | X56: 7 | Y56: 7 | Z56: =IF(N56<0,0,N56) -> 55000 | AH56: 1 | AI56: =IF(F56<=6,15,25) -> 25 | AJ56: =IF(O56<>0,25,15) -> 25 | AK56: =IF(AI56-T56=24,1,0) -> 0 | AL56: =IF(AH56-AK56=AH56,0,AH56) -> 0 | AM56: =IF(AK56<>0,U56,0) -> 0 | AN56: =IF(AK56=1,O56,0) -> 0 | AO56: =IF(AI56-T56=14,1,0) -> 0 | AP56: =IF(AH56-AO56=AH56,0,AH56) -> 0 | AQ56: =IF(AO56<>0,U56,0) -> 0 | AR56: =IF(AO56=1,O56,0) -> 0 | AS56: =IF(SUM(I56:M56)<>0,1,0) -> 0 | AT56: =AS56 -> 0 | AU56: =IF(O56>0,1,0) -> 1 | AV56: =IF(AK56+AO56+AU56=1,AU56,0) -> 1 | AW56: =IF(AI56-AV56=24,1,0) -> 1 | AX56: =IF(AH56-AW56=AH56,0,AH56) -> 1 | AY56: =IF(AW56=1,O56,0) -> 55000 | AZ56: =IF(AY56-BA56<>0,AY56,0) -> 55000 | BA56: =IF(AY56<0,AY56,0) -> 0 | BB56: =IF(AI56-AV56=14,1,0) -> 0 | BC56: =IF(AH56-BB56=AH56,0,AH56) -> 0 | BD56: =IF(BB56=1,O56,0) -> 0 | BE56: =IF(BD56<0,BD56,0) -> 0 | BF56: =IF(BD56-BE56<>0,BD56,0) -> 0
A57: 2853 | B57: TELLO DOMINGA MANUELA | C57: 264-5260938 | D57: RAWSON | E57: 11750 | F57: 42 | G57: 45000 | H57: -70000 | N57: =IF(H57>0,G57+H57-I57-J57-K57-L57-M57,G57-I57-J57-K57-L57-M57) -> 45000 | O57: =G57+H57-J57-I57-K57-L57-M57 -> -25000 | P57: =IF(G57+H57<0,0,G57+H57) -> 0 | S57: 46230 | X57: 7 | Y57: 7 | Z57: =IF(N57<0,0,N57) -> 45000 | AH57: 1 | AI57: =IF(F57<=6,15,25) -> 25 | AJ57: =IF(O57<>0,25,15) -> 25 | AK57: =IF(AI57-T57=24,1,0) -> 0 | AL57: =IF(AH57-AK57=AH57,0,AH57) -> 0 | AM57: =IF(AK57<>0,U57,0) -> 0 | AN57: =IF(AK57=1,O57,0) -> 0 | AO57: =IF(AI57-T57=14,1,0) -> 0 | AP57: =IF(AH57-AO57=AH57,0,AH57) -> 0 | AQ57: =IF(AO57<>0,U57,0) -> 0 | AR57: =IF(AO57=1,O57,0) -> 0 | AS57: =IF(SUM(I57:M57)<>0,1,0) -> 0 | AT57: =AS57 -> 0 | AU57: =IF(O57>0,1,0) -> 0 | AV57: =IF(AK57+AO57+AU57=1,AU57,0) -> 0 | AW57: =IF(AI57-AV57=24,1,0) -> 0 | AX57: =IF(AH57-AW57=AH57,0,AH57) -> 0 | AY57: =IF(AW57=1,O57,0) -> 0 | AZ57: =IF(AY57-BA57<>0,AY57,0) -> 0 | BA57: =IF(AY57<0,AY57,0) -> 0 | BB57: =IF(AI57-AV57=14,1,0) -> 0 | BC57: =IF(AH57-BB57=AH57,0,AH57) -> 0 | BD57: =IF(BB57=1,O57,0) -> 0 | BE57: =IF(BD57<0,BD57,0) -> 0 | BF57: =IF(BD57-BE57<>0,BD57,0) -> 0
A58: 2872 | B58: OLIVERA ELISA VALERIA | C58: 264-4447849 | D58: ANGACO | E58: 11648 | F58: 41 | G58: 55000 | H58: 0 | N58: =IF(H58>0,G58+H58-I58-J58-K58-L58-M58,G58-I58-J58-K58-L58-M58) -> 55000 | O58: =G58+H58-J58-I58-K58-L58-M58 -> 55000 | P58: =IF(G58+H58<0,0,G58+H58) -> 55000 | S58: 46220 | X58: 7 | Y58: 7 | Z58: =IF(N58<0,0,N58) -> 55000 | AH58: 1 | AI58: =IF(F58<=6,15,25) -> 25 | AJ58: =IF(O58<>0,25,15) -> 25 | AK58: =IF(AI58-T58=24,1,0) -> 0 | AL58: =IF(AH58-AK58=AH58,0,AH58) -> 0 | AM58: =IF(AK58<>0,U58,0) -> 0 | AN58: =IF(AK58=1,O58,0) -> 0 | AO58: =IF(AI58-T58=14,1,0) -> 0 | AP58: =IF(AH58-AO58=AH58,0,AH58) -> 0 | AQ58: =IF(AO58<>0,U58,0) -> 0 | AR58: =IF(AO58=1,O58,0) -> 0 | AS58: =IF(SUM(I58:M58)<>0,1,0) -> 0 | AT58: =AS58 -> 0 | AU58: =IF(O58>0,1,0) -> 1 | AV58: =IF(AK58+AO58+AU58=1,AU58,0) -> 1 | AW58: =IF(AI58-AV58=24,1,0) -> 1 | AX58: =IF(AH58-AW58=AH58,0,AH58) -> 1 | AY58: =IF(AW58=1,O58,0) -> 55000 | AZ58: =IF(AY58-BA58<>0,AY58,0) -> 55000 | BA58: =IF(AY58<0,AY58,0) -> 0 | BB58: =IF(AI58-AV58=14,1,0) -> 0 | BC58: =IF(AH58-BB58=AH58,0,AH58) -> 0 | BD58: =IF(BB58=1,O58,0) -> 0 | BE58: =IF(BD58<0,BD58,0) -> 0 | BF58: =IF(BD58-BE58<>0,BD58,0) -> 0
A59: 2877 | B59: ALCANIS SUSANA ELIZABETH | C59: 264-5778208 | D59: RAWSON | E59: 11783 | F59: 41 | G59: 40000 | H59: -20000 | N59: =IF(H59>0,G59+H59-I59-J59-K59-L59-M59,G59-I59-J59-K59-L59-M59) -> 40000 | O59: =G59+H59-J59-I59-K59-L59-M59 -> 20000 | P59: =IF(G59+H59<0,0,G59+H59) -> 20000 | S59: 46234 | X59: 7 | Y59: 7 | Z59: =IF(N59<0,0,N59) -> 40000 | AH59: 1 | AI59: =IF(F59<=6,15,25) -> 25 | AJ59: =IF(O59<>0,25,15) -> 25 | AK59: =IF(AI59-T59=24,1,0) -> 0 | AL59: =IF(AH59-AK59=AH59,0,AH59) -> 0 | AM59: =IF(AK59<>0,U59,0) -> 0 | AN59: =IF(AK59=1,O59,0) -> 0 | AO59: =IF(AI59-T59=14,1,0) -> 0 | AP59: =IF(AH59-AO59=AH59,0,AH59) -> 0 | AQ59: =IF(AO59<>0,U59,0) -> 0 | AR59: =IF(AO59=1,O59,0) -> 0 | AS59: =IF(SUM(I59:M59)<>0,1,0) -> 0 | AT59: =AS59 -> 0 | AU59: =IF(O59>0,1,0) -> 1 | AV59: =IF(AK59+AO59+AU59=1,AU59,0) -> 1 | AW59: =IF(AI59-AV59=24,1,0) -> 1 | AX59: =IF(AH59-AW59=AH59,0,AH59) -> 1 | AY59: =IF(AW59=1,O59,0) -> 20000 | AZ59: =IF(AY59-BA59<>0,AY59,0) -> 20000 | BA59: =IF(AY59<0,AY59,0) -> 0 | BB59: =IF(AI59-AV59=14,1,0) -> 0 | BC59: =IF(AH59-BB59=AH59,0,AH59) -> 0 | BD59: =IF(BB59=1,O59,0) -> 0 | BE59: =IF(BD59<0,BD59,0) -> 0 | BF59: =IF(BD59-BE59<>0,BD59,0) -> 0
A60: 2890 | B60: HUANCA QUISPE MIRIAM NANCY | C60: 264-5645707 | D60: RAWSON | E60: 11801 | F60: 41 | G60: 90000 | H60: 0 | N60: =IF(H60>0,G60+H60-I60-J60-K60-L60-M60,G60-I60-J60-K60-L60-M60) -> 90000 | O60: =G60+H60-J60-I60-K60-L60-M60 -> 90000 | P60: =IF(G60+H60<0,0,G60+H60) -> 90000 | S60: 46234 | X60: 7 | Y60: 7 | Z60: =IF(N60<0,0,N60) -> 90000 | AH60: 1 | AI60: =IF(F60<=6,15,25) -> 25 | AJ60: =IF(O60<>0,25,15) -> 25 | AK60: =IF(AI60-T60=24,1,0) -> 0 | AL60: =IF(AH60-AK60=AH60,0,AH60) -> 0 | AM60: =IF(AK60<>0,U60,0) -> 0 | AN60: =IF(AK60=1,O60,0) -> 0 | AO60: =IF(AI60-T60=14,1,0) -> 0 | AP60: =IF(AH60-AO60=AH60,0,AH60) -> 0 | AQ60: =IF(AO60<>0,U60,0) -> 0 | AR60: =IF(AO60=1,O60,0) -> 0 | AS60: =IF(SUM(I60:M60)<>0,1,0) -> 0 | AT60: =AS60 -> 0 | AU60: =IF(O60>0,1,0) -> 1 | AV60: =IF(AK60+AO60+AU60=1,AU60,0) -> 1 | AW60: =IF(AI60-AV60=24,1,0) -> 1 | AX60: =IF(AH60-AW60=AH60,0,AH60) -> 1 | AY60: =IF(AW60=1,O60,0) -> 90000 | AZ60: =IF(AY60-BA60<>0,AY60,0) -> 90000 | BA60: =IF(AY60<0,AY60,0) -> 0 | BB60: =IF(AI60-AV60=14,1,0) -> 0 | BC60: =IF(AH60-BB60=AH60,0,AH60) -> 0 | BD60: =IF(BB60=1,O60,0) -> 0 | BE60: =IF(BD60<0,BD60,0) -> 0 | BF60: =IF(BD60-BE60<>0,BD60,0) -> 0
... A97: 3182 | B97: OLMO CECILIA CRISTINA | C97: 264-5105298 | D97: CAUCETE | E97: 11970 | F97: 34 | G97: 80000 | H97: 0 | N97: =IF(H97>0,G97+H97-I97-J97-K97-L97-M97,G97-I97-J97-K97-L97-M97) -> 80000 | O97: =G97+H97-J97-I97-K97-L97-M97 -> 80000 | P97: =IF(G97+H97<0,0,G97+H97) -> 80000 | S97: 46213 | X97: 7 | Y97: 7 | Z97: =IF(N97<0,0,N97) -> 80000 | AH97: 1 | AI97: =IF(F97<=6,15,25) -> 25 | AJ97: =IF(O97<>0,25,15) -> 25 | AK97: =IF(AI97-T97=24,1,0) -> 0 | AL97: =IF(AH97-AK97=AH97,0,AH97) -> 0 | AM97: =IF(AK97<>0,U97,0) -> 0 | AN97: =IF(AK97=1,O97,0) -> 0 | AO97: =IF(AI97-T97=14,1,0) -> 0 | AP97: =IF(AH97-AO97=AH97,0,AH97) -> 0 | AQ97: =IF(AO97<>0,U97,0) -> 0 | AR97: =IF(AO97=1,O97,0) -> 0 | AS97: =IF(SUM(I97:M97)<>0,1,0) -> 0 | AT97: =AS97 -> 0 | AU97: =IF(O97>0,1,0) -> 1 | AV97: =IF(AK97+AO97+AU97=1,AU97,0) -> 1 | AW97: =IF(AI97-AV97=24,1,0) -> 1 | AX97: =IF(AH97-AW97=AH97,0,AH97) -> 1 | AY97: =IF(AW97=1,O97,0) -> 80000 | AZ97: =IF(AY97-BA97<>0,AY97,0) -> 80000 | BA97: =IF(AY97<0,AY97,0) -> 0 | BB97: =IF(AI97-AV97=14,1,0) -> 0 | BC97: =IF(AH97-BB97=AH97,0,AH97) -> 0 | BD97: =IF(BB97=1,O97,0) -> 0 | BE97: =IF(BD97<0,BD97,0) -> 0 | BF97: =IF(BD97-BE97<>0,BD97,0) -> 0
A98: 3184 | B98: MOLINA AGÜERO AYELEN VICTORIA | C98: 2645439804 | D98: POCITOS | E98: 11981 | F98: 34 | G98: 30000 | H98: 0 | N98: =IF(H98>0,G98+H98-I98-J98-K98-L98-M98,G98-I98-J98-K98-L98-M98) -> 30000 | O98: =G98+H98-J98-I98-K98-L98-M98 -> 30000 | P98: =IF(G98+H98<0,0,G98+H98) -> 30000 | Q98: 46204 | S98: 46204 | V98: MERCADO PAGO | X98: 7 | Y98: 7 | Z98: =IF(N98<0,0,N98) -> 30000 | AH98: 1 | AI98: =IF(F98<=6,15,25) -> 25 | AJ98: =IF(O98<>0,25,15) -> 25 | AK98: =IF(AI98-T98=24,1,0) -> 0 | AL98: =IF(AH98-AK98=AH98,0,AH98) -> 0 | AM98: =IF(AK98<>0,U98,0) -> 0 | AN98: =IF(AK98=1,O98,0) -> 0 | AO98: =IF(AI98-T98=14,1,0) -> 0 | AP98: =IF(AH98-AO98=AH98,0,AH98) -> 0 | AQ98: =IF(AO98<>0,U98,0) -> 0 | AR98: =IF(AO98=1,O98,0) -> 0 | AS98: =IF(SUM(I98:M98)<>0,1,0) -> 0 | AT98: =AS98 -> 0 | AU98: =IF(O98>0,1,0) -> 1 | AV98: =IF(AK98+AO98+AU98=1,AU98,0) -> 1 | AW98: =IF(AI98-AV98=24,1,0) -> 1 | AX98: =IF(AH98-AW98=AH98,0,AH98) -> 1 | AY98: =IF(AW98=1,O98,0) -> 30000 | AZ98: =IF(AY98-BA98<>0,AY98,0) -> 30000 | BA98: =IF(AY98<0,AY98,0) -> 0 | BB98: =IF(AI98-AV98=14,1,0) -> 0 | BC98: =IF(AH98-BB98=AH98,0,AH98) -> 0 | BD98: =IF(BB98=1,O98,0) -> 0 | BE98: =IF(BD98<0,BD98,0) -> 0 | BF98: =IF(BD98-BE98<>0,BD98,0) -> 0
A99: 3186 | B99: ORTEGA ROSA DEL JESUS | C99: 264-4101302 | D99: 9 DE JULIO | E99: 11983 | F99: 34 | G99: 70000 | H99: 0 | N99: =IF(H99>0,G99+H99-I99-J99-K99-L99-M99,G99-I99-J99-K99-L99-M99) -> 70000 | O99: =G99+H99-J99-I99-K99-L99-M99 -> 70000 | P99: =IF(G99+H99<0,0,G99+H99) -> 70000 | S99: 46234 | X99: 7 | Y99: 7 | Z99: =IF(N99<0,0,N99) -> 70000 | AH99: 1 | AI99: =IF(F99<=6,15,25) -> 25 | AJ99: =IF(O99<>0,25,15) -> 25 | AK99: =IF(AI99-T99=24,1,0) -> 0 | AL99: =IF(AH99-AK99=AH99,0,AH99) -> 0 | AM99: =IF(AK99<>0,U99,0) -> 0 | AN99: =IF(AK99=1,O99,0) -> 0 | AO99: =IF(AI99-T99=14,1,0) -> 0 | AP99: =IF(AH99-AO99=AH99,0,AH99) -> 0 | AQ99: =IF(AO99<>0,U99,0) -> 0 | AR99: =IF(AO99=1,O99,0) -> 0 | AS99: =IF(SUM(I99:M99)<>0,1,0) -> 0 | AT99: =AS99 -> 0 | AU99: =IF(O99>0,1,0) -> 1 | AV99: =IF(AK99+AO99+AU99=1,AU99,0) -> 1 | AW99: =IF(AI99-AV99=24,1,0) -> 1 | AX99: =IF(AH99-AW99=AH99,0,AH99) -> 1 | AY99: =IF(AW99=1,O99,0) -> 70000 | AZ99: =IF(AY99-BA99<>0,AY99,0) -> 70000 | BA99: =IF(AY99<0,AY99,0) -> 0 | BB99: =IF(AI99-AV99=14,1,0) -> 0 | BC99: =IF(AH99-BB99=AH99,0,AH99) -> 0 | BD99: =IF(BB99=1,O99,0) -> 0 | BE99: =IF(BD99<0,BD99,0) -> 0 | BF99: =IF(BD99-BE99<>0,BD99,0) -> 0
A100: 3200 | B100: FUENTE ROSA ELVIRA | C100: 264-4216221 | D100: RAWSON | E100: 11990 | F100: 33 | G100: 60000 | H100: 0 | N100: =IF(H100>0,G100+H100-I100-J100-K100-L100-M100,G100-I100-J100-K100-L100-M100) -> 60000 | O100: =G100+H100-J100-I100-K100-L100-M100 -> 60000 | P100: =IF(G100+H100<0,0,G100+H100) -> 60000 | S100: 46205 | X100: 7 | Y100: 7 | Z100: =IF(N100<0,0,N100) -> 60000 | AH100: 1 | AI100: =IF(F100<=6,15,25) -> 25 | AJ100: =IF(O100<>0,25,15) -> 25 | AK100: =IF(AI100-T100=24,1,0) -> 0 | AL100: =IF(AH100-AK100=AH100,0,AH100) -> 0 | AM100: =IF(AK100<>0,U100,0) -> 0 | AN100: =IF(AK100=1,O100,0) -> 0 | AO100: =IF(AI100-T100=14,1,0) -> 0 | AP100: =IF(AH100-AO100=AH100,0,AH100) -> 0 | AQ100: =IF(AO100<>0,U100,0) -> 0 | AR100: =IF(AO100=1,O100,0) -> 0 | AS100: =IF(SUM(I100:M100)<>0,1,0) -> 0 | AT100: =AS100 -> 0 | AU100: =IF(O100>0,1,0) -> 1 | AV100: =IF(AK100+AO100+AU100=1,AU100,0) -> 1 | AW100: =IF(AI100-AV100=24,1,0) -> 1 | AX100: =IF(AH100-AW100=AH100,0,AH100) -> 1 | AY100: =IF(AW100=1,O100,0) -> 60000 | AZ100: =IF(AY100-BA100<>0,AY100,0) -> 60000 | BA100: =IF(AY100<0,AY100,0) -> 0 | BB100: =IF(AI100-AV100=14,1,0) -> 0 | BC100: =IF(AH100-BB100=AH100,0,AH100) -> 0 | BD100: =IF(BB100=1,O100,0) -> 0 | BE100: =IF(BD100<0,BD100,0) -> 0 | BF100: =IF(BD100-BE100<>0,BD100,0) -> 0
A101: 3203 | B101: PEREZ MARIELA BENITA | C101: 264-5815004 | D101: POCITOS | E101: 20032 | F101: 33 | G101: 80000 | H101: 0 | N101: =IF(H101>0,G101+H101-I101-J101-K101-L101-M101,G101-I101-J101-K101-L101-M101) -> 80000 | O101: =G101+H101-J101-I101-K101-L101-M101 -> 80000 | P101: =IF(G101+H101<0,0,G101+H101) -> 80000 | S101: 46230 | X101: 7 | Y101: 7 | Z101: =IF(N101<0,0,N101) -> 80000 | AH101: 1 | AI101: =IF(F101<=6,15,25) -> 25 | AJ101: =IF(O101<>0,25,15) -> 25 | AK101: =IF(AI101-T101=24,1,0) -> 0 | AL101: =IF(AH101-AK101=AH101,0,AH101) -> 0 | AM101: =IF(AK101<>0,U101,0) -> 0 | AN101: =IF(AK101=1,O101,0) -> 0 | AO101: =IF(AI101-T101=14,1,0) -> 0 | AP101: =IF(AH101-AO101=AH101,0,AH101) -> 0 | AQ101: =IF(AO101<>0,U101,0) -> 0 | AR101: =IF(AO101=1,O101,0) -> 0 | AS101: =IF(SUM(I101:M101)<>0,1,0) -> 0 | AT101: =AS101 -> 0 | AU101: =IF(O101>0,1,0) -> 1 | AV101: =IF(AK101+AO101+AU101=1,AU101,0) -> 1 | AW101: =IF(AI101-AV101=24,1,0) -> 1 | AX101: =IF(AH101-AW101=AH101,0,AH101) -> 1 | AY101: =IF(AW101=1,O101,0) -> 80000 | AZ101: =IF(AY101-BA101<>0,AY101,0) -> 80000 | BA101: =IF(AY101<0,AY101,0) -> 0 | BB101: =IF(AI101-AV101=14,1,0) -> 0 | BC101: =IF(AH101-BB101=AH101,0,AH101) -> 0 | BD101: =IF(BB101=1,O101,0) -> 0 | BE101: =IF(BD101<0,BD101,0) -> 0 | BF101: =IF(BD101-BE101<>0,BD101,0) -> 0
A102: 3211 | B102: PEREZ PAULA ROSANA GABRIELA | C102: 264-6021447 | D102: 9 DE JULIO | E102: 20274 | F102: 33 | G102: 60000 | H102: 0 | N102: =IF(H102>0,G102+H102-I102-J102-K102-L102-M102,G102-I102-J102-K102-L102-M102) -> 60000 | O102: =G102+H102-J102-I102-K102-L102-M102 -> 60000 | P102: =IF(G102+H102<0,0,G102+H102) -> 60000 | S102: 46213 | X102: 7 | Y102: 7 | Z102: =IF(N102<0,0,N102) -> 60000 | AH102: 1 | AI102: =IF(F102<=6,15,25) -> 25 | AJ102: =IF(O102<>0,25,15) -> 25 | AK102: =IF(AI102-T102=24,1,0) -> 0 | AL102: =IF(AH102-AK102=AH102,0,AH102) -> 0 | AM102: =IF(AK102<>0,U102,0) -> 0 | AN102: =IF(AK102=1,O102,0) -> 0 | AO102: =IF(AI102-T102=14,1,0) -> 0 | AP102: =IF(AH102-AO102=AH102,0,AH102) -> 0 | AQ102: =IF(AO102<>0,U102,0) -> 0 | AR102: =IF(AO102=1,O102,0) -> 0 | AS102: =IF(SUM(I102:M102)<>0,1,0) -> 0 | AT102: =AS102 -> 0 | AU102: =IF(O102>0,1,0) -> 1 | AV102: =IF(AK102+AO102+AU102=1,AU102,0) -> 1 | AW102: =IF(AI102-AV102=24,1,0) -> 1 | AX102: =IF(AH102-AW102=AH102,0,AH102) -> 1 | AY102: =IF(AW102=1,O102,0) -> 60000 | AZ102: =IF(AY102-BA102<>0,AY102,0) -> 60000 | BA102: =IF(AY102<0,AY102,0) -> 0 | BB102: =IF(AI102-AV102=14,1,0) -> 0 | BC102: =IF(AH102-BB102=AH102,0,AH102) -> 0 | BD102: =IF(BB102=1,O102,0) -> 0 | BE102: =IF(BD102<0,BD102,0) -> 0 | BF102: =IF(BD102-BE102<>0,BD102,0) -> 0
A103: 3223 | B103: PEREIRA JULIO DAVID | C103: 264-5808073 | D103: RAWSON | E103: 268 | F103: 32 | G103: 40000 | H103: -20000 | N103: =IF(H103>0,G103+H103-I103-J103-K103-L103-M103,G103-I103-J103-K103-L103-M103) -> 40000 | O103: =G103+H103-J103-I103-K103-L103-M103 -> 20000 | P103: =IF(G103+H103<0,0,G103+H103) -> 20000 | S103: 46223 | X103: 7 | Y103: 7 | Z103: =IF(N103<0,0,N103) -> 40000 | AH103: 1 | AI103: =IF(F103<=6,15,25) -> 25 | AJ103: =IF(O103<>0,25,15) -> 25 | AK103: =IF(AI103-T103=24,1,0) -> 0 | AL103: =IF(AH103-AK103=AH103,0,AH103) -> 0 | AM103: =IF(AK103<>0,U103,0) -> 0 | AN103: =IF(AK103=1,O103,0) -> 0 | AO103: =IF(AI103-T103=14,1,0) -> 0 | AP103: =IF(AH103-AO103=AH103,0,AH103) -> 0 | AQ103: =IF(AO103<>0,U103,0) -> 0 | AR103: =IF(AO103=1,O103,0) -> 0 | AS103: =IF(SUM(I103:M103)<>0,1,0) -> 0 | AT103: =AS103 -> 0 | AU103: =IF(O103>0,1,0) -> 1 | AV103: =IF(AK103+AO103+AU103=1,AU103,0) -> 1 | AW103: =IF(AI103-AV103=24,1,0) -> 1 | AX103: =IF(AH103-AW103=AH103,0,AH103) -> 1 | AY103: =IF(AW103=1,O103,0) -> 20000 | AZ103: =IF(AY103-BA103<>0,AY103,0) -> 20000 | BA103: =IF(AY103<0,AY103,0) -> 0 | BB103: =IF(AI103-AV103=14,1,0) -> 0 | BC103: =IF(AH103-BB103=AH103,0,AH103) -> 0 | BD103: =IF(BB103=1,O103,0) -> 0 | BE103: =IF(BD103<0,BD103,0) -> 0 | BF103: =IF(BD103-BE103<>0,BD103,0) -> 0
A104: 3226 | B104: GONZALEZ GUTIERREZ RODRIGO | C104: 264-4818920 | D104: RAWSON | E104: 20062 | F104: 32 | G104: 200000 | H104: -380005 | N104: =IF(H104>0,G104+H104-I104-J104-K104-L104-M104,G104-I104-J104-K104-L104-M104) -> 200000 | O104: =G104+H104-J104-I104-K104-L104-M104 -> -180005 | P104: =IF(G104+H104<0,0,G104+H104) -> 0 | S104: 46234 | X104: 7 | Y104: 7 | Z104: =IF(N104<0,0,N104) -> 200000 | AH104: 1 | AI104: =IF(F104<=6,15,25) -> 25 | AJ104: =IF(O104<>0,25,15) -> 25 | AK104: =IF(AI104-T104=24,1,0) -> 0 | AL104: =IF(AH104-AK104=AH104,0,AH104) -> 0 | AM104: =IF(AK104<>0,U104,0) -> 0 | AN104: =IF(AK104=1,O104,0) -> 0 | AO104: =IF(AI104-T104=14,1,0) -> 0 | AP104: =IF(AH104-AO104=AH104,0,AH104) -> 0 | AQ104: =IF(AO104<>0,U104,0) -> 0 | AR104: =IF(AO104=1,O104,0) -> 0 | AS104: =IF(SUM(I104:M104)<>0,1,0) -> 0 | AT104: =AS104 -> 0 | AU104: =IF(O104>0,1,0) -> 0 | AV104: =IF(AK104+AO104+AU104=1,AU104,0) -> 0 | AW104: =IF(AI104-AV104=24,1,0) -> 0 | AX104: =IF(AH104-AW104=AH104,0,AH104) -> 0 | AY104: =IF(AW104=1,O104,0) -> 0 | AZ104: =IF(AY104-BA104<>0,AY104,0) -> 0 | BA104: =IF(AY104<0,AY104,0) -> 0 | BB104: =IF(AI104-AV104=14,1,0) -> 0 | BC104: =IF(AH104-BB104=AH104,0,AH104) -> 0 | BD104: =IF(BB104=1,O104,0) -> 0 | BE104: =IF(BD104<0,BD104,0) -> 0 | BF104: =IF(BD104-BE104<>0,BD104,0) -> 0
A105: 3249 | B105: SAIRE NATALIA LORENA | C105: 264-5069280 | D105: CHIMBAS | E105: 20300 | F105: 32 | G105: 60000 | H105: 60000 | N105: =IF(H105>0,G105+H105-I105-J105-K105-L105-M105,G105-I105-J105-K105-L105-M105) -> 120000 | O105: =G105+H105-J105-I105-K105-L105-M105 -> 120000 | P105: =IF(G105+H105<0,0,G105+H105) -> 120000 | S105: 46211 | X105: 7 | Y105: 7 | Z105: =IF(N105<0,0,N105) -> 120000 | AH105: 1 | AI105: =IF(F105<=6,15,25) -> 25 | AJ105: =IF(O105<>0,25,15) -> 25 | AK105: =IF(AI105-T105=24,1,0) -> 0 | AL105: =IF(AH105-AK105=AH105,0,AH105) -> 0 | AM105: =IF(AK105<>0,U105,0) -> 0 | AN105: =IF(AK105=1,O105,0) -> 0 | AO105: =IF(AI105-T105=14,1,0) -> 0 | AP105: =IF(AH105-AO105=AH105,0,AH105) -> 0 | AQ105: =IF(AO105<>0,U105,0) -> 0 | AR105: =IF(AO105=1,O105,0) -> 0 | AS105: =IF(SUM(I105:M105)<>0,1,0) -> 0 | AT105: =AS105 -> 0 | AU105: =IF(O105>0,1,0) -> 1 | AV105: =IF(AK105+AO105+AU105=1,AU105,0) -> 1 | AW105: =IF(AI105-AV105=24,1,0) -> 1 | AX105: =IF(AH105-AW105=AH105,0,AH105) -> 1 | AY105: =IF(AW105=1,O105,0) -> 120000 | AZ105: =IF(AY105-BA105<>0,AY105,0) -> 120000 | BA105: =IF(AY105<0,AY105,0) -> 0 | BB105: =IF(AI105-AV105=14,1,0) -> 0 | BC105: =IF(AH105-BB105=AH105,0,AH105) -> 0 | BD105: =IF(BB105=1,O105,0) -> 0 | BE105: =IF(BD105<0,BD105,0) -> 0 | BF105: =IF(BD105-BE105<>0,BD105,0) -> 0
A106: 3250 | B106: FARIAS JORGE LUIS | C106: 264-4817232 | D106: CHIMBAS | E106: 20073 | F106: 31 | G106: 99999.99 | H106: -0.22 | N106: =IF(H106>0,G106+H106-I106-J106-K106-L106-M106,G106-I106-J106-K106-L106-M106) -> 99999.99 | O106: =G106+H106-J106-I106-K106-L106-M106 -> 99999.77 | P106: =IF(G106+H106<0,0,G106+H106) -> 99999.77 | S106: 46205 | X106: 7 | Y106: 7 | Z106: =IF(N106<0,0,N106) -> 99999.99 | AH106: 1 | AI106: =IF(F106<=6,15,25) -> 25 | AJ106: =IF(O106<>0,25,15) -> 25 | AK106: =IF(AI106-T106=24,1,0) -> 0 | AL106: =IF(AH106-AK106=AH106,0,AH106) -> 0 | AM106: =IF(AK106<>0,U106,0) -> 0 | AN106: =IF(AK106=1,O106,0) -> 0 | AO106: =IF(AI106-T106=14,1,0) -> 0 | AP106: =IF(AH106-AO106=AH106,0,AH106) -> 0 | AQ106: =IF(AO106<>0,U106,0) -> 0 | AR106: =IF(AO106=1,O106,0) -> 0 | AS106: =IF(SUM(I106:M106)<>0,1,0) -> 0 | AT106: =AS106 -> 0 | AU106: =IF(O106>0,1,0) -> 1 | AV106: =IF(AK106+AO106+AU106=1,AU106,0) -> 1 | AW106: =IF(AI106-AV106=24,1,0) -> 1 | AX106: =IF(AH106-AW106=AH106,0,AH106) -> 1 | AY106: =IF(AW106=1,O106,0) -> 99999.77 | AZ106: =IF(AY106-BA106<>0,AY106,0) -> 99999.77 | BA106: =IF(AY106<0,AY106,0) -> 0 | BB106: =IF(AI106-AV106=14,1,0) -> 0 | BC106: =IF(AH106-BB106=AH106,0,AH106) -> 0 | BD106: =IF(BB106=1,O106,0) -> 0 | BE106: =IF(BD106<0,BD106,0) -> 0 | BF106: =IF(BD106-BE106<>0,BD106,0) -> 0
A107: 3251 | B107: TELLO CESAR ARMANDO | C107: 264-5437259 | D107: SAN JUAN | E107: 20298 | F107: 31 | G107: 70000 | H107: -4000 | N107: =IF(H107>0,G107+H107-I107-J107-K107-L107-M107,G107-I107-J107-K107-L107-M107) -> 70000 | O107: =G107+H107-J107-I107-K107-L107-M107 -> 66000 | P107: =IF(G107+H107<0,0,G107+H107) -> 66000 | S107: 46178 | X107: 7 | Y107: 7 | Z107: =IF(N107<0,0,N107) -> 70000 | AH107: 1 | AI107: =IF(F107<=6,15,25) -> 25 | AJ107: =IF(O107<>0,25,15) -> 25 | AK107: =IF(AI107-T107=24,1,0) -> 0 | AL107: =IF(AH107-AK107=AH107,0,AH107) -> 0 | AM107: =IF(AK107<>0,U107,0) -> 0 | AN107: =IF(AK107=1,O107,0) -> 0 | AO107: =IF(AI107-T107=14,1,0) -> 0 | AP107: =IF(AH107-AO107=AH107,0,AH107) -> 0 | AQ107: =IF(AO107<>0,U107,0) -> 0 | AR107: =IF(AO107=1,O107,0) -> 0 | AS107: =IF(SUM(I107:M107)<>0,1,0) -> 0 | AT107: =AS107 -> 0 | AU107: =IF(O107>0,1,0) -> 1 | AV107: =IF(AK107+AO107+AU107=1,AU107,0) -> 1 | AW107: =IF(AI107-AV107=24,1,0) -> 1 | AX107: =IF(AH107-AW107=AH107,0,AH107) -> 1 | AY107: =IF(AW107=1,O107,0) -> 66000 | AZ107: =IF(AY107-BA107<>0,AY107,0) -> 66000 | BA107: =IF(AY107<0,AY107,0) -> 0 | BB107: =IF(AI107-AV107=14,1,0) -> 0 | BC107: =IF(AH107-BB107=AH107,0,AH107) -> 0 | BD107: =IF(BB107=1,O107,0) -> 0 | BE107: =IF(BD107<0,BD107,0) -> 0 | BF107: =IF(BD107-BE107<>0,BD107,0) -> 0
A108: 3267 | B108: OLIVERA ELISA VALERIA | C108: 264-5318968 | D108: ANGACO | E108: 3974 | F108: 31 | G108: 55000 | H108: 0 | N108: =IF(H108>0,G108+H108-I108-J108-K108-L108-M108,G108-I108-J108-K108-L108-M108) -> 55000 | O108: =G108+H108-J108-I108-K108-L108-M108 -> 55000 | P108: =IF(G108+H108<0,0,G108+H108) -> 55000 | S108: 46220 | X108: 7 | Y108: 7 | Z108: =IF(N108<0,0,N108) -> 55000 | AH108: 1 | AI108: =IF(F108<=6,15,25) -> 25 | AJ108: =IF(O108<>0,25,15) -> 25 | AK108: =IF(AI108-T108=24,1,0) -> 0 | AL108: =IF(AH108-AK108=AH108,0,AH108) -> 0 | AM108: =IF(AK108<>0,U108,0) -> 0 | AN108: =IF(AK108=1,O108,0) -> 0 | AO108: =IF(AI108-T108=14,1,0) -> 0 | AP108: =IF(AH108-AO108=AH108,0,AH108) -> 0 | AQ108: =IF(AO108<>0,U108,0) -> 0 | AR108: =IF(AO108=1,O108,0) -> 0 | AS108: =IF(SUM(I108:M108)<>0,1,0) -> 0 | AT108: =AS108 -> 0 | AU108: =IF(O108>0,1,0) -> 1 | AV108: =IF(AK108+AO108+AU108=1,AU108,0) -> 1 | AW108: =IF(AI108-AV108=24,1,0) -> 1 | AX108: =IF(AH108-AW108=AH108,0,AH108) -> 1 | AY108: =IF(AW108=1,O108,0) -> 55000 | AZ108: =IF(AY108-BA108<>0,AY108,0) -> 55000 | BA108: =IF(AY108<0,AY108,0) -> 0 | BB108: =IF(AI108-AV108=14,1,0) -> 0 | BC108: =IF(AH108-BB108=AH108,0,AH108) -> 0 | BD108: =IF(BB108=1,O108,0) -> 0 | BE108: =IF(BD108<0,BD108,0) -> 0 | BF108: =IF(BD108-BE108<>0,BD108,0) -> 0
A109: 3300 | B109: REYNA VILLAFAÑE TAMARA ELINA | C109: 264-5834008 | D109: POCITOS | E109: 20118 | F109: 29 | G109: 50000 | H109: 0 | N109: =IF(H109>0,G109+H109-I109-J109-K109-L109-M109,G109-I109-J109-K109-L109-M109) -> 50000 | O109: =G109+H109-J109-I109-K109-L109-M109 -> 50000 | P109: =IF(G109+H109<0,0,G109+H109) -> 50000 | S109: 46203 | X109: 7 | Y109: 7 | Z109: =IF(N109<0,0,N109) -> 50000 | AH109: 1 | AI109: =IF(F109<=6,15,25) -> 25 | AJ109: =IF(O109<>0,25,15) -> 25 | AK109: =IF(AI109-T109=24,1,0) -> 0 | AL109: =IF(AH109-AK109=AH109,0,AH109) -> 0 | AM109: =IF(AK109<>0,U109,0) -> 0 | AN109: =IF(AK109=1,O109,0) -> 0 | AO109: =IF(AI109-T109=14,1,0) -> 0 | AP109: =IF(AH109-AO109=AH109,0,AH109) -> 0 | AQ109: =IF(AO109<>0,U109,0) -> 0 | AR109: =IF(AO109=1,O109,0) -> 0 | AS109: =IF(SUM(I109:M109)<>0,1,0) -> 0 | AT109: =AS109 -> 0 | AU109: =IF(O109>0,1,0) -> 1 | AV109: =IF(AK109+AO109+AU109=1,AU109,0) -> 1 | AW109: =IF(AI109-AV109=24,1,0) -> 1 | AX109: =IF(AH109-AW109=AH109,0,AH109) -> 1 | AY109: =IF(AW109=1,O109,0) -> 50000 | AZ109: =IF(AY109-BA109<>0,AY109,0) -> 50000 | BA109: =IF(AY109<0,AY109,0) -> 0 | BB109: =IF(AI109-AV109=14,1,0) -> 0 | BC109: =IF(AH109-BB109=AH109,0,AH109) -> 0 | BD109: =IF(BB109=1,O109,0) -> 0 | BE109: =IF(BD109<0,BD109,0) -> 0 | BF109: =IF(BD109-BE109<>0,BD109,0) -> 0
A110: 3303 | B110: CHAVEZ MARINE YASMIN | C110: 264-4745142 | D110: SAN JUAN | E110: 20123 | F110: 29 | G110: 60000 | H110: -60000 | N110: =IF(H110>0,G110+H110-I110-J110-K110-L110-M110,G110-I110-J110-K110-L110-M110) -> 60000 | O110: =G110+H110-J110-I110-K110-L110-M110 -> 0 | P110: =IF(G110+H110<0,0,G110+H110) -> 0 | S110: 46204 | X110: 7 | Y110: 7 | Z110: =IF(N110<0,0,N110) -> 60000 | AH110: 1 | AI110: =IF(F110<=6,15,25) -> 25 | AJ110: =IF(O110<>0,25,15) -> 15 | AK110: =IF(AI110-T110=24,1,0) -> 0 | AL110: =IF(AH110-AK110=AH110,0,AH110) -> 0 | AM110: =IF(AK110<>0,U110,0) -> 0 | AN110: =IF(AK110=1,O110,0) -> 0 | AO110: =IF(AI110-T110=14,1,0) -> 0 | AP110: =IF(AH110-AO110=AH110,0,AH110) -> 0 | AQ110: =IF(AO110<>0,U110,0) -> 0 | AR110: =IF(AO110=1,O110,0) -> 0 | AS110: =IF(SUM(I110:M110)<>0,1,0) -> 0 | AT110: =AS110 -> 0 | AU110: =IF(O110>0,1,0) -> 0 | AV110: =IF(AK110+AO110+AU110=1,AU110,0) -> 0 | AW110: =IF(AI110-AV110=24,1,0) -> 0 | AX110: =IF(AH110-AW110=AH110,0,AH110) -> 0 | AY110: =IF(AW110=1,O110,0) -> 0 | AZ110: =IF(AY110-BA110<>0,AY110,0) -> 0 | BA110: =IF(AY110<0,AY110,0) -> 0 | BB110: =IF(AI110-AV110=14,1,0) -> 0 | BC110: =IF(AH110-BB110=AH110,0,AH110) -> 0 | BD110: =IF(BB110=1,O110,0) -> 0 | BE110: =IF(BD110<0,BD110,0) -> 0 | BF110: =IF(BD110-BE110<>0,BD110,0) -> 0
... A127: 3402 | B127: NIEVAS ELIANA TERESITA | C127: 264-6269775 | D127: RAWSON | E127: 20215 | F127: 25 | G127: 60000 | H127: 0 | N127: =IF(H127>0,G127+H127-I127-J127-K127-L127-M127,G127-I127-J127-K127-L127-M127) -> 60000 | O127: =G127+H127-J127-I127-K127-L127-M127 -> 60000 | P127: =IF(G127+H127<0,0,G127+H127) -> 60000 | S127: 46234 | X127: 7 | Y127: 7 | Z127: =IF(N127<0,0,N127) -> 60000 | AH127: 1 | AI127: =IF(F127<=6,15,25) -> 25 | AJ127: =IF(O127<>0,25,15) -> 25 | AK127: =IF(AI127-T127=24,1,0) -> 0 | AL127: =IF(AH127-AK127=AH127,0,AH127) -> 0 | AM127: =IF(AK127<>0,U127,0) -> 0 | AN127: =IF(AK127=1,O127,0) -> 0 | AO127: =IF(AI127-T127=14,1,0) -> 0 | AP127: =IF(AH127-AO127=AH127,0,AH127) -> 0 | AQ127: =IF(AO127<>0,U127,0) -> 0 | AR127: =IF(AO127=1,O127,0) -> 0 | AS127: =IF(SUM(I127:M127)<>0,1,0) -> 0 | AT127: =AS127 -> 0 | AU127: =IF(O127>0,1,0) -> 1 | AV127: =IF(AK127+AO127+AU127=1,AU127,0) -> 1 | AW127: =IF(AI127-AV127=24,1,0) -> 1 | AX127: =IF(AH127-AW127=AH127,0,AH127) -> 1 | AY127: =IF(AW127=1,O127,0) -> 60000 | AZ127: =IF(AY127-BA127<>0,AY127,0) -> 60000 | BA127: =IF(AY127<0,AY127,0) -> 0 | BB127: =IF(AI127-AV127=14,1,0) -> 0 | BC127: =IF(AH127-BB127=AH127,0,AH127) -> 0 | BD127: =IF(BB127=1,O127,0) -> 0 | BE127: =IF(BD127<0,BD127,0) -> 0 | BF127: =IF(BD127-BE127<>0,BD127,0) -> 0
A128: 3404 | B128: BARBOZA G. VICTOR HUGO | C128: 2644441339 | D128: SANTA LUCIA | E128: 20270 | F128: 25 | G128: 60000 | H128: 0 | N128: =IF(H128>0,G128+H128-I128-J128-K128-L128-M128,G128-I128-J128-K128-L128-M128) -> 60000 | O128: =G128+H128-J128-I128-K128-L128-M128 -> 60000 | P128: =IF(G128+H128<0,0,G128+H128) -> 60000 | S128: 46211 | X128: 7 | Y128: 7 | Z128: =IF(N128<0,0,N128) -> 60000 | AH128: 1 | AI128: =IF(F128<=6,15,25) -> 25 | AJ128: =IF(O128<>0,25,15) -> 25 | AK128: =IF(AI128-T128=24,1,0) -> 0 | AL128: =IF(AH128-AK128=AH128,0,AH128) -> 0 | AM128: =IF(AK128<>0,U128,0) -> 0 | AN128: =IF(AK128=1,O128,0) -> 0 | AO128: =IF(AI128-T128=14,1,0) -> 0 | AP128: =IF(AH128-AO128=AH128,0,AH128) -> 0 | AQ128: =IF(AO128<>0,U128,0) -> 0 | AR128: =IF(AO128=1,O128,0) -> 0 | AS128: =IF(SUM(I128:M128)<>0,1,0) -> 0 | AT128: =AS128 -> 0 | AU128: =IF(O128>0,1,0) -> 1 | AV128: =IF(AK128+AO128+AU128=1,AU128,0) -> 1 | AW128: =IF(AI128-AV128=24,1,0) -> 1 | AX128: =IF(AH128-AW128=AH128,0,AH128) -> 1 | AY128: =IF(AW128=1,O128,0) -> 60000 | AZ128: =IF(AY128-BA128<>0,AY128,0) -> 60000 | BA128: =IF(AY128<0,AY128,0) -> 0 | BB128: =IF(AI128-AV128=14,1,0) -> 0 | BC128: =IF(AH128-BB128=AH128,0,AH128) -> 0 | BD128: =IF(BB128=1,O128,0) -> 0 | BE128: =IF(BD128<0,BD128,0) -> 0 | BF128: =IF(BD128-BE128<>0,BD128,0) -> 0
A129: 3409 | B129: VIDELA EDGARDO ORLANDO | C129: 264-4560699 | D129: MEDIA AGUA | E129: 20227 | F129: 25 | G129: 120000 | H129: -120000 | N129: =IF(H129>0,G129+H129-I129-J129-K129-L129-M129,G129-I129-J129-K129-L129-M129) -> 120000 | O129: =G129+H129-J129-I129-K129-L129-M129 -> 0 | P129: =IF(G129+H129<0,0,G129+H129) -> 0 | S129: 46213 | X129: 7 | Y129: 7 | Z129: =IF(N129<0,0,N129) -> 120000 | AH129: 1 | AI129: =IF(F129<=6,15,25) -> 25 | AJ129: =IF(O129<>0,25,15) -> 15 | AK129: =IF(AI129-T129=24,1,0) -> 0 | AL129: =IF(AH129-AK129=AH129,0,AH129) -> 0 | AM129: =IF(AK129<>0,U129,0) -> 0 | AN129: =IF(AK129=1,O129,0) -> 0 | AO129: =IF(AI129-T129=14,1,0) -> 0 | AP129: =IF(AH129-AO129=AH129,0,AH129) -> 0 | AQ129: =IF(AO129<>0,U129,0) -> 0 | AR129: =IF(AO129=1,O129,0) -> 0 | AS129: =IF(SUM(I129:M129)<>0,1,0) -> 0 | AT129: =AS129 -> 0 | AU129: =IF(O129>0,1,0) -> 0 | AV129: =IF(AK129+AO129+AU129=1,AU129,0) -> 0 | AW129: =IF(AI129-AV129=24,1,0) -> 0 | AX129: =IF(AH129-AW129=AH129,0,AH129) -> 0 | AY129: =IF(AW129=1,O129,0) -> 0 | AZ129: =IF(AY129-BA129<>0,AY129,0) -> 0 | BA129: =IF(AY129<0,AY129,0) -> 0 | BB129: =IF(AI129-AV129=14,1,0) -> 0 | BC129: =IF(AH129-BB129=AH129,0,AH129) -> 0 | BD129: =IF(BB129=1,O129,0) -> 0 | BE129: =IF(BD129<0,BD129,0) -> 0 | BF129: =IF(BD129-BE129<>0,BD129,0) -> 0
A130: 3418 | B130: CORTEZ ELIZONDO CELINA INES | C130: 264-5887078 | D130: RAWSON | E130: 20242 | F130: 24 | G130: 90000 | H130: 0 | N130: =IF(H130>0,G130+H130-I130-J130-K130-L130-M130,G130-I130-J130-K130-L130-M130) -> 90000 | O130: =G130+H130-J130-I130-K130-L130-M130 -> 90000 | P130: =IF(G130+H130<0,0,G130+H130) -> 90000 | S130: 46209 | X130: 7 | Y130: 7 | Z130: =IF(N130<0,0,N130) -> 90000 | AH130: 1 | AI130: =IF(F130<=6,15,25) -> 25 | AJ130: =IF(O130<>0,25,15) -> 25 | AK130: =IF(AI130-T130=24,1,0) -> 0 | AL130: =IF(AH130-AK130=AH130,0,AH130) -> 0 | AM130: =IF(AK130<>0,U130,0) -> 0 | AN130: =IF(AK130=1,O130,0) -> 0 | AO130: =IF(AI130-T130=14,1,0) -> 0 | AP130: =IF(AH130-AO130=AH130,0,AH130) -> 0 | AQ130: =IF(AO130<>0,U130,0) -> 0 | AR130: =IF(AO130=1,O130,0) -> 0 | AS130: =IF(SUM(I130:M130)<>0,1,0) -> 0 | AT130: =AS130 -> 0 | AU130: =IF(O130>0,1,0) -> 1 | AV130: =IF(AK130+AO130+AU130=1,AU130,0) -> 1 | AW130: =IF(AI130-AV130=24,1,0) -> 1 | AX130: =IF(AH130-AW130=AH130,0,AH130) -> 1 | AY130: =IF(AW130=1,O130,0) -> 90000 | AZ130: =IF(AY130-BA130<>0,AY130,0) -> 90000 | BA130: =IF(AY130<0,AY130,0) -> 0 | BB130: =IF(AI130-AV130=14,1,0) -> 0 | BC130: =IF(AH130-BB130=AH130,0,AH130) -> 0 | BD130: =IF(BB130=1,O130,0) -> 0 | BE130: =IF(BD130<0,BD130,0) -> 0 | BF130: =IF(BD130-BE130<>0,BD130,0) -> 0
A131: 3423 | B131: BALMACEDA QUINTERO ALEJANDRA NICOLE | C131: 264-4117004 | D131: SAN JUAN | E131: 20243 | F131: 24 | G131: 300000 | H131: 0 | N131: =IF(H131>0,G131+H131-I131-J131-K131-L131-M131,G131-I131-J131-K131-L131-M131) -> 300000 | O131: =G131+H131-J131-I131-K131-L131-M131 -> 300000 | P131: =IF(G131+H131<0,0,G131+H131) -> 300000 | S131: 46213 | X131: 7 | Y131: 7 | Z131: =IF(N131<0,0,N131) -> 300000 | AH131: 1 | AI131: =IF(F131<=6,15,25) -> 25 | AJ131: =IF(O131<>0,25,15) -> 25 | AK131: =IF(AI131-T131=24,1,0) -> 0 | AL131: =IF(AH131-AK131=AH131,0,AH131) -> 0 | AM131: =IF(AK131<>0,U131,0) -> 0 | AN131: =IF(AK131=1,O131,0) -> 0 | AO131: =IF(AI131-T131=14,1,0) -> 0 | AP131: =IF(AH131-AO131=AH131,0,AH131) -> 0 | AQ131: =IF(AO131<>0,U131,0) -> 0 | AR131: =IF(AO131=1,O131,0) -> 0 | AS131: =IF(SUM(I131:M131)<>0,1,0) -> 0 | AT131: =AS131 -> 0 | AU131: =IF(O131>0,1,0) -> 1 | AV131: =IF(AK131+AO131+AU131=1,AU131,0) -> 1 | AW131: =IF(AI131-AV131=24,1,0) -> 1 | AX131: =IF(AH131-AW131=AH131,0,AH131) -> 1 | AY131: =IF(AW131=1,O131,0) -> 300000 | AZ131: =IF(AY131-BA131<>0,AY131,0) -> 300000 | BA131: =IF(AY131<0,AY131,0) -> 0 | BB131: =IF(AI131-AV131=14,1,0) -> 0 | BC131: =IF(AH131-BB131=AH131,0,AH131) -> 0 | BD131: =IF(BB131=1,O131,0) -> 0 | BE131: =IF(BD131<0,BD131,0) -> 0 | BF131: =IF(BD131-BE131<>0,BD131,0) -> 0
A132: 3431 | B132: ANDRADA EDGAR ARIEL | C132: 264-5608849 | D132: SAN JUAN | E132: 20052 | F132: 24 | G132: 150000 | H132: 0 | N132: =IF(H132>0,G132+H132-I132-J132-K132-L132-M132,G132-I132-J132-K132-L132-M132) -> 150000 | O132: =G132+H132-J132-I132-K132-L132-M132 -> 150000 | P132: =IF(G132+H132<0,0,G132+H132) -> 150000 | S132: 46211 | X132: 7 | Y132: 7 | Z132: =IF(N132<0,0,N132) -> 150000 | AH132: 1 | AI132: =IF(F132<=6,15,25) -> 25 | AJ132: =IF(O132<>0,25,15) -> 25 | AK132: =IF(AI132-T132=24,1,0) -> 0 | AL132: =IF(AH132-AK132=AH132,0,AH132) -> 0 | AM132: =IF(AK132<>0,U132,0) -> 0 | AN132: =IF(AK132=1,O132,0) -> 0 | AO132: =IF(AI132-T132=14,1,0) -> 0 | AP132: =IF(AH132-AO132=AH132,0,AH132) -> 0 | AQ132: =IF(AO132<>0,U132,0) -> 0 | AR132: =IF(AO132=1,O132,0) -> 0 | AS132: =IF(SUM(I132:M132)<>0,1,0) -> 0 | AT132: =AS132 -> 0 | AU132: =IF(O132>0,1,0) -> 1 | AV132: =IF(AK132+AO132+AU132=1,AU132,0) -> 1 | AW132: =IF(AI132-AV132=24,1,0) -> 1 | AX132: =IF(AH132-AW132=AH132,0,AH132) -> 1 | AY132: =IF(AW132=1,O132,0) -> 150000 | AZ132: =IF(AY132-BA132<>0,AY132,0) -> 150000 | BA132: =IF(AY132<0,AY132,0) -> 0 | BB132: =IF(AI132-AV132=14,1,0) -> 0 | BC132: =IF(AH132-BB132=AH132,0,AH132) -> 0 | BD132: =IF(BB132=1,O132,0) -> 0 | BE132: =IF(BD132<0,BD132,0) -> 0 | BF132: =IF(BD132-BE132<>0,BD132,0) -> 0
A133: 3450 | B133: BAZAN FERNANDO EMANUEL | C133: 264-5681049 | D133: RAWSON | E133: 20315 | F133: 23 | G133: 200000 | H133: 0 | N133: =IF(H133>0,G133+H133-I133-J133-K133-L133-M133,G133-I133-J133-K133-L133-M133) -> 200000 | O133: =G133+H133-J133-I133-K133-L133-M133 -> 200000 | P133: =IF(G133+H133<0,0,G133+H133) -> 200000 | S133: 46209 | X133: 7 | Y133: 7 | Z133: =IF(N133<0,0,N133) -> 200000 | AH133: 1 | AI133: =IF(F133<=6,15,25) -> 25 | AJ133: =IF(O133<>0,25,15) -> 25 | AK133: =IF(AI133-T133=24,1,0) -> 0 | AL133: =IF(AH133-AK133=AH133,0,AH133) -> 0 | AM133: =IF(AK133<>0,U133,0) -> 0 | AN133: =IF(AK133=1,O133,0) -> 0 | AO133: =IF(AI133-T133=14,1,0) -> 0 | AP133: =IF(AH133-AO133=AH133,0,AH133) -> 0 | AQ133: =IF(AO133<>0,U133,0) -> 0 | AR133: =IF(AO133=1,O133,0) -> 0 | AS133: =IF(SUM(I133:M133)<>0,1,0) -> 0 | AT133: =AS133 -> 0 | AU133: =IF(O133>0,1,0) -> 1 | AV133: =IF(AK133+AO133+AU133=1,AU133,0) -> 1 | AW133: =IF(AI133-AV133=24,1,0) -> 1 | AX133: =IF(AH133-AW133=AH133,0,AH133) -> 1 | AY133: =IF(AW133=1,O133,0) -> 200000 | AZ133: =IF(AY133-BA133<>0,AY133,0) -> 200000 | BA133: =IF(AY133<0,AY133,0) -> 0 | BB133: =IF(AI133-AV133=14,1,0) -> 0 | BC133: =IF(AH133-BB133=AH133,0,AH133) -> 0 | BD133: =IF(BB133=1,O133,0) -> 0 | BE133: =IF(BD133<0,BD133,0) -> 0 | BF133: =IF(BD133-BE133<>0,BD133,0) -> 0
A134: 3451 | B134: GUAYAQUINCHAY FLAVIA GISELLE | C134: 264-6210837 | D134: 9 DE JULIO | E134: 3981 | F134: 22 | G134: 250000 | H134: 0 | N134: =IF(H134>0,G134+H134-I134-J134-K134-L134-M134,G134-I134-J134-K134-L134-M134) -> 250000 | O134: =G134+H134-J134-I134-K134-L134-M134 -> 250000 | P134: =IF(G134+H134<0,0,G134+H134) -> 250000 | S134: 46212 | X134: 7 | Y134: 7 | Z134: =IF(N134<0,0,N134) -> 250000 | AH134: 1 | AI134: =IF(F134<=6,15,25) -> 25 | AJ134: =IF(O134<>0,25,15) -> 25 | AK134: =IF(AI134-T134=24,1,0) -> 0 | AL134: =IF(AH134-AK134=AH134,0,AH134) -> 0 | AM134: =IF(AK134<>0,U134,0) -> 0 | AN134: =IF(AK134=1,O134,0) -> 0 | AO134: =IF(AI134-T134=14,1,0) -> 0 | AP134: =IF(AH134-AO134=AH134,0,AH134) -> 0 | AQ134: =IF(AO134<>0,U134,0) -> 0 | AR134: =IF(AO134=1,O134,0) -> 0 | AS134: =IF(SUM(I134:M134)<>0,1,0) -> 0 | AT134: =AS134 -> 0 | AU134: =IF(O134>0,1,0) -> 1 | AV134: =IF(AK134+AO134+AU134=1,AU134,0) -> 1 | AW134: =IF(AI134-AV134=24,1,0) -> 1 | AX134: =IF(AH134-AW134=AH134,0,AH134) -> 1 | AY134: =IF(AW134=1,O134,0) -> 250000 | AZ134: =IF(AY134-BA134<>0,AY134,0) -> 250000 | BA134: =IF(AY134<0,AY134,0) -> 0 | BB134: =IF(AI134-AV134=14,1,0) -> 0 | BC134: =IF(AH134-BB134=AH134,0,AH134) -> 0 | BD134: =IF(BB134=1,O134,0) -> 0 | BE134: =IF(BD134<0,BD134,0) -> 0 | BF134: =IF(BD134-BE134<>0,BD134,0) -> 0
A135: 3457 | B135: JIMENEZ HERNAN | C135: 264-5430399 | D135: CHIMBAS | E135: 20336 | F135: 22 | G135: 80000 | H135: 0 | N135: =IF(H135>0,G135+H135-I135-J135-K135-L135-M135,G135-I135-J135-K135-L135-M135) -> 80000 | O135: =G135+H135-J135-I135-K135-L135-M135 -> 80000 | P135: =IF(G135+H135<0,0,G135+H135) -> 80000 | S135: 46234 | X135: 7 | Y135: 7 | Z135: =IF(N135<0,0,N135) -> 80000 | AH135: 1 | AI135: =IF(F135<=6,15,25) -> 25 | AJ135: =IF(O135<>0,25,15) -> 25 | AK135: =IF(AI135-T135=24,1,0) -> 0 | AL135: =IF(AH135-AK135=AH135,0,AH135) -> 0 | AM135: =IF(AK135<>0,U135,0) -> 0 | AN135: =IF(AK135=1,O135,0) -> 0 | AO135: =IF(AI135-T135=14,1,0) -> 0 | AP135: =IF(AH135-AO135=AH135,0,AH135) -> 0 | AQ135: =IF(AO135<>0,U135,0) -> 0 | AR135: =IF(AO135=1,O135,0) -> 0 | AS135: =IF(SUM(I135:M135)<>0,1,0) -> 0 | AT135: =AS135 -> 0 | AU135: =IF(O135>0,1,0) -> 1 | AV135: =IF(AK135+AO135+AU135=1,AU135,0) -> 1 | AW135: =IF(AI135-AV135=24,1,0) -> 1 | AX135: =IF(AH135-AW135=AH135,0,AH135) -> 1 | AY135: =IF(AW135=1,O135,0) -> 80000 | AZ135: =IF(AY135-BA135<>0,AY135,0) -> 80000 | BA135: =IF(AY135<0,AY135,0) -> 0 | BB135: =IF(AI135-AV135=14,1,0) -> 0 | BC135: =IF(AH135-BB135=AH135,0,AH135) -> 0 | BD135: =IF(BB135=1,O135,0) -> 0 | BE135: =IF(BD135<0,BD135,0) -> 0 | BF135: =IF(BD135-BE135<>0,BD135,0) -> 0
A136: 3478 | B136: MARTINEZ ROMINA ELIANA | C136: 264-5068875 | D136: JACHAL | E136: 20331 | F136: 17 | G136: 120000 | H136: 0 | N136: =IF(H136>0,G136+H136-I136-J136-K136-L136-M136,G136-I136-J136-K136-L136-M136) -> 120000 | O136: =G136+H136-J136-I136-K136-L136-M136 -> 120000 | P136: =IF(G136+H136<0,0,G136+H136) -> 120000 | S136: 46205 | X136: 7 | Y136: 7 | Z136: =IF(N136<0,0,N136) -> 120000 | AH136: 1 | AI136: =IF(F136<=6,15,25) -> 25 | AJ136: =IF(O136<>0,25,15) -> 25 | AK136: =IF(AI136-T136=24,1,0) -> 0 | AL136: =IF(AH136-AK136=AH136,0,AH136) -> 0 | AM136: =IF(AK136<>0,U136,0) -> 0 | AN136: =IF(AK136=1,O136,0) -> 0 | AO136: =IF(AI136-T136=14,1,0) -> 0 | AP136: =IF(AH136-AO136=AH136,0,AH136) -> 0 | AQ136: =IF(AO136<>0,U136,0) -> 0 | AR136: =IF(AO136=1,O136,0) -> 0 | AS136: =IF(SUM(I136:M136)<>0,1,0) -> 0 | AT136: =AS136 -> 0 | AU136: =IF(O136>0,1,0) -> 1 | AV136: =IF(AK136+AO136+AU136=1,AU136,0) -> 1 | AW136: =IF(AI136-AV136=24,1,0) -> 1 | AX136: =IF(AH136-AW136=AH136,0,AH136) -> 1 | AY136: =IF(AW136=1,O136,0) -> 120000 | AZ136: =IF(AY136-BA136<>0,AY136,0) -> 120000 | BA136: =IF(AY136<0,AY136,0) -> 0 | BB136: =IF(AI136-AV136=14,1,0) -> 0 | BC136: =IF(AH136-BB136=AH136,0,AH136) -> 0 | BD136: =IF(BB136=1,O136,0) -> 0 | BE136: =IF(BD136<0,BD136,0) -> 0 | BF136: =IF(BD136-BE136<>0,BD136,0) -> 0
A137: 3488 | B137: SANCHEZ LOBOS AGOSTINA DEL VALLE | C137: 264-5809502 | D137: SAN JUAN | E137: 11513 | F137: 15 | G137: 300000 | H137: 0 | N137: =IF(H137>0,G137+H137-I137-J137-K137-L137-M137,G137-I137-J137-K137-L137-M137) -> 300000 | O137: =G137+H137-J137-I137-K137-L137-M137 -> 300000 | P137: =IF(G137+H137<0,0,G137+H137) -> 300000 | S137: 46213 | X137: 7 | Y137: 7 | Z137: =IF(N137<0,0,N137) -> 300000 | AH137: 1 | AI137: =IF(F137<=6,15,25) -> 25 | AJ137: =IF(O137<>0,25,15) -> 25 | AK137: =IF(AI137-T137=24,1,0) -> 0 | AL137: =IF(AH137-AK137=AH137,0,AH137) -> 0 | AM137: =IF(AK137<>0,U137,0) -> 0 | AN137: =IF(AK137=1,O137,0) -> 0 | AO137: =IF(AI137-T137=14,1,0) -> 0 | AP137: =IF(AH137-AO137=AH137,0,AH137) -> 0 | AQ137: =IF(AO137<>0,U137,0) -> 0 | AR137: =IF(AO137=1,O137,0) -> 0 | AS137: =IF(SUM(I137:M137)<>0,1,0) -> 0 | AT137: =AS137 -> 0 | AU137: =IF(O137>0,1,0) -> 1 | AV137: =IF(AK137+AO137+AU137=1,AU137,0) -> 1 | AW137: =IF(AI137-AV137=24,1,0) -> 1 | AX137: =IF(AH137-AW137=AH137,0,AH137) -> 1 | AY137: =IF(AW137=1,O137,0) -> 300000 | AZ137: =IF(AY137-BA137<>0,AY137,0) -> 300000 | BA137: =IF(AY137<0,AY137,0) -> 0 | BB137: =IF(AI137-AV137=14,1,0) -> 0 | BC137: =IF(AH137-BB137=AH137,0,AH137) -> 0 | BD137: =IF(BB137=1,O137,0) -> 0 | BE137: =IF(BD137<0,BD137,0) -> 0 | BF137: =IF(BD137-BE137<>0,BD137,0) -> 0
A138: 3490 | B138: QUINTEROS GERARDO JAVIER | C138: 295-6617583 | D138: POCITOS | E138: 20351 | F138: 15 | G138: 300000 | H138: -600000 | N138: =IF(H138>0,G138+H138-I138-J138-K138-L138-M138,G138-I138-J138-K138-L138-M138) -> 300000 | O138: =G138+H138-J138-I138-K138-L138-M138 -> -300000 | P138: =IF(G138+H138<0,0,G138+H138) -> 0 | S138: 46211 | X138: 7 | Y138: 7 | Z138: =IF(N138<0,0,N138) -> 300000 | AH138: 1 | AI138: =IF(F138<=6,15,25) -> 25 | AJ138: =IF(O138<>0,25,15) -> 25 | AK138: =IF(AI138-T138=24,1,0) -> 0 | AL138: =IF(AH138-AK138=AH138,0,AH138) -> 0 | AM138: =IF(AK138<>0,U138,0) -> 0 | AN138: =IF(AK138=1,O138,0) -> 0 | AO138: =IF(AI138-T138=14,1,0) -> 0 | AP138: =IF(AH138-AO138=AH138,0,AH138) -> 0 | AQ138: =IF(AO138<>0,U138,0) -> 0 | AR138: =IF(AO138=1,O138,0) -> 0 | AS138: =IF(SUM(I138:M138)<>0,1,0) -> 0 | AT138: =AS138 -> 0 | AU138: =IF(O138>0,1,0) -> 0 | AV138: =IF(AK138+AO138+AU138=1,AU138,0) -> 0 | AW138: =IF(AI138-AV138=24,1,0) -> 0 | AX138: =IF(AH138-AW138=AH138,0,AH138) -> 0 | AY138: =IF(AW138=1,O138,0) -> 0 | AZ138: =IF(AY138-BA138<>0,AY138,0) -> 0 | BA138: =IF(AY138<0,AY138,0) -> 0 | BB138: =IF(AI138-AV138=14,1,0) -> 0 | BC138: =IF(AH138-BB138=AH138,0,AH138) -> 0 | BD138: =IF(BB138=1,O138,0) -> 0 | BE138: =IF(BD138<0,BD138,0) -> 0 | BF138: =IF(BD138-BE138<>0,BD138,0) -> 0
A139: 3491 | B139: SIMAN JUANA BEATRIZ | C139: 264-5058882 | D139: SAN JUAN | E139: 20356 | F139: 15 | G139: 200000 | H139: 0 | N139: =IF(H139>0,G139+H139-I139-J139-K139-L139-M139,G139-I139-J139-K139-L139-M139) -> 200000 | O139: =G139+H139-J139-I139-K139-L139-M139 -> 200000 | P139: =IF(G139+H139<0,0,G139+H139) -> 200000 | S139: 46206 | X139: 7 | Y139: 7 | Z139: =IF(N139<0,0,N139) -> 200000 | AH139: 1 | AI139: =IF(F139<=6,15,25) -> 25 | AJ139: =IF(O139<>0,25,15) -> 25 | AK139: =IF(AI139-T139=24,1,0) -> 0 | AL139: =IF(AH139-AK139=AH139,0,AH139) -> 0 | AM139: =IF(AK139<>0,U139,0) -> 0 | AN139: =IF(AK139=1,O139,0) -> 0 | AO139: =IF(AI139-T139=14,1,0) -> 0 | AP139: =IF(AH139-AO139=AH139,0,AH139) -> 0 | AQ139: =IF(AO139<>0,U139,0) -> 0 | AR139: =IF(AO139=1,O139,0) -> 0 | AS139: =IF(SUM(I139:M139)<>0,1,0) -> 0 | AT139: =AS139 -> 0 | AU139: =IF(O139>0,1,0) -> 1 | AV139: =IF(AK139+AO139+AU139=1,AU139,0) -> 1 | AW139: =IF(AI139-AV139=24,1,0) -> 1 | AX139: =IF(AH139-AW139=AH139,0,AH139) -> 1 | AY139: =IF(AW139=1,O139,0) -> 200000 | AZ139: =IF(AY139-BA139<>0,AY139,0) -> 200000 | BA139: =IF(AY139<0,AY139,0) -> 0 | BB139: =IF(AI139-AV139=14,1,0) -> 0 | BC139: =IF(AH139-BB139=AH139,0,AH139) -> 0 | BD139: =IF(BB139=1,O139,0) -> 0 | BE139: =IF(BD139<0,BD139,0) -> 0 | BF139: =IF(BD139-BE139<>0,BD139,0) -> 0
A140: 3548 | B140: ALCANIS SUSANA ELIZABETH | C140: 264-5778208 | D140: SAN JUAN | E140: 10674 | F140: 4 | G140: 100000 | H140: 0 | N140: =IF(H140>0,G140+H140-I140-J140-K140-L140-M140,G140-I140-J140-K140-L140-M140) -> 100000 | O140: =G140+H140-J140-I140-K140-L140-M140 -> 100000 | P140: =IF(G140+H140<0,0,G140+H140) -> 100000 | S140: 46234 | X140: 7 | Y140: 7 | Z140: =IF(N140<0,0,N140) -> 100000 | AH140: 1 | AI140: =IF(F140<=6,15,25) -> 15 | AJ140: =IF(O140<>0,25,15) -> 25 | AK140: =IF(AI140-T140=24,1,0) -> 0 | AL140: =IF(AH140-AK140=AH140,0,AH140) -> 0 | AM140: =IF(AK140<>0,U140,0) -> 0 | AN140: =IF(AK140=1,O140,0) -> 0 | AO140: =IF(AI140-T140=14,1,0) -> 0 | AP140: =IF(AH140-AO140=AH140,0,AH140) -> 0 | AQ140: =IF(AO140<>0,U140,0) -> 0 | AR140: =IF(AO140=1,O140,0) -> 0 | AS140: =IF(SUM(I140:M140)<>0,1,0) -> 0 | AT140: =AS140 -> 0 | AU140: =IF(O140>0,1,0) -> 1 | AV140: =IF(AK140+AO140+AU140=1,AU140,0) -> 1 | AW140: =IF(AI140-AV140=24,1,0) -> 0 | AX140: =IF(AH140-AW140=AH140,0,AH140) -> 0 | AY140: =IF(AW140=1,O140,0) -> 0 | AZ140: =IF(AY140-BA140<>0,AY140,0) -> 0 | BA140: =IF(AY140<0,AY140,0) -> 0 | BB140: =IF(AI140-AV140=14,1,0) -> 1 | BC140: =IF(AH140-BB140=AH140,0,AH140) -> 1 | BD140: =IF(BB140=1,O140,0) -> 100000 | BE140: =IF(BD140<0,BD140,0) -> 0 | BF140: =IF(BD140-BE140<>0,BD140,0) -> 100000
B141: TOTAL COB SIN CUP | G141: ='COBRANZA SIN CUPONES'!G26 -> 0 | I141: ='COBRANZA SIN CUPONES'!H26 -> 160000 | J141: ='COBRANZA SIN CUPONES'!I26 -> 0 | O141: =G141+H141-J141-I141-K141-L141-M141 -> -160000 | X141: 1 | AH141: =COUNTIF(A$4:B$140,A141) -> 0 | AI141: =IF(F141<=6,15,25) -> 15 | AJ141: =IF(O141<>0,25,15) -> 25 | AK141: =IF(AI141-T141=24,1,0) -> 0 | AL141: =IF(AH141-AK141=AH141,0,AH141) -> 0 | AM141: =IF(AK141<>0,U141,0) -> 0 | AN141: =IF(AK141=1,O141,0) -> 0 | AO141: =IF(AI141-T141=14,1,0) -> 0 | AP141: =IF(AH141-AO141=AH141,0,AH141) -> 0 | AQ141: =IF(AO141<>0,U141,0) -> 0 | AR141: =IF(AO141=1,O141,0) -> 0 | AS141: =IF(SUM(I141:M141)<>0,1,0) -> 1 | AT141: =AS141 -> 1 | AU141: =IF(O141>0,1,0) -> 0 | AV141: =IF(AK141+AO141+AU141=1,AU141,0) -> 0 | AW141: =IF(AI141-AV141=24,1,0) -> 0 | AX141: =IF(AH141-AW141=AH141,0,AH141) -> 0 | AY141: =IF(AW141=1,O141,0) -> 0 | AZ141: =IF(AY141-BA141<>0,AY141,0) -> 0 | BA141: =IF(AY141<0,AY141,0) -> 0 | BB141: =IF(AI141-AV141=14,1,0) -> 0 | BC141: =IF(AH141-BB141=AH141,0,AH141) -> 0 | BD141: =IF(BB141=1,O141,0) -> 0 | BE141: =IF(BD141<0,BD141,0) -> 0 | BF141: =IF(BD141-BE141<>0,BD141,0) -> 0
I142: NORMAL | J142: ADELANTADO | K142: X AJUSTE | M142: X AJUSTES CAJAS | Q142: DIF. FINANCIERA | AH142: =COUNTIF(AH4:AH140,"1") -> 137
AH143: =COUNTIFS($X$1:$X$140,$A$1,AH1:AH140,1) -> 137 | AI143: ******* | AJ143: ******* | AK143: =SUMIF($X$4:$X$140,$A$1,AK4:AK140) -> 0 | AL143: =COUNTIFS($X$1:$X$140,$A$1,AL1:AL140,1) -> 0 | AM143: =COUNTIFS($X$1:$X$140,$A$1,AM1:AM140,1) -> 0 | AN143: =SUMIF($X$4:$X$140,$A$1,AN4:AN140) -> 0 | AO143: =SUMIF($X$4:$X$140,$A$1,AO4:AO140) -> 0 | AP143: =COUNTIFS($X$1:$X$140,$A$1,AP1:AP140,1) -> 0 | AQ143: =COUNTIFS($X$1:$X$140,$A$1,AQ1:AQ140,1) -> 0 | AR143: =SUMIF($X$4:$X$140,$A$1,AR4:AR140) -> 0 | AS143: =SUMIF($X$4:$X$140,$A$1,AS4:AS140) -> 0 | AT143: =COUNTIFS($X$1:$X$140,$A$1,AT1:AT140,1) -> 0 | AU143: =SUMIF($X$4:$X$140,$A$1,AU4:AU140) -> 120 | AV143: =COUNTIFS($X$1:$X$140,$A$1,AV1:AV140,1) -> 120 | AW143: =SUMIF($X$4:$X$140,$A$1,AW4:AW140) -> 119 | AX143: =COUNTIFS($X$1:$X$140,$A$1,AX1:AX140,1) -> 119 | AY143: =SUMIF($X$4:$X$140,$A$1,AY4:AY140) -> 9428961.8 | AZ143: =SUMIF($X$4:$X$140,$A$1,AZ4:AZ140) -> 9428961.8 | BA143: =SUMIF($X$4:$X$140,$A$1,BA4:BA140) -> 0 | BB143: =SUMIF($X$4:$X$140,$A$1,BB4:BB140) -> 1 | BC143: =COUNTIFS($X$1:$X$140,$A$1,BC1:BC140,1) -> 1 | BD143: =SUMIF($X$4:$X$140,$A$1,BD4:BD140) -> 100000 | BE143: =SUMIF($X$4:$X$140,$A$1,BE4:BE140) -> 0 | BF143: =SUMIF($X$4:$X$140,$A$1,BF4:BF140) -> 100000
P151: OBLIGACION DE PAGO
A152: =COUNTIF(X4:X140,A1) -> 137 | B152: CLIENTES | C152: TOTAL COBRANZA NORMAL ----> | E152: =I152 -> 0 | F152: A COBRAR | G152: =SUMIF(X4:X140,A1,G4:G140) -> 11550995 | H152: =SUMIF(X4:X140,A1,H4:H140) -> -3437050.2 | I152: =SUMIF(X4:X140,A1,I4:I140) -> 0 | J152: =SUMIF(X4:X140,A1,J4:J140) -> 0 | K152: =SUMIF(X4:X140,A1,K4:K140) -> 0 | L152: =SUMIF(X4:X140,A1,L4:L140) -> 0 | M152: =SUMIF(X4:X140,A1,M4:M140) -> 0 | N152: =SUM(N4:N141) -> 11755995 | O152: =SUMIF(X4:X140,A1,O4:O140) -> 8113944.8 | P152: =SUMIF(X4:X140,A1,P4:P140) -> 9528961.8 | Q152: =P152-O152 -> 1415017 | T152: =SUMIF(X4:X140,A1,T4:T140) -> 0 | U152: =COUNTIFS(X1:X140,A1,U1:U140,"<=5") -> 0 | Z152: =SUM(Z4:Z141) -> 11755995
A153: =AH142 -> 137 | B153: TOTAL CLIENTES | C153: TOTAL COBRANZA X ADELANTADO-> | E153: =J152 -> 0
C154: TOTAL COBRANZA DE TERCEROS-> | E154: =L152 -> 0
C155: TOTAL COBRANZA S/CUPONES -> | E155: ='COBRANZA SIN CUPONES'!J26 -> 160000 | F155: TOTAL ABONADO AL COBRADOR--> | I155: =E152+E153+E155 -> 160000 | L155: COBRANZA | M155: COMISION
C156: TOTAL COBRANZA X M. ELECT-> | E156: =M152 -> 0 | J156: NORMAL | L156: =I152 -> 0 | M156: =L156*M165% -> 0
C157: TOTAL COBRANZA | E157: =SUM(E152:E156) -> 160000 | J157: X ADELANTADO | L157: =E153 -> 0 | M157: =L157*M166% -> 0
J158: X OFICINA | L158: =E154 -> 0 | M158: =L158*M168% -> 0
J159: SIN CUPONES | L159: =E155 -> 160000 | M159: =L159*M165% -> 12800
J160: X M ELECTRONICOS | L160: =E156 -> 0 | M160: =L160*M167% -> 0
E161: $ | F161: % | J161: TOTALES | L161: =SUM(L156:L160) -> 160000 | M161: =SUM(M156:M160) -> 12800
A162: CLIENTES | C162: IMPORTE | D162: CUOTAS | E162: X CLIENTE
A163: =A152 -> 137 | B163: TOTAL | C163: =P152 -> 9528961.8 | D163: =A152 -> 137 | E163: =C163/A163 -> 69554.465 | F163: =H163-G163 -> 1 | G163: =IF(H163=100,0,SUM(F164+F167+F168+F171+F169)-1) -> 0 | H163: =SUM(F164+F167+F168+F171+F169) -> 1
A164: =A165+A166 -> 0 | B164: BAJAS | C164: =C165+C166 -> 0 | D164: =T152 -> 0 | E164: =C164/D164 -> #DIV/0! | F164: =C164/C163 -> 0 | O164: TOTAL SALIDO | Q164: =SUMIF(H4:H140,">0",H4:H140)+G152 -> 11755995
A165: =AP143 -> 0 | B165: BAJA CTA 1-6 | C165: =AR143 -> 0 | D165: =AO143 -> 0 | E165: =C165/D165 -> #DIV/0! | F165: =C165/C163 -> 0 | L165: COMISION % | M165: 8 | O165: TOTAL COBRADO | Q165: =E157 -> 160000
A166: =AL143 -> 0 | B166: BAJA CTA 7-X | C166: =AN143 -> 0 | D166: =AK143 -> 0 | E166: =C166/D166 -> #DIV/0! | F166: =C166/C163 -> 0 | L166: COMISION PAGO X ADEL % | M166: 8 | O166: SALDO | Q166: =Q164-Q165 -> 11595995
A167: =AT143 -> 0 | B167: PAGADOS | C167: =I152+M152+L152 -> 0 | D167: =AS143 -> 0 | E167: =C167/D167 -> #DIV/0! | F167: =C167/C163 -> 0 | G167: =C167/(C163-C164) -> 0 | H167: C/BAJAS | L167: COMISION X BCO. POSNET O M.P % | M167: 8 | O167: PORCENTAJE COBRANZA | Q167: =Q165/Q164 -> 0.013610077
...

Sheet Hoja2
A1: COD
A2: 816 | B2: 1
A3: 823 | B3: 2
A4: 834 | B4: 3
A5: 1186 | B5: 4
A6: 1417 | B6: 5
A7: 1457 | B7: 6
A8: 1597 | B8: 7
A9: 1601 | B9: 8
A10: 1671 | B10: 9
A11: 1791 | B11: 10
A12: 1829 | B12: 11
A13: 1870 | B13: 12
... A138: 3548 | B138: 137

Sheet COBRANZA SIN CUPONES
A1: COBRANZA SIN CUPONES
H2: PAGOS
H3: AUTOHOGAR
A4: COD | B4: CLIENTE | C4: TELEFONO | D4: LOCALIDAD | E4: SOLI | F4: N°CUOTA | G4: VALOR CUOTA | H4: PAGO | I4: PAGO X ADEL | J4: TOTAL | K4: COMISION | L4: A RENDIR | M4: N° COBRADOR | N4: OBSERVACIONES
A5: 1449 | B5: ESCUELA ANA LORENA | E5: 8865 | H5: 160000 | J5: =H5+I5 -> 160000 | K5: =J5*AUTOHOGAR!$M$165% -> 12800 | L5: =J5-K5 -> 147200
J6: =H6+I6 -> 0 | K6: =J6*AUTOHOGAR!$M$165% -> 0 | L6: =J6-K6 -> 0
J7: =H7+I7 -> 0 | K7: =J7*AUTOHOGAR!$M$165% -> 0 | L7: =J7-K7 -> 0
J8: =H8+I8 -> 0 | K8: =J8*AUTOHOGAR!$M$165% -> 0 | L8: =J8-K8 -> 0
J9: =H9+I9 -> 0 | K9: =J9*AUTOHOGAR!$M$165% -> 0 | L9: =J9-K9 -> 0
J10: =H10+I10 -> 0 | K10: =J10*AUTOHOGAR!$M$165% -> 0 | L10: =J10-K10 -> 0
J11: =H11+I11 -> 0 | K11: =J11*AUTOHOGAR!$M$165% -> 0 | L11: =J11-K11 -> 0
J12: =H12+I12 -> 0 | K12: =J12*AUTOHOGAR!$M$165% -> 0 | L12: =J12-K12 -> 0
J13: =H13+I13 -> 0 | K13: =J13*AUTOHOGAR!$M$165% -> 0 | L13: =J13-K13 -> 0
J14: =H14+I14 -> 0 | K14: =J14*AUTOHOGAR!$M$165% -> 0 | L14: =J14-K14 -> 0
J15: =H15+I15 -> 0 | K15: =J15*AUTOHOGAR!$M$165% -> 0 | L15: =J15-K15 -> 0
J16: =H16+I16 -> 0 | K16: =J16*AUTOHOGAR!$M$165% -> 0 | L16: =J16-K16 -> 0
J17: =H17+I17 -> 0 | K17: =J17*AUTOHOGAR!$M$165% -> 0 | L17: =J17-K17 -> 0
... J24: =H24+I24 -> 0 | K24: =J24*AUTOHOGAR!$M$165% -> 0 | L24: =J24-K24 -> 0
A26: =COUNTA(A5:A24) -> 1 | H26: =SUM(H5:H25) -> 160000 | I26: =SUM(I5:I25) -> 0 | J26: =SUM(J5:J25) -> 160000 | K26: =SUM(K5:K25) -> 12800 | L26: =SUM(L5:L25) -> 147200

Sheet PAGARA
A1: CLIENTE | B1: (Todas)
A3: Etiquetas de fila | B3: Suma de CON MORA
A4: (en blanco) | B4: 476000
A5: Total general | B5: 476000

Sheet PAGARA DETALLADO
A3: Suma de CON MORA | B3: Etiquetas de columna
A4: Etiquetas de fila | B4: (en blanco) | C4: Total general
A5: ESTRELLA MICAELA DEL ROCIO | B5: 11000 | C5: 11000 | R5: 45540
A6: RAMIREZ PAULA ALEJANDRA | B6: 15000 | C6: 15000
A7: MOLINI BETINA LAURA | B7: 10000 | C7: 10000
A8: AGUILAR FIDEL CHOQUE | B8: 20000 | C8: 20000
A9: OYOLA SANCHEZ SABRINA MAILEN | B9: 4000 | C9: 4000 | M9: 30000 | Q9: 45547 | V9: GALICIA
A10: CARRIZO ALEJANDRA NELLY | B10: 9000 | C10: 9000 | R10: 45551
A11: HERRERA FRANCISCO ANTONIO | B11: 12000 | C11: 12000
A12: CARPIO NORMA ANA | B12: 7000 | C12: 7000
A13: LORENZETTI LANZILOTTA SANDRA P. | B13: 10000 | C13: 10000
A14: VARGAS MARIA HORTENCIA | B14: 6000 | C14: 6000 | R14: 45625
A15: BALMACEDA MAZA FRANCISCO EMILIO | B15: 7000 | C15: 7000 | R15: 45618
A16: CAJAS HUGO RICARDO | B16: 10000 | C16: 10000 | V16: en febro aumenta esta con un prestamo
A17: OCHOA BARBARA YAMILA | B17: 6000 | C17: 6000 | I17: 30000 | Q17: 45542
A18: ALANIZ CINTIA MACARENA | B18: 5000 | C18: 5000
A19: HEREDIA JUAN CARLOS | B19: 10000 | C19: 10000
A20: AGÜERO PATRICIO JAVIER | B20: 5000 | C20: 5000 | I20: 30000 | Q20: 45545
A21: BUSTOS NELLY MABEL | B21: 6800 | C21: 6800 | I21: 30000 | Q21: 45547 | V21: aumenta a 60.000
A22: ZAMBRA MARIA SOLEDAD | B22: 10000 | C22: 10000 | M22: 30000 | Q22: 45547 | R22: 45547
A23: GALDEANO CARRIZO HERNAN | B23: 8000 | C23: 8000
A24: PASTEN OLMOS ROSA MANUELA | B24: 4500 | C24: 4500
A25: AGUERO CARLOS MORENO | B25: 9000 | C25: 9000
A26: PUJADO LOBOS MARTIN DAVID | B26: 3000 | C26: 3000
A27: MARINERO GERMAN ANTONIO | B27: 10000 | C27: 10000
A28: MOLINA EMANUEL MARCOS JAIRO | B28: 8000 | C28: 8000 | R28: 45551 | V28: no aumenta
A29: OCAMPO BLAS RICARDO | B29: 7000 | C29: 7000
A30: MERCADO ANA BELEN | B30: 7000 | C30: 7000
A31: KENNY NOELIA VANESA | B31: 10000 | C31: 10000
A32: CAROSELLI YANINA CAROLINA | B32: 6000 | C32: 6000 | I32: 30000 | Q32: 45615 | R32: 45615 | V32: no aumenta
A33: PEREZ LUCAS SEBASTIAN | B33: 4000 | C33: 4000
A34: SALCEDO JORGE LUIS | B34: 8500 | C34: 8500
A35: NUÑEZ PAMELA GISELLE | B35: 8000 | C35: 8000
A36: GUTIERREZ ATENCIO ELDA VANESA | B36: 10000 | C36: 10000 | R36: 45551
A37: CEVALLE JORGE LEONARDO | B37: 12000 | C37: 12000 | I37: 35000 | Q37: 45615 | R37: 45615 | V37: aumenta a 55.000
A38: SILLERO GABRIELA SOLEDAD | B38: 5000 | C38: 5000
A39: NAVARRO EDUARDO AGUSTIN | B39: 15000 | C39: 15000 | V39: no aumenta
A40: RIVEROS DAYANA ESTEFANIA | B40: 10000 | C40: 10000 | R40: 45623
A41: CASTRO OSCAR ALBERTO | B41: 9700 | C41: 9700 | R41: 45617
A42: ARIA MIRTA GLADYS | B42: 5000 | C42: 5000
A43: SANTAMARIA RIVEROS DAYANA ELIANA | B43: 10000 | C43: 10000 | V43: no aumenta
A44: MALLEA ATENCIO PAULA CECILIA | B44: 7000 | C44: 7000 | M44: 30000 | Q44: 45615 | V44: no aumenta
A45: FERRA CASTRO GASTON MAXIMILIANO | B45: 8000 | C45: 8000 | R45: 45551 | V45: aumetna a 60000
A46: GATICA SEBASTIAN DARIO | B46: 12000 | C46: 12000
A47: MERCADO MOLINA LEILA BELEN | B47: 5000 | C47: 5000 | I47: 30000 | Q47: 45614 | R47: 45614 | V47: no aumenta
A48: PARRA SIXTO ANTONIO | B48: 5000 | C48: 5000 | I48: 30000 | Q48: 45548 | R48: 45548 | V48: posible baja no aumenta
A49: GOMEZ CARINA JULIETA | B49: 10000 | C49: 10000 | R49: 45616
A50: OLIVERA GISELA ROMINA | B50: 12000 | C50: 12000 | V50: no aumenta
A51: JOFRE CAROLINA IVANA | B51: 6000 | C51: 6000 | V51: no aumenta
A52: ILLANES EDUARDO ADRIAN | B52: 15000 | C52: 15000
A53: JANAVEL SILVIA LILIANA | B53: 8500 | C53: 8500 | R53: 45617 | V53: aumenta a 80.000
A54: CASTAN MARIA ARGENTINA | B54: 10000 | C54: 10000 | V54: no aumenta
A55: ANDRADA JORGELINA AIDA | B55: 12000 | C55: 12000 | R55: 45617
A56: MERCADO MOLINA DAYANA ELIZABETH | B56: 5000 | C56: 5000
A57: LIZARDE SERGIO DANIEL | B57: 7000 | C57: 7000 | R57: 45618
A58: PAEZ EDUARDO ANTONIO | B58: 10000 | C58: 10000 | I58: 30000 | Q58: 45548 | R58: 45548
A59: JOFRE GRACIELA CRISTINA | B59: 10000 | C59: 10000 | R59: 45624
A60: Total general | B60: 476000 | C60: 476000 | V60: no aumenta
I61: 25000 | Q61: 45615 | R61: 45551 | V61: no aumenta
R62: 45551
M63: 55000 | Q63: 45548 | R63: 45548 | V63: MERCADO PAGO
R66: 45551 | V66: no aumenta mas no puede
R68: 45624
V70: no aumenta
V72: no puede aumenta mas
I73: 30000 | Q73: 45545 | V73: aumenta a 55.000
V74: no aumenta
M75: 30000 | Q75: 45547 | R75: 45547 | V75: aumenta a 60.000
V78: tiene discapacida no puede aumentar
R80: 45551
M85: 30000 | Q85: 45548 | R85: 45548 | V85: MERCADO PAGO
V86: no aumenta
I88: 30000 | Q88: 45544
R89: 45551
M90: 30000 | Q90: 45615 | V90: no aumenta
R91: 45551 | V91: no puede pagar mas
R92: 45551
V93: esta con problema de salud estuvo grave
V94: no puede pagar mas q 30.000
I95: 30000 | Q95: 45615 | V95: aumenta a 30000
R96: 45624
I97: 40000 | Q97: 45545 | V97: aumenta a 55.000
V99: no aumenta
I100: 40000 | Q100: 45548 | R100: 45548 | V100: no peude pagar mas q 30.000
R101: 45618
I102: 30000 | Q102: 45548 | R102: 45621
R103: 45551 | V103: aumenta a 60.000
V105: aumenta a 60.000
I106: 30000 | Q106: 45615 | T106: 1 | U106: 1 | V106: pausa plan paga la carpeta carbajl norma 3 carpetas mas
I107: 30000 | Q107: 45548 | R107: 45548 | V107: aumenta a 55.000
R108: 45618
R109: 45617
R110: 45551 | V110: no quiere auemntar mas quiere la casa se le hablo mas de una vez queria poner abogado
R112: 45551 | V112: no aumenta
M113: 10000 | Q113: 45615 | R113: 45551 | V113: no aumenta
I115: 30000 | Q115: 45547
R116: 45619
V117: ya aumento
V118: no puede pagar mas
R124: 45551 | V124: paga en 2 veces porque no le alcanza no puede aumentar
...

Sheet COB
A1: 1 | B1: BANCO | C1: 1
A2: 2 | B2: OFICINA SAN JUAN | C2: 3
A3: 3 | C3: 1
A4: 4 | B4: COBRADOR SAN JUAN | C4: 2
A5: 5 | C5: 1
A6: 6 | C6: 1
A7: 7 | B7: MEDIOS ELECTRONICOS | C7: 3
A8: 8 | C8: 2
A9: 9 | C9: 2
B14: BANCO O M ELECTRONICOS | C14: =COUNTIF(C1:C9,1) -> 4
B15: COBRADORES | C15: =COUNTIF(C1:C9,2) -> 3
B16: SUCURSALES | C16: =COUNTIF(C1:C9,3) -> 2
B17: OTRO MEDIO | C17: =COUNTIF(C1:C9,4) -> 0
C19: =SUM(C14:C18) -> 9
