Workbook
Name _GoBack: AUTOHOGAR!#REF!
Name entrega: '[1]Sugerencia Rendiciones '!$BP$2:$BP$11
Name tipo: '[1]Sugerencia Rendiciones '!$D$3:$D$11

Sheet AUTOHOGAR
A1: 7 | B1: =IF(A1<>0,VLOOKUP(A1,COB!A1:B9,2),"COBRADOR INEXISTENTE") -> MEDIOS ELECTRONICOS | D1: AGOSTO | E1: 2026 | F1: TOTAL | I1: EL ARRASTE ES EL DINERO PENDIENTE O A FAVOR DEL CLIENTE | AI1: 15 C 1-6 | AS1: SI EL | AU1: SI EL CLIENTE
G2: A COBRAR | I2: PAGOS | N2: SAL. REAL | O2: SALDO | P2: SALDO /P ESTAD | Q2: FECHAS | Z2: SALDO P/ | AB2: PROBLEMAS | AC2: CORDOBA | AE2: NO PASO | AH2: TOTAL | AI2: 25 C 7-X | AS2: CLIEN PAGO | AU2: DEBE ALGO | AY2: CALCULO | AZ2: MOROSO | BA2: X ADEL | BD2: CALCULO | BE2: X ADEL | BF2: MOROSO
A3: COD | B3: CLIENTE | C3: TELEFONO | D3: LOCALIDAD | E3: SOLI | F3: CTA | G3: CUOTAS | H3: ARRASTRE | I3: PAGO | J3: PAGO X ADEL | K3: PAGO ANTES | L3: X OFICINA | M3: BCO O ELECT | N3: CON MORA | O3: SISTEMA | P3: PLANILLA SALIDA | Q3: PAGO | R3: PAGARA | S3: PAGO MES ANT | T3: BAJA | U3: MOTIVO | V3: OBSERVACIONES | W3: TERMOMETRO | X3: COB | Y3: COB XX | Z3: COMISION | AA3: PAGARA | AB3: CON VEND | AC3: CON VENTAS | AD3: CON PROP. EC | AE3: EL COB | AF3: OTROS | AG3: OBSERVACIONES | AH3: CLIENTES | AI3: paramet 1 | AJ3: paramet 2 | AK3: BAJAS 7-X | AL3: CLIENTES | AM3: MOTIVOS | AN3: $ | AO3: BAJAS 1-6 | AP3: CLIENTES | AQ3: MOTIVOS | AR3: $ | AS3: PAGADOS | AT3: CLIENTES | AU3: MORO O BAJA | AV3: N° CLIEN | AW3: MOROSOS 7 -X | AX3: CLIENTES | AY3: $ | BA3: $ | BB3: MOROSOS 1 -6 | BC3: CLIENTES | BD3: $ | BF3: $
A4: 816 | B4: GUEVARA ANTONIO NICOLAS | C4: 264-4837119 | D4: HUACO | E4: 9287 | F4: 93 | G4: 40000 | H4: 0 | M4: 40000 | N4: =IF(H4>0,G4+H4-I4-J4-K4-L4-M4,G4-I4-J4-K4-L4-M4) -> 0 | O4: =G4+H4-J4-I4-K4-L4-M4 -> 0 | P4: =IF(G4+H4<0,0,G4+H4) -> 40000 | Q4: 46237 | S4: 46205 | V4: MERCADO PAGO | X4: 7 | Y4: 7 | Z4: =IF(N4<0,0,N4) -> 0 | AH4: 1 | AI4: =IF(F4<=6,15,25) -> 25 | AJ4: =IF(O4<>0,25,15) -> 15 | AK4: =IF(AI4-T4=24,1,0) -> 0 | AL4: =IF(AH4-AK4=AH4,0,AH4) -> 0 | AM4: =IF(AK4<>0,U4,0) -> 0 | AN4: =IF(AK4=1,O4,0) -> 0 | AO4: =IF(AI4-T4=14,1,0) -> 0 | AP4: =IF(AH4-AO4=AH4,0,AH4) -> 0 | AQ4: =IF(AO4<>0,U4,0) -> 0 | AR4: =IF(AO4=1,O4,0) -> 0 | AS4: =IF(SUM(I4:M4)<>0,1,0) -> 1 | AT4: =AS4 -> 1 | AU4: =IF(O4>0,1,0) -> 0 | AV4: =IF(AK4+AO4+AU4=1,AU4,0) -> 0 | AW4: =IF(AI4-AV4=24,1,0) -> 0 | AX4: =IF(AH4-AW4=AH4,0,AH4) -> 0 | AY4: =IF(AW4=1,O4,0) -> 0 | AZ4: =IF(AY4-BA4<>0,AY4,0) -> 0 | BA4: =IF(AY4<0,AY4,0) -> 0 | BB4: =IF(AI4-AV4=14,1,0) -> 0 | BC4: =IF(AH4-BB4=AH4,0,AH4) -> 0 | BD4: =IF(BB4=1,O4,0) -> 0 | BE4: =IF(BD4<0,BD4,0) -> 0 | BF4: =IF(BD4-BE4<>0,BD4,0) -> 0
A5: 823 | B5: JOFRE ELIZABETH DEL VALLE | C5: 264-4122541 | D5: JACHAL | E5: 9375 | F5: 93 | G5: 30000 | H5: -3500 | M5: 30000 | N5: =IF(H5>0,G5+H5-I5-J5-K5-L5-M5,G5-I5-J5-K5-L5-M5) -> 0 | O5: =G5+H5-J5-I5-K5-L5-M5 -> -3500 | P5: =IF(G5+H5<0,0,G5+H5) -> 26500 | Q5: 46265 | R5: 46265 | S5: 46234 | V5: MERCADO PAGO | X5: 7 | Y5: 7 | Z5: =IF(N5<0,0,N5) -> 0 | AH5: 1 | AI5: =IF(F5<=6,15,25) -> 25 | AJ5: =IF(O5<>0,25,15) -> 25 | AK5: =IF(AI5-T5=24,1,0) -> 0 | AL5: =IF(AH5-AK5=AH5,0,AH5) -> 0 | AM5: =IF(AK5<>0,U5,0) -> 0 | AN5: =IF(AK5=1,O5,0) -> 0 | AO5: =IF(AI5-T5=14,1,0) -> 0 | AP5: =IF(AH5-AO5=AH5,0,AH5) -> 0 | AQ5: =IF(AO5<>0,U5,0) -> 0 | AR5: =IF(AO5=1,O5,0) -> 0 | AS5: =IF(SUM(I5:M5)<>0,1,0) -> 1 | AT5: =AS5 -> 1 | AU5: =IF(O5>0,1,0) -> 0 | AV5: =IF(AK5+AO5+AU5=1,AU5,0) -> 0 | AW5: =IF(AI5-AV5=24,1,0) -> 0 | AX5: =IF(AH5-AW5=AH5,0,AH5) -> 0 | AY5: =IF(AW5=1,O5,0) -> 0 | AZ5: =IF(AY5-BA5<>0,AY5,0) -> 0 | BA5: =IF(AY5<0,AY5,0) -> 0 | BB5: =IF(AI5-AV5=14,1,0) -> 0 | BC5: =IF(AH5-BB5=AH5,0,AH5) -> 0 | BD5: =IF(BB5=1,O5,0) -> 0 | BE5: =IF(BD5<0,BD5,0) -> 0 | BF5: =IF(BD5-BE5<>0,BD5,0) -> 0
A6: 834 | B6: BALMACEDA ESTER MARIA | C6: 2644442152 | D6: JACHAL | E6: 9034 | F6: 93 | G6: 60000 | H6: -4000 | M6: 60000 | N6: =IF(H6>0,G6+H6-I6-J6-K6-L6-M6,G6-I6-J6-K6-L6-M6) -> 0 | O6: =G6+H6-J6-I6-K6-L6-M6 -> -4000 | P6: =IF(G6+H6<0,0,G6+H6) -> 56000 | Q6: 46265 | R6: 46265 | S6: 46234 | V6: MERCADO PAGO | X6: 7 | Y6: 7 | Z6: =IF(N6<0,0,N6) -> 0 | AH6: 1 | AI6: =IF(F6<=6,15,25) -> 25 | AJ6: =IF(O6<>0,25,15) -> 25 | AK6: =IF(AI6-T6=24,1,0) -> 0 | AL6: =IF(AH6-AK6=AH6,0,AH6) -> 0 | AM6: =IF(AK6<>0,U6,0) -> 0 | AN6: =IF(AK6=1,O6,0) -> 0 | AO6: =IF(AI6-T6=14,1,0) -> 0 | AP6: =IF(AH6-AO6=AH6,0,AH6) -> 0 | AQ6: =IF(AO6<>0,U6,0) -> 0 | AR6: =IF(AO6=1,O6,0) -> 0 | AS6: =IF(SUM(I6:M6)<>0,1,0) -> 1 | AT6: =AS6 -> 1 | AU6: =IF(O6>0,1,0) -> 0 | AV6: =IF(AK6+AO6+AU6=1,AU6,0) -> 0 | AW6: =IF(AI6-AV6=24,1,0) -> 0 | AX6: =IF(AH6-AW6=AH6,0,AH6) -> 0 | AY6: =IF(AW6=1,O6,0) -> 0 | AZ6: =IF(AY6-BA6<>0,AY6,0) -> 0 | BA6: =IF(AY6<0,AY6,0) -> 0 | BB6: =IF(AI6-AV6=14,1,0) -> 0 | BC6: =IF(AH6-BB6=AH6,0,AH6) -> 0 | BD6: =IF(BB6=1,O6,0) -> 0 | BE6: =IF(BD6<0,BD6,0) -> 0 | BF6: =IF(BD6-BE6<>0,BD6,0) -> 0
A7: 1186 | B7: GARAY MARCELO | C7: 264-5269535 | D7: SAN JUAN | E7: 8984 | F7: 84 | G7: 80000 | H7: -24000 | M7: 80000 | N7: =IF(H7>0,G7+H7-I7-J7-K7-L7-M7,G7-I7-J7-K7-L7-M7) -> 0 | O7: =G7+H7-J7-I7-K7-L7-M7 -> -24000 | P7: =IF(G7+H7<0,0,G7+H7) -> 56000 | Q7: 46237 | R7: 46237 | S7: 46211 | V7: MERCADO PAGO | X7: 7 | Y7: 7 | Z7: =IF(N7<0,0,N7) -> 0 | AH7: 1 | AI7: =IF(F7<=6,15,25) -> 25 | AJ7: =IF(O7<>0,25,15) -> 25 | AK7: =IF(AI7-T7=24,1,0) -> 0 | AL7: =IF(AH7-AK7=AH7,0,AH7) -> 0 | AM7: =IF(AK7<>0,U7,0) -> 0 | AN7: =IF(AK7=1,O7,0) -> 0 | AO7: =IF(AI7-T7=14,1,0) -> 0 | AP7: =IF(AH7-AO7=AH7,0,AH7) -> 0 | AQ7: =IF(AO7<>0,U7,0) -> 0 | AR7: =IF(AO7=1,O7,0) -> 0 | AS7: =IF(SUM(I7:M7)<>0,1,0) -> 1 | AT7: =AS7 -> 1 | AU7: =IF(O7>0,1,0) -> 0 | AV7: =IF(AK7+AO7+AU7=1,AU7,0) -> 0 | AW7: =IF(AI7-AV7=24,1,0) -> 0 | AX7: =IF(AH7-AW7=AH7,0,AH7) -> 0 | AY7: =IF(AW7=1,O7,0) -> 0 | AZ7: =IF(AY7-BA7<>0,AY7,0) -> 0 | BA7: =IF(AY7<0,AY7,0) -> 0 | BB7: =IF(AI7-AV7=14,1,0) -> 0 | BC7: =IF(AH7-BB7=AH7,0,AH7) -> 0 | BD7: =IF(BB7=1,O7,0) -> 0 | BE7: =IF(BD7<0,BD7,0) -> 0 | BF7: =IF(BD7-BE7<>0,BD7,0) -> 0
A8: 1417 | B8: GARAY MARCELO ROBERTO | C8: 264-5269535 | D8: SAN JUAN | E8: 8539 | F8: 77 | G8: 80000 | H8: -6000 | M8: 80000 | N8: =IF(H8>0,G8+H8-I8-J8-K8-L8-M8,G8-I8-J8-K8-L8-M8) -> 0 | O8: =G8+H8-J8-I8-K8-L8-M8 -> -6000 | P8: =IF(G8+H8<0,0,G8+H8) -> 74000 | Q8: 46237 | R8: 46237 | S8: 46211 | V8: MERCADO PAGO | X8: 7 | Y8: 7 | Z8: =IF(N8<0,0,N8) -> 0 | AH8: 1 | AI8: =IF(F8<=6,15,25) -> 25 | AJ8: =IF(O8<>0,25,15) -> 25 | AK8: =IF(AI8-T8=24,1,0) -> 0 | AL8: =IF(AH8-AK8=AH8,0,AH8) -> 0 | AM8: =IF(AK8<>0,U8,0) -> 0 | AN8: =IF(AK8=1,O8,0) -> 0 | AO8: =IF(AI8-T8=14,1,0) -> 0 | AP8: =IF(AH8-AO8=AH8,0,AH8) -> 0 | AQ8: =IF(AO8<>0,U8,0) -> 0 | AR8: =IF(AO8=1,O8,0) -> 0 | AS8: =IF(SUM(I8:M8)<>0,1,0) -> 1 | AT8: =AS8 -> 1 | AU8: =IF(O8>0,1,0) -> 0 | AV8: =IF(AK8+AO8+AU8=1,AU8,0) -> 0 | AW8: =IF(AI8-AV8=24,1,0) -> 0 | AX8: =IF(AH8-AW8=AH8,0,AH8) -> 0 | AY8: =IF(AW8=1,O8,0) -> 0 | AZ8: =IF(AY8-BA8<>0,AY8,0) -> 0 | BA8: =IF(AY8<0,AY8,0) -> 0 | BB8: =IF(AI8-AV8=14,1,0) -> 0 | BC8: =IF(AH8-BB8=AH8,0,AH8) -> 0 | BD8: =IF(BB8=1,O8,0) -> 0 | BE8: =IF(BD8<0,BD8,0) -> 0 | BF8: =IF(BD8-BE8<>0,BD8,0) -> 0
A9: 1457 | B9: PASTEN EMILCE SABRINA | C9: 264-4739119 | D9: RIVADAVIA | E9: 8864 | F9: 76 | G9: 60000 | H9: -15000 | M9: 60000 | N9: =IF(H9>0,G9+H9-I9-J9-K9-L9-M9,G9-I9-J9-K9-L9-M9) -> 0 | O9: =G9+H9-J9-I9-K9-L9-M9 -> -15000 | P9: =IF(G9+H9<0,0,G9+H9) -> 45000 | Q9: 46265 | R9: 46265 | S9: 46234 | V9: MERCADO PAGO | X9: 7 | Y9: 7 | Z9: =IF(N9<0,0,N9) -> 0 | AH9: 1 | AI9: =IF(F9<=6,15,25) -> 25 | AJ9: =IF(O9<>0,25,15) -> 25 | AK9: =IF(AI9-T9=24,1,0) -> 0 | AL9: =IF(AH9-AK9=AH9,0,AH9) -> 0 | AM9: =IF(AK9<>0,U9,0) -> 0 | AN9: =IF(AK9=1,O9,0) -> 0 | AO9: =IF(AI9-T9=14,1,0) -> 0 | AP9: =IF(AH9-AO9=AH9,0,AH9) -> 0 | AQ9: =IF(AO9<>0,U9,0) -> 0 | AR9: =IF(AO9=1,O9,0) -> 0 | AS9: =IF(SUM(I9:M9)<>0,1,0) -> 1 | AT9: =AS9 -> 1 | AU9: =IF(O9>0,1,0) -> 0 | AV9: =IF(AK9+AO9+AU9=1,AU9,0) -> 0 | AW9: =IF(AI9-AV9=24,1,0) -> 0 | AX9: =IF(AH9-AW9=AH9,0,AH9) -> 0 | AY9: =IF(AW9=1,O9,0) -> 0 | AZ9: =IF(AY9-BA9<>0,AY9,0) -> 0 | BA9: =IF(AY9<0,AY9,0) -> 0 | BB9: =IF(AI9-AV9=14,1,0) -> 0 | BC9: =IF(AH9-BB9=AH9,0,AH9) -> 0 | BD9: =IF(BB9=1,O9,0) -> 0 | BE9: =IF(BD9<0,BD9,0) -> 0 | BF9: =IF(BD9-BE9<>0,BD9,0) -> 0
A10: 1597 | B10: ALMAZAN JUAN ARIEL | C10: 264-6245764 | D10: RAWSON | E10: 9625 | F10: 73 | G10: 60000 | H10: 0 | M10: 60000 | N10: =IF(H10>0,G10+H10-I10-J10-K10-L10-M10,G10-I10-J10-K10-L10-M10) -> 0 | O10: =G10+H10-J10-I10-K10-L10-M10 -> 0 | P10: =IF(G10+H10<0,0,G10+H10) -> 60000 | Q10: 46265 | R10: 46265 | S10: 46234 | V10: MERCADO PAGO | X10: 7 | Y10: 7 | Z10: =IF(N10<0,0,N10) -> 0 | AH10: 1 | AI10: =IF(F10<=6,15,25) -> 25 | AJ10: =IF(O10<>0,25,15) -> 15 | AK10: =IF(AI10-T10=24,1,0) -> 0 | AL10: =IF(AH10-AK10=AH10,0,AH10) -> 0 | AM10: =IF(AK10<>0,U10,0) -> 0 | AN10: =IF(AK10=1,O10,0) -> 0 | AO10: =IF(AI10-T10=14,1,0) -> 0 | AP10: =IF(AH10-AO10=AH10,0,AH10) -> 0 | AQ10: =IF(AO10<>0,U10,0) -> 0 | AR10: =IF(AO10=1,O10,0) -> 0 | AS10: =IF(SUM(I10:M10)<>0,1,0) -> 1 | AT10: =AS10 -> 1 | AU10: =IF(O10>0,1,0) -> 0 | AV10: =IF(AK10+AO10+AU10=1,AU10,0) -> 0 | AW10: =IF(AI10-AV10=24,1,0) -> 0 | AX10: =IF(AH10-AW10=AH10,0,AH10) -> 0 | AY10: =IF(AW10=1,O10,0) -> 0 | AZ10: =IF(AY10-BA10<>0,AY10,0) -> 0 | BA10: =IF(AY10<0,AY10,0) -> 0 | BB10: =IF(AI10-AV10=14,1,0) -> 0 | BC10: =IF(AH10-BB10=AH10,0,AH10) -> 0 | BD10: =IF(BB10=1,O10,0) -> 0 | BE10: =IF(BD10<0,BD10,0) -> 0 | BF10: =IF(BD10-BE10<>0,BD10,0) -> 0
A11: 1601 | B11: BUSTOS ELIZABETH NOEMI | C11: 264-5207638 | D11: SANTA LUCIA | E11: 9594 | F11: 73 | G11: 80000 | H11: 0 | M11: 80000 | N11: =IF(H11>0,G11+H11-I11-J11-K11-L11-M11,G11-I11-J11-K11-L11-M11) -> 0 | O11: =G11+H11-J11-I11-K11-L11-M11 -> 0 | P11: =IF(G11+H11<0,0,G11+H11) -> 80000 | Q11: 46238 | R11: 46238 | S11: 46209 | V11: MERCADO PAGO | X11: 7 | Y11: 7 | Z11: =IF(N11<0,0,N11) -> 0 | AH11: 1 | AI11: =IF(F11<=6,15,25) -> 25 | AJ11: =IF(O11<>0,25,15) -> 15 | AK11: =IF(AI11-T11=24,1,0) -> 0 | AL11: =IF(AH11-AK11=AH11,0,AH11) -> 0 | AM11: =IF(AK11<>0,U11,0) -> 0 | AN11: =IF(AK11=1,O11,0) -> 0 | AO11: =IF(AI11-T11=14,1,0) -> 0 | AP11: =IF(AH11-AO11=AH11,0,AH11) -> 0 | AQ11: =IF(AO11<>0,U11,0) -> 0 | AR11: =IF(AO11=1,O11,0) -> 0 | AS11: =IF(SUM(I11:M11)<>0,1,0) -> 1 | AT11: =AS11 -> 1 | AU11: =IF(O11>0,1,0) -> 0 | AV11: =IF(AK11+AO11+AU11=1,AU11,0) -> 0 | AW11: =IF(AI11-AV11=24,1,0) -> 0 | AX11: =IF(AH11-AW11=AH11,0,AH11) -> 0 | AY11: =IF(AW11=1,O11,0) -> 0 | AZ11: =IF(AY11-BA11<>0,AY11,0) -> 0 | BA11: =IF(AY11<0,AY11,0) -> 0 | BB11: =IF(AI11-AV11=14,1,0) -> 0 | BC11: =IF(AH11-BB11=AH11,0,AH11) -> 0 | BD11: =IF(BB11=1,O11,0) -> 0 | BE11: =IF(BD11<0,BD11,0) -> 0 | BF11: =IF(BD11-BE11<>0,BD11,0) -> 0
A12: 1671 | B12: TRIGO ESPEJO CARLOS JAVIER | C12: 2645414691 | D12: RAWSON | E12: 9740 | F12: 73 | G12: 30000 | H12: -32000 | M12: 30000 | N12: =IF(H12>0,G12+H12-I12-J12-K12-L12-M12,G12-I12-J12-K12-L12-M12) -> 0 | O12: =G12+H12-J12-I12-K12-L12-M12 -> -32000 | P12: =IF(G12+H12<0,0,G12+H12) -> 0 | Q12: 46265 | R12: 46265 | S12: 46234 | V12: MERCADO PAGO | X12: 7 | Y12: 7 | Z12: =IF(N12<0,0,N12) -> 0 | AH12: 1 | AI12: =IF(F12<=6,15,25) -> 25 | AJ12: =IF(O12<>0,25,15) -> 25 | AK12: =IF(AI12-T12=24,1,0) -> 0 | AL12: =IF(AH12-AK12=AH12,0,AH12) -> 0 | AM12: =IF(AK12<>0,U12,0) -> 0 | AN12: =IF(AK12=1,O12,0) -> 0 | AO12: =IF(AI12-T12=14,1,0) -> 0 | AP12: =IF(AH12-AO12=AH12,0,AH12) -> 0 | AQ12: =IF(AO12<>0,U12,0) -> 0 | AR12: =IF(AO12=1,O12,0) -> 0 | AS12: =IF(SUM(I12:M12)<>0,1,0) -> 1 | AT12: =AS12 -> 1 | AU12: =IF(O12>0,1,0) -> 0 | AV12: =IF(AK12+AO12+AU12=1,AU12,0) -> 0 | AW12: =IF(AI12-AV12=24,1,0) -> 0 | AX12: =IF(AH12-AW12=AH12,0,AH12) -> 0 | AY12: =IF(AW12=1,O12,0) -> 0 | AZ12: =IF(AY12-BA12<>0,AY12,0) -> 0 | BA12: =IF(AY12<0,AY12,0) -> 0 | BB12: =IF(AI12-AV12=14,1,0) -> 0 | BC12: =IF(AH12-BB12=AH12,0,AH12) -> 0 | BD12: =IF(BB12=1,O12,0) -> 0 | BE12: =IF(BD12<0,BD12,0) -> 0 | BF12: =IF(BD12-BE12<>0,BD12,0) -> 0
A13: 1791 | B13: MUÑOZ ALICIA ADRIANA | C13: 264-4700323 | D13: CHIMBAS | E13: 9908 | F13: 71 | G13: 60000 | H13: -15000 | M13: 60000 | N13: =IF(H13>0,G13+H13-I13-J13-K13-L13-M13,G13-I13-J13-K13-L13-M13) -> 0 | O13: =G13+H13-J13-I13-K13-L13-M13 -> -15000 | P13: =IF(G13+H13<0,0,G13+H13) -> 45000 | Q13: 46259 | R13: 46252 | S13: 46223 | V13: EFECTIVO OFICINA | X13: 7 | Y13: 7 | Z13: =IF(N13<0,0,N13) -> 0 | AH13: 1 | AI13: =IF(F13<=6,15,25) -> 25 | AJ13: =IF(O13<>0,25,15) -> 25 | AK13: =IF(AI13-T13=24,1,0) -> 0 | AL13: =IF(AH13-AK13=AH13,0,AH13) -> 0 | AM13: =IF(AK13<>0,U13,0) -> 0 | AN13: =IF(AK13=1,O13,0) -> 0 | AO13: =IF(AI13-T13=14,1,0) -> 0 | AP13: =IF(AH13-AO13=AH13,0,AH13) -> 0 | AQ13: =IF(AO13<>0,U13,0) -> 0 | AR13: =IF(AO13=1,O13,0) -> 0 | AS13: =IF(SUM(I13:M13)<>0,1,0) -> 1 | AT13: =AS13 -> 1 | AU13: =IF(O13>0,1,0) -> 0 | AV13: =IF(AK13+AO13+AU13=1,AU13,0) -> 0 | AW13: =IF(AI13-AV13=24,1,0) -> 0 | AX13: =IF(AH13-AW13=AH13,0,AH13) -> 0 | AY13: =IF(AW13=1,O13,0) -> 0 | AZ13: =IF(AY13-BA13<>0,AY13,0) -> 0 | BA13: =IF(AY13<0,AY13,0) -> 0 | BB13: =IF(AI13-AV13=14,1,0) -> 0 | BC13: =IF(AH13-BB13=AH13,0,AH13) -> 0 | BD13: =IF(BB13=1,O13,0) -> 0 | BE13: =IF(BD13<0,BD13,0) -> 0 | BF13: =IF(BD13-BE13<>0,BD13,0) -> 0
A14: 1829 | B14: MANRIQUE BRIZUELA BARBARA ELIZABETH | C14: 2644112914 | D14: JACHAL | E14: 9936 | F14: 70 | G14: 300000 | H14: -5000 | M14: 300000 | N14: =IF(H14>0,G14+H14-I14-J14-K14-L14-M14,G14-I14-J14-K14-L14-M14) -> 0 | O14: =G14+H14-J14-I14-K14-L14-M14 -> -5000 | P14: =IF(G14+H14<0,0,G14+H14) -> 295000 | Q14: 46255 | R14: 46255 | S14: 46234 | V14: MERCADO PAGO | X14: 7 | Y14: 7 | Z14: =IF(N14<0,0,N14) -> 0 | AH14: 1 | AI14: =IF(F14<=6,15,25) -> 25 | AJ14: =IF(O14<>0,25,15) -> 25 | AK14: =IF(AI14-T14=24,1,0) -> 0 | AL14: =IF(AH14-AK14=AH14,0,AH14) -> 0 | AM14: =IF(AK14<>0,U14,0) -> 0 | AN14: =IF(AK14=1,O14,0) -> 0 | AO14: =IF(AI14-T14=14,1,0) -> 0 | AP14: =IF(AH14-AO14=AH14,0,AH14) -> 0 | AQ14: =IF(AO14<>0,U14,0) -> 0 | AR14: =IF(AO14=1,O14,0) -> 0 | AS14: =IF(SUM(I14:M14)<>0,1,0) -> 1 | AT14: =AS14 -> 1 | AU14: =IF(O14>0,1,0) -> 0 | AV14: =IF(AK14+AO14+AU14=1,AU14,0) -> 0 | AW14: =IF(AI14-AV14=24,1,0) -> 0 | AX14: =IF(AH14-AW14=AH14,0,AH14) -> 0 | AY14: =IF(AW14=1,O14,0) -> 0 | AZ14: =IF(AY14-BA14<>0,AY14,0) -> 0 | BA14: =IF(AY14<0,AY14,0) -> 0 | BB14: =IF(AI14-AV14=14,1,0) -> 0 | BC14: =IF(AH14-BB14=AH14,0,AH14) -> 0 | BD14: =IF(BB14=1,O14,0) -> 0 | BE14: =IF(BD14<0,BD14,0) -> 0 | BF14: =IF(BD14-BE14<>0,BD14,0) -> 0
A15: 1870 | B15: OCHOA ERICA DEBORA | C15: 264-5178841 | D15: SAN JUAN | E15: 9889 | F15: 69 | G15: 40000 | H15: 0 | I15: 40000 | N15: =IF(H15>0,G15+H15-I15-J15-K15-L15-M15,G15-I15-J15-K15-L15-M15) -> 0 | O15: =G15+H15-J15-I15-K15-L15-M15 -> 0 | P15: =IF(G15+H15<0,0,G15+H15) -> 40000 | Q15: 46245 | R15: 46245 | S15: 46225 | V15: EFECTIVO | X15: 7 | Y15: 7 | Z15: =IF(N15<0,0,N15) -> 0 | AH15: 1 | AI15: =IF(F15<=6,15,25) -> 25 | AJ15: =IF(O15<>0,25,15) -> 15 | AK15: =IF(AI15-T15=24,1,0) -> 0 | AL15: =IF(AH15-AK15=AH15,0,AH15) -> 0 | AM15: =IF(AK15<>0,U15,0) -> 0 | AN15: =IF(AK15=1,O15,0) -> 0 | AO15: =IF(AI15-T15=14,1,0) -> 0 | AP15: =IF(AH15-AO15=AH15,0,AH15) -> 0 | AQ15: =IF(AO15<>0,U15,0) -> 0 | AR15: =IF(AO15=1,O15,0) -> 0 | AS15: =IF(SUM(I15:M15)<>0,1,0) -> 1 | AT15: =AS15 -> 1 | AU15: =IF(O15>0,1,0) -> 0 | AV15: =IF(AK15+AO15+AU15=1,AU15,0) -> 0 | AW15: =IF(AI15-AV15=24,1,0) -> 0 | AX15: =IF(AH15-AW15=AH15,0,AH15) -> 0 | AY15: =IF(AW15=1,O15,0) -> 0 | AZ15: =IF(AY15-BA15<>0,AY15,0) -> 0 | BA15: =IF(AY15<0,AY15,0) -> 0 | BB15: =IF(AI15-AV15=14,1,0) -> 0 | BC15: =IF(AH15-BB15=AH15,0,AH15) -> 0 | BD15: =IF(BB15=1,O15,0) -> 0 | BE15: =IF(BD15<0,BD15,0) -> 0 | BF15: =IF(BD15-BE15<>0,BD15,0) -> 0
A16: 1871 | B16: FERNANDEZ GORIA GABRIELA CELESTE | C16: 264-5676031 | D16: RIVADAVIA | E16: 9891 | F16: 69 | G16: 35000 | H16: 0 | M16: 35000 | N16: =IF(H16>0,G16+H16-I16-J16-K16-L16-M16,G16-I16-J16-K16-L16-M16) -> 0 | O16: =G16+H16-J16-I16-K16-L16-M16 -> 0 | P16: =IF(G16+H16<0,0,G16+H16) -> 35000 | Q16: 46265 | R16: 46265 | S16: 46234 | V16: MERCADO PAGO | X16: 7 | Y16: 7 | Z16: =IF(N16<0,0,N16) -> 0 | AH16: 1 | AI16: =IF(F16<=6,15,25) -> 25 | AJ16: =IF(O16<>0,25,15) -> 15 | AK16: =IF(AI16-T16=24,1,0) -> 0 | AL16: =IF(AH16-AK16=AH16,0,AH16) -> 0 | AM16: =IF(AK16<>0,U16,0) -> 0 | AN16: =IF(AK16=1,O16,0) -> 0 | AO16: =IF(AI16-T16=14,1,0) -> 0 | AP16: =IF(AH16-AO16=AH16,0,AH16) -> 0 | AQ16: =IF(AO16<>0,U16,0) -> 0 | AR16: =IF(AO16=1,O16,0) -> 0 | AS16: =IF(SUM(I16:M16)<>0,1,0) -> 1 | AT16: =AS16 -> 1 | AU16: =IF(O16>0,1,0) -> 0 | AV16: =IF(AK16+AO16+AU16=1,AU16,0) -> 0 | AW16: =IF(AI16-AV16=24,1,0) -> 0 | AX16: =IF(AH16-AW16=AH16,0,AH16) -> 0 | AY16: =IF(AW16=1,O16,0) -> 0 | AZ16: =IF(AY16-BA16<>0,AY16,0) -> 0 | BA16: =IF(AY16<0,AY16,0) -> 0 | BB16: =IF(AI16-AV16=14,1,0) -> 0 | BC16: =IF(AH16-BB16=AH16,0,AH16) -> 0 | BD16: =IF(BB16=1,O16,0) -> 0 | BE16: =IF(BD16<0,BD16,0) -> 0 | BF16: =IF(BD16-BE16<>0,BD16,0) -> 0
A17: 1900 | B17: CERDA FABIAN ALEJANDRO | C17: 264-6621777 | D17: CHIMBAS | E17: 10012 | F17: 69 | G17: 60000 | H17: -60000 | M17: 60000 | N17: =IF(H17>0,G17+H17-I17-J17-K17-L17-M17,G17-I17-J17-K17-L17-M17) -> 0 | O17: =G17+H17-J17-I17-K17-L17-M17 -> -60000 | P17: =IF(G17+H17<0,0,G17+H17) -> 0 | Q17: 46265 | R17: 46265 | S17: 46234 | V17: MERCADO PAGO | X17: 7 | Y17: 7 | Z17: =IF(N17<0,0,N17) -> 0 | AH17: 1 | AI17: =IF(F17<=6,15,25) -> 25 | AJ17: =IF(O17<>0,25,15) -> 25 | AK17: =IF(AI17-T17=24,1,0) -> 0 | AL17: =IF(AH17-AK17=AH17,0,AH17) -> 0 | AM17: =IF(AK17<>0,U17,0) -> 0 | AN17: =IF(AK17=1,O17,0) -> 0 | AO17: =IF(AI17-T17=14,1,0) -> 0 | AP17: =IF(AH17-AO17=AH17,0,AH17) -> 0 | AQ17: =IF(AO17<>0,U17,0) -> 0 | AR17: =IF(AO17=1,O17,0) -> 0 | AS17: =IF(SUM(I17:M17)<>0,1,0) -> 1 | AT17: =AS17 -> 1 | AU17: =IF(O17>0,1,0) -> 0 | AV17: =IF(AK17+AO17+AU17=1,AU17,0) -> 0 | AW17: =IF(AI17-AV17=24,1,0) -> 0 | AX17: =IF(AH17-AW17=AH17,0,AH17) -> 0 | AY17: =IF(AW17=1,O17,0) -> 0 | AZ17: =IF(AY17-BA17<>0,AY17,0) -> 0 | BA17: =IF(AY17<0,AY17,0) -> 0 | BB17: =IF(AI17-AV17=14,1,0) -> 0 | BC17: =IF(AH17-BB17=AH17,0,AH17) -> 0 | BD17: =IF(BB17=1,O17,0) -> 0 | BE17: =IF(BD17<0,BD17,0) -> 0 | BF17: =IF(BD17-BE17<>0,BD17,0) -> 0
A18: 1954 | B18: GUTIERREZ ATENCIO ELDA VANESA | C18: 264-4580614 | D18: ZONDA | E18: 10045 | F18: 67 | G18: 50000 | H18: -30000 | M18: 50000 | N18: =IF(H18>0,G18+H18-I18-J18-K18-L18-M18,G18-I18-J18-K18-L18-M18) -> 0 | O18: =G18+H18-J18-I18-K18-L18-M18 -> -30000 | P18: =IF(G18+H18<0,0,G18+H18) -> 20000 | Q18: 46237 | R18: 46237 | S18: 46204 | V18: MERCADO PAGO | X18: 7 | Y18: 7 | Z18: =IF(N18<0,0,N18) -> 0 | AH18: 1 | AI18: =IF(F18<=6,15,25) -> 25 | AJ18: =IF(O18<>0,25,15) -> 25 | AK18: =IF(AI18-T18=24,1,0) -> 0 | AL18: =IF(AH18-AK18=AH18,0,AH18) -> 0 | AM18: =IF(AK18<>0,U18,0) -> 0 | AN18: =IF(AK18=1,O18,0) -> 0 | AO18: =IF(AI18-T18=14,1,0) -> 0 | AP18: =IF(AH18-AO18=AH18,0,AH18) -> 0 | AQ18: =IF(AO18<>0,U18,0) -> 0 | AR18: =IF(AO18=1,O18,0) -> 0 | AS18: =IF(SUM(I18:M18)<>0,1,0) -> 1 | AT18: =AS18 -> 1 | AU18: =IF(O18>0,1,0) -> 0 | AV18: =IF(AK18+AO18+AU18=1,AU18,0) -> 0 | AW18: =IF(AI18-AV18=24,1,0) -> 0 | AX18: =IF(AH18-AW18=AH18,0,AH18) -> 0 | AY18: =IF(AW18=1,O18,0) -> 0 | AZ18: =IF(AY18-BA18<>0,AY18,0) -> 0 | BA18: =IF(AY18<0,AY18,0) -> 0 | BB18: =IF(AI18-AV18=14,1,0) -> 0 | BC18: =IF(AH18-BB18=AH18,0,AH18) -> 0 | BD18: =IF(BB18=1,O18,0) -> 0 | BE18: =IF(BD18<0,BD18,0) -> 0 | BF18: =IF(BD18-BE18<>0,BD18,0) -> 0
A19: 1999 | B19: PEREZ JOSE ISMAEL | C19: 264-5122570 | D19: SAN JUAN | E19: 10192 | F19: 66 | G19: 60000 | H19: -75000 | M19: 120000 | N19: =IF(H19>0,G19+H19-I19-J19-K19-L19-M19,G19-I19-J19-K19-L19-M19) -> -60000 | O19: =G19+H19-J19-I19-K19-L19-M19 -> -135000 | P19: =IF(G19+H19<0,0,G19+H19) -> 0 | Q19: 46265 | R19: 46244 | S19: 46213 | V19: MERCADO PAGO | W19: PAGO AGOSTO Y SEPTIEMBRE | X19: 7 | Y19: 7 | Z19: =IF(N19<0,0,N19) -> 0 | AH19: 1 | AI19: =IF(F19<=6,15,25) -> 25 | AJ19: =IF(O19<>0,25,15) -> 25 | AK19: =IF(AI19-T19=24,1,0) -> 0 | AL19: =IF(AH19-AK19=AH19,0,AH19) -> 0 | AM19: =IF(AK19<>0,U19,0) -> 0 | AN19: =IF(AK19=1,O19,0) -> 0 | AO19: =IF(AI19-T19=14,1,0) -> 0 | AP19: =IF(AH19-AO19=AH19,0,AH19) -> 0 | AQ19: =IF(AO19<>0,U19,0) -> 0 | AR19: =IF(AO19=1,O19,0) -> 0 | AS19: =IF(SUM(I19:M19)<>0,1,0) -> 1 | AT19: =AS19 -> 1 | AU19: =IF(O19>0,1,0) -> 0 | AV19: =IF(AK19+AO19+AU19=1,AU19,0) -> 0 | AW19: =IF(AI19-AV19=24,1,0) -> 0 | AX19: =IF(AH19-AW19=AH19,0,AH19) -> 0 | AY19: =IF(AW19=1,O19,0) -> 0 | AZ19: =IF(AY19-BA19<>0,AY19,0) -> 0 | BA19: =IF(AY19<0,AY19,0) -> 0 | BB19: =IF(AI19-AV19=14,1,0) -> 0 | BC19: =IF(AH19-BB19=AH19,0,AH19) -> 0 | BD19: =IF(BB19=1,O19,0) -> 0 | BE19: =IF(BD19<0,BD19,0) -> 0 | BF19: =IF(BD19-BE19<>0,BD19,0) -> 0
A20: 2010 | B20: PEREYRA NUVIA CELESTE | C20: 264-4829505 | D20: SANTA LUCIA | E20: 10206 | F20: 66 | G20: 30000 | H20: -28000 | M20: 30000 | N20: =IF(H20>0,G20+H20-I20-J20-K20-L20-M20,G20-I20-J20-K20-L20-M20) -> 0 | O20: =G20+H20-J20-I20-K20-L20-M20 -> -28000 | P20: =IF(G20+H20<0,0,G20+H20) -> 2000 | Q20: 46265 | R20: 46265 | S20: 46234 | V20: MERCADO PAGO | X20: 7 | Y20: 7 | Z20: =IF(N20<0,0,N20) -> 0 | AH20: 1 | AI20: =IF(F20<=6,15,25) -> 25 | AJ20: =IF(O20<>0,25,15) -> 25 | AK20: =IF(AI20-T20=24,1,0) -> 0 | AL20: =IF(AH20-AK20=AH20,0,AH20) -> 0 | AM20: =IF(AK20<>0,U20,0) -> 0 | AN20: =IF(AK20=1,O20,0) -> 0 | AO20: =IF(AI20-T20=14,1,0) -> 0 | AP20: =IF(AH20-AO20=AH20,0,AH20) -> 0 | AQ20: =IF(AO20<>0,U20,0) -> 0 | AR20: =IF(AO20=1,O20,0) -> 0 | AS20: =IF(SUM(I20:M20)<>0,1,0) -> 1 | AT20: =AS20 -> 1 | AU20: =IF(O20>0,1,0) -> 0 | AV20: =IF(AK20+AO20+AU20=1,AU20,0) -> 0 | AW20: =IF(AI20-AV20=24,1,0) -> 0 | AX20: =IF(AH20-AW20=AH20,0,AH20) -> 0 | AY20: =IF(AW20=1,O20,0) -> 0 | AZ20: =IF(AY20-BA20<>0,AY20,0) -> 0 | BA20: =IF(AY20<0,AY20,0) -> 0 | BB20: =IF(AI20-AV20=14,1,0) -> 0 | BC20: =IF(AH20-BB20=AH20,0,AH20) -> 0 | BD20: =IF(BB20=1,O20,0) -> 0 | BE20: =IF(BD20<0,BD20,0) -> 0 | BF20: =IF(BD20-BE20<>0,BD20,0) -> 0
A21: 2015 | B21: ELIZONDO MARIO SANTIAGO | C21: 264-5061888 | D21: ALBARDON | E21: 10189 | F21: 66 | G21: 70000 | H21: -118000 | N21: =IF(H21>0,G21+H21-I21-J21-K21-L21-M21,G21-I21-J21-K21-L21-M21) -> 70000 | O21: =G21+H21-J21-I21-K21-L21-M21 -> -48000 | P21: =IF(G21+H21<0,0,G21+H21) -> 0 | S21: 70000 | T21: 1 | U21: 1 | V21: BAJA Y DEVOLUCION | X21: 7 | Y21: 7 | Z21: =IF(N21<0,0,N21) -> 70000 | AH21: 1 | AI21: =IF(F21<=6,15,25) -> 25 | AJ21: =IF(O21<>0,25,15) -> 25 | AK21: =IF(AI21-T21=24,1,0) -> 1 | AL21: =IF(AH21-AK21=AH21,0,AH21) -> 1 | AM21: =IF(AK21<>0,U21,0) -> 1 | AN21: =IF(AK21=1,O21,0) -> -48000 | AO21: =IF(AI21-T21=14,1,0) -> 0 | AP21: =IF(AH21-AO21=AH21,0,AH21) -> 0 | AQ21: =IF(AO21<>0,U21,0) -> 0 | AR21: =IF(AO21=1,O21,0) -> 0 | AS21: =IF(SUM(I21:M21)<>0,1,0) -> 0 | AT21: =AS21 -> 0 | AU21: =IF(O21>0,1,0) -> 0 | AV21: =IF(AK21+AO21+AU21=1,AU21,0) -> 0 | AW21: =IF(AI21-AV21=24,1,0) -> 0 | AX21: =IF(AH21-AW21=AH21,0,AH21) -> 0 | AY21: =IF(AW21=1,O21,0) -> 0 | AZ21: =IF(AY21-BA21<>0,AY21,0) -> 0 | BA21: =IF(AY21<0,AY21,0) -> 0 | BB21: =IF(AI21-AV21=14,1,0) -> 0 | BC21: =IF(AH21-BB21=AH21,0,AH21) -> 0 | BD21: =IF(BB21=1,O21,0) -> 0 | BE21: =IF(BD21<0,BD21,0) -> 0 | BF21: =IF(BD21-BE21<>0,BD21,0) -> 0
A22: 2024 | B22: BUENO VALERIA VANESA | C22: 264-5435239 | D22: RAWSON | E22: 10095 | F22: 66 | G22: 30000 | H22: -24000 | M22: 30000 | N22: =IF(H22>0,G22+H22-I22-J22-K22-L22-M22,G22-I22-J22-K22-L22-M22) -> 0 | O22: =G22+H22-J22-I22-K22-L22-M22 -> -24000 | P22: =IF(G22+H22<0,0,G22+H22) -> 6000 | Q22: 46239 | R22: 46240 | S22: 46209 | V22: MERCADO PAGO | X22: 7 | Y22: 7 | Z22: =IF(N22<0,0,N22) -> 0 | AH22: 1 | AI22: =IF(F22<=6,15,25) -> 25 | AJ22: =IF(O22<>0,25,15) -> 25 | AK22: =IF(AI22-T22=24,1,0) -> 0 | AL22: =IF(AH22-AK22=AH22,0,AH22) -> 0 | AM22: =IF(AK22<>0,U22,0) -> 0 | AN22: =IF(AK22=1,O22,0) -> 0 | AO22: =IF(AI22-T22=14,1,0) -> 0 | AP22: =IF(AH22-AO22=AH22,0,AH22) -> 0 | AQ22: =IF(AO22<>0,U22,0) -> 0 | AR22: =IF(AO22=1,O22,0) -> 0 | AS22: =IF(SUM(I22:M22)<>0,1,0) -> 1 | AT22: =AS22 -> 1 | AU22: =IF(O22>0,1,0) -> 0 | AV22: =IF(AK22+AO22+AU22=1,AU22,0) -> 0 | AW22: =IF(AI22-AV22=24,1,0) -> 0 | AX22: =IF(AH22-AW22=AH22,0,AH22) -> 0 | AY22: =IF(AW22=1,O22,0) -> 0 | AZ22: =IF(AY22-BA22<>0,AY22,0) -> 0 | BA22: =IF(AY22<0,AY22,0) -> 0 | BB22: =IF(AI22-AV22=14,1,0) -> 0 | BC22: =IF(AH22-BB22=AH22,0,AH22) -> 0 | BD22: =IF(BB22=1,O22,0) -> 0 | BE22: =IF(BD22<0,BD22,0) -> 0 | BF22: =IF(BD22-BE22<>0,BD22,0) -> 0
A23: 2095 | B23: PAREDES HUGO ARIEL | C23: 264-7409479 | D23: RODEO | E23: 10288 | F23: 64 | G23: 65000 | H23: 0 | M23: 65000 | N23: =IF(H23>0,G23+H23-I23-J23-K23-L23-M23,G23-I23-J23-K23-L23-M23) -> 0 | O23: =G23+H23-J23-I23-K23-L23-M23 -> 0 | P23: =IF(G23+H23<0,0,G23+H23) -> 65000 | Q23: 46241 | R23: 46241 | S23: 46211 | V23: MERCADO PAGO | X23: 7 | Y23: 7 | Z23: =IF(N23<0,0,N23) -> 0 | AH23: 1 | AI23: =IF(F23<=6,15,25) -> 25 | AJ23: =IF(O23<>0,25,15) -> 15 | AK23: =IF(AI23-T23=24,1,0) -> 0 | AL23: =IF(AH23-AK23=AH23,0,AH23) -> 0 | AM23: =IF(AK23<>0,U23,0) -> 0 | AN23: =IF(AK23=1,O23,0) -> 0 | AO23: =IF(AI23-T23=14,1,0) -> 0 | AP23: =IF(AH23-AO23=AH23,0,AH23) -> 0 | AQ23: =IF(AO23<>0,U23,0) -> 0 | AR23: =IF(AO23=1,O23,0) -> 0 | AS23: =IF(SUM(I23:M23)<>0,1,0) -> 1 | AT23: =AS23 -> 1 | AU23: =IF(O23>0,1,0) -> 0 | AV23: =IF(AK23+AO23+AU23=1,AU23,0) -> 0 | AW23: =IF(AI23-AV23=24,1,0) -> 0 | AX23: =IF(AH23-AW23=AH23,0,AH23) -> 0 | AY23: =IF(AW23=1,O23,0) -> 0 | AZ23: =IF(AY23-BA23<>0,AY23,0) -> 0 | BA23: =IF(AY23<0,AY23,0) -> 0 | BB23: =IF(AI23-AV23=14,1,0) -> 0 | BC23: =IF(AH23-BB23=AH23,0,AH23) -> 0 | BD23: =IF(BB23=1,O23,0) -> 0 | BE23: =IF(BD23<0,BD23,0) -> 0 | BF23: =IF(BD23-BE23<>0,BD23,0) -> 0
A24: 2119 | B24: RIVEROS HUGO GUSTAVO | C24: 264-4816549 | D24: CHIMBAS | E24: 10430 | F24: 63 | G24: 30000 | H24: 0 | M24: 30000 | N24: =IF(H24>0,G24+H24-I24-J24-K24-L24-M24,G24-I24-J24-K24-L24-M24) -> 0 | O24: =G24+H24-J24-I24-K24-L24-M24 -> 0 | P24: =IF(G24+H24<0,0,G24+H24) -> 30000 | Q24: 46239 | R24: 46239 | S24: 46176 | V24: MERCADO PAGO | X24: 7 | Y24: 7 | Z24: =IF(N24<0,0,N24) -> 0 | AH24: 1 | AI24: =IF(F24<=6,15,25) -> 25 | AJ24: =IF(O24<>0,25,15) -> 15 | AK24: =IF(AI24-T24=24,1,0) -> 0 | AL24: =IF(AH24-AK24=AH24,0,AH24) -> 0 | AM24: =IF(AK24<>0,U24,0) -> 0 | AN24: =IF(AK24=1,O24,0) -> 0 | AO24: =IF(AI24-T24=14,1,0) -> 0 | AP24: =IF(AH24-AO24=AH24,0,AH24) -> 0 | AQ24: =IF(AO24<>0,U24,0) -> 0 | AR24: =IF(AO24=1,O24,0) -> 0 | AS24: =IF(SUM(I24:M24)<>0,1,0) -> 1 | AT24: =AS24 -> 1 | AU24: =IF(O24>0,1,0) -> 0 | AV24: =IF(AK24+AO24+AU24=1,AU24,0) -> 0 | AW24: =IF(AI24-AV24=24,1,0) -> 0 | AX24: =IF(AH24-AW24=AH24,0,AH24) -> 0 | AY24: =IF(AW24=1,O24,0) -> 0 | AZ24: =IF(AY24-BA24<>0,AY24,0) -> 0 | BA24: =IF(AY24<0,AY24,0) -> 0 | BB24: =IF(AI24-AV24=14,1,0) -> 0 | BC24: =IF(AH24-BB24=AH24,0,AH24) -> 0 | BD24: =IF(BB24=1,O24,0) -> 0 | BE24: =IF(BD24<0,BD24,0) -> 0 | BF24: =IF(BD24-BE24<>0,BD24,0) -> 0
A25: 2120 | B25: CALDERON ROSANA ANALIA | C25: 264-5315461 | D25: CHIMBAS | E25: 10281 | F25: 63 | G25: 500000 | H25: -80000 | M25: 500000 | N25: =IF(H25>0,G25+H25-I25-J25-K25-L25-M25,G25-I25-J25-K25-L25-M25) -> 0 | O25: =G25+H25-J25-I25-K25-L25-M25 -> -80000 | P25: =IF(G25+H25<0,0,G25+H25) -> 420000 | Q25: 46209 | R25: 46208 | S25: 46176 | V25: MERCADO PAGO | X25: 7 | Y25: 7 | Z25: =IF(N25<0,0,N25) -> 0 | AH25: 1 | AI25: =IF(F25<=6,15,25) -> 25 | AJ25: =IF(O25<>0,25,15) -> 25 | AK25: =IF(AI25-T25=24,1,0) -> 0 | AL25: =IF(AH25-AK25=AH25,0,AH25) -> 0 | AM25: =IF(AK25<>0,U25,0) -> 0 | AN25: =IF(AK25=1,O25,0) -> 0 | AO25: =IF(AI25-T25=14,1,0) -> 0 | AP25: =IF(AH25-AO25=AH25,0,AH25) -> 0 | AQ25: =IF(AO25<>0,U25,0) -> 0 | AR25: =IF(AO25=1,O25,0) -> 0 | AS25: =IF(SUM(I25:M25)<>0,1,0) -> 1 | AT25: =AS25 -> 1 | AU25: =IF(O25>0,1,0) -> 0 | AV25: =IF(AK25+AO25+AU25=1,AU25,0) -> 0 | AW25: =IF(AI25-AV25=24,1,0) -> 0 | AX25: =IF(AH25-AW25=AH25,0,AH25) -> 0 | AY25: =IF(AW25=1,O25,0) -> 0 | AZ25: =IF(AY25-BA25<>0,AY25,0) -> 0 | BA25: =IF(AY25<0,AY25,0) -> 0 | BB25: =IF(AI25-AV25=14,1,0) -> 0 | BC25: =IF(AH25-BB25=AH25,0,AH25) -> 0 | BD25: =IF(BB25=1,O25,0) -> 0 | BE25: =IF(BD25<0,BD25,0) -> 0 | BF25: =IF(BD25-BE25<>0,BD25,0) -> 0
A26: 2207 | B26: ORELLANO VERA YESICA BEATRIZ | C26: 2644656518 | D26: RAWSON | E26: 10449 | F26: 61 | G26: 60000 | H26: 0 | M26: 60000 | N26: =IF(H26>0,G26+H26-I26-J26-K26-L26-M26,G26-I26-J26-K26-L26-M26) -> 0 | O26: =G26+H26-J26-I26-K26-L26-M26 -> 0 | P26: =IF(G26+H26<0,0,G26+H26) -> 60000 | Q26: 46245 | R26: 46245 | S26: 46209 | V26: GALICIA | X26: 7 | Y26: 7 | Z26: =IF(N26<0,0,N26) -> 0 | AH26: 1 | AI26: =IF(F26<=6,15,25) -> 25 | AJ26: =IF(O26<>0,25,15) -> 15 | AK26: =IF(AI26-T26=24,1,0) -> 0 | AL26: =IF(AH26-AK26=AH26,0,AH26) -> 0 | AM26: =IF(AK26<>0,U26,0) -> 0 | AN26: =IF(AK26=1,O26,0) -> 0 | AO26: =IF(AI26-T26=14,1,0) -> 0 | AP26: =IF(AH26-AO26=AH26,0,AH26) -> 0 | AQ26: =IF(AO26<>0,U26,0) -> 0 | AR26: =IF(AO26=1,O26,0) -> 0 | AS26: =IF(SUM(I26:M26)<>0,1,0) -> 1 | AT26: =AS26 -> 1 | AU26: =IF(O26>0,1,0) -> 0 | AV26: =IF(AK26+AO26+AU26=1,AU26,0) -> 0 | AW26: =IF(AI26-AV26=24,1,0) -> 0 | AX26: =IF(AH26-AW26=AH26,0,AH26) -> 0 | AY26: =IF(AW26=1,O26,0) -> 0 | AZ26: =IF(AY26-BA26<>0,AY26,0) -> 0 | BA26: =IF(AY26<0,AY26,0) -> 0 | BB26: =IF(AI26-AV26=14,1,0) -> 0 | BC26: =IF(AH26-BB26=AH26,0,AH26) -> 0 | BD26: =IF(BB26=1,O26,0) -> 0 | BE26: =IF(BD26<0,BD26,0) -> 0 | BF26: =IF(BD26-BE26<>0,BD26,0) -> 0
A27: 2326 | B27: RUIZ FABIANA ANDREA | C27: 264-4519628 | D27: RAWSON | E27: 11089 | F27: 59 | G27: 60000 | H27: -10000 | M27: 60000 | N27: =IF(H27>0,G27+H27-I27-J27-K27-L27-M27,G27-I27-J27-K27-L27-M27) -> 0 | O27: =G27+H27-J27-I27-K27-L27-M27 -> -10000 | P27: =IF(G27+H27<0,0,G27+H27) -> 50000 | Q27: 46245 | R27: 46244 | S27: 46213 | V27: MERCADO PAGO | X27: 7 | Y27: 7 | Z27: =IF(N27<0,0,N27) -> 0 | AH27: 1 | AI27: =IF(F27<=6,15,25) -> 25 | AJ27: =IF(O27<>0,25,15) -> 25 | AK27: =IF(AI27-T27=24,1,0) -> 0 | AL27: =IF(AH27-AK27=AH27,0,AH27) -> 0 | AM27: =IF(AK27<>0,U27,0) -> 0 | AN27: =IF(AK27=1,O27,0) -> 0 | AO27: =IF(AI27-T27=14,1,0) -> 0 | AP27: =IF(AH27-AO27=AH27,0,AH27) -> 0 | AQ27: =IF(AO27<>0,U27,0) -> 0 | AR27: =IF(AO27=1,O27,0) -> 0 | AS27: =IF(SUM(I27:M27)<>0,1,0) -> 1 | AT27: =AS27 -> 1 | AU27: =IF(O27>0,1,0) -> 0 | AV27: =IF(AK27+AO27+AU27=1,AU27,0) -> 0 | AW27: =IF(AI27-AV27=24,1,0) -> 0 | AX27: =IF(AH27-AW27=AH27,0,AH27) -> 0 | AY27: =IF(AW27=1,O27,0) -> 0 | AZ27: =IF(AY27-BA27<>0,AY27,0) -> 0 | BA27: =IF(AY27<0,AY27,0) -> 0 | BB27: =IF(AI27-AV27=14,1,0) -> 0 | BC27: =IF(AH27-BB27=AH27,0,AH27) -> 0 | BD27: =IF(BB27=1,O27,0) -> 0 | BE27: =IF(BD27<0,BD27,0) -> 0 | BF27: =IF(BD27-BE27<>0,BD27,0) -> 0
A28: 2339 | B28: ESCUDERO ANGELA VICTORIA | C28: 264-5534094 | D28: 9 DE JULIO | E28: 11193 | F28: 59 | G28: 60000 | H28: 0 | M28: 60000 | N28: =IF(H28>0,G28+H28-I28-J28-K28-L28-M28,G28-I28-J28-K28-L28-M28) -> 0 | O28: =G28+H28-J28-I28-K28-L28-M28 -> 0 | P28: =IF(G28+H28<0,0,G28+H28) -> 60000 | Q28: 46259 | R28: 46264 | S28: 46233 | V28: EFECTIVO OFICINA | X28: 7 | Y28: 7 | Z28: =IF(N28<0,0,N28) -> 0 | AH28: 1 | AI28: =IF(F28<=6,15,25) -> 25 | AJ28: =IF(O28<>0,25,15) -> 15 | AK28: =IF(AI28-T28=24,1,0) -> 0 | AL28: =IF(AH28-AK28=AH28,0,AH28) -> 0 | AM28: =IF(AK28<>0,U28,0) -> 0 | AN28: =IF(AK28=1,O28,0) -> 0 | AO28: =IF(AI28-T28=14,1,0) -> 0 | AP28: =IF(AH28-AO28=AH28,0,AH28) -> 0 | AQ28: =IF(AO28<>0,U28,0) -> 0 | AR28: =IF(AO28=1,O28,0) -> 0 | AS28: =IF(SUM(I28:M28)<>0,1,0) -> 1 | AT28: =AS28 -> 1 | AU28: =IF(O28>0,1,0) -> 0 | AV28: =IF(AK28+AO28+AU28=1,AU28,0) -> 0 | AW28: =IF(AI28-AV28=24,1,0) -> 0 | AX28: =IF(AH28-AW28=AH28,0,AH28) -> 0 | AY28: =IF(AW28=1,O28,0) -> 0 | AZ28: =IF(AY28-BA28<>0,AY28,0) -> 0 | BA28: =IF(AY28<0,AY28,0) -> 0 | BB28: =IF(AI28-AV28=14,1,0) -> 0 | BC28: =IF(AH28-BB28=AH28,0,AH28) -> 0 | BD28: =IF(BB28=1,O28,0) -> 0 | BE28: =IF(BD28<0,BD28,0) -> 0 | BF28: =IF(BD28-BE28<>0,BD28,0) -> 0
A29: 2360 | B29: NUÑEZ CHIRINO VIVIANA DEL CARMEN | C29: 264-6730916 | D29: POCITOS | E29: 11245 | F29: 59 | G29: 60000 | H29: 0 | M29: 60000 | N29: =IF(H29>0,G29+H29-I29-J29-K29-L29-M29,G29-I29-J29-K29-L29-M29) -> 0 | O29: =G29+H29-J29-I29-K29-L29-M29 -> 0 | P29: =IF(G29+H29<0,0,G29+H29) -> 60000 | Q29: 46237 | R29: 46237 | S29: 46216 | V29: MERCADO PAGO | X29: 7 | Y29: 7 | Z29: =IF(N29<0,0,N29) -> 0 | AH29: 1 | AI29: =IF(F29<=6,15,25) -> 25 | AJ29: =IF(O29<>0,25,15) -> 15 | AK29: =IF(AI29-T29=24,1,0) -> 0 | AL29: =IF(AH29-AK29=AH29,0,AH29) -> 0 | AM29: =IF(AK29<>0,U29,0) -> 0 | AN29: =IF(AK29=1,O29,0) -> 0 | AO29: =IF(AI29-T29=14,1,0) -> 0 | AP29: =IF(AH29-AO29=AH29,0,AH29) -> 0 | AQ29: =IF(AO29<>0,U29,0) -> 0 | AR29: =IF(AO29=1,O29,0) -> 0 | AS29: =IF(SUM(I29:M29)<>0,1,0) -> 1 | AT29: =AS29 -> 1 | AU29: =IF(O29>0,1,0) -> 0 | AV29: =IF(AK29+AO29+AU29=1,AU29,0) -> 0 | AW29: =IF(AI29-AV29=24,1,0) -> 0 | AX29: =IF(AH29-AW29=AH29,0,AH29) -> 0 | AY29: =IF(AW29=1,O29,0) -> 0 | AZ29: =IF(AY29-BA29<>0,AY29,0) -> 0 | BA29: =IF(AY29<0,AY29,0) -> 0 | BB29: =IF(AI29-AV29=14,1,0) -> 0 | BC29: =IF(AH29-BB29=AH29,0,AH29) -> 0 | BD29: =IF(BB29=1,O29,0) -> 0 | BE29: =IF(BD29<0,BD29,0) -> 0 | BF29: =IF(BD29-BE29<>0,BD29,0) -> 0
A30: 2374 | B30: ARABENA HECTOR ARIEL | C30: 264-4742020 | D30: SAN JUAN | E30: 11219 | F30: 58 | G30: 60000 | H30: -4500 | M30: 60000 | N30: =IF(H30>0,G30+H30-I30-J30-K30-L30-M30,G30-I30-J30-K30-L30-M30) -> 0 | O30: =G30+H30-J30-I30-K30-L30-M30 -> -4500 | P30: =IF(G30+H30<0,0,G30+H30) -> 55500 | Q30: 46265 | R30: 46265 | S30: 46234 | V30: MERCADO PAGO | X30: 7 | Y30: 7 | Z30: =IF(N30<0,0,N30) -> 0 | AH30: 1 | AI30: =IF(F30<=6,15,25) -> 25 | AJ30: =IF(O30<>0,25,15) -> 25 | AK30: =IF(AI30-T30=24,1,0) -> 0 | AL30: =IF(AH30-AK30=AH30,0,AH30) -> 0 | AM30: =IF(AK30<>0,U30,0) -> 0 | AN30: =IF(AK30=1,O30,0) -> 0 | AO30: =IF(AI30-T30=14,1,0) -> 0 | AP30: =IF(AH30-AO30=AH30,0,AH30) -> 0 | AQ30: =IF(AO30<>0,U30,0) -> 0 | AR30: =IF(AO30=1,O30,0) -> 0 | AS30: =IF(SUM(I30:M30)<>0,1,0) -> 1 | AT30: =AS30 -> 1 | AU30: =IF(O30>0,1,0) -> 0 | AV30: =IF(AK30+AO30+AU30=1,AU30,0) -> 0 | AW30: =IF(AI30-AV30=24,1,0) -> 0 | AX30: =IF(AH30-AW30=AH30,0,AH30) -> 0 | AY30: =IF(AW30=1,O30,0) -> 0 | AZ30: =IF(AY30-BA30<>0,AY30,0) -> 0 | BA30: =IF(AY30<0,AY30,0) -> 0 | BB30: =IF(AI30-AV30=14,1,0) -> 0 | BC30: =IF(AH30-BB30=AH30,0,AH30) -> 0 | BD30: =IF(BB30=1,O30,0) -> 0 | BE30: =IF(BD30<0,BD30,0) -> 0 | BF30: =IF(BD30-BE30<>0,BD30,0) -> 0
A31: 2461 | B31: ANDRES ESPINDOLA WALTER DARIO | C31: 264-4158966 | D31: POCITOS | E31: 11305 | F31: 57 | G31: 55000 | H31: 0 | M31: 55000 | N31: =IF(H31>0,G31+H31-I31-J31-K31-L31-M31,G31-I31-J31-K31-L31-M31) -> 0 | O31: =G31+H31-J31-I31-K31-L31-M31 -> 0 | P31: =IF(G31+H31<0,0,G31+H31) -> 55000 | Q31: 46248 | R31: 46248 | S31: 46217 | V31: MERCADO PAGO | X31: 7 | Y31: 7 | Z31: =IF(N31<0,0,N31) -> 0 | AH31: 1 | AI31: =IF(F31<=6,15,25) -> 25 | AJ31: =IF(O31<>0,25,15) -> 15 | AK31: =IF(AI31-T31=24,1,0) -> 0 | AL31: =IF(AH31-AK31=AH31,0,AH31) -> 0 | AM31: =IF(AK31<>0,U31,0) -> 0 | AN31: =IF(AK31=1,O31,0) -> 0 | AO31: =IF(AI31-T31=14,1,0) -> 0 | AP31: =IF(AH31-AO31=AH31,0,AH31) -> 0 | AQ31: =IF(AO31<>0,U31,0) -> 0 | AR31: =IF(AO31=1,O31,0) -> 0 | AS31: =IF(SUM(I31:M31)<>0,1,0) -> 1 | AT31: =AS31 -> 1 | AU31: =IF(O31>0,1,0) -> 0 | AV31: =IF(AK31+AO31+AU31=1,AU31,0) -> 0 | AW31: =IF(AI31-AV31=24,1,0) -> 0 | AX31: =IF(AH31-AW31=AH31,0,AH31) -> 0 | AY31: =IF(AW31=1,O31,0) -> 0 | AZ31: =IF(AY31-BA31<>0,AY31,0) -> 0 | BA31: =IF(AY31<0,AY31,0) -> 0 | BB31: =IF(AI31-AV31=14,1,0) -> 0 | BC31: =IF(AH31-BB31=AH31,0,AH31) -> 0 | BD31: =IF(BB31=1,O31,0) -> 0 | BE31: =IF(BD31<0,BD31,0) -> 0 | BF31: =IF(BD31-BE31<>0,BD31,0) -> 0
A32: 2486 | B32: ARIAS YESICA TAMARA | C32: 299-5486406 | D32: NEUQUEN | E32: 11347 | F32: 56 | G32: 40000 | H32: -45000 | M32: 40000 | N32: =IF(H32>0,G32+H32-I32-J32-K32-L32-M32,G32-I32-J32-K32-L32-M32) -> 0 | O32: =G32+H32-J32-I32-K32-L32-M32 -> -45000 | P32: =IF(G32+H32<0,0,G32+H32) -> 0 | Q32: 46246 | R32: 46246 | S32: 46216 | V32: MERCADO PAGO | X32: 7 | Y32: 7 | Z32: =IF(N32<0,0,N32) -> 0 | AH32: 1 | AI32: =IF(F32<=6,15,25) -> 25 | AJ32: =IF(O32<>0,25,15) -> 25 | AK32: =IF(AI32-T32=24,1,0) -> 0 | AL32: =IF(AH32-AK32=AH32,0,AH32) -> 0 | AM32: =IF(AK32<>0,U32,0) -> 0 | AN32: =IF(AK32=1,O32,0) -> 0 | AO32: =IF(AI32-T32=14,1,0) -> 0 | AP32: =IF(AH32-AO32=AH32,0,AH32) -> 0 | AQ32: =IF(AO32<>0,U32,0) -> 0 | AR32: =IF(AO32=1,O32,0) -> 0 | AS32: =IF(SUM(I32:M32)<>0,1,0) -> 1 | AT32: =AS32 -> 1 | AU32: =IF(O32>0,1,0) -> 0 | AV32: =IF(AK32+AO32+AU32=1,AU32,0) -> 0 | AW32: =IF(AI32-AV32=24,1,0) -> 0 | AX32: =IF(AH32-AW32=AH32,0,AH32) -> 0 | AY32: =IF(AW32=1,O32,0) -> 0 | AZ32: =IF(AY32-BA32<>0,AY32,0) -> 0 | BA32: =IF(AY32<0,AY32,0) -> 0 | BB32: =IF(AI32-AV32=14,1,0) -> 0 | BC32: =IF(AH32-BB32=AH32,0,AH32) -> 0 | BD32: =IF(BB32=1,O32,0) -> 0 | BE32: =IF(BD32<0,BD32,0) -> 0 | BF32: =IF(BD32-BE32<>0,BD32,0) -> 0
A33: 2489 | B33: YACANTE ALLENDE FRANCISCO JAVIER | C33: 264-4557852 | D33: SAN JUAN | E33: 11359 | F33: 56 | G33: 150000 | H33: -30000 | M33: 150000 | N33: =IF(H33>0,G33+H33-I33-J33-K33-L33-M33,G33-I33-J33-K33-L33-M33) -> 0 | O33: =G33+H33-J33-I33-K33-L33-M33 -> -30000 | P33: =IF(G33+H33<0,0,G33+H33) -> 120000 | Q33: 46261 | R33: 46261 | S33: 46227 | V33: EFECTIVO OFICINA | X33: 7 | Y33: 7 | Z33: =IF(N33<0,0,N33) -> 0 | AH33: 1 | AI33: =IF(F33<=6,15,25) -> 25 | AJ33: =IF(O33<>0,25,15) -> 25 | AK33: =IF(AI33-T33=24,1,0) -> 0 | AL33: =IF(AH33-AK33=AH33,0,AH33) -> 0 | AM33: =IF(AK33<>0,U33,0) -> 0 | AN33: =IF(AK33=1,O33,0) -> 0 | AO33: =IF(AI33-T33=14,1,0) -> 0 | AP33: =IF(AH33-AO33=AH33,0,AH33) -> 0 | AQ33: =IF(AO33<>0,U33,0) -> 0 | AR33: =IF(AO33=1,O33,0) -> 0 | AS33: =IF(SUM(I33:M33)<>0,1,0) -> 1 | AT33: =AS33 -> 1 | AU33: =IF(O33>0,1,0) -> 0 | AV33: =IF(AK33+AO33+AU33=1,AU33,0) -> 0 | AW33: =IF(AI33-AV33=24,1,0) -> 0 | AX33: =IF(AH33-AW33=AH33,0,AH33) -> 0 | AY33: =IF(AW33=1,O33,0) -> 0 | AZ33: =IF(AY33-BA33<>0,AY33,0) -> 0 | BA33: =IF(AY33<0,AY33,0) -> 0 | BB33: =IF(AI33-AV33=14,1,0) -> 0 | BC33: =IF(AH33-BB33=AH33,0,AH33) -> 0 | BD33: =IF(BB33=1,O33,0) -> 0 | BE33: =IF(BD33<0,BD33,0) -> 0 | BF33: =IF(BD33-BE33<>0,BD33,0) -> 0
A34: 2526 | B34: CRUZ INES CAROLINA | C34: 264-5111481 | D34: BARREAL | E34: 11399 | F34: 55 | G34: 50000 | H34: 0 | M34: 50000 | N34: =IF(H34>0,G34+H34-I34-J34-K34-L34-M34,G34-I34-J34-K34-L34-M34) -> 0 | O34: =G34+H34-J34-I34-K34-L34-M34 -> 0 | P34: =IF(G34+H34<0,0,G34+H34) -> 50000 | Q34: 46258 | R34: 46259 | S34: 46217 | V34: MERCADO PAGO | X34: 7 | Y34: 7 | Z34: =IF(N34<0,0,N34) -> 0 | AH34: 1 | AI34: =IF(F34<=6,15,25) -> 25 | AJ34: =IF(O34<>0,25,15) -> 15 | AK34: =IF(AI34-T34=24,1,0) -> 0 | AL34: =IF(AH34-AK34=AH34,0,AH34) -> 0 | AM34: =IF(AK34<>0,U34,0) -> 0 | AN34: =IF(AK34=1,O34,0) -> 0 | AO34: =IF(AI34-T34=14,1,0) -> 0 | AP34: =IF(AH34-AO34=AH34,0,AH34) -> 0 | AQ34: =IF(AO34<>0,U34,0) -> 0 | AR34: =IF(AO34=1,O34,0) -> 0 | AS34: =IF(SUM(I34:M34)<>0,1,0) -> 1 | AT34: =AS34 -> 1 | AU34: =IF(O34>0,1,0) -> 0 | AV34: =IF(AK34+AO34+AU34=1,AU34,0) -> 0 | AW34: =IF(AI34-AV34=24,1,0) -> 0 | AX34: =IF(AH34-AW34=AH34,0,AH34) -> 0 | AY34: =IF(AW34=1,O34,0) -> 0 | AZ34: =IF(AY34-BA34<>0,AY34,0) -> 0 | BA34: =IF(AY34<0,AY34,0) -> 0 | BB34: =IF(AI34-AV34=14,1,0) -> 0 | BC34: =IF(AH34-BB34=AH34,0,AH34) -> 0 | BD34: =IF(BB34=1,O34,0) -> 0 | BE34: =IF(BD34<0,BD34,0) -> 0 | BF34: =IF(BD34-BE34<>0,BD34,0) -> 0
A35: 2543 | B35: HIDALGO MORENO MAURO | C35: 264-4059779 | D35: SAN JUAN | E35: 11367 | F35: 54 | G35: 60000 | H35: 0 | M35: 60000 | N35: =IF(H35>0,G35+H35-I35-J35-K35-L35-M35,G35-I35-J35-K35-L35-M35) -> 0 | O35: =G35+H35-J35-I35-K35-L35-M35 -> 0 | P35: =IF(G35+H35<0,0,G35+H35) -> 60000 | Q35: 46265 | R35: 46265 | S35: 46234 | V35: MERCADO PAGO | X35: 7 | Y35: 7 | Z35: =IF(N35<0,0,N35) -> 0 | AH35: 1 | AI35: =IF(F35<=6,15,25) -> 25 | AJ35: =IF(O35<>0,25,15) -> 15 | AK35: =IF(AI35-T35=24,1,0) -> 0 | AL35: =IF(AH35-AK35=AH35,0,AH35) -> 0 | AM35: =IF(AK35<>0,U35,0) -> 0 | AN35: =IF(AK35=1,O35,0) -> 0 | AO35: =IF(AI35-T35=14,1,0) -> 0 | AP35: =IF(AH35-AO35=AH35,0,AH35) -> 0 | AQ35: =IF(AO35<>0,U35,0) -> 0 | AR35: =IF(AO35=1,O35,0) -> 0 | AS35: =IF(SUM(I35:M35)<>0,1,0) -> 1 | AT35: =AS35 -> 1 | AU35: =IF(O35>0,1,0) -> 0 | AV35: =IF(AK35+AO35+AU35=1,AU35,0) -> 0 | AW35: =IF(AI35-AV35=24,1,0) -> 0 | AX35: =IF(AH35-AW35=AH35,0,AH35) -> 0 | AY35: =IF(AW35=1,O35,0) -> 0 | AZ35: =IF(AY35-BA35<>0,AY35,0) -> 0 | BA35: =IF(AY35<0,AY35,0) -> 0 | BB35: =IF(AI35-AV35=14,1,0) -> 0 | BC35: =IF(AH35-BB35=AH35,0,AH35) -> 0 | BD35: =IF(BB35=1,O35,0) -> 0 | BE35: =IF(BD35<0,BD35,0) -> 0 | BF35: =IF(BD35-BE35<>0,BD35,0) -> 0
A36: 2545 | B36: DIAZ ANTONELLA YAMILA | C36: 264-4743505 | D36: JACHAL | E36: 11371 | F36: 54 | G36: 300000 | H36: 0 | N36: =IF(H36>0,G36+H36-I36-J36-K36-L36-M36,G36-I36-J36-K36-L36-M36) -> 300000 | O36: =G36+H36-J36-I36-K36-L36-M36 -> 300000 | P36: =IF(G36+H36<0,0,G36+H36) -> 300000 | R36: 46259 | S36: 46217 | W36: NO QUISO PAGAR EL JUEVES 3 VA POR OFICINA Y ALLI ARREGLA LO DE LAS CUOTAS | X36: 7 | Y36: 7 | Z36: =IF(N36<0,0,N36) -> 300000 | AH36: 1 | AI36: =IF(F36<=6,15,25) -> 25 | AJ36: =IF(O36<>0,25,15) -> 25 | AK36: =IF(AI36-T36=24,1,0) -> 0 | AL36: =IF(AH36-AK36=AH36,0,AH36) -> 0 | AM36: =IF(AK36<>0,U36,0) -> 0 | AN36: =IF(AK36=1,O36,0) -> 0 | AO36: =IF(AI36-T36=14,1,0) -> 0 | AP36: =IF(AH36-AO36=AH36,0,AH36) -> 0 | AQ36: =IF(AO36<>0,U36,0) -> 0 | AR36: =IF(AO36=1,O36,0) -> 0 | AS36: =IF(SUM(I36:M36)<>0,1,0) -> 0 | AT36: =AS36 -> 0 | AU36: =IF(O36>0,1,0) -> 1 | AV36: =IF(AK36+AO36+AU36=1,AU36,0) -> 1 | AW36: =IF(AI36-AV36=24,1,0) -> 1 | AX36: =IF(AH36-AW36=AH36,0,AH36) -> 1 | AY36: =IF(AW36=1,O36,0) -> 300000 | AZ36: =IF(AY36-BA36<>0,AY36,0) -> 300000 | BA36: =IF(AY36<0,AY36,0) -> 0 | BB36: =IF(AI36-AV36=14,1,0) -> 0 | BC36: =IF(AH36-BB36=AH36,0,AH36) -> 0 | BD36: =IF(BB36=1,O36,0) -> 0 | BE36: =IF(BD36<0,BD36,0) -> 0 | BF36: =IF(BD36-BE36<>0,BD36,0) -> 0
A37: 2548 | B37: LARA ELVIO ARNALDO | C37: 264-6613176 | D37: SAN JUAN | E37: 11381 | F37: 54 | G37: 60000 | H37: -10000 | M37: 60000 | N37: =IF(H37>0,G37+H37-I37-J37-K37-L37-M37,G37-I37-J37-K37-L37-M37) -> 0 | O37: =G37+H37-J37-I37-K37-L37-M37 -> -10000 | P37: =IF(G37+H37<0,0,G37+H37) -> 50000 | Q37: 46251 | R37: 46251 | S37: 46223 | V37: MERCADO PAGO | X37: 7 | Y37: 7 | Z37: =IF(N37<0,0,N37) -> 0 | AH37: 1 | AI37: =IF(F37<=6,15,25) -> 25 | AJ37: =IF(O37<>0,25,15) -> 25 | AK37: =IF(AI37-T37=24,1,0) -> 0 | AL37: =IF(AH37-AK37=AH37,0,AH37) -> 0 | AM37: =IF(AK37<>0,U37,0) -> 0 | AN37: =IF(AK37=1,O37,0) -> 0 | AO37: =IF(AI37-T37=14,1,0) -> 0 | AP37: =IF(AH37-AO37=AH37,0,AH37) -> 0 | AQ37: =IF(AO37<>0,U37,0) -> 0 | AR37: =IF(AO37=1,O37,0) -> 0 | AS37: =IF(SUM(I37:M37)<>0,1,0) -> 1 | AT37: =AS37 -> 1 | AU37: =IF(O37>0,1,0) -> 0 | AV37: =IF(AK37+AO37+AU37=1,AU37,0) -> 0 | AW37: =IF(AI37-AV37=24,1,0) -> 0 | AX37: =IF(AH37-AW37=AH37,0,AH37) -> 0 | AY37: =IF(AW37=1,O37,0) -> 0 | AZ37: =IF(AY37-BA37<>0,AY37,0) -> 0 | BA37: =IF(AY37<0,AY37,0) -> 0 | BB37: =IF(AI37-AV37=14,1,0) -> 0 | BC37: =IF(AH37-BB37=AH37,0,AH37) -> 0 | BD37: =IF(BB37=1,O37,0) -> 0 | BE37: =IF(BD37<0,BD37,0) -> 0 | BF37: =IF(BD37-BE37<>0,BD37,0) -> 0
A38: 2549 | B38: VAZQUEZ LUCIA NILDA | C38: 264-6194557 | D38: RAWSON | E38: 11382 | F38: 54 | G38: 60000 | H38: -24000 | M38: 60000 | N38: =IF(H38>0,G38+H38-I38-J38-K38-L38-M38,G38-I38-J38-K38-L38-M38) -> 0 | O38: =G38+H38-J38-I38-K38-L38-M38 -> -24000 | P38: =IF(G38+H38<0,0,G38+H38) -> 36000 | Q38: 46247 | R38: 46247 | S38: 46211 | V38: MERCADO PAGO | X38: 7 | Y38: 7 | Z38: =IF(N38<0,0,N38) -> 0 | AH38: 1 | AI38: =IF(F38<=6,15,25) -> 25 | AJ38: =IF(O38<>0,25,15) -> 25 | AK38: =IF(AI38-T38=24,1,0) -> 0 | AL38: =IF(AH38-AK38=AH38,0,AH38) -> 0 | AM38: =IF(AK38<>0,U38,0) -> 0 | AN38: =IF(AK38=1,O38,0) -> 0 | AO38: =IF(AI38-T38=14,1,0) -> 0 | AP38: =IF(AH38-AO38=AH38,0,AH38) -> 0 | AQ38: =IF(AO38<>0,U38,0) -> 0 | AR38: =IF(AO38=1,O38,0) -> 0 | AS38: =IF(SUM(I38:M38)<>0,1,0) -> 1 | AT38: =AS38 -> 1 | AU38: =IF(O38>0,1,0) -> 0 | AV38: =IF(AK38+AO38+AU38=1,AU38,0) -> 0 | AW38: =IF(AI38-AV38=24,1,0) -> 0 | AX38: =IF(AH38-AW38=AH38,0,AH38) -> 0 | AY38: =IF(AW38=1,O38,0) -> 0 | AZ38: =IF(AY38-BA38<>0,AY38,0) -> 0 | BA38: =IF(AY38<0,AY38,0) -> 0 | BB38: =IF(AI38-AV38=14,1,0) -> 0 | BC38: =IF(AH38-BB38=AH38,0,AH38) -> 0 | BD38: =IF(BB38=1,O38,0) -> 0 | BE38: =IF(BD38<0,BD38,0) -> 0 | BF38: =IF(BD38-BE38<>0,BD38,0) -> 0
A39: 2556 | B39: HORQUERA BARRRIONUEVO CLAUDIA ELIZABETH | C39: 264-4047122 | D39: POCITOS | E39: 11440 | F39: 54 | G39: 60000 | H39: 0 | M39: 60000 | N39: =IF(H39>0,G39+H39-I39-J39-K39-L39-M39,G39-I39-J39-K39-L39-M39) -> 0 | O39: =G39+H39-J39-I39-K39-L39-M39 -> 0 | P39: =IF(G39+H39<0,0,G39+H39) -> 60000 | Q39: 46254 | R39: 46254 | S39: 46223 | V39: MERCADO PAGO | X39: 7 | Y39: 7 | Z39: =IF(N39<0,0,N39) -> 0 | AH39: 1 | AI39: =IF(F39<=6,15,25) -> 25 | AJ39: =IF(O39<>0,25,15) -> 15 | AK39: =IF(AI39-T39=24,1,0) -> 0 | AL39: =IF(AH39-AK39=AH39,0,AH39) -> 0 | AM39: =IF(AK39<>0,U39,0) -> 0 | AN39: =IF(AK39=1,O39,0) -> 0 | AO39: =IF(AI39-T39=14,1,0) -> 0 | AP39: =IF(AH39-AO39=AH39,0,AH39) -> 0 | AQ39: =IF(AO39<>0,U39,0) -> 0 | AR39: =IF(AO39=1,O39,0) -> 0 | AS39: =IF(SUM(I39:M39)<>0,1,0) -> 1 | AT39: =AS39 -> 1 | AU39: =IF(O39>0,1,0) -> 0 | AV39: =IF(AK39+AO39+AU39=1,AU39,0) -> 0 | AW39: =IF(AI39-AV39=24,1,0) -> 0 | AX39: =IF(AH39-AW39=AH39,0,AH39) -> 0 | AY39: =IF(AW39=1,O39,0) -> 0 | AZ39: =IF(AY39-BA39<>0,AY39,0) -> 0 | BA39: =IF(AY39<0,AY39,0) -> 0 | BB39: =IF(AI39-AV39=14,1,0) -> 0 | BC39: =IF(AH39-BB39=AH39,0,AH39) -> 0 | BD39: =IF(BB39=1,O39,0) -> 0 | BE39: =IF(BD39<0,BD39,0) -> 0 | BF39: =IF(BD39-BE39<>0,BD39,0) -> 0
A40: 2578 | B40: LEPEZ MEDINA MIRIAM AYELEN | C40: 264-5143197 | D40: SAN JUAN | E40: 11425 | F40: 53 | G40: 60000 | H40: 0 | M40: 60000 | N40: =IF(H40>0,G40+H40-I40-J40-K40-L40-M40,G40-I40-J40-K40-L40-M40) -> 0 | O40: =G40+H40-J40-I40-K40-L40-M40 -> 0 | P40: =IF(G40+H40<0,0,G40+H40) -> 60000 | Q40: 46265 | R40: 46265 | S40: 46234 | V40: MERCADO PAGO | X40: 7 | Y40: 7 | Z40: =IF(N40<0,0,N40) -> 0 | AH40: 1 | AI40: =IF(F40<=6,15,25) -> 25 | AJ40: =IF(O40<>0,25,15) -> 15 | AK40: =IF(AI40-T40=24,1,0) -> 0 | AL40: =IF(AH40-AK40=AH40,0,AH40) -> 0 | AM40: =IF(AK40<>0,U40,0) -> 0 | AN40: =IF(AK40=1,O40,0) -> 0 | AO40: =IF(AI40-T40=14,1,0) -> 0 | AP40: =IF(AH40-AO40=AH40,0,AH40) -> 0 | AQ40: =IF(AO40<>0,U40,0) -> 0 | AR40: =IF(AO40=1,O40,0) -> 0 | AS40: =IF(SUM(I40:M40)<>0,1,0) -> 1 | AT40: =AS40 -> 1 | AU40: =IF(O40>0,1,0) -> 0 | AV40: =IF(AK40+AO40+AU40=1,AU40,0) -> 0 | AW40: =IF(AI40-AV40=24,1,0) -> 0 | AX40: =IF(AH40-AW40=AH40,0,AH40) -> 0 | AY40: =IF(AW40=1,O40,0) -> 0 | AZ40: =IF(AY40-BA40<>0,AY40,0) -> 0 | BA40: =IF(AY40<0,AY40,0) -> 0 | BB40: =IF(AI40-AV40=14,1,0) -> 0 | BC40: =IF(AH40-BB40=AH40,0,AH40) -> 0 | BD40: =IF(BB40=1,O40,0) -> 0 | BE40: =IF(BD40<0,BD40,0) -> 0 | BF40: =IF(BD40-BE40<>0,BD40,0) -> 0
A41: 2580 | B41: CALDERON ELIANA ELIZABETH | C41: 264-4147056 | D41: MARQUESADO | E41: 11428 | F41: 53 | G41: 60000 | H41: 0 | M41: 60000 | N41: =IF(H41>0,G41+H41-I41-J41-K41-L41-M41,G41-I41-J41-K41-L41-M41) -> 0 | O41: =G41+H41-J41-I41-K41-L41-M41 -> 0 | P41: =IF(G41+H41<0,0,G41+H41) -> 60000 | Q41: 46255 | R41: 46254 | S41: 46223 | V41: MERCADO PAGO | X41: 7 | Y41: 7 | Z41: =IF(N41<0,0,N41) -> 0 | AH41: 1 | AI41: =IF(F41<=6,15,25) -> 25 | AJ41: =IF(O41<>0,25,15) -> 15 | AK41: =IF(AI41-T41=24,1,0) -> 0 | AL41: =IF(AH41-AK41=AH41,0,AH41) -> 0 | AM41: =IF(AK41<>0,U41,0) -> 0 | AN41: =IF(AK41=1,O41,0) -> 0 | AO41: =IF(AI41-T41=14,1,0) -> 0 | AP41: =IF(AH41-AO41=AH41,0,AH41) -> 0 | AQ41: =IF(AO41<>0,U41,0) -> 0 | AR41: =IF(AO41=1,O41,0) -> 0 | AS41: =IF(SUM(I41:M41)<>0,1,0) -> 1 | AT41: =AS41 -> 1 | AU41: =IF(O41>0,1,0) -> 0 | AV41: =IF(AK41+AO41+AU41=1,AU41,0) -> 0 | AW41: =IF(AI41-AV41=24,1,0) -> 0 | AX41: =IF(AH41-AW41=AH41,0,AH41) -> 0 | AY41: =IF(AW41=1,O41,0) -> 0 | AZ41: =IF(AY41-BA41<>0,AY41,0) -> 0 | BA41: =IF(AY41<0,AY41,0) -> 0 | BB41: =IF(AI41-AV41=14,1,0) -> 0 | BC41: =IF(AH41-BB41=AH41,0,AH41) -> 0 | BD41: =IF(BB41=1,O41,0) -> 0 | BE41: =IF(BD41<0,BD41,0) -> 0 | BF41: =IF(BD41-BE41<>0,BD41,0) -> 0
A42: 2583 | B42: SANCHEZ CESAR ALEJANDRO | C42: 264-4731496 | D42: SAN JUAN | E42: 11432 | F42: 53 | G42: 60000 | H42: -180000 | N42: =IF(H42>0,G42+H42-I42-J42-K42-L42-M42,G42-I42-J42-K42-L42-M42) -> 60000 | O42: =G42+H42-J42-I42-K42-L42-M42 -> -120000 | P42: =IF(G42+H42<0,0,G42+H42) -> 0 | R42: 46265 | S42: 46205 | W42: YA ESTA PAGA EN EL MES DE JULIO | X42: 7 | Y42: 7 | Z42: =IF(N42<0,0,N42) -> 60000 | AH42: 1 | AI42: =IF(F42<=6,15,25) -> 25 | AJ42: =IF(O42<>0,25,15) -> 25 | AK42: =IF(AI42-T42=24,1,0) -> 0 | AL42: =IF(AH42-AK42=AH42,0,AH42) -> 0 | AM42: =IF(AK42<>0,U42,0) -> 0 | AN42: =IF(AK42=1,O42,0) -> 0 | AO42: =IF(AI42-T42=14,1,0) -> 0 | AP42: =IF(AH42-AO42=AH42,0,AH42) -> 0 | AQ42: =IF(AO42<>0,U42,0) -> 0 | AR42: =IF(AO42=1,O42,0) -> 0 | AS42: =IF(SUM(I42:M42)<>0,1,0) -> 0 | AT42: =AS42 -> 0 | AU42: =IF(O42>0,1,0) -> 0 | AV42: =IF(AK42+AO42+AU42=1,AU42,0) -> 0 | AW42: =IF(AI42-AV42=24,1,0) -> 0 | AX42: =IF(AH42-AW42=AH42,0,AH42) -> 0 | AY42: =IF(AW42=1,O42,0) -> 0 | AZ42: =IF(AY42-BA42<>0,AY42,0) -> 0 | BA42: =IF(AY42<0,AY42,0) -> 0 | BB42: =IF(AI42-AV42=14,1,0) -> 0 | BC42: =IF(AH42-BB42=AH42,0,AH42) -> 0 | BD42: =IF(BB42=1,O42,0) -> 0 | BE42: =IF(BD42<0,BD42,0) -> 0 | BF42: =IF(BD42-BE42<>0,BD42,0) -> 0
A43: 2585 | B43: GOMEZ EDITH JORGELINA | C43: 264-5069722 | D43: CHIMBAS | E43: 11434 | F43: 53 | G43: 60000 | H43: -200000 | M43: 60000 | N43: =IF(H43>0,G43+H43-I43-J43-K43-L43-M43,G43-I43-J43-K43-L43-M43) -> 0 | O43: =G43+H43-J43-I43-K43-L43-M43 -> -200000 | P43: =IF(G43+H43<0,0,G43+H43) -> 0 | Q43: 46265 | R43: 46263 | S43: 46232 | V43: MERCADO PAGO | X43: 7 | Y43: 7 | Z43: =IF(N43<0,0,N43) -> 0 | AH43: 1 | AI43: =IF(F43<=6,15,25) -> 25 | AJ43: =IF(O43<>0,25,15) -> 25 | AK43: =IF(AI43-T43=24,1,0) -> 0 | AL43: =IF(AH43-AK43=AH43,0,AH43) -> 0 | AM43: =IF(AK43<>0,U43,0) -> 0 | AN43: =IF(AK43=1,O43,0) -> 0 | AO43: =IF(AI43-T43=14,1,0) -> 0 | AP43: =IF(AH43-AO43=AH43,0,AH43) -> 0 | AQ43: =IF(AO43<>0,U43,0) -> 0 | AR43: =IF(AO43=1,O43,0) -> 0 | AS43: =IF(SUM(I43:M43)<>0,1,0) -> 1 | AT43: =AS43 -> 1 | AU43: =IF(O43>0,1,0) -> 0 | AV43: =IF(AK43+AO43+AU43=1,AU43,0) -> 0 | AW43: =IF(AI43-AV43=24,1,0) -> 0 | AX43: =IF(AH43-AW43=AH43,0,AH43) -> 0 | AY43: =IF(AW43=1,O43,0) -> 0 | AZ43: =IF(AY43-BA43<>0,AY43,0) -> 0 | BA43: =IF(AY43<0,AY43,0) -> 0 | BB43: =IF(AI43-AV43=14,1,0) -> 0 | BC43: =IF(AH43-BB43=AH43,0,AH43) -> 0 | BD43: =IF(BB43=1,O43,0) -> 0 | BE43: =IF(BD43<0,BD43,0) -> 0 | BF43: =IF(BD43-BE43<>0,BD43,0) -> 0
A44: 2615 | B44: OCHOA MARIA LUISA | C44: 264-4449786 | D44: LA RIOJA CAPITAL | E44: 11506 | F44: 52 | G44: 60000 | H44: 0 | M44: 60000 | N44: =IF(H44>0,G44+H44-I44-J44-K44-L44-M44,G44-I44-J44-K44-L44-M44) -> 0 | O44: =G44+H44-J44-I44-K44-L44-M44 -> 0 | P44: =IF(G44+H44<0,0,G44+H44) -> 60000 | Q44: 46253 | R44: 46253 | S44: 46218 | V44: MERCADO PAGO | X44: 7 | Y44: 7 | Z44: =IF(N44<0,0,N44) -> 0 | AH44: 1 | AI44: =IF(F44<=6,15,25) -> 25 | AJ44: =IF(O44<>0,25,15) -> 15 | AK44: =IF(AI44-T44=24,1,0) -> 0 | AL44: =IF(AH44-AK44=AH44,0,AH44) -> 0 | AM44: =IF(AK44<>0,U44,0) -> 0 | AN44: =IF(AK44=1,O44,0) -> 0 | AO44: =IF(AI44-T44=14,1,0) -> 0 | AP44: =IF(AH44-AO44=AH44,0,AH44) -> 0 | AQ44: =IF(AO44<>0,U44,0) -> 0 | AR44: =IF(AO44=1,O44,0) -> 0 | AS44: =IF(SUM(I44:M44)<>0,1,0) -> 1 | AT44: =AS44 -> 1 | AU44: =IF(O44>0,1,0) -> 0 | AV44: =IF(AK44+AO44+AU44=1,AU44,0) -> 0 | AW44: =IF(AI44-AV44=24,1,0) -> 0 | AX44: =IF(AH44-AW44=AH44,0,AH44) -> 0 | AY44: =IF(AW44=1,O44,0) -> 0 | AZ44: =IF(AY44-BA44<>0,AY44,0) -> 0 | BA44: =IF(AY44<0,AY44,0) -> 0 | BB44: =IF(AI44-AV44=14,1,0) -> 0 | BC44: =IF(AH44-BB44=AH44,0,AH44) -> 0 | BD44: =IF(BB44=1,O44,0) -> 0 | BE44: =IF(BD44<0,BD44,0) -> 0 | BF44: =IF(BD44-BE44<>0,BD44,0) -> 0
A45: 2616 | B45: ESPIN CRISTINA CECILIA | C45: 264 416-0830 | D45: RIVADAVIA | E45: 11516 | F45: 51 | G45: 60000 | H45: 0 | M45: 60000 | N45: =IF(H45>0,G45+H45-I45-J45-K45-L45-M45,G45-I45-J45-K45-L45-M45) -> 0 | O45: =G45+H45-J45-I45-K45-L45-M45 -> 0 | P45: =IF(G45+H45<0,0,G45+H45) -> 60000 | Q45: 46247 | R45: 46244 | S45: 46213 | V45: MERCADO PAGO | X45: 7 | Y45: 7 | Z45: =IF(N45<0,0,N45) -> 0 | AH45: 1 | AI45: =IF(F45<=6,15,25) -> 25 | AJ45: =IF(O45<>0,25,15) -> 15 | AK45: =IF(AI45-T45=24,1,0) -> 0 | AL45: =IF(AH45-AK45=AH45,0,AH45) -> 0 | AM45: =IF(AK45<>0,U45,0) -> 0 | AN45: =IF(AK45=1,O45,0) -> 0 | AO45: =IF(AI45-T45=14,1,0) -> 0 | AP45: =IF(AH45-AO45=AH45,0,AH45) -> 0 | AQ45: =IF(AO45<>0,U45,0) -> 0 | AR45: =IF(AO45=1,O45,0) -> 0 | AS45: =IF(SUM(I45:M45)<>0,1,0) -> 1 | AT45: =AS45 -> 1 | AU45: =IF(O45>0,1,0) -> 0 | AV45: =IF(AK45+AO45+AU45=1,AU45,0) -> 0 | AW45: =IF(AI45-AV45=24,1,0) -> 0 | AX45: =IF(AH45-AW45=AH45,0,AH45) -> 0 | AY45: =IF(AW45=1,O45,0) -> 0 | AZ45: =IF(AY45-BA45<>0,AY45,0) -> 0 | BA45: =IF(AY45<0,AY45,0) -> 0 | BB45: =IF(AI45-AV45=14,1,0) -> 0 | BC45: =IF(AH45-BB45=AH45,0,AH45) -> 0 | BD45: =IF(BB45=1,O45,0) -> 0 | BE45: =IF(BD45<0,BD45,0) -> 0 | BF45: =IF(BD45-BE45<>0,BD45,0) -> 0
A46: 2622 | B46: BRITOS MARIA DE LOS ANGELES | C46: 264-4363490 | D46: RAWSON | E46: 11518 | F46: 51 | G46: 60000 | H46: 0 | M46: 60000 | N46: =IF(H46>0,G46+H46-I46-J46-K46-L46-M46,G46-I46-J46-K46-L46-M46) -> 0 | O46: =G46+H46-J46-I46-K46-L46-M46 -> 0 | P46: =IF(G46+H46<0,0,G46+H46) -> 60000 | Q46: 46255 | R46: 46255 | S46: 46227 | V46: MERCADO PAGO | X46: 7 | Y46: 7 | Z46: =IF(N46<0,0,N46) -> 0 | AH46: 1 | AI46: =IF(F46<=6,15,25) -> 25 | AJ46: =IF(O46<>0,25,15) -> 15 | AK46: =IF(AI46-T46=24,1,0) -> 0 | AL46: =IF(AH46-AK46=AH46,0,AH46) -> 0 | AM46: =IF(AK46<>0,U46,0) -> 0 | AN46: =IF(AK46=1,O46,0) -> 0 | AO46: =IF(AI46-T46=14,1,0) -> 0 | AP46: =IF(AH46-AO46=AH46,0,AH46) -> 0 | AQ46: =IF(AO46<>0,U46,0) -> 0 | AR46: =IF(AO46=1,O46,0) -> 0 | AS46: =IF(SUM(I46:M46)<>0,1,0) -> 1 | AT46: =AS46 -> 1 | AU46: =IF(O46>0,1,0) -> 0 | AV46: =IF(AK46+AO46+AU46=1,AU46,0) -> 0 | AW46: =IF(AI46-AV46=24,1,0) -> 0 | AX46: =IF(AH46-AW46=AH46,0,AH46) -> 0 | AY46: =IF(AW46=1,O46,0) -> 0 | AZ46: =IF(AY46-BA46<>0,AY46,0) -> 0 | BA46: =IF(AY46<0,AY46,0) -> 0 | BB46: =IF(AI46-AV46=14,1,0) -> 0 | BC46: =IF(AH46-BB46=AH46,0,AH46) -> 0 | BD46: =IF(BB46=1,O46,0) -> 0 | BE46: =IF(BD46<0,BD46,0) -> 0 | BF46: =IF(BD46-BE46<>0,BD46,0) -> 0
A47: 2714 | B47: VILLACORTA FABIANA ALEJANDRA | C47: 264-6726589 | D47: RAWSON | E47: 11635 | F47: 48 | G47: 80000 | H47: -30000 | M47: 80000 | N47: =IF(H47>0,G47+H47-I47-J47-K47-L47-M47,G47-I47-J47-K47-L47-M47) -> 0 | O47: =G47+H47-J47-I47-K47-L47-M47 -> -30000 | P47: =IF(G47+H47<0,0,G47+H47) -> 50000 | Q47: 46238 | R47: 46238 | S47: 46213 | V47: MERCADO PAGO | X47: 7 | Y47: 7 | Z47: =IF(N47<0,0,N47) -> 0 | AH47: 1 | AI47: =IF(F47<=6,15,25) -> 25 | AJ47: =IF(O47<>0,25,15) -> 25 | AK47: =IF(AI47-T47=24,1,0) -> 0 | AL47: =IF(AH47-AK47=AH47,0,AH47) -> 0 | AM47: =IF(AK47<>0,U47,0) -> 0 | AN47: =IF(AK47=1,O47,0) -> 0 | AO47: =IF(AI47-T47=14,1,0) -> 0 | AP47: =IF(AH47-AO47=AH47,0,AH47) -> 0 | AQ47: =IF(AO47<>0,U47,0) -> 0 | AR47: =IF(AO47=1,O47,0) -> 0 | AS47: =IF(SUM(I47:M47)<>0,1,0) -> 1 | AT47: =AS47 -> 1 | AU47: =IF(O47>0,1,0) -> 0 | AV47: =IF(AK47+AO47+AU47=1,AU47,0) -> 0 | AW47: =IF(AI47-AV47=24,1,0) -> 0 | AX47: =IF(AH47-AW47=AH47,0,AH47) -> 0 | AY47: =IF(AW47=1,O47,0) -> 0 | AZ47: =IF(AY47-BA47<>0,AY47,0) -> 0 | BA47: =IF(AY47<0,AY47,0) -> 0 | BB47: =IF(AI47-AV47=14,1,0) -> 0 | BC47: =IF(AH47-BB47=AH47,0,AH47) -> 0 | BD47: =IF(BB47=1,O47,0) -> 0 | BE47: =IF(BD47<0,BD47,0) -> 0 | BF47: =IF(BD47-BE47<>0,BD47,0) -> 0
A48: 2717 | B48: MILLA VERONICA ANTONIA | C48: 264-4727755 | D48: POCITOS | E48: 11639 | F48: 48 | G48: 70000 | H48: 70000 | M48: 70000 | N48: =IF(H48>0,G48+H48-I48-J48-K48-L48-M48,G48-I48-J48-K48-L48-M48) -> 70000 | O48: =G48+H48-J48-I48-K48-L48-M48 -> 70000 | P48: =IF(G48+H48<0,0,G48+H48) -> 140000 | Q48: 46235 | R48: 46235 | S48: 46203 | V48: MERCADO PAGO | X48: 7 | Y48: 7 | Z48: =IF(N48<0,0,N48) -> 70000 | AH48: 1 | AI48: =IF(F48<=6,15,25) -> 25 | AJ48: =IF(O48<>0,25,15) -> 25 | AK48: =IF(AI48-T48=24,1,0) -> 0 | AL48: =IF(AH48-AK48=AH48,0,AH48) -> 0 | AM48: =IF(AK48<>0,U48,0) -> 0 | AN48: =IF(AK48=1,O48,0) -> 0 | AO48: =IF(AI48-T48=14,1,0) -> 0 | AP48: =IF(AH48-AO48=AH48,0,AH48) -> 0 | AQ48: =IF(AO48<>0,U48,0) -> 0 | AR48: =IF(AO48=1,O48,0) -> 0 | AS48: =IF(SUM(I48:M48)<>0,1,0) -> 1 | AT48: =AS48 -> 1 | AU48: =IF(O48>0,1,0) -> 1 | AV48: =IF(AK48+AO48+AU48=1,AU48,0) -> 1 | AW48: =IF(AI48-AV48=24,1,0) -> 1 | AX48: =IF(AH48-AW48=AH48,0,AH48) -> 1 | AY48: =IF(AW48=1,O48,0) -> 70000 | AZ48: =IF(AY48-BA48<>0,AY48,0) -> 70000 | BA48: =IF(AY48<0,AY48,0) -> 0 | BB48: =IF(AI48-AV48=14,1,0) -> 0 | BC48: =IF(AH48-BB48=AH48,0,AH48) -> 0 | BD48: =IF(BB48=1,O48,0) -> 0 | BE48: =IF(BD48<0,BD48,0) -> 0 | BF48: =IF(BD48-BE48<>0,BD48,0) -> 0
A49: 2727 | B49: SORIA PALACIO GERMAN OMAR | C49: 264-4758154 | D49: POCITOS | E49: 11644 | F49: 48 | G49: 70000 | H49: 0 | M49: 70000 | N49: =IF(H49>0,G49+H49-I49-J49-K49-L49-M49,G49-I49-J49-K49-L49-M49) -> 0 | O49: =G49+H49-J49-I49-K49-L49-M49 -> 0 | P49: =IF(G49+H49<0,0,G49+H49) -> 70000 | Q49: 46265 | R49: 46264 | S49: 46233 | V49: MERCADO PAGO | X49: 7 | Y49: 7 | Z49: =IF(N49<0,0,N49) -> 0 | AH49: 1 | AI49: =IF(F49<=6,15,25) -> 25 | AJ49: =IF(O49<>0,25,15) -> 15 | AK49: =IF(AI49-T49=24,1,0) -> 0 | AL49: =IF(AH49-AK49=AH49,0,AH49) -> 0 | AM49: =IF(AK49<>0,U49,0) -> 0 | AN49: =IF(AK49=1,O49,0) -> 0 | AO49: =IF(AI49-T49=14,1,0) -> 0 | AP49: =IF(AH49-AO49=AH49,0,AH49) -> 0 | AQ49: =IF(AO49<>0,U49,0) -> 0 | AR49: =IF(AO49=1,O49,0) -> 0 | AS49: =IF(SUM(I49:M49)<>0,1,0) -> 1 | AT49: =AS49 -> 1 | AU49: =IF(O49>0,1,0) -> 0 | AV49: =IF(AK49+AO49+AU49=1,AU49,0) -> 0 | AW49: =IF(AI49-AV49=24,1,0) -> 0 | AX49: =IF(AH49-AW49=AH49,0,AH49) -> 0 | AY49: =IF(AW49=1,O49,0) -> 0 | AZ49: =IF(AY49-BA49<>0,AY49,0) -> 0 | BA49: =IF(AY49<0,AY49,0) -> 0 | BB49: =IF(AI49-AV49=14,1,0) -> 0 | BC49: =IF(AH49-BB49=AH49,0,AH49) -> 0 | BD49: =IF(BB49=1,O49,0) -> 0 | BE49: =IF(BD49<0,BD49,0) -> 0 | BF49: =IF(BD49-BE49<>0,BD49,0) -> 0
A50: 2744 | B50: ARROYO MARIANA DEOLINDA | C50: 264-5725038 | D50: ANGACO | E50: 11631 | F50: 47 | G50: 60000 | H50: -24000 | I50: 60000 | N50: =IF(H50>0,G50+H50-I50-J50-K50-L50-M50,G50-I50-J50-K50-L50-M50) -> 0 | O50: =G50+H50-J50-I50-K50-L50-M50 -> -24000 | P50: =IF(G50+H50<0,0,G50+H50) -> 36000 | Q50: 46248 | R50: 46248 | S50: 46218 | V50: POSNET OFICINA | X50: 7 | Y50: 7 | Z50: =IF(N50<0,0,N50) -> 0 | AH50: 1 | AI50: =IF(F50<=6,15,25) -> 25 | AJ50: =IF(O50<>0,25,15) -> 25 | AK50: =IF(AI50-T50=24,1,0) -> 0 | AL50: =IF(AH50-AK50=AH50,0,AH50) -> 0 | AM50: =IF(AK50<>0,U50,0) -> 0 | AN50: =IF(AK50=1,O50,0) -> 0 | AO50: =IF(AI50-T50=14,1,0) -> 0 | AP50: =IF(AH50-AO50=AH50,0,AH50) -> 0 | AQ50: =IF(AO50<>0,U50,0) -> 0 | AR50: =IF(AO50=1,O50,0) -> 0 | AS50: =IF(SUM(I50:M50)<>0,1,0) -> 1 | AT50: =AS50 -> 1 | AU50: =IF(O50>0,1,0) -> 0 | AV50: =IF(AK50+AO50+AU50=1,AU50,0) -> 0 | AW50: =IF(AI50-AV50=24,1,0) -> 0 | AX50: =IF(AH50-AW50=AH50,0,AH50) -> 0 | AY50: =IF(AW50=1,O50,0) -> 0 | AZ50: =IF(AY50-BA50<>0,AY50,0) -> 0 | BA50: =IF(AY50<0,AY50,0) -> 0 | BB50: =IF(AI50-AV50=14,1,0) -> 0 | BC50: =IF(AH50-BB50=AH50,0,AH50) -> 0 | BD50: =IF(BB50=1,O50,0) -> 0 | BE50: =IF(BD50<0,BD50,0) -> 0 | BF50: =IF(BD50-BE50<>0,BD50,0) -> 0
A51: 2747 | B51: MALDONADO NELLY LEONOR | C51: 264-6716597 | D51: SAN JUAN | E51: 11656 | F51: 47 | G51: 99999 | H51: -260011 | M51: 100000 | N51: =IF(H51>0,G51+H51-I51-J51-K51-L51-M51,G51-I51-J51-K51-L51-M51) -> -1 | O51: =G51+H51-J51-I51-K51-L51-M51 -> -260012 | P51: =IF(G51+H51<0,0,G51+H51) -> 0 | Q51: 46248 | R51: 46248 | S51: 46211 | V51: MERCADO PAGO | X51: 7 | Y51: 7 | Z51: =IF(N51<0,0,N51) -> 0 | AH51: 1 | AI51: =IF(F51<=6,15,25) -> 25 | AJ51: =IF(O51<>0,25,15) -> 25 | AK51: =IF(AI51-T51=24,1,0) -> 0 | AL51: =IF(AH51-AK51=AH51,0,AH51) -> 0 | AM51: =IF(AK51<>0,U51,0) -> 0 | AN51: =IF(AK51=1,O51,0) -> 0 | AO51: =IF(AI51-T51=14,1,0) -> 0 | AP51: =IF(AH51-AO51=AH51,0,AH51) -> 0 | AQ51: =IF(AO51<>0,U51,0) -> 0 | AR51: =IF(AO51=1,O51,0) -> 0 | AS51: =IF(SUM(I51:M51)<>0,1,0) -> 1 | AT51: =AS51 -> 1 | AU51: =IF(O51>0,1,0) -> 0 | AV51: =IF(AK51+AO51+AU51=1,AU51,0) -> 0 | AW51: =IF(AI51-AV51=24,1,0) -> 0 | AX51: =IF(AH51-AW51=AH51,0,AH51) -> 0 | AY51: =IF(AW51=1,O51,0) -> 0 | AZ51: =IF(AY51-BA51<>0,AY51,0) -> 0 | BA51: =IF(AY51<0,AY51,0) -> 0 | BB51: =IF(AI51-AV51=14,1,0) -> 0 | BC51: =IF(AH51-BB51=AH51,0,AH51) -> 0 | BD51: =IF(BB51=1,O51,0) -> 0 | BE51: =IF(BD51<0,BD51,0) -> 0 | BF51: =IF(BD51-BE51<>0,BD51,0) -> 0
A52: 2755 | B52: ALVAREZ MORAN CARMEN BEATRIZ | C52: 264-5895577 | D52: EL RINCON | E52: 11668 | F52: 47 | G52: 60000 | H52: 0 | M52: 60000 | N52: =IF(H52>0,G52+H52-I52-J52-K52-L52-M52,G52-I52-J52-K52-L52-M52) -> 0 | O52: =G52+H52-J52-I52-K52-L52-M52 -> 0 | P52: =IF(G52+H52<0,0,G52+H52) -> 60000 | Q52: 46238 | R52: 46238 | S52: 46205 | V52: MERCADO PAGO | X52: 7 | Y52: 7 | Z52: =IF(N52<0,0,N52) -> 0 | AH52: 1 | AI52: =IF(F52<=6,15,25) -> 25 | AJ52: =IF(O52<>0,25,15) -> 15 | AK52: =IF(AI52-T52=24,1,0) -> 0 | AL52: =IF(AH52-AK52=AH52,0,AH52) -> 0 | AM52: =IF(AK52<>0,U52,0) -> 0 | AN52: =IF(AK52=1,O52,0) -> 0 | AO52: =IF(AI52-T52=14,1,0) -> 0 | AP52: =IF(AH52-AO52=AH52,0,AH52) -> 0 | AQ52: =IF(AO52<>0,U52,0) -> 0 | AR52: =IF(AO52=1,O52,0) -> 0 | AS52: =IF(SUM(I52:M52)<>0,1,0) -> 1 | AT52: =AS52 -> 1 | AU52: =IF(O52>0,1,0) -> 0 | AV52: =IF(AK52+AO52+AU52=1,AU52,0) -> 0 | AW52: =IF(AI52-AV52=24,1,0) -> 0 | AX52: =IF(AH52-AW52=AH52,0,AH52) -> 0 | AY52: =IF(AW52=1,O52,0) -> 0 | AZ52: =IF(AY52-BA52<>0,AY52,0) -> 0 | BA52: =IF(AY52<0,AY52,0) -> 0 | BB52: =IF(AI52-AV52=14,1,0) -> 0 | BC52: =IF(AH52-BB52=AH52,0,AH52) -> 0 | BD52: =IF(BB52=1,O52,0) -> 0 | BE52: =IF(BD52<0,BD52,0) -> 0 | BF52: =IF(BD52-BE52<>0,BD52,0) -> 0
A53: 2760 | B53: PEREZ ALEJANDRO MAXIMILIANO | C53: 264-6706973 | D53: ANGUALASTO | E53: 11688 | F53: 47 | G53: 60000 | H53: 0 | M53: 60000 | N53: =IF(H53>0,G53+H53-I53-J53-K53-L53-M53,G53-I53-J53-K53-L53-M53) -> 0 | O53: =G53+H53-J53-I53-K53-L53-M53 -> 0 | P53: =IF(G53+H53<0,0,G53+H53) -> 60000 | Q53: 46244 | R53: 46244 | S53: 46213 | V53: MERCADO PAGO | X53: 7 | Y53: 7 | Z53: =IF(N53<0,0,N53) -> 0 | AH53: 1 | AI53: =IF(F53<=6,15,25) -> 25 | AJ53: =IF(O53<>0,25,15) -> 15 | AK53: =IF(AI53-T53=24,1,0) -> 0 | AL53: =IF(AH53-AK53=AH53,0,AH53) -> 0 | AM53: =IF(AK53<>0,U53,0) -> 0 | AN53: =IF(AK53=1,O53,0) -> 0 | AO53: =IF(AI53-T53=14,1,0) -> 0 | AP53: =IF(AH53-AO53=AH53,0,AH53) -> 0 | AQ53: =IF(AO53<>0,U53,0) -> 0 | AR53: =IF(AO53=1,O53,0) -> 0 | AS53: =IF(SUM(I53:M53)<>0,1,0) -> 1 | AT53: =AS53 -> 1 | AU53: =IF(O53>0,1,0) -> 0 | AV53: =IF(AK53+AO53+AU53=1,AU53,0) -> 0 | AW53: =IF(AI53-AV53=24,1,0) -> 0 | AX53: =IF(AH53-AW53=AH53,0,AH53) -> 0 | AY53: =IF(AW53=1,O53,0) -> 0 | AZ53: =IF(AY53-BA53<>0,AY53,0) -> 0 | BA53: =IF(AY53<0,AY53,0) -> 0 | BB53: =IF(AI53-AV53=14,1,0) -> 0 | BC53: =IF(AH53-BB53=AH53,0,AH53) -> 0 | BD53: =IF(BB53=1,O53,0) -> 0 | BE53: =IF(BD53<0,BD53,0) -> 0 | BF53: =IF(BD53-BE53<>0,BD53,0) -> 0
A54: 2802 | B54: ARAYA PABLO RAUL | C54: 261-7751681 | D54: VILLA TULUMAYA | E54: 11702 | F54: 45 | G54: 60000 | H54: 0 | M54: 60000 | N54: =IF(H54>0,G54+H54-I54-J54-K54-L54-M54,G54-I54-J54-K54-L54-M54) -> 0 | O54: =G54+H54-J54-I54-K54-L54-M54 -> 0 | P54: =IF(G54+H54<0,0,G54+H54) -> 60000 | Q54: 46248 | R54: 46248 | S54: 46219 | V54: MERCADO PAGO | X54: 7 | Y54: 7 | Z54: =IF(N54<0,0,N54) -> 0 | AH54: 1 | AI54: =IF(F54<=6,15,25) -> 25 | AJ54: =IF(O54<>0,25,15) -> 15 | AK54: =IF(AI54-T54=24,1,0) -> 0 | AL54: =IF(AH54-AK54=AH54,0,AH54) -> 0 | AM54: =IF(AK54<>0,U54,0) -> 0 | AN54: =IF(AK54=1,O54,0) -> 0 | AO54: =IF(AI54-T54=14,1,0) -> 0 | AP54: =IF(AH54-AO54=AH54,0,AH54) -> 0 | AQ54: =IF(AO54<>0,U54,0) -> 0 | AR54: =IF(AO54=1,O54,0) -> 0 | AS54: =IF(SUM(I54:M54)<>0,1,0) -> 1 | AT54: =AS54 -> 1 | AU54: =IF(O54>0,1,0) -> 0 | AV54: =IF(AK54+AO54+AU54=1,AU54,0) -> 0 | AW54: =IF(AI54-AV54=24,1,0) -> 0 | AX54: =IF(AH54-AW54=AH54,0,AH54) -> 0 | AY54: =IF(AW54=1,O54,0) -> 0 | AZ54: =IF(AY54-BA54<>0,AY54,0) -> 0 | BA54: =IF(AY54<0,AY54,0) -> 0 | BB54: =IF(AI54-AV54=14,1,0) -> 0 | BC54: =IF(AH54-BB54=AH54,0,AH54) -> 0 | BD54: =IF(BB54=1,O54,0) -> 0 | BE54: =IF(BD54<0,BD54,0) -> 0 | BF54: =IF(BD54-BE54<>0,BD54,0) -> 0
A55: 2816 | B55: ESPINOZA SALAS ELVIA MATILDE | C55: 264-6719959 | D55: 9 DE JULIO | E55: 11701 | F55: 44 | G55: 60000 | H55: 0 | M55: 60000 | N55: =IF(H55>0,G55+H55-I55-J55-K55-L55-M55,G55-I55-J55-K55-L55-M55) -> 0 | O55: =G55+H55-J55-I55-K55-L55-M55 -> 0 | P55: =IF(G55+H55<0,0,G55+H55) -> 60000 | Q55: 46266 | R55: 46234 | S55: 46234 | V55: MERCADO PAGO | X55: 7 | Y55: 7 | Z55: =IF(N55<0,0,N55) -> 0 | AH55: 1 | AI55: =IF(F55<=6,15,25) -> 25 | AJ55: =IF(O55<>0,25,15) -> 15 | AK55: =IF(AI55-T55=24,1,0) -> 0 | AL55: =IF(AH55-AK55=AH55,0,AH55) -> 0 | AM55: =IF(AK55<>0,U55,0) -> 0 | AN55: =IF(AK55=1,O55,0) -> 0 | AO55: =IF(AI55-T55=14,1,0) -> 0 | AP55: =IF(AH55-AO55=AH55,0,AH55) -> 0 | AQ55: =IF(AO55<>0,U55,0) -> 0 | AR55: =IF(AO55=1,O55,0) -> 0 | AS55: =IF(SUM(I55:M55)<>0,1,0) -> 1 | AT55: =AS55 -> 1 | AU55: =IF(O55>0,1,0) -> 0 | AV55: =IF(AK55+AO55+AU55=1,AU55,0) -> 0 | AW55: =IF(AI55-AV55=24,1,0) -> 0 | AX55: =IF(AH55-AW55=AH55,0,AH55) -> 0 | AY55: =IF(AW55=1,O55,0) -> 0 | AZ55: =IF(AY55-BA55<>0,AY55,0) -> 0 | BA55: =IF(AY55<0,AY55,0) -> 0 | BB55: =IF(AI55-AV55=14,1,0) -> 0 | BC55: =IF(AH55-BB55=AH55,0,AH55) -> 0 | BD55: =IF(BB55=1,O55,0) -> 0 | BE55: =IF(BD55<0,BD55,0) -> 0 | BF55: =IF(BD55-BE55<>0,BD55,0) -> 0
A56: 2836 | B56: DELGADO FERNANDO EXEQUIEL | C56: 264-6614350 | D56: SAN JUAN | E56: 11737 | F56: 43 | G56: 55000 | H56: 0 | M56: 55000 | N56: =IF(H56>0,G56+H56-I56-J56-K56-L56-M56,G56-I56-J56-K56-L56-M56) -> 0 | O56: =G56+H56-J56-I56-K56-L56-M56 -> 0 | P56: =IF(G56+H56<0,0,G56+H56) -> 55000 | Q56: 46246 | R56: 46246 | S56: 46218 | V56: MERCADO PAGO | X56: 7 | Y56: 7 | Z56: =IF(N56<0,0,N56) -> 0 | AH56: 1 | AI56: =IF(F56<=6,15,25) -> 25 | AJ56: =IF(O56<>0,25,15) -> 15 | AK56: =IF(AI56-T56=24,1,0) -> 0 | AL56: =IF(AH56-AK56=AH56,0,AH56) -> 0 | AM56: =IF(AK56<>0,U56,0) -> 0 | AN56: =IF(AK56=1,O56,0) -> 0 | AO56: =IF(AI56-T56=14,1,0) -> 0 | AP56: =IF(AH56-AO56=AH56,0,AH56) -> 0 | AQ56: =IF(AO56<>0,U56,0) -> 0 | AR56: =IF(AO56=1,O56,0) -> 0 | AS56: =IF(SUM(I56:M56)<>0,1,0) -> 1 | AT56: =AS56 -> 1 | AU56: =IF(O56>0,1,0) -> 0 | AV56: =IF(AK56+AO56+AU56=1,AU56,0) -> 0 | AW56: =IF(AI56-AV56=24,1,0) -> 0 | AX56: =IF(AH56-AW56=AH56,0,AH56) -> 0 | AY56: =IF(AW56=1,O56,0) -> 0 | AZ56: =IF(AY56-BA56<>0,AY56,0) -> 0 | BA56: =IF(AY56<0,AY56,0) -> 0 | BB56: =IF(AI56-AV56=14,1,0) -> 0 | BC56: =IF(AH56-BB56=AH56,0,AH56) -> 0 | BD56: =IF(BB56=1,O56,0) -> 0 | BE56: =IF(BD56<0,BD56,0) -> 0 | BF56: =IF(BD56-BE56<>0,BD56,0) -> 0
A57: 2853 | B57: TELLO DOMINGA MANUELA | C57: 264-5260938 | D57: RAWSON | E57: 11750 | F57: 42 | G57: 45000 | H57: -70000 | M57: 45000 | N57: =IF(H57>0,G57+H57-I57-J57-K57-L57-M57,G57-I57-J57-K57-L57-M57) -> 0 | O57: =G57+H57-J57-I57-K57-L57-M57 -> -70000 | P57: =IF(G57+H57<0,0,G57+H57) -> 0 | Q57: 46260 | R57: 46259 | S57: 46230 | V57: MERCADO PAGO | X57: 7 | Y57: 7 | Z57: =IF(N57<0,0,N57) -> 0 | AH57: 1 | AI57: =IF(F57<=6,15,25) -> 25 | AJ57: =IF(O57<>0,25,15) -> 25 | AK57: =IF(AI57-T57=24,1,0) -> 0 | AL57: =IF(AH57-AK57=AH57,0,AH57) -> 0 | AM57: =IF(AK57<>0,U57,0) -> 0 | AN57: =IF(AK57=1,O57,0) -> 0 | AO57: =IF(AI57-T57=14,1,0) -> 0 | AP57: =IF(AH57-AO57=AH57,0,AH57) -> 0 | AQ57: =IF(AO57<>0,U57,0) -> 0 | AR57: =IF(AO57=1,O57,0) -> 0 | AS57: =IF(SUM(I57:M57)<>0,1,0) -> 1 | AT57: =AS57 -> 1 | AU57: =IF(O57>0,1,0) -> 0 | AV57: =IF(AK57+AO57+AU57=1,AU57,0) -> 0 | AW57: =IF(AI57-AV57=24,1,0) -> 0 | AX57: =IF(AH57-AW57=AH57,0,AH57) -> 0 | AY57: =IF(AW57=1,O57,0) -> 0 | AZ57: =IF(AY57-BA57<>0,AY57,0) -> 0 | BA57: =IF(AY57<0,AY57,0) -> 0 | BB57: =IF(AI57-AV57=14,1,0) -> 0 | BC57: =IF(AH57-BB57=AH57,0,AH57) -> 0 | BD57: =IF(BB57=1,O57,0) -> 0 | BE57: =IF(BD57<0,BD57,0) -> 0 | BF57: =IF(BD57-BE57<>0,BD57,0) -> 0
A58: 2872 | B58: OLIVERA ELISA VALERIA | C58: 264-4447849 | D58: ANGACO | E58: 11648 | F58: 41 | G58: 55000 | H58: 0 | M58: 55000 | N58: =IF(H58>0,G58+H58-I58-J58-K58-L58-M58,G58-I58-J58-K58-L58-M58) -> 0 | O58: =G58+H58-J58-I58-K58-L58-M58 -> 0 | P58: =IF(G58+H58<0,0,G58+H58) -> 55000 | Q58: 46254 | R58: 46259 | S58: 46220 | V58: PAGO FACIL | X58: 7 | Y58: 7 | Z58: =IF(N58<0,0,N58) -> 0 | AH58: 1 | AI58: =IF(F58<=6,15,25) -> 25 | AJ58: =IF(O58<>0,25,15) -> 15 | AK58: =IF(AI58-T58=24,1,0) -> 0 | AL58: =IF(AH58-AK58=AH58,0,AH58) -> 0 | AM58: =IF(AK58<>0,U58,0) -> 0 | AN58: =IF(AK58=1,O58,0) -> 0 | AO58: =IF(AI58-T58=14,1,0) -> 0 | AP58: =IF(AH58-AO58=AH58,0,AH58) -> 0 | AQ58: =IF(AO58<>0,U58,0) -> 0 | AR58: =IF(AO58=1,O58,0) -> 0 | AS58: =IF(SUM(I58:M58)<>0,1,0) -> 1 | AT58: =AS58 -> 1 | AU58: =IF(O58>0,1,0) -> 0 | AV58: =IF(AK58+AO58+AU58=1,AU58,0) -> 0 | AW58: =IF(AI58-AV58=24,1,0) -> 0 | AX58: =IF(AH58-AW58=AH58,0,AH58) -> 0 | AY58: =IF(AW58=1,O58,0) -> 0 | AZ58: =IF(AY58-BA58<>0,AY58,0) -> 0 | BA58: =IF(AY58<0,AY58,0) -> 0 | BB58: =IF(AI58-AV58=14,1,0) -> 0 | BC58: =IF(AH58-BB58=AH58,0,AH58) -> 0 | BD58: =IF(BB58=1,O58,0) -> 0 | BE58: =IF(BD58<0,BD58,0) -> 0 | BF58: =IF(BD58-BE58<>0,BD58,0) -> 0
A59: 2877 | B59: ALCANIS SUSANA ELIZABETH | C59: 264-5778208 | D59: RAWSON | E59: 11783 | F59: 41 | G59: 40000 | H59: -20000 | M59: 40000 | N59: =IF(H59>0,G59+H59-I59-J59-K59-L59-M59,G59-I59-J59-K59-L59-M59) -> 0 | O59: =G59+H59-J59-I59-K59-L59-M59 -> -20000 | P59: =IF(G59+H59<0,0,G59+H59) -> 20000 | Q59: 46265 | R59: 46265 | S59: 46234 | V59: MERCADO PAGO | X59: 7 | Y59: 7 | Z59: =IF(N59<0,0,N59) -> 0 | AH59: 1 | AI59: =IF(F59<=6,15,25) -> 25 | AJ59: =IF(O59<>0,25,15) -> 25 | AK59: =IF(AI59-T59=24,1,0) -> 0 | AL59: =IF(AH59-AK59=AH59,0,AH59) -> 0 | AM59: =IF(AK59<>0,U59,0) -> 0 | AN59: =IF(AK59=1,O59,0) -> 0 | AO59: =IF(AI59-T59=14,1,0) -> 0 | AP59: =IF(AH59-AO59=AH59,0,AH59) -> 0 | AQ59: =IF(AO59<>0,U59,0) -> 0 | AR59: =IF(AO59=1,O59,0) -> 0 | AS59: =IF(SUM(I59:M59)<>0,1,0) -> 1 | AT59: =AS59 -> 1 | AU59: =IF(O59>0,1,0) -> 0 | AV59: =IF(AK59+AO59+AU59=1,AU59,0) -> 0 | AW59: =IF(AI59-AV59=24,1,0) -> 0 | AX59: =IF(AH59-AW59=AH59,0,AH59) -> 0 | AY59: =IF(AW59=1,O59,0) -> 0 | AZ59: =IF(AY59-BA59<>0,AY59,0) -> 0 | BA59: =IF(AY59<0,AY59,0) -> 0 | BB59: =IF(AI59-AV59=14,1,0) -> 0 | BC59: =IF(AH59-BB59=AH59,0,AH59) -> 0 | BD59: =IF(BB59=1,O59,0) -> 0 | BE59: =IF(BD59<0,BD59,0) -> 0 | BF59: =IF(BD59-BE59<>0,BD59,0) -> 0
A60: 2890 | B60: HUANCA QUISPE MIRIAM NANCY | C60: 264-5645707 | D60: RAWSON | E60: 11801 | F60: 41 | G60: 90000 | H60: 0 | M60: 90000 | N60: =IF(H60>0,G60+H60-I60-J60-K60-L60-M60,G60-I60-J60-K60-L60-M60) -> 0 | O60: =G60+H60-J60-I60-K60-L60-M60 -> 0 | P60: =IF(G60+H60<0,0,G60+H60) -> 90000 | Q60: 46265 | R60: 46265 | S60: 46234 | V60: MERCADO PAGO | X60: 7 | Y60: 7 | Z60: =IF(N60<0,0,N60) -> 0 | AH60: 1 | AI60: =IF(F60<=6,15,25) -> 25 | AJ60: =IF(O60<>0,25,15) -> 15 | AK60: =IF(AI60-T60=24,1,0) -> 0 | AL60: =IF(AH60-AK60=AH60,0,AH60) -> 0 | AM60: =IF(AK60<>0,U60,0) -> 0 | AN60: =IF(AK60=1,O60,0) -> 0 | AO60: =IF(AI60-T60=14,1,0) -> 0 | AP60: =IF(AH60-AO60=AH60,0,AH60) -> 0 | AQ60: =IF(AO60<>0,U60,0) -> 0 | AR60: =IF(AO60=1,O60,0) -> 0 | AS60: =IF(SUM(I60:M60)<>0,1,0) -> 1 | AT60: =AS60 -> 1 | AU60: =IF(O60>0,1,0) -> 0 | AV60: =IF(AK60+AO60+AU60=1,AU60,0) -> 0 | AW60: =IF(AI60-AV60=24,1,0) -> 0 | AX60: =IF(AH60-AW60=AH60,0,AH60) -> 0 | AY60: =IF(AW60=1,O60,0) -> 0 | AZ60: =IF(AY60-BA60<>0,AY60,0) -> 0 | BA60: =IF(AY60<0,AY60,0) -> 0 | BB60: =IF(AI60-AV60=14,1,0) -> 0 | BC60: =IF(AH60-BB60=AH60,0,AH60) -> 0 | BD60: =IF(BB60=1,O60,0) -> 0 | BE60: =IF(BD60<0,BD60,0) -> 0 | BF60: =IF(BD60-BE60<>0,BD60,0) -> 0
A61: 2892 | B61: ORMEÑO DEGO ANDRES | C61: 264-4993610 | D61: RAWSON | E61: 11803 | F61: 41 | G61: 80000 | H61: 0 | M61: 80000 | N61: =IF(H61>0,G61+H61-I61-J61-K61-L61-M61,G61-I61-J61-K61-L61-M61) -> 0 | O61: =G61+H61-J61-I61-K61-L61-M61 -> 0 | P61: =IF(G61+H61<0,0,G61+H61) -> 80000 | Q61: 46248 | R61: 46248 | S61: 46225 | V61: MERCADO PAGO | X61: 7 | Y61: 7 | Z61: =IF(N61<0,0,N61) -> 0 | AH61: 1 | AI61: =IF(F61<=6,15,25) -> 25 | AJ61: =IF(O61<>0,25,15) -> 15 | AK61: =IF(AI61-T61=24,1,0) -> 0 | AL61: =IF(AH61-AK61=AH61,0,AH61) -> 0 | AM61: =IF(AK61<>0,U61,0) -> 0 | AN61: =IF(AK61=1,O61,0) -> 0 | AO61: =IF(AI61-T61=14,1,0) -> 0 | AP61: =IF(AH61-AO61=AH61,0,AH61) -> 0 | AQ61: =IF(AO61<>0,U61,0) -> 0 | AR61: =IF(AO61=1,O61,0) -> 0 | AS61: =IF(SUM(I61:M61)<>0,1,0) -> 1 | AT61: =AS61 -> 1 | AU61: =IF(O61>0,1,0) -> 0 | AV61: =IF(AK61+AO61+AU61=1,AU61,0) -> 0 | AW61: =IF(AI61-AV61=24,1,0) -> 0 | AX61: =IF(AH61-AW61=AH61,0,AH61) -> 0 | AY61: =IF(AW61=1,O61,0) -> 0 | AZ61: =IF(AY61-BA61<>0,AY61,0) -> 0 | BA61: =IF(AY61<0,AY61,0) -> 0 | BB61: =IF(AI61-AV61=14,1,0) -> 0 | BC61: =IF(AH61-BB61=AH61,0,AH61) -> 0 | BD61: =IF(BB61=1,O61,0) -> 0 | BE61: =IF(BD61<0,BD61,0) -> 0 | BF61: =IF(BD61-BE61<>0,BD61,0) -> 0
A62: 2897 | B62: ESPEJO ALEXANDRA VANESA | C62: 264-5163415 | D62: SAN JUAN | E62: 11810 | F62: 41 | G62: 80000 | H62: 0 | N62: =IF(H62>0,G62+H62-I62-J62-K62-L62-M62,G62-I62-J62-K62-L62-M62) -> 80000 | O62: =G62+H62-J62-I62-K62-L62-M62 -> 80000 | P62: =IF(G62+H62<0,0,G62+H62) -> 80000 | R62: 46264 | S62: 46218 | W62: NO PAGO PROBLEMAS ECONOMICOS | X62: 7 | Y62: 7 | Z62: =IF(N62<0,0,N62) -> 80000 | AH62: 1 | AI62: =IF(F62<=6,15,25) -> 25 | AJ62: =IF(O62<>0,25,15) -> 25 | AK62: =IF(AI62-T62=24,1,0) -> 0 | AL62: =IF(AH62-AK62=AH62,0,AH62) -> 0 | AM62: =IF(AK62<>0,U62,0) -> 0 | AN62: =IF(AK62=1,O62,0) -> 0 | AO62: =IF(AI62-T62=14,1,0) -> 0 | AP62: =IF(AH62-AO62=AH62,0,AH62) -> 0 | AQ62: =IF(AO62<>0,U62,0) -> 0 | AR62: =IF(AO62=1,O62,0) -> 0 | AS62: =IF(SUM(I62:M62)<>0,1,0) -> 0 | AT62: =AS62 -> 0 | AU62: =IF(O62>0,1,0) -> 1 | AV62: =IF(AK62+AO62+AU62=1,AU62,0) -> 1 | AW62: =IF(AI62-AV62=24,1,0) -> 1 | AX62: =IF(AH62-AW62=AH62,0,AH62) -> 1 | AY62: =IF(AW62=1,O62,0) -> 80000 | AZ62: =IF(AY62-BA62<>0,AY62,0) -> 80000 | BA62: =IF(AY62<0,AY62,0) -> 0 | BB62: =IF(AI62-AV62=14,1,0) -> 0 | BC62: =IF(AH62-BB62=AH62,0,AH62) -> 0 | BD62: =IF(BB62=1,O62,0) -> 0 | BE62: =IF(BD62<0,BD62,0) -> 0 | BF62: =IF(BD62-BE62<>0,BD62,0) -> 0
A63: 2948 | B63: MARTINEZ CRISTIAN IVAN | C63: 264-5738515 | D63: SAN JUAN | E63: 11842 | F63: 39 | G63: 120000 | H63: 0 | M63: 120000 | N63: =IF(H63>0,G63+H63-I63-J63-K63-L63-M63,G63-I63-J63-K63-L63-M63) -> 0 | O63: =G63+H63-J63-I63-K63-L63-M63 -> 0 | P63: =IF(G63+H63<0,0,G63+H63) -> 120000 | Q63: 46244 | R63: 46244 | S63: 46213 | X63: 7 | Y63: 7 | Z63: =IF(N63<0,0,N63) -> 0 | AH63: 1 | AI63: =IF(F63<=6,15,25) -> 25 | AJ63: =IF(O63<>0,25,15) -> 15 | AK63: =IF(AI63-T63=24,1,0) -> 0 | AL63: =IF(AH63-AK63=AH63,0,AH63) -> 0 | AM63: =IF(AK63<>0,U63,0) -> 0 | AN63: =IF(AK63=1,O63,0) -> 0 | AO63: =IF(AI63-T63=14,1,0) -> 0 | AP63: =IF(AH63-AO63=AH63,0,AH63) -> 0 | AQ63: =IF(AO63<>0,U63,0) -> 0 | AR63: =IF(AO63=1,O63,0) -> 0 | AS63: =IF(SUM(I63:M63)<>0,1,0) -> 1 | AT63: =AS63 -> 1 | AU63: =IF(O63>0,1,0) -> 0 | AV63: =IF(AK63+AO63+AU63=1,AU63,0) -> 0 | AW63: =IF(AI63-AV63=24,1,0) -> 0 | AX63: =IF(AH63-AW63=AH63,0,AH63) -> 0 | AY63: =IF(AW63=1,O63,0) -> 0 | AZ63: =IF(AY63-BA63<>0,AY63,0) -> 0 | BA63: =IF(AY63<0,AY63,0) -> 0 | BB63: =IF(AI63-AV63=14,1,0) -> 0 | BC63: =IF(AH63-BB63=AH63,0,AH63) -> 0 | BD63: =IF(BB63=1,O63,0) -> 0 | BE63: =IF(BD63<0,BD63,0) -> 0 | BF63: =IF(BD63-BE63<>0,BD63,0) -> 0
A64: 2960 | B64: ARANCIBIA GALLARDO JORGE IVAN | C64: 264-5713755 | D64: SAN JUAN | E64: 11871 | F64: 39 | G64: 30000 | H64: 0 | M64: 30000 | N64: =IF(H64>0,G64+H64-I64-J64-K64-L64-M64,G64-I64-J64-K64-L64-M64) -> 0 | O64: =G64+H64-J64-I64-K64-L64-M64 -> 0 | P64: =IF(G64+H64<0,0,G64+H64) -> 30000 | Q64: 46246 | R64: 46246 | S64: 46212 | V64: MERCADO PAGO | X64: 7 | Y64: 7 | Z64: =IF(N64<0,0,N64) -> 0 | AH64: 1 | AI64: =IF(F64<=6,15,25) -> 25 | AJ64: =IF(O64<>0,25,15) -> 15 | AK64: =IF(AI64-T64=24,1,0) -> 0 | AL64: =IF(AH64-AK64=AH64,0,AH64) -> 0 | AM64: =IF(AK64<>0,U64,0) -> 0 | AN64: =IF(AK64=1,O64,0) -> 0 | AO64: =IF(AI64-T64=14,1,0) -> 0 | AP64: =IF(AH64-AO64=AH64,0,AH64) -> 0 | AQ64: =IF(AO64<>0,U64,0) -> 0 | AR64: =IF(AO64=1,O64,0) -> 0 | AS64: =IF(SUM(I64:M64)<>0,1,0) -> 1 | AT64: =AS64 -> 1 | AU64: =IF(O64>0,1,0) -> 0 | AV64: =IF(AK64+AO64+AU64=1,AU64,0) -> 0 | AW64: =IF(AI64-AV64=24,1,0) -> 0 | AX64: =IF(AH64-AW64=AH64,0,AH64) -> 0 | AY64: =IF(AW64=1,O64,0) -> 0 | AZ64: =IF(AY64-BA64<>0,AY64,0) -> 0 | BA64: =IF(AY64<0,AY64,0) -> 0 | BB64: =IF(AI64-AV64=14,1,0) -> 0 | BC64: =IF(AH64-BB64=AH64,0,AH64) -> 0 | BD64: =IF(BB64=1,O64,0) -> 0 | BE64: =IF(BD64<0,BD64,0) -> 0 | BF64: =IF(BD64-BE64<>0,BD64,0) -> 0
A65: 2964 | B65: MARIN FARIAS MAURICIO ALEJANDRO | C65: 264-5858110 | D65: POCITOS | E65: 11875 | F65: 39 | G65: 99999 | H65: -5 | M65: 100000 | N65: =IF(H65>0,G65+H65-I65-J65-K65-L65-M65,G65-I65-J65-K65-L65-M65) -> -1 | O65: =G65+H65-J65-I65-K65-L65-M65 -> -6 | P65: =IF(G65+H65<0,0,G65+H65) -> 99994 | Q65: 46242 | R65: 46209 | S65: 46209 | V65: MERCADO PAGO | X65: 7 | Y65: 7 | Z65: =IF(N65<0,0,N65) -> 0 | AH65: 1 | AI65: =IF(F65<=6,15,25) -> 25 | AJ65: =IF(O65<>0,25,15) -> 25 | AK65: =IF(AI65-T65=24,1,0) -> 0 | AL65: =IF(AH65-AK65=AH65,0,AH65) -> 0 | AM65: =IF(AK65<>0,U65,0) -> 0 | AN65: =IF(AK65=1,O65,0) -> 0 | AO65: =IF(AI65-T65=14,1,0) -> 0 | AP65: =IF(AH65-AO65=AH65,0,AH65) -> 0 | AQ65: =IF(AO65<>0,U65,0) -> 0 | AR65: =IF(AO65=1,O65,0) -> 0 | AS65: =IF(SUM(I65:M65)<>0,1,0) -> 1 | AT65: =AS65 -> 1 | AU65: =IF(O65>0,1,0) -> 0 | AV65: =IF(AK65+AO65+AU65=1,AU65,0) -> 0 | AW65: =IF(AI65-AV65=24,1,0) -> 0 | AX65: =IF(AH65-AW65=AH65,0,AH65) -> 0 | AY65: =IF(AW65=1,O65,0) -> 0 | AZ65: =IF(AY65-BA65<>0,AY65,0) -> 0 | BA65: =IF(AY65<0,AY65,0) -> 0 | BB65: =IF(AI65-AV65=14,1,0) -> 0 | BC65: =IF(AH65-BB65=AH65,0,AH65) -> 0 | BD65: =IF(BB65=1,O65,0) -> 0 | BE65: =IF(BD65<0,BD65,0) -> 0 | BF65: =IF(BD65-BE65<>0,BD65,0) -> 0
A66: 2980 | B66: TAPIA GONZALEZ CATERINA | C66: 264-5863829 | D66: POCITOS | E66: 11894 | F66: 39 | G66: 65000 | H66: 0 | M66: 65000 | N66: =IF(H66>0,G66+H66-I66-J66-K66-L66-M66,G66-I66-J66-K66-L66-M66) -> 0 | O66: =G66+H66-J66-I66-K66-L66-M66 -> 0 | P66: =IF(G66+H66<0,0,G66+H66) -> 65000 | Q66: 46244 | R66: 46244 | S66: 46209 | V66: MERCADO PAGO | X66: 7 | Y66: 7 | Z66: =IF(N66<0,0,N66) -> 0 | AH66: 1 | AI66: =IF(F66<=6,15,25) -> 25 | AJ66: =IF(O66<>0,25,15) -> 15 | AK66: =IF(AI66-T66=24,1,0) -> 0 | AL66: =IF(AH66-AK66=AH66,0,AH66) -> 0 | AM66: =IF(AK66<>0,U66,0) -> 0 | AN66: =IF(AK66=1,O66,0) -> 0 | AO66: =IF(AI66-T66=14,1,0) -> 0 | AP66: =IF(AH66-AO66=AH66,0,AH66) -> 0 | AQ66: =IF(AO66<>0,U66,0) -> 0 | AR66: =IF(AO66=1,O66,0) -> 0 | AS66: =IF(SUM(I66:M66)<>0,1,0) -> 1 | AT66: =AS66 -> 1 | AU66: =IF(O66>0,1,0) -> 0 | AV66: =IF(AK66+AO66+AU66=1,AU66,0) -> 0 | AW66: =IF(AI66-AV66=24,1,0) -> 0 | AX66: =IF(AH66-AW66=AH66,0,AH66) -> 0 | AY66: =IF(AW66=1,O66,0) -> 0 | AZ66: =IF(AY66-BA66<>0,AY66,0) -> 0 | BA66: =IF(AY66<0,AY66,0) -> 0 | BB66: =IF(AI66-AV66=14,1,0) -> 0 | BC66: =IF(AH66-BB66=AH66,0,AH66) -> 0 | BD66: =IF(BB66=1,O66,0) -> 0 | BE66: =IF(BD66<0,BD66,0) -> 0 | BF66: =IF(BD66-BE66<>0,BD66,0) -> 0
A67: 2992 | B67: PAZ MAURICIO DANIEL | C67: 264-5519338 | D67: POCITOS | E67: 11891 | F67: 38 | G67: 36000 | H67: -18000 | M67: 36000 | N67: =IF(H67>0,G67+H67-I67-J67-K67-L67-M67,G67-I67-J67-K67-L67-M67) -> 0 | O67: =G67+H67-J67-I67-K67-L67-M67 -> -18000 | P67: =IF(G67+H67<0,0,G67+H67) -> 18000 | Q67: 46244 | R67: 46244 | S67: 46211 | V67: MERCADO PAGO | X67: 7 | Y67: 7 | Z67: =IF(N67<0,0,N67) -> 0 | AH67: 1 | AI67: =IF(F67<=6,15,25) -> 25 | AJ67: =IF(O67<>0,25,15) -> 25 | AK67: =IF(AI67-T67=24,1,0) -> 0 | AL67: =IF(AH67-AK67=AH67,0,AH67) -> 0 | AM67: =IF(AK67<>0,U67,0) -> 0 | AN67: =IF(AK67=1,O67,0) -> 0 | AO67: =IF(AI67-T67=14,1,0) -> 0 | AP67: =IF(AH67-AO67=AH67,0,AH67) -> 0 | AQ67: =IF(AO67<>0,U67,0) -> 0 | AR67: =IF(AO67=1,O67,0) -> 0 | AS67: =IF(SUM(I67:M67)<>0,1,0) -> 1 | AT67: =AS67 -> 1 | AU67: =IF(O67>0,1,0) -> 0 | AV67: =IF(AK67+AO67+AU67=1,AU67,0) -> 0 | AW67: =IF(AI67-AV67=24,1,0) -> 0 | AX67: =IF(AH67-AW67=AH67,0,AH67) -> 0 | AY67: =IF(AW67=1,O67,0) -> 0 | AZ67: =IF(AY67-BA67<>0,AY67,0) -> 0 | BA67: =IF(AY67<0,AY67,0) -> 0 | BB67: =IF(AI67-AV67=14,1,0) -> 0 | BC67: =IF(AH67-BB67=AH67,0,AH67) -> 0 | BD67: =IF(BB67=1,O67,0) -> 0 | BE67: =IF(BD67<0,BD67,0) -> 0 | BF67: =IF(BD67-BE67<>0,BD67,0) -> 0
A68: 2998 | B68: CHAMORRO PEREA MARTIN ALFREDO | C68: 264-4647030 | D68: CHIMBAS | E68: 11899 | F68: 38 | G68: 65000 | H68: 0 | M68: 65000 | N68: =IF(H68>0,G68+H68-I68-J68-K68-L68-M68,G68-I68-J68-K68-L68-M68) -> 0 | O68: =G68+H68-J68-I68-K68-L68-M68 -> 0 | P68: =IF(G68+H68<0,0,G68+H68) -> 65000 | Q68: 46244 | R68: 46244 | S68: 46213 | V68: MERCADO PAGO | X68: 7 | Y68: 7 | Z68: =IF(N68<0,0,N68) -> 0 | AH68: 1 | AI68: =IF(F68<=6,15,25) -> 25 | AJ68: =IF(O68<>0,25,15) -> 15 | AK68: =IF(AI68-T68=24,1,0) -> 0 | AL68: =IF(AH68-AK68=AH68,0,AH68) -> 0 | AM68: =IF(AK68<>0,U68,0) -> 0 | AN68: =IF(AK68=1,O68,0) -> 0 | AO68: =IF(AI68-T68=14,1,0) -> 0 | AP68: =IF(AH68-AO68=AH68,0,AH68) -> 0 | AQ68: =IF(AO68<>0,U68,0) -> 0 | AR68: =IF(AO68=1,O68,0) -> 0 | AS68: =IF(SUM(I68:M68)<>0,1,0) -> 1 | AT68: =AS68 -> 1 | AU68: =IF(O68>0,1,0) -> 0 | AV68: =IF(AK68+AO68+AU68=1,AU68,0) -> 0 | AW68: =IF(AI68-AV68=24,1,0) -> 0 | AX68: =IF(AH68-AW68=AH68,0,AH68) -> 0 | AY68: =IF(AW68=1,O68,0) -> 0 | AZ68: =IF(AY68-BA68<>0,AY68,0) -> 0 | BA68: =IF(AY68<0,AY68,0) -> 0 | BB68: =IF(AI68-AV68=14,1,0) -> 0 | BC68: =IF(AH68-BB68=AH68,0,AH68) -> 0 | BD68: =IF(BB68=1,O68,0) -> 0 | BE68: =IF(BD68<0,BD68,0) -> 0 | BF68: =IF(BD68-BE68<>0,BD68,0) -> 0
A69: 3011 | B69: MADRID CARLOS MARCELO | C69: 264-5697471 | D69: RAWSON | E69: 11103 | F69: 37 | G69: 60000 | H69: 0 | M69: 60000 | N69: =IF(H69>0,G69+H69-I69-J69-K69-L69-M69,G69-I69-J69-K69-L69-M69) -> 0 | O69: =G69+H69-J69-I69-K69-L69-M69 -> 0 | P69: =IF(G69+H69<0,0,G69+H69) -> 60000 | Q69: 46244 | R69: 46244 | S69: 46218 | V69: MERCADO PAGO | X69: 7 | Y69: 7 | Z69: =IF(N69<0,0,N69) -> 0 | AH69: 1 | AI69: =IF(F69<=6,15,25) -> 25 | AJ69: =IF(O69<>0,25,15) -> 15 | AK69: =IF(AI69-T69=24,1,0) -> 0 | AL69: =IF(AH69-AK69=AH69,0,AH69) -> 0 | AM69: =IF(AK69<>0,U69,0) -> 0 | AN69: =IF(AK69=1,O69,0) -> 0 | AO69: =IF(AI69-T69=14,1,0) -> 0 | AP69: =IF(AH69-AO69=AH69,0,AH69) -> 0 | AQ69: =IF(AO69<>0,U69,0) -> 0 | AR69: =IF(AO69=1,O69,0) -> 0 | AS69: =IF(SUM(I69:M69)<>0,1,0) -> 1 | AT69: =AS69 -> 1 | AU69: =IF(O69>0,1,0) -> 0 | AV69: =IF(AK69+AO69+AU69=1,AU69,0) -> 0 | AW69: =IF(AI69-AV69=24,1,0) -> 0 | AX69: =IF(AH69-AW69=AH69,0,AH69) -> 0 | AY69: =IF(AW69=1,O69,0) -> 0 | AZ69: =IF(AY69-BA69<>0,AY69,0) -> 0 | BA69: =IF(AY69<0,AY69,0) -> 0 | BB69: =IF(AI69-AV69=14,1,0) -> 0 | BC69: =IF(AH69-BB69=AH69,0,AH69) -> 0 | BD69: =IF(BB69=1,O69,0) -> 0 | BE69: =IF(BD69<0,BD69,0) -> 0 | BF69: =IF(BD69-BE69<>0,BD69,0) -> 0
A70: 3013 | B70: HERRERA ROCIO BELEN | C70: 264-5835013 | D70: RAWSON | E70: 11145 | F70: 37 | G70: 75000 | H70: 0 | M70: 75000 | N70: =IF(H70>0,G70+H70-I70-J70-K70-L70-M70,G70-I70-J70-K70-L70-M70) -> 0 | O70: =G70+H70-J70-I70-K70-L70-M70 -> 0 | P70: =IF(G70+H70<0,0,G70+H70) -> 75000 | Q70: 46262 | R70: 46249 | S70: 46224 | V70: MERCADO PAGO POR OFICINA | W70: NO PAGARA HASTA QUE LO LLAMEN | X70: 7 | Y70: 7 | Z70: =IF(N70<0,0,N70) -> 0 | AH70: 1 | AI70: =IF(F70<=6,15,25) -> 25 | AJ70: =IF(O70<>0,25,15) -> 15 | AK70: =IF(AI70-T70=24,1,0) -> 0 | AL70: =IF(AH70-AK70=AH70,0,AH70) -> 0 | AM70: =IF(AK70<>0,U70,0) -> 0 | AN70: =IF(AK70=1,O70,0) -> 0 | AO70: =IF(AI70-T70=14,1,0) -> 0 | AP70: =IF(AH70-AO70=AH70,0,AH70) -> 0 | AQ70: =IF(AO70<>0,U70,0) -> 0 | AR70: =IF(AO70=1,O70,0) -> 0 | AS70: =IF(SUM(I70:M70)<>0,1,0) -> 1 | AT70: =AS70 -> 1 | AU70: =IF(O70>0,1,0) -> 0 | AV70: =IF(AK70+AO70+AU70=1,AU70,0) -> 0 | AW70: =IF(AI70-AV70=24,1,0) -> 0 | AX70: =IF(AH70-AW70=AH70,0,AH70) -> 0 | AY70: =IF(AW70=1,O70,0) -> 0 | AZ70: =IF(AY70-BA70<>0,AY70,0) -> 0 | BA70: =IF(AY70<0,AY70,0) -> 0 | BB70: =IF(AI70-AV70=14,1,0) -> 0 | BC70: =IF(AH70-BB70=AH70,0,AH70) -> 0 | BD70: =IF(BB70=1,O70,0) -> 0 | BE70: =IF(BD70<0,BD70,0) -> 0 | BF70: =IF(BD70-BE70<>0,BD70,0) -> 0
A71: 3027 | B71: LUCERO CARMONA YAQUELINA ELIZABETH | C71: 264-6106850 | D71: CHIMBAS | E71: 10161 | F71: 36 | G71: 60000 | H71: -30000 | M71: 60000 | N71: =IF(H71>0,G71+H71-I71-J71-K71-L71-M71,G71-I71-J71-K71-L71-M71) -> 0 | O71: =G71+H71-J71-I71-K71-L71-M71 -> -30000 | P71: =IF(G71+H71<0,0,G71+H71) -> 30000 | Q71: 46245 | R71: 46245 | S71: 46216 | V71: MERCADO PAGO | X71: 7 | Y71: 7 | Z71: =IF(N71<0,0,N71) -> 0 | AH71: 1 | AI71: =IF(F71<=6,15,25) -> 25 | AJ71: =IF(O71<>0,25,15) -> 25 | AK71: =IF(AI71-T71=24,1,0) -> 0 | AL71: =IF(AH71-AK71=AH71,0,AH71) -> 0 | AM71: =IF(AK71<>0,U71,0) -> 0 | AN71: =IF(AK71=1,O71,0) -> 0 | AO71: =IF(AI71-T71=14,1,0) -> 0 | AP71: =IF(AH71-AO71=AH71,0,AH71) -> 0 | AQ71: =IF(AO71<>0,U71,0) -> 0 | AR71: =IF(AO71=1,O71,0) -> 0 | AS71: =IF(SUM(I71:M71)<>0,1,0) -> 1 | AT71: =AS71 -> 1 | AU71: =IF(O71>0,1,0) -> 0 | AV71: =IF(AK71+AO71+AU71=1,AU71,0) -> 0 | AW71: =IF(AI71-AV71=24,1,0) -> 0 | AX71: =IF(AH71-AW71=AH71,0,AH71) -> 0 | AY71: =IF(AW71=1,O71,0) -> 0 | AZ71: =IF(AY71-BA71<>0,AY71,0) -> 0 | BA71: =IF(AY71<0,AY71,0) -> 0 | BB71: =IF(AI71-AV71=14,1,0) -> 0 | BC71: =IF(AH71-BB71=AH71,0,AH71) -> 0 | BD71: =IF(BB71=1,O71,0) -> 0 | BE71: =IF(BD71<0,BD71,0) -> 0 | BF71: =IF(BD71-BE71<>0,BD71,0) -> 0
A72: 3031 | B72: SANCHEZ ADARVEZ FEDERICO JAVIER | C72: 264-5413514 | D72: SAN JUAN | E72: 10168 | F72: 36 | G72: 75000 | H72: -50000 | M72: 75000 | N72: =IF(H72>0,G72+H72-I72-J72-K72-L72-M72,G72-I72-J72-K72-L72-M72) -> 0 | O72: =G72+H72-J72-I72-K72-L72-M72 -> -50000 | P72: =IF(G72+H72<0,0,G72+H72) -> 25000 | Q72: 46244 | R72: 46244 | S72: 46213 | V72: MERCADO PAGO | X72: 7 | Y72: 7 | Z72: =IF(N72<0,0,N72) -> 0 | AH72: 1 | AI72: =IF(F72<=6,15,25) -> 25 | AJ72: =IF(O72<>0,25,15) -> 25 | AK72: =IF(AI72-T72=24,1,0) -> 0 | AL72: =IF(AH72-AK72=AH72,0,AH72) -> 0 | AM72: =IF(AK72<>0,U72,0) -> 0 | AN72: =IF(AK72=1,O72,0) -> 0 | AO72: =IF(AI72-T72=14,1,0) -> 0 | AP72: =IF(AH72-AO72=AH72,0,AH72) -> 0 | AQ72: =IF(AO72<>0,U72,0) -> 0 | AR72: =IF(AO72=1,O72,0) -> 0 | AS72: =IF(SUM(I72:M72)<>0,1,0) -> 1 | AT72: =AS72 -> 1 | AU72: =IF(O72>0,1,0) -> 0 | AV72: =IF(AK72+AO72+AU72=1,AU72,0) -> 0 | AW72: =IF(AI72-AV72=24,1,0) -> 0 | AX72: =IF(AH72-AW72=AH72,0,AH72) -> 0 | AY72: =IF(AW72=1,O72,0) -> 0 | AZ72: =IF(AY72-BA72<>0,AY72,0) -> 0 | BA72: =IF(AY72<0,AY72,0) -> 0 | BB72: =IF(AI72-AV72=14,1,0) -> 0 | BC72: =IF(AH72-BB72=AH72,0,AH72) -> 0 | BD72: =IF(BB72=1,O72,0) -> 0 | BE72: =IF(BD72<0,BD72,0) -> 0 | BF72: =IF(BD72-BE72<>0,BD72,0) -> 0
A73: 3036 | B73: FALCON ARTEZ YANINA VANESA | C73: 264-4806498 | D73: CHIMBAS | E73: 10489 | F73: 36 | G73: 100000 | H73: 0 | N73: =IF(H73>0,G73+H73-I73-J73-K73-L73-M73,G73-I73-J73-K73-L73-M73) -> 100000 | O73: =G73+H73-J73-I73-K73-L73-M73 -> 100000 | P73: =IF(G73+H73<0,0,G73+H73) -> 100000 | R73: 46265 | S73: 46234 | W73: VA PAGAR EL DIA JUEVES 3 PORQUE NO TENIA PAGA LAS DOS JUNTAS | X73: 7 | Y73: 7 | Z73: =IF(N73<0,0,N73) -> 100000 | AH73: 1 | AI73: =IF(F73<=6,15,25) -> 25 | AJ73: =IF(O73<>0,25,15) -> 25 | AK73: =IF(AI73-T73=24,1,0) -> 0 | AL73: =IF(AH73-AK73=AH73,0,AH73) -> 0 | AM73: =IF(AK73<>0,U73,0) -> 0 | AN73: =IF(AK73=1,O73,0) -> 0 | AO73: =IF(AI73-T73=14,1,0) -> 0 | AP73: =IF(AH73-AO73=AH73,0,AH73) -> 0 | AQ73: =IF(AO73<>0,U73,0) -> 0 | AR73: =IF(AO73=1,O73,0) -> 0 | AS73: =IF(SUM(I73:M73)<>0,1,0) -> 0 | AT73: =AS73 -> 0 | AU73: =IF(O73>0,1,0) -> 1 | AV73: =IF(AK73+AO73+AU73=1,AU73,0) -> 1 | AW73: =IF(AI73-AV73=24,1,0) -> 1 | AX73: =IF(AH73-AW73=AH73,0,AH73) -> 1 | AY73: =IF(AW73=1,O73,0) -> 100000 | AZ73: =IF(AY73-BA73<>0,AY73,0) -> 100000 | BA73: =IF(AY73<0,AY73,0) -> 0 | BB73: =IF(AI73-AV73=14,1,0) -> 0 | BC73: =IF(AH73-BB73=AH73,0,AH73) -> 0 | BD73: =IF(BB73=1,O73,0) -> 0 | BE73: =IF(BD73<0,BD73,0) -> 0 | BF73: =IF(BD73-BE73<>0,BD73,0) -> 0
A74: 3044 | B74: MACHUCA DIEGO MARTIN | C74: 264-6735637 | D74: SAN JUAN | E74: 11131 | F74: 36 | G74: 65000 | H74: 0 | M74: 65000 | N74: =IF(H74>0,G74+H74-I74-J74-K74-L74-M74,G74-I74-J74-K74-L74-M74) -> 0 | O74: =G74+H74-J74-I74-K74-L74-M74 -> 0 | P74: =IF(G74+H74<0,0,G74+H74) -> 65000 | Q74: 46245 | R74: 46245 | S74: 46213 | V74: MERCADO PAGO | X74: 7 | Y74: 7 | Z74: =IF(N74<0,0,N74) -> 0 | AH74: 1 | AI74: =IF(F74<=6,15,25) -> 25 | AJ74: =IF(O74<>0,25,15) -> 15 | AK74: =IF(AI74-T74=24,1,0) -> 0 | AL74: =IF(AH74-AK74=AH74,0,AH74) -> 0 | AM74: =IF(AK74<>0,U74,0) -> 0 | AN74: =IF(AK74=1,O74,0) -> 0 | AO74: =IF(AI74-T74=14,1,0) -> 0 | AP74: =IF(AH74-AO74=AH74,0,AH74) -> 0 | AQ74: =IF(AO74<>0,U74,0) -> 0 | AR74: =IF(AO74=1,O74,0) -> 0 | AS74: =IF(SUM(I74:M74)<>0,1,0) -> 1 | AT74: =AS74 -> 1 | AU74: =IF(O74>0,1,0) -> 0 | AV74: =IF(AK74+AO74+AU74=1,AU74,0) -> 0 | AW74: =IF(AI74-AV74=24,1,0) -> 0 | AX74: =IF(AH74-AW74=AH74,0,AH74) -> 0 | AY74: =IF(AW74=1,O74,0) -> 0 | AZ74: =IF(AY74-BA74<>0,AY74,0) -> 0 | BA74: =IF(AY74<0,AY74,0) -> 0 | BB74: =IF(AI74-AV74=14,1,0) -> 0 | BC74: =IF(AH74-BB74=AH74,0,AH74) -> 0 | BD74: =IF(BB74=1,O74,0) -> 0 | BE74: =IF(BD74<0,BD74,0) -> 0 | BF74: =IF(BD74-BE74<>0,BD74,0) -> 0
A75: 3047 | B75: DI CARLO DIAZ FLORENCIA BELEN | C75: 2645 46-2770 | D75: RAWSON | E75: 11136 | F75: 36 | G75: 60000 | H75: -40000 | M75: 60000 | N75: =IF(H75>0,G75+H75-I75-J75-K75-L75-M75,G75-I75-J75-K75-L75-M75) -> 0 | O75: =G75+H75-J75-I75-K75-L75-M75 -> -40000 | P75: =IF(G75+H75<0,0,G75+H75) -> 20000 | Q75: 46246 | R75: 46246 | S75: 46209 | V75: MERCADO PAGO | X75: 7 | Y75: 7 | Z75: =IF(N75<0,0,N75) -> 0 | AH75: 1 | AI75: =IF(F75<=6,15,25) -> 25 | AJ75: =IF(O75<>0,25,15) -> 25 | AK75: =IF(AI75-T75=24,1,0) -> 0 | AL75: =IF(AH75-AK75=AH75,0,AH75) -> 0 | AM75: =IF(AK75<>0,U75,0) -> 0 | AN75: =IF(AK75=1,O75,0) -> 0 | AO75: =IF(AI75-T75=14,1,0) -> 0 | AP75: =IF(AH75-AO75=AH75,0,AH75) -> 0 | AQ75: =IF(AO75<>0,U75,0) -> 0 | AR75: =IF(AO75=1,O75,0) -> 0 | AS75: =IF(SUM(I75:M75)<>0,1,0) -> 1 | AT75: =AS75 -> 1 | AU75: =IF(O75>0,1,0) -> 0 | AV75: =IF(AK75+AO75+AU75=1,AU75,0) -> 0 | AW75: =IF(AI75-AV75=24,1,0) -> 0 | AX75: =IF(AH75-AW75=AH75,0,AH75) -> 0 | AY75: =IF(AW75=1,O75,0) -> 0 | AZ75: =IF(AY75-BA75<>0,AY75,0) -> 0 | BA75: =IF(AY75<0,AY75,0) -> 0 | BB75: =IF(AI75-AV75=14,1,0) -> 0 | BC75: =IF(AH75-BB75=AH75,0,AH75) -> 0 | BD75: =IF(BB75=1,O75,0) -> 0 | BE75: =IF(BD75<0,BD75,0) -> 0 | BF75: =IF(BD75-BE75<>0,BD75,0) -> 0
A76: 3062 | B76: LAIMES INGRID NICOLE SOLEDAD | C76: 264-5573680 | D76: JACHAL | E76: 11925 | F76: 35 | G76: 60000 | H76: -80000 | M76: 60000 | N76: =IF(H76>0,G76+H76-I76-J76-K76-L76-M76,G76-I76-J76-K76-L76-M76) -> 0 | O76: =G76+H76-J76-I76-K76-L76-M76 -> -80000 | P76: =IF(G76+H76<0,0,G76+H76) -> 0 | Q76: 46242 | R76: 46242 | S76: 46211 | V76: MERCADO PAGO | X76: 7 | Y76: 7 | Z76: =IF(N76<0,0,N76) -> 0 | AH76: 1 | AI76: =IF(F76<=6,15,25) -> 25 | AJ76: =IF(O76<>0,25,15) -> 25 | AK76: =IF(AI76-T76=24,1,0) -> 0 | AL76: =IF(AH76-AK76=AH76,0,AH76) -> 0 | AM76: =IF(AK76<>0,U76,0) -> 0 | AN76: =IF(AK76=1,O76,0) -> 0 | AO76: =IF(AI76-T76=14,1,0) -> 0 | AP76: =IF(AH76-AO76=AH76,0,AH76) -> 0 | AQ76: =IF(AO76<>0,U76,0) -> 0 | AR76: =IF(AO76=1,O76,0) -> 0 | AS76: =IF(SUM(I76:M76)<>0,1,0) -> 1 | AT76: =AS76 -> 1 | AU76: =IF(O76>0,1,0) -> 0 | AV76: =IF(AK76+AO76+AU76=1,AU76,0) -> 0 | AW76: =IF(AI76-AV76=24,1,0) -> 0 | AX76: =IF(AH76-AW76=AH76,0,AH76) -> 0 | AY76: =IF(AW76=1,O76,0) -> 0 | AZ76: =IF(AY76-BA76<>0,AY76,0) -> 0 | BA76: =IF(AY76<0,AY76,0) -> 0 | BB76: =IF(AI76-AV76=14,1,0) -> 0 | BC76: =IF(AH76-BB76=AH76,0,AH76) -> 0 | BD76: =IF(BB76=1,O76,0) -> 0 | BE76: =IF(BD76<0,BD76,0) -> 0 | BF76: =IF(BD76-BE76<>0,BD76,0) -> 0
A77: 3080 | B77: CASTILLO MARTHA BEATRIZ | C77: 264-4479687 | D77: SAN JUAN | E77: 11937 | F77: 35 | G77: 60000 | H77: 0 | M77: 60000 | N77: =IF(H77>0,G77+H77-I77-J77-K77-L77-M77,G77-I77-J77-K77-L77-M77) -> 0 | O77: =G77+H77-J77-I77-K77-L77-M77 -> 0 | P77: =IF(G77+H77<0,0,G77+H77) -> 60000 | Q77: 46265 | R77: 46264 | S77: 46204 | V77: MERCADO PAGO | X77: 7 | Y77: 7 | Z77: =IF(N77<0,0,N77) -> 0 | AH77: 1 | AI77: =IF(F77<=6,15,25) -> 25 | AJ77: =IF(O77<>0,25,15) -> 15 | AK77: =IF(AI77-T77=24,1,0) -> 0 | AL77: =IF(AH77-AK77=AH77,0,AH77) -> 0 | AM77: =IF(AK77<>0,U77,0) -> 0 | AN77: =IF(AK77=1,O77,0) -> 0 | AO77: =IF(AI77-T77=14,1,0) -> 0 | AP77: =IF(AH77-AO77=AH77,0,AH77) -> 0 | AQ77: =IF(AO77<>0,U77,0) -> 0 | AR77: =IF(AO77=1,O77,0) -> 0 | AS77: =IF(SUM(I77:M77)<>0,1,0) -> 1 | AT77: =AS77 -> 1 | AU77: =IF(O77>0,1,0) -> 0 | AV77: =IF(AK77+AO77+AU77=1,AU77,0) -> 0 | AW77: =IF(AI77-AV77=24,1,0) -> 0 | AX77: =IF(AH77-AW77=AH77,0,AH77) -> 0 | AY77: =IF(AW77=1,O77,0) -> 0 | AZ77: =IF(AY77-BA77<>0,AY77,0) -> 0 | BA77: =IF(AY77<0,AY77,0) -> 0 | BB77: =IF(AI77-AV77=14,1,0) -> 0 | BC77: =IF(AH77-BB77=AH77,0,AH77) -> 0 | BD77: =IF(BB77=1,O77,0) -> 0 | BE77: =IF(BD77<0,BD77,0) -> 0 | BF77: =IF(BD77-BE77<>0,BD77,0) -> 0
A78: 3083 | B78: ESPEJO PAOLA GISELA | C78: 264-5692712 | D78: SANTA LUCIA | E78: 11991 | F78: 35 | G78: 30000 | H78: 0 | M78: 30000 | N78: =IF(H78>0,G78+H78-I78-J78-K78-L78-M78,G78-I78-J78-K78-L78-M78) -> 0 | O78: =G78+H78-J78-I78-K78-L78-M78 -> 0 | P78: =IF(G78+H78<0,0,G78+H78) -> 30000 | Q78: 46258 | R78: 46258 | S78: 46219 | V78: MERCADO PAGO | X78: 7 | Y78: 7 | Z78: =IF(N78<0,0,N78) -> 0 | AH78: 1 | AI78: =IF(F78<=6,15,25) -> 25 | AJ78: =IF(O78<>0,25,15) -> 15 | AK78: =IF(AI78-T78=24,1,0) -> 0 | AL78: =IF(AH78-AK78=AH78,0,AH78) -> 0 | AM78: =IF(AK78<>0,U78,0) -> 0 | AN78: =IF(AK78=1,O78,0) -> 0 | AO78: =IF(AI78-T78=14,1,0) -> 0 | AP78: =IF(AH78-AO78=AH78,0,AH78) -> 0 | AQ78: =IF(AO78<>0,U78,0) -> 0 | AR78: =IF(AO78=1,O78,0) -> 0 | AS78: =IF(SUM(I78:M78)<>0,1,0) -> 1 | AT78: =AS78 -> 1 | AU78: =IF(O78>0,1,0) -> 0 | AV78: =IF(AK78+AO78+AU78=1,AU78,0) -> 0 | AW78: =IF(AI78-AV78=24,1,0) -> 0 | AX78: =IF(AH78-AW78=AH78,0,AH78) -> 0 | AY78: =IF(AW78=1,O78,0) -> 0 | AZ78: =IF(AY78-BA78<>0,AY78,0) -> 0 | BA78: =IF(AY78<0,AY78,0) -> 0 | BB78: =IF(AI78-AV78=14,1,0) -> 0 | BC78: =IF(AH78-BB78=AH78,0,AH78) -> 0 | BD78: =IF(BB78=1,O78,0) -> 0 | BE78: =IF(BD78<0,BD78,0) -> 0 | BF78: =IF(BD78-BE78<>0,BD78,0) -> 0
A79: 3084 | B79: CARDOZO MIRANDA PAOLA VANESA | C79: 264-6059918 | D79: MEDIA AGUA | E79: 11992 | F79: 35 | G79: 60000 | H79: 0 | M79: 60000 | N79: =IF(H79>0,G79+H79-I79-J79-K79-L79-M79,G79-I79-J79-K79-L79-M79) -> 0 | O79: =G79+H79-J79-I79-K79-L79-M79 -> 0 | P79: =IF(G79+H79<0,0,G79+H79) -> 60000 | Q79: 46244 | R79: 46244 | S79: 46213 | V79: MERCADO PAGO | X79: 7 | Y79: 7 | Z79: =IF(N79<0,0,N79) -> 0 | AH79: 1 | AI79: =IF(F79<=6,15,25) -> 25 | AJ79: =IF(O79<>0,25,15) -> 15 | AK79: =IF(AI79-T79=24,1,0) -> 0 | AL79: =IF(AH79-AK79=AH79,0,AH79) -> 0 | AM79: =IF(AK79<>0,U79,0) -> 0 | AN79: =IF(AK79=1,O79,0) -> 0 | AO79: =IF(AI79-T79=14,1,0) -> 0 | AP79: =IF(AH79-AO79=AH79,0,AH79) -> 0 | AQ79: =IF(AO79<>0,U79,0) -> 0 | AR79: =IF(AO79=1,O79,0) -> 0 | AS79: =IF(SUM(I79:M79)<>0,1,0) -> 1 | AT79: =AS79 -> 1 | AU79: =IF(O79>0,1,0) -> 0 | AV79: =IF(AK79+AO79+AU79=1,AU79,0) -> 0 | AW79: =IF(AI79-AV79=24,1,0) -> 0 | AX79: =IF(AH79-AW79=AH79,0,AH79) -> 0 | AY79: =IF(AW79=1,O79,0) -> 0 | AZ79: =IF(AY79-BA79<>0,AY79,0) -> 0 | BA79: =IF(AY79<0,AY79,0) -> 0 | BB79: =IF(AI79-AV79=14,1,0) -> 0 | BC79: =IF(AH79-BB79=AH79,0,AH79) -> 0 | BD79: =IF(BB79=1,O79,0) -> 0 | BE79: =IF(BD79<0,BD79,0) -> 0 | BF79: =IF(BD79-BE79<>0,BD79,0) -> 0
A80: 3088 | B80: PAEZ MARIO JAVIER | C80: 264-4675674 | D80: SAN JUAN | E80: 20011 | F80: 35 | G80: 50000 | H80: 0 | M80: 50000 | N80: =IF(H80>0,G80+H80-I80-J80-K80-L80-M80,G80-I80-J80-K80-L80-M80) -> 0 | O80: =G80+H80-J80-I80-K80-L80-M80 -> 0 | P80: =IF(G80+H80<0,0,G80+H80) -> 50000 | Q80: 46246 | R80: 46246 | S80: 46213 | V80: MERCADO PAGO | X80: 7 | Y80: 7 | Z80: =IF(N80<0,0,N80) -> 0 | AH80: 1 | AI80: =IF(F80<=6,15,25) -> 25 | AJ80: =IF(O80<>0,25,15) -> 15 | AK80: =IF(AI80-T80=24,1,0) -> 0 | AL80: =IF(AH80-AK80=AH80,0,AH80) -> 0 | AM80: =IF(AK80<>0,U80,0) -> 0 | AN80: =IF(AK80=1,O80,0) -> 0 | AO80: =IF(AI80-T80=14,1,0) -> 0 | AP80: =IF(AH80-AO80=AH80,0,AH80) -> 0 | AQ80: =IF(AO80<>0,U80,0) -> 0 | AR80: =IF(AO80=1,O80,0) -> 0 | AS80: =IF(SUM(I80:M80)<>0,1,0) -> 1 | AT80: =AS80 -> 1 | AU80: =IF(O80>0,1,0) -> 0 | AV80: =IF(AK80+AO80+AU80=1,AU80,0) -> 0 | AW80: =IF(AI80-AV80=24,1,0) -> 0 | AX80: =IF(AH80-AW80=AH80,0,AH80) -> 0 | AY80: =IF(AW80=1,O80,0) -> 0 | AZ80: =IF(AY80-BA80<>0,AY80,0) -> 0 | BA80: =IF(AY80<0,AY80,0) -> 0 | BB80: =IF(AI80-AV80=14,1,0) -> 0 | BC80: =IF(AH80-BB80=AH80,0,AH80) -> 0 | BD80: =IF(BB80=1,O80,0) -> 0 | BE80: =IF(BD80<0,BD80,0) -> 0 | BF80: =IF(BD80-BE80<>0,BD80,0) -> 0
A81: 3100 | B81: MELIAN LILIANA BEATRIZ | C81: 264-4047597 | D81: SANTA LUCIA | E81: 20007 | F81: 35 | G81: 30000 | H81: -10000 | N81: =IF(H81>0,G81+H81-I81-J81-K81-L81-M81,G81-I81-J81-K81-L81-M81) -> 30000 | O81: =G81+H81-J81-I81-K81-L81-M81 -> 20000 | P81: =IF(G81+H81<0,0,G81+H81) -> 20000 | Q81: 46252 | R81: 46252 | S81: 46220 | V81: MERCADO PAGO | X81: 7 | Y81: 7 | Z81: =IF(N81<0,0,N81) -> 30000 | AH81: 1 | AI81: =IF(F81<=6,15,25) -> 25 | AJ81: =IF(O81<>0,25,15) -> 25 | AK81: =IF(AI81-T81=24,1,0) -> 0 | AL81: =IF(AH81-AK81=AH81,0,AH81) -> 0 | AM81: =IF(AK81<>0,U81,0) -> 0 | AN81: =IF(AK81=1,O81,0) -> 0 | AO81: =IF(AI81-T81=14,1,0) -> 0 | AP81: =IF(AH81-AO81=AH81,0,AH81) -> 0 | AQ81: =IF(AO81<>0,U81,0) -> 0 | AR81: =IF(AO81=1,O81,0) -> 0 | AS81: =IF(SUM(I81:M81)<>0,1,0) -> 0 | AT81: =AS81 -> 0 | AU81: =IF(O81>0,1,0) -> 1 | AV81: =IF(AK81+AO81+AU81=1,AU81,0) -> 1 | AW81: =IF(AI81-AV81=24,1,0) -> 1 | AX81: =IF(AH81-AW81=AH81,0,AH81) -> 1 | AY81: =IF(AW81=1,O81,0) -> 20000 | AZ81: =IF(AY81-BA81<>0,AY81,0) -> 20000 | BA81: =IF(AY81<0,AY81,0) -> 0 | BB81: =IF(AI81-AV81=14,1,0) -> 0 | BC81: =IF(AH81-BB81=AH81,0,AH81) -> 0 | BD81: =IF(BB81=1,O81,0) -> 0 | BE81: =IF(BD81<0,BD81,0) -> 0 | BF81: =IF(BD81-BE81<>0,BD81,0) -> 0
A82: 3109 | B82: DIAZ ERNESTO FABIAN | C82: 264-5892492 | D82: RAWSON | E82: 11620 | F82: 35 | G82: 60000 | H82: 0 | M82: 60000 | N82: =IF(H82>0,G82+H82-I82-J82-K82-L82-M82,G82-I82-J82-K82-L82-M82) -> 0 | O82: =G82+H82-J82-I82-K82-L82-M82 -> 0 | P82: =IF(G82+H82<0,0,G82+H82) -> 60000 | Q82: 46265 | R82: 46263 | S82: 46232 | V82: MERCADO PAGO | X82: 7 | Y82: 7 | Z82: =IF(N82<0,0,N82) -> 0 | AH82: 1 | AI82: =IF(F82<=6,15,25) -> 25 | AJ82: =IF(O82<>0,25,15) -> 15 | AK82: =IF(AI82-T82=24,1,0) -> 0 | AL82: =IF(AH82-AK82=AH82,0,AH82) -> 0 | AM82: =IF(AK82<>0,U82,0) -> 0 | AN82: =IF(AK82=1,O82,0) -> 0 | AO82: =IF(AI82-T82=14,1,0) -> 0 | AP82: =IF(AH82-AO82=AH82,0,AH82) -> 0 | AQ82: =IF(AO82<>0,U82,0) -> 0 | AR82: =IF(AO82=1,O82,0) -> 0 | AS82: =IF(SUM(I82:M82)<>0,1,0) -> 1 | AT82: =AS82 -> 1 | AU82: =IF(O82>0,1,0) -> 0 | AV82: =IF(AK82+AO82+AU82=1,AU82,0) -> 0 | AW82: =IF(AI82-AV82=24,1,0) -> 0 | AX82: =IF(AH82-AW82=AH82,0,AH82) -> 0 | AY82: =IF(AW82=1,O82,0) -> 0 | AZ82: =IF(AY82-BA82<>0,AY82,0) -> 0 | BA82: =IF(AY82<0,AY82,0) -> 0 | BB82: =IF(AI82-AV82=14,1,0) -> 0 | BC82: =IF(AH82-BB82=AH82,0,AH82) -> 0 | BD82: =IF(BB82=1,O82,0) -> 0 | BE82: =IF(BD82<0,BD82,0) -> 0 | BF82: =IF(BD82-BE82<>0,BD82,0) -> 0
A83: 3112 | B83: DIAZ MIGUEL ANGEL | C83: 264-5103121 | D83: MEDIA AGUA | E83: 11919 | F83: 35 | G83: 60000 | H83: 0 | M83: 60000 | N83: =IF(H83>0,G83+H83-I83-J83-K83-L83-M83,G83-I83-J83-K83-L83-M83) -> 0 | O83: =G83+H83-J83-I83-K83-L83-M83 -> 0 | P83: =IF(G83+H83<0,0,G83+H83) -> 60000 | Q83: 46254 | R83: 46254 | S83: 46223 | V83: MERCADO PAGO | X83: 7 | Y83: 7 | Z83: =IF(N83<0,0,N83) -> 0 | AH83: 1 | AI83: =IF(F83<=6,15,25) -> 25 | AJ83: =IF(O83<>0,25,15) -> 15 | AK83: =IF(AI83-T83=24,1,0) -> 0 | AL83: =IF(AH83-AK83=AH83,0,AH83) -> 0 | AM83: =IF(AK83<>0,U83,0) -> 0 | AN83: =IF(AK83=1,O83,0) -> 0 | AO83: =IF(AI83-T83=14,1,0) -> 0 | AP83: =IF(AH83-AO83=AH83,0,AH83) -> 0 | AQ83: =IF(AO83<>0,U83,0) -> 0 | AR83: =IF(AO83=1,O83,0) -> 0 | AS83: =IF(SUM(I83:M83)<>0,1,0) -> 1 | AT83: =AS83 -> 1 | AU83: =IF(O83>0,1,0) -> 0 | AV83: =IF(AK83+AO83+AU83=1,AU83,0) -> 0 | AW83: =IF(AI83-AV83=24,1,0) -> 0 | AX83: =IF(AH83-AW83=AH83,0,AH83) -> 0 | AY83: =IF(AW83=1,O83,0) -> 0 | AZ83: =IF(AY83-BA83<>0,AY83,0) -> 0 | BA83: =IF(AY83<0,AY83,0) -> 0 | BB83: =IF(AI83-AV83=14,1,0) -> 0 | BC83: =IF(AH83-BB83=AH83,0,AH83) -> 0 | BD83: =IF(BB83=1,O83,0) -> 0 | BE83: =IF(BD83<0,BD83,0) -> 0 | BF83: =IF(BD83-BE83<>0,BD83,0) -> 0
A84: 3114 | B84: VALDEZ DANISA ANGELES | C84: 264-6292028 | D84: SAN JUAN | E84: 11921 | F84: 35 | G84: 30000 | H84: -3000 | M84: 30000 | N84: =IF(H84>0,G84+H84-I84-J84-K84-L84-M84,G84-I84-J84-K84-L84-M84) -> 0 | O84: =G84+H84-J84-I84-K84-L84-M84 -> -3000 | P84: =IF(G84+H84<0,0,G84+H84) -> 27000 | Q84: 46246 | R84: 46246 | S84: 46216 | V84: MERCADO PAGO | X84: 7 | Y84: 7 | Z84: =IF(N84<0,0,N84) -> 0 | AH84: 1 | AI84: =IF(F84<=6,15,25) -> 25 | AJ84: =IF(O84<>0,25,15) -> 25 | AK84: =IF(AI84-T84=24,1,0) -> 0 | AL84: =IF(AH84-AK84=AH84,0,AH84) -> 0 | AM84: =IF(AK84<>0,U84,0) -> 0 | AN84: =IF(AK84=1,O84,0) -> 0 | AO84: =IF(AI84-T84=14,1,0) -> 0 | AP84: =IF(AH84-AO84=AH84,0,AH84) -> 0 | AQ84: =IF(AO84<>0,U84,0) -> 0 | AR84: =IF(AO84=1,O84,0) -> 0 | AS84: =IF(SUM(I84:M84)<>0,1,0) -> 1 | AT84: =AS84 -> 1 | AU84: =IF(O84>0,1,0) -> 0 | AV84: =IF(AK84+AO84+AU84=1,AU84,0) -> 0 | AW84: =IF(AI84-AV84=24,1,0) -> 0 | AX84: =IF(AH84-AW84=AH84,0,AH84) -> 0 | AY84: =IF(AW84=1,O84,0) -> 0 | AZ84: =IF(AY84-BA84<>0,AY84,0) -> 0 | BA84: =IF(AY84<0,AY84,0) -> 0 | BB84: =IF(AI84-AV84=14,1,0) -> 0 | BC84: =IF(AH84-BB84=AH84,0,AH84) -> 0 | BD84: =IF(BB84=1,O84,0) -> 0 | BE84: =IF(BD84<0,BD84,0) -> 0 | BF84: =IF(BD84-BE84<>0,BD84,0) -> 0
A85: 3115 | B85: ROJAS RAQUEL EVANGELINA | C85: 264-5213213 | D85: CAUCETE | E85: 11938 | F85: 35 | G85: 30000 | H85: 0 | M85: 30000 | N85: =IF(H85>0,G85+H85-I85-J85-K85-L85-M85,G85-I85-J85-K85-L85-M85) -> 0 | O85: =G85+H85-J85-I85-K85-L85-M85 -> 0 | P85: =IF(G85+H85<0,0,G85+H85) -> 30000 | Q85: 46247 | R85: 46217 | S85: 46217 | V85: MERCADO PAGO | X85: 7 | Y85: 7 | Z85: =IF(N85<0,0,N85) -> 0 | AH85: 1 | AI85: =IF(F85<=6,15,25) -> 25 | AJ85: =IF(O85<>0,25,15) -> 15 | AK85: =IF(AI85-T85=24,1,0) -> 0 | AL85: =IF(AH85-AK85=AH85,0,AH85) -> 0 | AM85: =IF(AK85<>0,U85,0) -> 0 | AN85: =IF(AK85=1,O85,0) -> 0 | AO85: =IF(AI85-T85=14,1,0) -> 0 | AP85: =IF(AH85-AO85=AH85,0,AH85) -> 0 | AQ85: =IF(AO85<>0,U85,0) -> 0 | AR85: =IF(AO85=1,O85,0) -> 0 | AS85: =IF(SUM(I85:M85)<>0,1,0) -> 1 | AT85: =AS85 -> 1 | AU85: =IF(O85>0,1,0) -> 0 | AV85: =IF(AK85+AO85+AU85=1,AU85,0) -> 0 | AW85: =IF(AI85-AV85=24,1,0) -> 0 | AX85: =IF(AH85-AW85=AH85,0,AH85) -> 0 | AY85: =IF(AW85=1,O85,0) -> 0 | AZ85: =IF(AY85-BA85<>0,AY85,0) -> 0 | BA85: =IF(AY85<0,AY85,0) -> 0 | BB85: =IF(AI85-AV85=14,1,0) -> 0 | BC85: =IF(AH85-BB85=AH85,0,AH85) -> 0 | BD85: =IF(BB85=1,O85,0) -> 0 | BE85: =IF(BD85<0,BD85,0) -> 0 | BF85: =IF(BD85-BE85<>0,BD85,0) -> 0
A86: 3118 | B86: MACIAS DANIELA VALERIA | C86: 264-4038388 | D86: SAN JUAN | E86: 11940 | F86: 35 | G86: 60000 | H86: 60000 | N86: =IF(H86>0,G86+H86-I86-J86-K86-L86-M86,G86-I86-J86-K86-L86-M86) -> 120000 | O86: =G86+H86-J86-I86-K86-L86-M86 -> 120000 | P86: =IF(G86+H86<0,0,G86+H86) -> 120000 | R86: 46233 | S86: 46203 | T86: 1 | U86: 1 | V86: BAJA POR FALTADE PAGO Y COMUNICACIÓN | X86: 7 | Y86: 7 | Z86: =IF(N86<0,0,N86) -> 120000 | AH86: 1 | AI86: =IF(F86<=6,15,25) -> 25 | AJ86: =IF(O86<>0,25,15) -> 25 | AK86: =IF(AI86-T86=24,1,0) -> 1 | AL86: =IF(AH86-AK86=AH86,0,AH86) -> 1 | AM86: =IF(AK86<>0,U86,0) -> 1 | AN86: =IF(AK86=1,O86,0) -> 120000 | AO86: =IF(AI86-T86=14,1,0) -> 0 | AP86: =IF(AH86-AO86=AH86,0,AH86) -> 0 | AQ86: =IF(AO86<>0,U86,0) -> 0 | AR86: =IF(AO86=1,O86,0) -> 0 | AS86: =IF(SUM(I86:M86)<>0,1,0) -> 0 | AT86: =AS86 -> 0 | AU86: =IF(O86>0,1,0) -> 1 | AV86: =IF(AK86+AO86+AU86=1,AU86,0) -> 0 | AW86: =IF(AI86-AV86=24,1,0) -> 0 | AX86: =IF(AH86-AW86=AH86,0,AH86) -> 0 | AY86: =IF(AW86=1,O86,0) -> 0 | AZ86: =IF(AY86-BA86<>0,AY86,0) -> 0 | BA86: =IF(AY86<0,AY86,0) -> 0 | BB86: =IF(AI86-AV86=14,1,0) -> 0 | BC86: =IF(AH86-BB86=AH86,0,AH86) -> 0 | BD86: =IF(BB86=1,O86,0) -> 0 | BE86: =IF(BD86<0,BD86,0) -> 0 | BF86: =IF(BD86-BE86<>0,BD86,0) -> 0
A87: 3119 | B87: RECHES SANCHEZ ELBIO | C87: 264-5023303 | D87: RAWSON | E87: 11941 | F87: 35 | G87: 60000 | H87: 0 | M87: 60000 | N87: =IF(H87>0,G87+H87-I87-J87-K87-L87-M87,G87-I87-J87-K87-L87-M87) -> 0 | O87: =G87+H87-J87-I87-K87-L87-M87 -> 0 | P87: =IF(G87+H87<0,0,G87+H87) -> 60000 | Q87: 46239 | R87: 46239 | S87: 46213 | V87: MERCADO PAGO | X87: 7 | Y87: 7 | Z87: =IF(N87<0,0,N87) -> 0 | AH87: 1 | AI87: =IF(F87<=6,15,25) -> 25 | AJ87: =IF(O87<>0,25,15) -> 15 | AK87: =IF(AI87-T87=24,1,0) -> 0 | AL87: =IF(AH87-AK87=AH87,0,AH87) -> 0 | AM87: =IF(AK87<>0,U87,0) -> 0 | AN87: =IF(AK87=1,O87,0) -> 0 | AO87: =IF(AI87-T87=14,1,0) -> 0 | AP87: =IF(AH87-AO87=AH87,0,AH87) -> 0 | AQ87: =IF(AO87<>0,U87,0) -> 0 | AR87: =IF(AO87=1,O87,0) -> 0 | AS87: =IF(SUM(I87:M87)<>0,1,0) -> 1 | AT87: =AS87 -> 1 | AU87: =IF(O87>0,1,0) -> 0 | AV87: =IF(AK87+AO87+AU87=1,AU87,0) -> 0 | AW87: =IF(AI87-AV87=24,1,0) -> 0 | AX87: =IF(AH87-AW87=AH87,0,AH87) -> 0 | AY87: =IF(AW87=1,O87,0) -> 0 | AZ87: =IF(AY87-BA87<>0,AY87,0) -> 0 | BA87: =IF(AY87<0,AY87,0) -> 0 | BB87: =IF(AI87-AV87=14,1,0) -> 0 | BC87: =IF(AH87-BB87=AH87,0,AH87) -> 0 | BD87: =IF(BB87=1,O87,0) -> 0 | BE87: =IF(BD87<0,BD87,0) -> 0 | BF87: =IF(BD87-BE87<>0,BD87,0) -> 0
A88: 3128 | B88: ARAYA GRISELDA ROSA | C88: 264-4707695 | D88: RAWSON | E88: 11977 | F88: 35 | G88: 60000 | H88: 0 | I88: 60000 | N88: =IF(H88>0,G88+H88-I88-J88-K88-L88-M88,G88-I88-J88-K88-L88-M88) -> 0 | O88: =G88+H88-J88-I88-K88-L88-M88 -> 0 | P88: =IF(G88+H88<0,0,G88+H88) -> 60000 | Q88: 46237 | R88: 46237 | S88: 46206 | V88: MERCADO PAGO | X88: 7 | Y88: 7 | Z88: =IF(N88<0,0,N88) -> 0 | AH88: 1 | AI88: =IF(F88<=6,15,25) -> 25 | AJ88: =IF(O88<>0,25,15) -> 15 | AK88: =IF(AI88-T88=24,1,0) -> 0 | AL88: =IF(AH88-AK88=AH88,0,AH88) -> 0 | AM88: =IF(AK88<>0,U88,0) -> 0 | AN88: =IF(AK88=1,O88,0) -> 0 | AO88: =IF(AI88-T88=14,1,0) -> 0 | AP88: =IF(AH88-AO88=AH88,0,AH88) -> 0 | AQ88: =IF(AO88<>0,U88,0) -> 0 | AR88: =IF(AO88=1,O88,0) -> 0 | AS88: =IF(SUM(I88:M88)<>0,1,0) -> 1 | AT88: =AS88 -> 1 | AU88: =IF(O88>0,1,0) -> 0 | AV88: =IF(AK88+AO88+AU88=1,AU88,0) -> 0 | AW88: =IF(AI88-AV88=24,1,0) -> 0 | AX88: =IF(AH88-AW88=AH88,0,AH88) -> 0 | AY88: =IF(AW88=1,O88,0) -> 0 | AZ88: =IF(AY88-BA88<>0,AY88,0) -> 0 | BA88: =IF(AY88<0,AY88,0) -> 0 | BB88: =IF(AI88-AV88=14,1,0) -> 0 | BC88: =IF(AH88-BB88=AH88,0,AH88) -> 0 | BD88: =IF(BB88=1,O88,0) -> 0 | BE88: =IF(BD88<0,BD88,0) -> 0 | BF88: =IF(BD88-BE88<>0,BD88,0) -> 0
A89: 3129 | B89: MARTINEZ BENAVIDEZ ANDREA ROSANA | C89: 264-5071309 | D89: SAN JUAN | E89: 11980 | F89: 35 | G89: 60000 | H89: 0 | M89: 60000 | N89: =IF(H89>0,G89+H89-I89-J89-K89-L89-M89,G89-I89-J89-K89-L89-M89) -> 0 | O89: =G89+H89-J89-I89-K89-L89-M89 -> 0 | P89: =IF(G89+H89<0,0,G89+H89) -> 60000 | Q89: 46248 | R89: 46216 | S89: 46216 | V89: MERCADO PAGO | X89: 7 | Y89: 7 | Z89: =IF(N89<0,0,N89) -> 0 | AH89: 1 | AI89: =IF(F89<=6,15,25) -> 25 | AJ89: =IF(O89<>0,25,15) -> 15 | AK89: =IF(AI89-T89=24,1,0) -> 0 | AL89: =IF(AH89-AK89=AH89,0,AH89) -> 0 | AM89: =IF(AK89<>0,U89,0) -> 0 | AN89: =IF(AK89=1,O89,0) -> 0 | AO89: =IF(AI89-T89=14,1,0) -> 0 | AP89: =IF(AH89-AO89=AH89,0,AH89) -> 0 | AQ89: =IF(AO89<>0,U89,0) -> 0 | AR89: =IF(AO89=1,O89,0) -> 0 | AS89: =IF(SUM(I89:M89)<>0,1,0) -> 1 | AT89: =AS89 -> 1 | AU89: =IF(O89>0,1,0) -> 0 | AV89: =IF(AK89+AO89+AU89=1,AU89,0) -> 0 | AW89: =IF(AI89-AV89=24,1,0) -> 0 | AX89: =IF(AH89-AW89=AH89,0,AH89) -> 0 | AY89: =IF(AW89=1,O89,0) -> 0 | AZ89: =IF(AY89-BA89<>0,AY89,0) -> 0 | BA89: =IF(AY89<0,AY89,0) -> 0 | BB89: =IF(AI89-AV89=14,1,0) -> 0 | BC89: =IF(AH89-BB89=AH89,0,AH89) -> 0 | BD89: =IF(BB89=1,O89,0) -> 0 | BE89: =IF(BD89<0,BD89,0) -> 0 | BF89: =IF(BD89-BE89<>0,BD89,0) -> 0
A90: 3130 | B90: GENTILI CHIRINO SABRINA ANABELA | C90: 264-5842222 | D90: SANTA LUCIA | E90: 11623 | F90: 35 | G90: 60000 | H90: 0 | M90: 60000 | N90: =IF(H90>0,G90+H90-I90-J90-K90-L90-M90,G90-I90-J90-K90-L90-M90) -> 0 | O90: =G90+H90-J90-I90-K90-L90-M90 -> 0 | P90: =IF(G90+H90<0,0,G90+H90) -> 60000 | Q90: 46237 | R90: 46237 | S90: 46213 | V90: MERCADO PAGO | X90: 7 | Y90: 7 | Z90: =IF(N90<0,0,N90) -> 0 | AH90: 1 | AI90: =IF(F90<=6,15,25) -> 25 | AJ90: =IF(O90<>0,25,15) -> 15 | AK90: =IF(AI90-T90=24,1,0) -> 0 | AL90: =IF(AH90-AK90=AH90,0,AH90) -> 0 | AM90: =IF(AK90<>0,U90,0) -> 0 | AN90: =IF(AK90=1,O90,0) -> 0 | AO90: =IF(AI90-T90=14,1,0) -> 0 | AP90: =IF(AH90-AO90=AH90,0,AH90) -> 0 | AQ90: =IF(AO90<>0,U90,0) -> 0 | AR90: =IF(AO90=1,O90,0) -> 0 | AS90: =IF(SUM(I90:M90)<>0,1,0) -> 1 | AT90: =AS90 -> 1 | AU90: =IF(O90>0,1,0) -> 0 | AV90: =IF(AK90+AO90+AU90=1,AU90,0) -> 0 | AW90: =IF(AI90-AV90=24,1,0) -> 0 | AX90: =IF(AH90-AW90=AH90,0,AH90) -> 0 | AY90: =IF(AW90=1,O90,0) -> 0 | AZ90: =IF(AY90-BA90<>0,AY90,0) -> 0 | BA90: =IF(AY90<0,AY90,0) -> 0 | BB90: =IF(AI90-AV90=14,1,0) -> 0 | BC90: =IF(AH90-BB90=AH90,0,AH90) -> 0 | BD90: =IF(BB90=1,O90,0) -> 0 | BE90: =IF(BD90<0,BD90,0) -> 0 | BF90: =IF(BD90-BE90<>0,BD90,0) -> 0
A91: 3134 | B91: CHAVEZ CELIA DEOLINDA | C91: 264-5066140 | D91: RAWSON | E91: 269 | F91: 35 | G91: 60000 | H91: 0 | I91: 60000 | N91: =IF(H91>0,G91+H91-I91-J91-K91-L91-M91,G91-I91-J91-K91-L91-M91) -> 0 | O91: =G91+H91-J91-I91-K91-L91-M91 -> 0 | P91: =IF(G91+H91<0,0,G91+H91) -> 60000 | Q91: 46246 | R91: 46246 | S91: 46216 | V91: EFECTIVO OFICINA | X91: 7 | Y91: 7 | Z91: =IF(N91<0,0,N91) -> 0 | AH91: 1 | AI91: =IF(F91<=6,15,25) -> 25 | AJ91: =IF(O91<>0,25,15) -> 15 | AK91: =IF(AI91-T91=24,1,0) -> 0 | AL91: =IF(AH91-AK91=AH91,0,AH91) -> 0 | AM91: =IF(AK91<>0,U91,0) -> 0 | AN91: =IF(AK91=1,O91,0) -> 0 | AO91: =IF(AI91-T91=14,1,0) -> 0 | AP91: =IF(AH91-AO91=AH91,0,AH91) -> 0 | AQ91: =IF(AO91<>0,U91,0) -> 0 | AR91: =IF(AO91=1,O91,0) -> 0 | AS91: =IF(SUM(I91:M91)<>0,1,0) -> 1 | AT91: =AS91 -> 1 | AU91: =IF(O91>0,1,0) -> 0 | AV91: =IF(AK91+AO91+AU91=1,AU91,0) -> 0 | AW91: =IF(AI91-AV91=24,1,0) -> 0 | AX91: =IF(AH91-AW91=AH91,0,AH91) -> 0 | AY91: =IF(AW91=1,O91,0) -> 0 | AZ91: =IF(AY91-BA91<>0,AY91,0) -> 0 | BA91: =IF(AY91<0,AY91,0) -> 0 | BB91: =IF(AI91-AV91=14,1,0) -> 0 | BC91: =IF(AH91-BB91=AH91,0,AH91) -> 0 | BD91: =IF(BB91=1,O91,0) -> 0 | BE91: =IF(BD91<0,BD91,0) -> 0 | BF91: =IF(BD91-BE91<>0,BD91,0) -> 0
A92: 3137 | B92: REINOSO LUISA ALEJANDRA | C92: 264-4196459 | D92: SAN JUAN | E92: 20002 | F92: 35 | G92: 55000 | H92: 0 | M92: 55000 | N92: =IF(H92>0,G92+H92-I92-J92-K92-L92-M92,G92-I92-J92-K92-L92-M92) -> 0 | O92: =G92+H92-J92-I92-K92-L92-M92 -> 0 | P92: =IF(G92+H92<0,0,G92+H92) -> 55000 | Q92: 46237 | R92: 46237 | S92: 46213 | V92: MERCADO PAGO | X92: 7 | Y92: 7 | Z92: =IF(N92<0,0,N92) -> 0 | AH92: 1 | AI92: =IF(F92<=6,15,25) -> 25 | AJ92: =IF(O92<>0,25,15) -> 15 | AK92: =IF(AI92-T92=24,1,0) -> 0 | AL92: =IF(AH92-AK92=AH92,0,AH92) -> 0 | AM92: =IF(AK92<>0,U92,0) -> 0 | AN92: =IF(AK92=1,O92,0) -> 0 | AO92: =IF(AI92-T92=14,1,0) -> 0 | AP92: =IF(AH92-AO92=AH92,0,AH92) -> 0 | AQ92: =IF(AO92<>0,U92,0) -> 0 | AR92: =IF(AO92=1,O92,0) -> 0 | AS92: =IF(SUM(I92:M92)<>0,1,0) -> 1 | AT92: =AS92 -> 1 | AU92: =IF(O92>0,1,0) -> 0 | AV92: =IF(AK92+AO92+AU92=1,AU92,0) -> 0 | AW92: =IF(AI92-AV92=24,1,0) -> 0 | AX92: =IF(AH92-AW92=AH92,0,AH92) -> 0 | AY92: =IF(AW92=1,O92,0) -> 0 | AZ92: =IF(AY92-BA92<>0,AY92,0) -> 0 | BA92: =IF(AY92<0,AY92,0) -> 0 | BB92: =IF(AI92-AV92=14,1,0) -> 0 | BC92: =IF(AH92-BB92=AH92,0,AH92) -> 0 | BD92: =IF(BB92=1,O92,0) -> 0 | BE92: =IF(BD92<0,BD92,0) -> 0 | BF92: =IF(BD92-BE92<>0,BD92,0) -> 0
A93: 3142 | B93: RODRIGUEZ FLORA ETELVINA | C93: 264-4729466 | D93: CHIMBAS | E93: 11965 | F93: 35 | G93: 60000 | H93: -10000 | M93: 60000 | N93: =IF(H93>0,G93+H93-I93-J93-K93-L93-M93,G93-I93-J93-K93-L93-M93) -> 0 | O93: =G93+H93-J93-I93-K93-L93-M93 -> -10000 | P93: =IF(G93+H93<0,0,G93+H93) -> 50000 | Q93: 46239 | R93: 46239 | S93: 46204 | V93: MERCADO PAGO | X93: 7 | Y93: 7 | Z93: =IF(N93<0,0,N93) -> 0 | AH93: 1 | AI93: =IF(F93<=6,15,25) -> 25 | AJ93: =IF(O93<>0,25,15) -> 25 | AK93: =IF(AI93-T93=24,1,0) -> 0 | AL93: =IF(AH93-AK93=AH93,0,AH93) -> 0 | AM93: =IF(AK93<>0,U93,0) -> 0 | AN93: =IF(AK93=1,O93,0) -> 0 | AO93: =IF(AI93-T93=14,1,0) -> 0 | AP93: =IF(AH93-AO93=AH93,0,AH93) -> 0 | AQ93: =IF(AO93<>0,U93,0) -> 0 | AR93: =IF(AO93=1,O93,0) -> 0 | AS93: =IF(SUM(I93:M93)<>0,1,0) -> 1 | AT93: =AS93 -> 1 | AU93: =IF(O93>0,1,0) -> 0 | AV93: =IF(AK93+AO93+AU93=1,AU93,0) -> 0 | AW93: =IF(AI93-AV93=24,1,0) -> 0 | AX93: =IF(AH93-AW93=AH93,0,AH93) -> 0 | AY93: =IF(AW93=1,O93,0) -> 0 | AZ93: =IF(AY93-BA93<>0,AY93,0) -> 0 | BA93: =IF(AY93<0,AY93,0) -> 0 | BB93: =IF(AI93-AV93=14,1,0) -> 0 | BC93: =IF(AH93-BB93=AH93,0,AH93) -> 0 | BD93: =IF(BB93=1,O93,0) -> 0 | BE93: =IF(BD93<0,BD93,0) -> 0 | BF93: =IF(BD93-BE93<>0,BD93,0) -> 0
A94: 3158 | B94: POBLETE VIVIANA GRACIELA | C94: 264-4630593 | D94: RODEO | E94: 20018 | F94: 34 | G94: 80000 | H94: 0 | N94: =IF(H94>0,G94+H94-I94-J94-K94-L94-M94,G94-I94-J94-K94-L94-M94) -> 80000 | O94: =G94+H94-J94-I94-K94-L94-M94 -> 80000 | P94: =IF(G94+H94<0,0,G94+H94) -> 80000 | R94: 46259 | S94: 46209 | W94: NO RESPONDE PERO NO DARE DE BAJA | X94: 7 | Y94: 7 | Z94: =IF(N94<0,0,N94) -> 80000 | AH94: 1 | AI94: =IF(F94<=6,15,25) -> 25 | AJ94: =IF(O94<>0,25,15) -> 25 | AK94: =IF(AI94-T94=24,1,0) -> 0 | AL94: =IF(AH94-AK94=AH94,0,AH94) -> 0 | AM94: =IF(AK94<>0,U94,0) -> 0 | AN94: =IF(AK94=1,O94,0) -> 0 | AO94: =IF(AI94-T94=14,1,0) -> 0 | AP94: =IF(AH94-AO94=AH94,0,AH94) -> 0 | AQ94: =IF(AO94<>0,U94,0) -> 0 | AR94: =IF(AO94=1,O94,0) -> 0 | AS94: =IF(SUM(I94:M94)<>0,1,0) -> 0 | AT94: =AS94 -> 0 | AU94: =IF(O94>0,1,0) -> 1 | AV94: =IF(AK94+AO94+AU94=1,AU94,0) -> 1 | AW94: =IF(AI94-AV94=24,1,0) -> 1 | AX94: =IF(AH94-AW94=AH94,0,AH94) -> 1 | AY94: =IF(AW94=1,O94,0) -> 80000 | AZ94: =IF(AY94-BA94<>0,AY94,0) -> 80000 | BA94: =IF(AY94<0,AY94,0) -> 0 | BB94: =IF(AI94-AV94=14,1,0) -> 0 | BC94: =IF(AH94-BB94=AH94,0,AH94) -> 0 | BD94: =IF(BB94=1,O94,0) -> 0 | BE94: =IF(BD94<0,BD94,0) -> 0 | BF94: =IF(BD94-BE94<>0,BD94,0) -> 0
A95: 3163 | B95: FERNANDEZ CLAUDIA CAROLINA | C95: 264-4455717 | D95: SAN JUAN | E95: 20025 | F95: 34 | G95: 200000 | H95: 0 | M95: 200000 | N95: =IF(H95>0,G95+H95-I95-J95-K95-L95-M95,G95-I95-J95-K95-L95-M95) -> 0 | O95: =G95+H95-J95-I95-K95-L95-M95 -> 0 | P95: =IF(G95+H95<0,0,G95+H95) -> 200000 | Q95: 46245 | R95: 46245 | S95: 46217 | V95: MERCADO PAGO | X95: 7 | Y95: 7 | Z95: =IF(N95<0,0,N95) -> 0 | AH95: 1 | AI95: =IF(F95<=6,15,25) -> 25 | AJ95: =IF(O95<>0,25,15) -> 15 | AK95: =IF(AI95-T95=24,1,0) -> 0 | AL95: =IF(AH95-AK95=AH95,0,AH95) -> 0 | AM95: =IF(AK95<>0,U95,0) -> 0 | AN95: =IF(AK95=1,O95,0) -> 0 | AO95: =IF(AI95-T95=14,1,0) -> 0 | AP95: =IF(AH95-AO95=AH95,0,AH95) -> 0 | AQ95: =IF(AO95<>0,U95,0) -> 0 | AR95: =IF(AO95=1,O95,0) -> 0 | AS95: =IF(SUM(I95:M95)<>0,1,0) -> 1 | AT95: =AS95 -> 1 | AU95: =IF(O95>0,1,0) -> 0 | AV95: =IF(AK95+AO95+AU95=1,AU95,0) -> 0 | AW95: =IF(AI95-AV95=24,1,0) -> 0 | AX95: =IF(AH95-AW95=AH95,0,AH95) -> 0 | AY95: =IF(AW95=1,O95,0) -> 0 | AZ95: =IF(AY95-BA95<>0,AY95,0) -> 0 | BA95: =IF(AY95<0,AY95,0) -> 0 | BB95: =IF(AI95-AV95=14,1,0) -> 0 | BC95: =IF(AH95-BB95=AH95,0,AH95) -> 0 | BD95: =IF(BB95=1,O95,0) -> 0 | BE95: =IF(BD95<0,BD95,0) -> 0 | BF95: =IF(BD95-BE95<>0,BD95,0) -> 0
A96: 3177 | B96: ALCARAZ RICARDO RAMON | C96: 264-5794260 | D96: EL RINCON | E96: 11939 | F96: 34 | G96: 30000 | H96: 15000 | N96: =IF(H96>0,G96+H96-I96-J96-K96-L96-M96,G96-I96-J96-K96-L96-M96) -> 45000 | O96: =G96+H96-J96-I96-K96-L96-M96 -> 45000 | P96: =IF(G96+H96<0,0,G96+H96) -> 45000 | R96: 46264 | S96: 46203 | W96: PAGA LAS DOS JUNTAS EL 3/08 | X96: 7 | Y96: 7 | Z96: =IF(N96<0,0,N96) -> 45000 | AH96: 1 | AI96: =IF(F96<=6,15,25) -> 25 | AJ96: =IF(O96<>0,25,15) -> 25 | AK96: =IF(AI96-T96=24,1,0) -> 0 | AL96: =IF(AH96-AK96=AH96,0,AH96) -> 0 | AM96: =IF(AK96<>0,U96,0) -> 0 | AN96: =IF(AK96=1,O96,0) -> 0 | AO96: =IF(AI96-T96=14,1,0) -> 0 | AP96: =IF(AH96-AO96=AH96,0,AH96) -> 0 | AQ96: =IF(AO96<>0,U96,0) -> 0 | AR96: =IF(AO96=1,O96,0) -> 0 | AS96: =IF(SUM(I96:M96)<>0,1,0) -> 0 | AT96: =AS96 -> 0 | AU96: =IF(O96>0,1,0) -> 1 | AV96: =IF(AK96+AO96+AU96=1,AU96,0) -> 1 | AW96: =IF(AI96-AV96=24,1,0) -> 1 | AX96: =IF(AH96-AW96=AH96,0,AH96) -> 1 | AY96: =IF(AW96=1,O96,0) -> 45000 | AZ96: =IF(AY96-BA96<>0,AY96,0) -> 45000 | BA96: =IF(AY96<0,AY96,0) -> 0 | BB96: =IF(AI96-AV96=14,1,0) -> 0 | BC96: =IF(AH96-BB96=AH96,0,AH96) -> 0 | BD96: =IF(BB96=1,O96,0) -> 0 | BE96: =IF(BD96<0,BD96,0) -> 0 | BF96: =IF(BD96-BE96<>0,BD96,0) -> 0
A97: 3182 | B97: OLMO CECILIA CRISTINA | C97: 264-5105298 | D97: CAUCETE | E97: 11970 | F97: 34 | G97: 80000 | H97: 0 | M97: 80000 | N97: =IF(H97>0,G97+H97-I97-J97-K97-L97-M97,G97-I97-J97-K97-L97-M97) -> 0 | O97: =G97+H97-J97-I97-K97-L97-M97 -> 0 | P97: =IF(G97+H97<0,0,G97+H97) -> 80000 | Q97: 46248 | R97: 46248 | S97: 46213 | V97: MERCADO PAGO | X97: 7 | Y97: 7 | Z97: =IF(N97<0,0,N97) -> 0 | AH97: 1 | AI97: =IF(F97<=6,15,25) -> 25 | AJ97: =IF(O97<>0,25,15) -> 15 | AK97: =IF(AI97-T97=24,1,0) -> 0 | AL97: =IF(AH97-AK97=AH97,0,AH97) -> 0 | AM97: =IF(AK97<>0,U97,0) -> 0 | AN97: =IF(AK97=1,O97,0) -> 0 | AO97: =IF(AI97-T97=14,1,0) -> 0 | AP97: =IF(AH97-AO97=AH97,0,AH97) -> 0 | AQ97: =IF(AO97<>0,U97,0) -> 0 | AR97: =IF(AO97=1,O97,0) -> 0 | AS97: =IF(SUM(I97:M97)<>0,1,0) -> 1 | AT97: =AS97 -> 1 | AU97: =IF(O97>0,1,0) -> 0 | AV97: =IF(AK97+AO97+AU97=1,AU97,0) -> 0 | AW97: =IF(AI97-AV97=24,1,0) -> 0 | AX97: =IF(AH97-AW97=AH97,0,AH97) -> 0 | AY97: =IF(AW97=1,O97,0) -> 0 | AZ97: =IF(AY97-BA97<>0,AY97,0) -> 0 | BA97: =IF(AY97<0,AY97,0) -> 0 | BB97: =IF(AI97-AV97=14,1,0) -> 0 | BC97: =IF(AH97-BB97=AH97,0,AH97) -> 0 | BD97: =IF(BB97=1,O97,0) -> 0 | BE97: =IF(BD97<0,BD97,0) -> 0 | BF97: =IF(BD97-BE97<>0,BD97,0) -> 0
A98: 3184 | B98: MOLINA AGÜERO AYELEN VICTORIA | C98: 2645439804 | D98: POCITOS | E98: 11981 | F98: 34 | G98: 30000 | H98: 0 | M98: 30000 | N98: =IF(H98>0,G98+H98-I98-J98-K98-L98-M98,G98-I98-J98-K98-L98-M98) -> 0 | O98: =G98+H98-J98-I98-K98-L98-M98 -> 0 | P98: =IF(G98+H98<0,0,G98+H98) -> 30000 | Q98: 46235 | R98: 46235 | S98: 46204 | V98: MERCADO PAGO | X98: 7 | Y98: 7 | Z98: =IF(N98<0,0,N98) -> 0 | AH98: 1 | AI98: =IF(F98<=6,15,25) -> 25 | AJ98: =IF(O98<>0,25,15) -> 15 | AK98: =IF(AI98-T98=24,1,0) -> 0 | AL98: =IF(AH98-AK98=AH98,0,AH98) -> 0 | AM98: =IF(AK98<>0,U98,0) -> 0 | AN98: =IF(AK98=1,O98,0) -> 0 | AO98: =IF(AI98-T98=14,1,0) -> 0 | AP98: =IF(AH98-AO98=AH98,0,AH98) -> 0 | AQ98: =IF(AO98<>0,U98,0) -> 0 | AR98: =IF(AO98=1,O98,0) -> 0 | AS98: =IF(SUM(I98:M98)<>0,1,0) -> 1 | AT98: =AS98 -> 1 | AU98: =IF(O98>0,1,0) -> 0 | AV98: =IF(AK98+AO98+AU98=1,AU98,0) -> 0 | AW98: =IF(AI98-AV98=24,1,0) -> 0 | AX98: =IF(AH98-AW98=AH98,0,AH98) -> 0 | AY98: =IF(AW98=1,O98,0) -> 0 | AZ98: =IF(AY98-BA98<>0,AY98,0) -> 0 | BA98: =IF(AY98<0,AY98,0) -> 0 | BB98: =IF(AI98-AV98=14,1,0) -> 0 | BC98: =IF(AH98-BB98=AH98,0,AH98) -> 0 | BD98: =IF(BB98=1,O98,0) -> 0 | BE98: =IF(BD98<0,BD98,0) -> 0 | BF98: =IF(BD98-BE98<>0,BD98,0) -> 0
A99: 3186 | B99: ORTEGA ROSA DEL JESUS | C99: 264-4101302 | D99: 9 DE JULIO | E99: 11983 | F99: 34 | G99: 70000 | H99: 0 | M99: 70000 | N99: =IF(H99>0,G99+H99-I99-J99-K99-L99-M99,G99-I99-J99-K99-L99-M99) -> 0 | O99: =G99+H99-J99-I99-K99-L99-M99 -> 0 | P99: =IF(G99+H99<0,0,G99+H99) -> 70000 | Q99: 46263 | R99: 46265 | S99: 46234 | V99: MERCADO PAGO | X99: 7 | Y99: 7 | Z99: =IF(N99<0,0,N99) -> 0 | AH99: 1 | AI99: =IF(F99<=6,15,25) -> 25 | AJ99: =IF(O99<>0,25,15) -> 15 | AK99: =IF(AI99-T99=24,1,0) -> 0 | AL99: =IF(AH99-AK99=AH99,0,AH99) -> 0 | AM99: =IF(AK99<>0,U99,0) -> 0 | AN99: =IF(AK99=1,O99,0) -> 0 | AO99: =IF(AI99-T99=14,1,0) -> 0 | AP99: =IF(AH99-AO99=AH99,0,AH99) -> 0 | AQ99: =IF(AO99<>0,U99,0) -> 0 | AR99: =IF(AO99=1,O99,0) -> 0 | AS99: =IF(SUM(I99:M99)<>0,1,0) -> 1 | AT99: =AS99 -> 1 | AU99: =IF(O99>0,1,0) -> 0 | AV99: =IF(AK99+AO99+AU99=1,AU99,0) -> 0 | AW99: =IF(AI99-AV99=24,1,0) -> 0 | AX99: =IF(AH99-AW99=AH99,0,AH99) -> 0 | AY99: =IF(AW99=1,O99,0) -> 0 | AZ99: =IF(AY99-BA99<>0,AY99,0) -> 0 | BA99: =IF(AY99<0,AY99,0) -> 0 | BB99: =IF(AI99-AV99=14,1,0) -> 0 | BC99: =IF(AH99-BB99=AH99,0,AH99) -> 0 | BD99: =IF(BB99=1,O99,0) -> 0 | BE99: =IF(BD99<0,BD99,0) -> 0 | BF99: =IF(BD99-BE99<>0,BD99,0) -> 0
A100: 3200 | B100: FUENTE ROSA ELVIRA | C100: 264-4216221 | D100: RAWSON | E100: 11990 | F100: 33 | G100: 60000 | H100: 0 | M100: 60000 | N100: =IF(H100>0,G100+H100-I100-J100-K100-L100-M100,G100-I100-J100-K100-L100-M100) -> 0 | O100: =G100+H100-J100-I100-K100-L100-M100 -> 0 | P100: =IF(G100+H100<0,0,G100+H100) -> 60000 | Q100: 46245 | R100: 46245 | S100: 46205 | V100: GALICIA | X100: 7 | Y100: 7 | Z100: =IF(N100<0,0,N100) -> 0 | AH100: 1 | AI100: =IF(F100<=6,15,25) -> 25 | AJ100: =IF(O100<>0,25,15) -> 15 | AK100: =IF(AI100-T100=24,1,0) -> 0 | AL100: =IF(AH100-AK100=AH100,0,AH100) -> 0 | AM100: =IF(AK100<>0,U100,0) -> 0 | AN100: =IF(AK100=1,O100,0) -> 0 | AO100: =IF(AI100-T100=14,1,0) -> 0 | AP100: =IF(AH100-AO100=AH100,0,AH100) -> 0 | AQ100: =IF(AO100<>0,U100,0) -> 0 | AR100: =IF(AO100=1,O100,0) -> 0 | AS100: =IF(SUM(I100:M100)<>0,1,0) -> 1 | AT100: =AS100 -> 1 | AU100: =IF(O100>0,1,0) -> 0 | AV100: =IF(AK100+AO100+AU100=1,AU100,0) -> 0 | AW100: =IF(AI100-AV100=24,1,0) -> 0 | AX100: =IF(AH100-AW100=AH100,0,AH100) -> 0 | AY100: =IF(AW100=1,O100,0) -> 0 | AZ100: =IF(AY100-BA100<>0,AY100,0) -> 0 | BA100: =IF(AY100<0,AY100,0) -> 0 | BB100: =IF(AI100-AV100=14,1,0) -> 0 | BC100: =IF(AH100-BB100=AH100,0,AH100) -> 0 | BD100: =IF(BB100=1,O100,0) -> 0 | BE100: =IF(BD100<0,BD100,0) -> 0 | BF100: =IF(BD100-BE100<>0,BD100,0) -> 0
...

Sheet PENDIENTES AGOSTO
A1: 7 | B1: =IF(A1<>0,VLOOKUP(A1,COB!A1:B9,2),"COBRADOR INEXISTENTE") -> MEDIOS ELECTRONICOS | D1: AGOSTO | E1: 2026 | F1: TOTAL | I1: EL ARRASTE ES EL DINERO PENDIENTE O A FAVOR DEL CLIENTE
G2: A COBRAR | I2: PAGOS | N2: SAL. REAL | O2: SALDO | P2: SALDO /P ESTAD | Q2: FECHAS
A3: COD | B3: CLIENTE | C3: TELEFONO | D3: LOCALIDAD | E3: SOLI | F3: CTA | G3: CUOTAS | H3: ARRASTRE | I3: PAGO | J3: PAGO X ADEL | K3: PAGO ANTES | L3: X OFICINA | M3: BCO O ELECT | N3: CON MORA | O3: SISTEMA | P3: PLANILLA SALIDA | Q3: PAGO | R3: PAGARA | S3: PAGO MES ANT | T3: BAJA | U3: MOTIVO | V3: OBSERVACIONES | W3: TERMOMETRO
A4: 2015 | B4: ELIZONDO MARIO SANTIAGO | C4: 264-5061888 | D4: ALBARDON | E4: 10189 | F4: 66 | G4: 70000 | H4: -118000 | N4: =IF(H4>0,G4+H4-I4-J4-K4-L4-M4,G4-I4-J4-K4-L4-M4) -> 70000 | O4: =G4+H4-J4-I4-K4-L4-M4 -> -48000 | P4: =IF(G4+H4<0,0,G4+H4) -> 0 | S4: 70000 | T4: 1 | U4: 1 | V4: BAJA Y DEVOLUCION
A5: 2545 | B5: DIAZ ANTONELLA YAMILA | C5: 264-4743505 | D5: JACHAL | E5: 11371 | F5: 54 | G5: 300000 | H5: 0 | N5: =IF(H5>0,G5+H5-I5-J5-K5-L5-M5,G5-I5-J5-K5-L5-M5) -> 300000 | O5: =G5+H5-J5-I5-K5-L5-M5 -> 300000 | P5: =IF(G5+H5<0,0,G5+H5) -> 300000 | R5: 46259 | S5: 46217 | W5: NO QUISO PAGAR EL JUEVES 3 VA POR OFICINA Y ALLI ARREGLA LO DE LAS CUOTAS
A6: 2897 | B6: ESPEJO ALEXANDRA VANESA | C6: 264-5163415 | D6: SAN JUAN | E6: 11810 | F6: 41 | G6: 80000 | H6: 0 | N6: =IF(H6>0,G6+H6-I6-J6-K6-L6-M6,G6-I6-J6-K6-L6-M6) -> 80000 | O6: =G6+H6-J6-I6-K6-L6-M6 -> 80000 | P6: =IF(G6+H6<0,0,G6+H6) -> 80000 | R6: 46264 | S6: 46218 | W6: NO PAGO PROBLEMAS ECONOMICOS
A7: 3036 | B7: FALCON ARTEZ YANINA VANESA | C7: 264-4806498 | D7: CHIMBAS | E7: 10489 | F7: 36 | G7: 100000 | H7: 0 | N7: =IF(H7>0,G7+H7-I7-J7-K7-L7-M7,G7-I7-J7-K7-L7-M7) -> 100000 | O7: =G7+H7-J7-I7-K7-L7-M7 -> 100000 | P7: =IF(G7+H7<0,0,G7+H7) -> 100000 | R7: 46265 | S7: 46234 | W7: VA PAGAR EL DIA JUEVES 3 PORQUE NO TENIA PAGA LAS DOS JUNTAS
A8: 3118 | B8: MACIAS DANIELA VALERIA | C8: 264-4038388 | D8: SAN JUAN | E8: 11940 | F8: 35 | G8: 60000 | H8: 60000 | N8: =IF(H8>0,G8+H8-I8-J8-K8-L8-M8,G8-I8-J8-K8-L8-M8) -> 120000 | O8: =G8+H8-J8-I8-K8-L8-M8 -> 120000 | P8: =IF(G8+H8<0,0,G8+H8) -> 120000 | R8: 46233 | S8: 46203 | T8: 1 | U8: 1 | V8: BAJA POR FALTADE PAGO Y COMUNICACIÓN
A9: 3158 | B9: POBLETE VIVIANA GRACIELA | C9: 264-4630593 | D9: RODEO | E9: 20018 | F9: 34 | G9: 80000 | H9: 0 | N9: =IF(H9>0,G9+H9-I9-J9-K9-L9-M9,G9-I9-J9-K9-L9-M9) -> 80000 | O9: =G9+H9-J9-I9-K9-L9-M9 -> 80000 | P9: =IF(G9+H9<0,0,G9+H9) -> 80000 | R9: 46259 | S9: 46209 | W9: NO RESPONDE PERO NO DARE DE BAJA
A10: 3177 | B10: ALCARAZ RICARDO RAMON | C10: 264-5794260 | D10: EL RINCON | E10: 11939 | F10: 34 | G10: 30000 | H10: 15000 | N10: =IF(H10>0,G10+H10-I10-J10-K10-L10-M10,G10-I10-J10-K10-L10-M10) -> 45000 | O10: =G10+H10-J10-I10-K10-L10-M10 -> 45000 | P10: =IF(G10+H10<0,0,G10+H10) -> 45000 | R10: 46264 | S10: 46203 | W10: PAGA LAS DOS JUNTAS EL 3/08
A11: 3249 | B11: SAIRE NATALIA LORENA | C11: 264-5069280 | D11: CHIMBAS | E11: 20300 | F11: 32 | G11: 60000 | H11: 60000 | M11: 60000 | N11: =IF(H11>0,G11+H11-I11-J11-K11-L11-M11,G11-I11-J11-K11-L11-M11) -> 60000 | O11: =G11+H11-J11-I11-K11-L11-M11 -> 60000 | P11: =IF(G11+H11<0,0,G11+H11) -> 120000 | Q11: 46245 | R11: 46245 | S11: 46211 | V11: MERCADO PAGO | W11: PAGO JULIO DEBE AGOSTO
A12: 3371 | B12: PAEZ ILIANA YAEL | C12: 264-6299108 | D12: SAN JUAN | E12: 20186 | F12: 27 | G12: 99999 | H12: -13 | N12: =IF(H12>0,G12+H12-I12-J12-K12-L12-M12,G12-I12-J12-K12-L12-M12) -> 99999 | O12: =G12+H12-J12-I12-K12-L12-M12 -> 99986 | P12: =IF(G12+H12<0,0,G12+H12) -> 99986 | R12: 46261 | S12: 46230 | W12: PAGA EN SEPTIEMBRE LAS DOS JUNTAS
A13: 3400 | B13: CALIVA PAMELA LORENA | C13: 264-5899505 | D13: POCITOS | E13: 20201 | F13: 25 | G13: 60000 | H13: 0 | N13: =IF(H13>0,G13+H13-I13-J13-K13-L13-M13,G13-I13-J13-K13-L13-M13) -> 60000 | O13: =G13+H13-J13-I13-K13-L13-M13 -> 60000 | P13: =IF(G13+H13<0,0,G13+H13) -> 60000 | S13: 46211 | W13: NO RESPONDE PERO NO DARE DE BAJA
A14: 3401 | B14: NIEVAS CINTHYA DAYANA | C14: 264-6216892 | D14: RAWSON | E14: 20219 | F14: 25 | G14: 60000 | H14: -60000 | N14: =IF(H14>0,G14+H14-I14-J14-K14-L14-M14,G14-I14-J14-K14-L14-M14) -> 60000 | O14: =G14+H14-J14-I14-K14-L14-M14 -> 0 | P14: =IF(G14+H14<0,0,G14+H14) -> 0 | R14: 46234 | S14: 46234 | W14: ELLA YA PAGO EN JULIO ESTA CUOTA
A15: 3457 | B15: JIMENEZ HERNAN | C15: 264-5430399 | D15: CHIMBAS | E15: 20336 | F15: 22 | G15: 80000 | H15: 0 | N15: =IF(H15>0,G15+H15-I15-J15-K15-L15-M15,G15-I15-J15-K15-L15-M15) -> 80000 | O15: =G15+H15-J15-I15-K15-L15-M15 -> 80000 | P15: =IF(G15+H15<0,0,G15+H15) -> 80000 | R15: 46234 | S15: 46234 | W15: RECLAMO POR PROPUESTA
A16: 3491 | B16: SIMAN JUANA BEATRIZ | C16: 264-5058882 | D16: SAN JUAN | E16: 20356 | F16: 15 | G16: 200000 | H16: 0 | N16: =IF(H16>0,G16+H16-I16-J16-K16-L16-M16,G16-I16-J16-K16-L16-M16) -> 200000 | O16: =G16+H16-J16-I16-K16-L16-M16 -> 200000 | P16: =IF(G16+H16<0,0,G16+H16) -> 200000 | S16: 46206 | T16: 1 | U16: 1 | V16: BAJA INFORMA EDUARDO
B17: TOTAL COB SIN CUP | G17: ='COBRANZA SIN CUPONES'!G26 -> 0 | I17: ='COBRANZA SIN CUPONES'!H26 -> 525000 | J17: ='COBRANZA SIN CUPONES'!I26 -> 0 | O17: =G17+H17-J17-I17-K17-L17-M17 -> -525000
P26: OBLIGACION DE PAGO
A27: =COUNTIF(X4:X16,A1) -> 0 | B27: CLIENTES | C27: TOTAL COBRANZA NORMAL ----> | E27: =I27 -> 0 | F27: A COBRAR | G27: =SUMIF(X4:X16,A1,G4:G16) -> 0 | H27: =SUMIF(X4:X16,A1,H4:H16) -> 0 | I27: =SUMIF(X4:X16,A1,I4:I16) -> 0 | J27: =SUMIF(X4:X16,A1,J4:J16) -> 0 | K27: =SUMIF(X4:X16,A1,K4:K16) -> 0 | L27: =SUMIF(X4:X16,A1,L4:L16) -> 0 | M27: =SUMIF(X4:X16,A1,M4:M16) -> 0 | N27: =SUM(N4:N17) -> 1354999 | O27: =SUMIF(X4:X16,A1,O4:O16) -> 0 | P27: =SUMIF(X4:X16,A1,P4:P16) -> 0 | Q27: =P27-O27 -> 0 | T27: =SUMIF(X4:X16,A1,T4:T16) -> 0 | U27: =COUNTIFS(X1:X16,A1,U1:U16,"<=5") -> 0

Sheet COBRANZA SIN CUPONES
A1: COBRANZA SIN CUPONES
H2: PAGOS
H3: AUTOHOGAR
A4: COD | B4: CLIENTE | C4: TELEFONO | D4: LOCALIDAD | E4: SOLI | F4: N°CUOTA | G4: VALOR CUOTA | H4: PAGO | I4: PAGO X ADEL | J4: TOTAL | K4: COMISION | L4: A RENDIR | M4: N° COBRADOR | N4: OBSERVACIONES
A5: 1449 | B5: ESCUELA ANA LORENA | E5: 8865 | H5: 160000 | J5: =H5+I5 -> 160000 | K5: =J5*AUTOHOGAR!$M$165% -> 12800 | L5: =J5-K5 -> 147200
A6: 2947 | B6: CASTRO FLORES | E6: 11832 | H6: 40000 | J6: =H6+I6 -> 40000 | K6: =J6*AUTOHOGAR!$M$165% -> 3200 | L6: =J6-K6 -> 36800
A7: 3145 | B7: MONTAÑA MARGARITA | E7: 11961 | H7: 60000 | J7: =H7+I7 -> 60000 | K7: =J7*AUTOHOGAR!$M$165% -> 4800 | L7: =J7-K7 -> 55200
A8: 3056 | B8: GONZALEZ MARCELA | E8: 10167 | G8: 60000 | H8: 115000 | J8: =H8+I8 -> 115000 | K8: =J8*AUTOHOGAR!$M$165% -> 9200 | L8: =J8-K8 -> 105800
A9: 3444 | B9: GOMEZ LILIANA | E9: 20302 | H9: 150000 | J9: =H9+I9 -> 150000 | K9: =J9*AUTOHOGAR!$M$165% -> 12000 | L9: =J9-K9 -> 138000
J10: =H10+I10 -> 0 | K10: =J10*AUTOHOGAR!$M$165% -> 0 | L10: =J10-K10 -> 0
J11: =H11+I11 -> 0 | K11: =J11*AUTOHOGAR!$M$165% -> 0 | L11: =J11-K11 -> 0
J12: =H12+I12 -> 0 | K12: =J12*AUTOHOGAR!$M$165% -> 0 | L12: =J12-K12 -> 0
J13: =H13+I13 -> 0 | K13: =J13*AUTOHOGAR!$M$165% -> 0 | L13: =J13-K13 -> 0
J14: =H14+I14 -> 0 | K14: =J14*AUTOHOGAR!$M$165% -> 0 | L14: =J14-K14 -> 0
J15: =H15+I15 -> 0 | K15: =J15*AUTOHOGAR!$M$165% -> 0 | L15: =J15-K15 -> 0
J16: =H16+I16 -> 0 | K16: =J16*AUTOHOGAR!$M$165% -> 0 | L16: =J16-K16 -> 0
J17: =H17+I17 -> 0 | K17: =J17*AUTOHOGAR!$M$165% -> 0 | L17: =J17-K17 -> 0
J18: =H18+I18 -> 0 | K18: =J18*AUTOHOGAR!$M$165% -> 0 | L18: =J18-K18 -> 0
J19: =H19+I19 -> 0 | K19: =J19*AUTOHOGAR!$M$165% -> 0 | L19: =J19-K19 -> 0
J20: =H20+I20 -> 0 | K20: =J20*AUTOHOGAR!$M$165% -> 0 | L20: =J20-K20 -> 0
J21: =H21+I21 -> 0 | K21: =J21*AUTOHOGAR!$M$165% -> 0 | L21: =J21-K21 -> 0
... J24: =H24+I24 -> 0 | K24: =J24*AUTOHOGAR!$M$165% -> 0 | L24: =J24-K24 -> 0
A26: =COUNTA(A5:A24) -> 5 | H26: =SUM(H5:H25) -> 525000 | I26: =SUM(I5:I25) -> 0 | J26: =SUM(J5:J25) -> 525000 | K26: =SUM(K5:K25) -> 42000 | L26: =SUM(L5:L25) -> 483000

Sheet PAGARA
A1: CLIENTE | B1: (Todas)
A3: Etiquetas de fila | B3: Suma de CON MORA
A4: (en blanco) | B4: 476000
A5: Total general | B5: 476000

Sheet PAGARA DETALLADO
A3: Suma de CON MORA | B3: Etiquetas de columna
A4: Etiquetas de fila | B4: (en blanco) | C4: Total general
A5: ESTRELLA MICAELA DEL ROCIO | B5: 11000 | C5: 11000 | R5: 45540
A6: RAMIREZ PAULA ALEJANDRA | B6: 15000 | C6: 15000
A7: MOLINI BETINA LAURA | B7: 10000 | C7: 10000
A8: AGUILAR FIDEL CHOQUE | B8: 20000 | C8: 20000
A9: OYOLA SANCHEZ SABRINA MAILEN | B9: 4000 | C9: 4000 | M9: 30000 | Q9: 45547 | V9: GALICIA
A10: CARRIZO ALEJANDRA NELLY | B10: 9000 | C10: 9000 | R10: 45551
A11: HERRERA FRANCISCO ANTONIO | B11: 12000 | C11: 12000
A12: CARPIO NORMA ANA | B12: 7000 | C12: 7000
A13: LORENZETTI LANZILOTTA SANDRA P. | B13: 10000 | C13: 10000
A14: VARGAS MARIA HORTENCIA | B14: 6000 | C14: 6000 | R14: 45625
A15: BALMACEDA MAZA FRANCISCO EMILIO | B15: 7000 | C15: 7000 | R15: 45618
A16: CAJAS HUGO RICARDO | B16: 10000 | C16: 10000 | V16: en febro aumenta esta con un prestamo
A17: OCHOA BARBARA YAMILA | B17: 6000 | C17: 6000 | I17: 30000 | Q17: 45542
A18: ALANIZ CINTIA MACARENA | B18: 5000 | C18: 5000
A19: HEREDIA JUAN CARLOS | B19: 10000 | C19: 10000
A20: AGÜERO PATRICIO JAVIER | B20: 5000 | C20: 5000 | I20: 30000 | Q20: 45545
A21: BUSTOS NELLY MABEL | B21: 6800 | C21: 6800 | I21: 30000 | Q21: 45547 | V21: aumenta a 60.000
A22: ZAMBRA MARIA SOLEDAD | B22: 10000 | C22: 10000 | M22: 30000 | Q22: 45547 | R22: 45547
A23: GALDEANO CARRIZO HERNAN | B23: 8000 | C23: 8000
A24: PASTEN OLMOS ROSA MANUELA | B24: 4500 | C24: 4500
A25: AGUERO CARLOS MORENO | B25: 9000 | C25: 9000
A26: PUJADO LOBOS MARTIN DAVID | B26: 3000 | C26: 3000
A27: MARINERO GERMAN ANTONIO | B27: 10000 | C27: 10000
A28: MOLINA EMANUEL MARCOS JAIRO | B28: 8000 | C28: 8000 | R28: 45551 | V28: no aumenta
A29: OCAMPO BLAS RICARDO | B29: 7000 | C29: 7000
A30: MERCADO ANA BELEN | B30: 7000 | C30: 7000
A31: KENNY NOELIA VANESA | B31: 10000 | C31: 10000
A32: CAROSELLI YANINA CAROLINA | B32: 6000 | C32: 6000 | I32: 30000 | Q32: 45615 | R32: 45615 | V32: no aumenta
A33: PEREZ LUCAS SEBASTIAN | B33: 4000 | C33: 4000
A34: SALCEDO JORGE LUIS | B34: 8500 | C34: 8500
A35: NUÑEZ PAMELA GISELLE | B35: 8000 | C35: 8000
A36: GUTIERREZ ATENCIO ELDA VANESA | B36: 10000 | C36: 10000 | R36: 45551
A37: CEVALLE JORGE LEONARDO | B37: 12000 | C37: 12000 | I37: 35000 | Q37: 45615 | R37: 45615 | V37: aumenta a 55.000
A38: SILLERO GABRIELA SOLEDAD | B38: 5000 | C38: 5000
A39: NAVARRO EDUARDO AGUSTIN | B39: 15000 | C39: 15000 | V39: no aumenta
A40: RIVEROS DAYANA ESTEFANIA | B40: 10000 | C40: 10000 | R40: 45623
A41: CASTRO OSCAR ALBERTO | B41: 9700 | C41: 9700 | R41: 45617
A42: ARIA MIRTA GLADYS | B42: 5000 | C42: 5000
A43: SANTAMARIA RIVEROS DAYANA ELIANA | B43: 10000 | C43: 10000 | V43: no aumenta
A44: MALLEA ATENCIO PAULA CECILIA | B44: 7000 | C44: 7000 | M44: 30000 | Q44: 45615 | V44: no aumenta
A45: FERRA CASTRO GASTON MAXIMILIANO | B45: 8000 | C45: 8000 | R45: 45551 | V45: aumetna a 60000
A46: GATICA SEBASTIAN DARIO | B46: 12000 | C46: 12000
A47: MERCADO MOLINA LEILA BELEN | B47: 5000 | C47: 5000 | I47: 30000 | Q47: 45614 | R47: 45614 | V47: no aumenta
A48: PARRA SIXTO ANTONIO | B48: 5000 | C48: 5000 | I48: 30000 | Q48: 45548 | R48: 45548 | V48: posible baja no aumenta
A49: GOMEZ CARINA JULIETA | B49: 10000 | C49: 10000 | R49: 45616
A50: OLIVERA GISELA ROMINA | B50: 12000 | C50: 12000 | V50: no aumenta
A51: JOFRE CAROLINA IVANA | B51: 6000 | C51: 6000 | V51: no aumenta
A52: ILLANES EDUARDO ADRIAN | B52: 15000 | C52: 15000
A53: JANAVEL SILVIA LILIANA | B53: 8500 | C53: 8500 | R53: 45617 | V53: aumenta a 80.000
A54: CASTAN MARIA ARGENTINA | B54: 10000 | C54: 10000 | V54: no aumenta
A55: ANDRADA JORGELINA AIDA | B55: 12000 | C55: 12000 | R55: 45617
A56: MERCADO MOLINA DAYANA ELIZABETH | B56: 5000 | C56: 5000
A57: LIZARDE SERGIO DANIEL | B57: 7000 | C57: 7000 | R57: 45618
A58: PAEZ EDUARDO ANTONIO | B58: 10000 | C58: 10000 | I58: 30000 | Q58: 45548 | R58: 45548
A59: JOFRE GRACIELA CRISTINA | B59: 10000 | C59: 10000 | R59: 45624
A60: Total general | B60: 476000 | C60: 476000 | V60: no aumenta
I61: 25000 | Q61: 45615 | R61: 45551 | V61: no aumenta
R62: 45551
M63: 55000 | Q63: 45548 | R63: 45548 | V63: MERCADO PAGO
R66: 45551 | V66: no aumenta mas no puede
R68: 45624
V70: no aumenta
V72: no puede aumenta mas
I73: 30000 | Q73: 45545 | V73: aumenta a 55.000
V74: no aumenta
M75: 30000 | Q75: 45547 | R75: 45547 | V75: aumenta a 60.000
V78: tiene discapacida no puede aumentar
R80: 45551
M85: 30000 | Q85: 45548 | R85: 45548 | V85: MERCADO PAGO
V86: no aumenta
I88: 30000 | Q88: 45544
R89: 45551
M90: 30000 | Q90: 45615 | V90: no aumenta
R91: 45551 | V91: no puede pagar mas
R92: 45551
V93: esta con problema de salud estuvo grave
V94: no puede pagar mas q 30.000
I95: 30000 | Q95: 45615 | V95: aumenta a 30000
R96: 45624
I97: 40000 | Q97: 45545 | V97: aumenta a 55.000
V99: no aumenta
I100: 40000 | Q100: 45548 | R100: 45548 | V100: no peude pagar mas q 30.000
R101: 45618
I102: 30000 | Q102: 45548 | R102: 45621
R103: 45551 | V103: aumenta a 60.000
V105: aumenta a 60.000
I106: 30000 | Q106: 45615 | T106: 1 | U106: 1 | V106: pausa plan paga la carpeta carbajl norma 3 carpetas mas
I107: 30000 | Q107: 45548 | R107: 45548 | V107: aumenta a 55.000
R108: 45618
R109: 45617
R110: 45551 | V110: no quiere auemntar mas quiere la casa se le hablo mas de una vez queria poner abogado
R112: 45551 | V112: no aumenta
M113: 10000 | Q113: 45615 | R113: 45551 | V113: no aumenta
I115: 30000 | Q115: 45547
R116: 45619
V117: ya aumento
V118: no puede pagar mas
R124: 45551 | V124: paga en 2 veces porque no le alcanza no puede aumentar
...

Sheet COB
A1: 1 | B1: BANCO | C1: 1
A2: 2 | B2: OFICINA SAN JUAN | C2: 3
A3: 3 | C3: 1
A4: 4 | B4: COBRADOR SAN JUAN | C4: 2
A5: 5 | C5: 1
A6: 6 | C6: 1
A7: 7 | B7: MEDIOS ELECTRONICOS | C7: 3
A8: 8 | C8: 2
A9: 9 | C9: 2
B14: BANCO O M ELECTRONICOS | C14: =COUNTIF(C1:C9,1) -> 4
B15: COBRADORES | C15: =COUNTIF(C1:C9,2) -> 3
B16: SUCURSALES | C16: =COUNTIF(C1:C9,3) -> 2
B17: OTRO MEDIO | C17: =COUNTIF(C1:C9,4) -> 0
C19: =SUM(C14:C18) -> 9
